Workbook

Sheet คู่มือ Guide
B1: คู่มือการใช้งาน / User Guide — Project Control: Plan vs Actual (v2)
B3: 1. ภาพรวมไฟล์ / Workbook Overview
B4: ไฟล์นี้ใช้ควบคุมและรายงานความก้าวหน้าโครงการก่อสร้างตามแนวทางสากล ได้แก่ การวัดผลงานถ่วงน้ำหนัก (Weighted Progress), S-Curve, Earned Value Management (EVM) และ Earned Schedule (ES) พร้อมทะเบียนขยายเวลาและการคำนวณค่าปรับ ใช้ซ้ำกับโครงการอื่นได้
B5: ชีต / Sheet | C5: ใช้ทำอะไร / Purpose | D5: ต้องกรอกอะไร / What to fill
B6: ตั้งค่า Setup | C6: ข้อมูลหลักของสัญญา วันที่ตรวจวัด รอบตัดงวด อัตราค่าปรับ และรายชื่อหมวดงาน (WBS ระดับ 1) | D6: ทุกช่องสีเหลือง (ตั้งค่าครั้งแรก) + เปลี่ยน Status Date ทุกงวด
B7: Dashboard | C7: สรุปตัวชี้วัดทั้งหมด (เวลา / ต้นทุน / ขยายเวลา-ค่าปรับ) พร้อมกราฟ S-Curve และกราฟ EVM | D7: ไม่ต้องกรอก – คำนวณอัตโนมัติ
B8: รายงาน Report | C8: รายงานประจำงวดพร้อมพิมพ์ (A4) ใช้ส่งผู้ว่าจ้าง/ผู้ควบคุมงาน มีช่องลงนาม | D8: กรอกเฉพาะหัวข้อ 6 ปัญหาและแนวทางแก้ไข
B9: แผนงาน Schedule | C9: รายการงานแบบ WBS: น้ำหนักงาน, แผนเดิม (Baseline), แผนเร่งรัด (Revised), ผลงานจริง, การวิเคราะห์รายรายการ และ Gantt Chart | D9: ครั้งแรก: หมวด รายการ น้ำหนัก วันตามแผน • ทุกงวด: วันเริ่ม/เสร็จจริง และ % จริง
B10: S-Curve | C10: ตารางรายงวดสำหรับ S-Curve และ EVM (PV / EV / AC) รวมถึงเงินเบิกจ่าย | D10: ทุกงวด: % จริงสะสม, AC ต้นทุนจริงในงวด, เงินเบิกจ่ายในงวด
B11: ขยายเวลา EOT | C11: ทะเบียนเหตุการณ์ล่าช้าและการขอขยายเวลา (EOT) – วันที่อนุมัติจะไปขยายวันสิ้นสุดสัญญาอัตโนมัติ | D11: ทุกครั้งที่มีเหตุการณ์ล่าช้า / ยื่นหนังสือ / ได้รับผลพิจารณา
B13: 2. สัญลักษณ์สี / Color Legend
B14: ช่องพื้นเหลือง ตัวน้ำเงิน | C14: ช่องที่ให้กรอก (Input) – แก้ไขได้
B15: ช่องพื้นขาว ตัวดำ | C15: สูตรคำนวณ – ถูกล็อกไว้กันแก้โดยไม่ตั้งใจ | D15: ปลดล็อก: รีวิว (Review) → ยกเลิกการป้องกันแผ่นงาน (ไม่มีรหัสผ่าน)
B16: Gantt สีฟ้า | C16: ช่วงเวลาตามแผนเดิม (Baseline)
B17: Gantt สีส้ม | C17: ช่วงที่ทำงานจริง (นอกช่วงแผน)
B18: Gantt สีเขียว | C18: ทำงานจริงตรงกับช่วงแผน
B19: หัวคอลัมน์ Gantt สีแดง | C19: งวดที่มีวันตรวจวัด (Status Date)
B20: แถวสีส้มอ่อนในชีต S-Curve | C20: งวดปัจจุบัน – กรอกผลงานจริงของงวดนี้
B21: สถานะสีแดง / เหลือง / เขียว | C21: ล่าช้ามาก / เฝ้าระวัง / ตามแผน
B23: 3. ขั้นตอนตั้งค่าโครงการใหม่ / New Project Setup
B24: 1) ชีต ตั้งค่า Setup: กรอกชื่อโครงการ คู่สัญญา มูลค่าสัญญา วันเริ่ม ระยะเวลา อัตราค่าปรับ และรายชื่อหมวดงาน (สูงสุด 10 หมวด)
B25: 2) ชีต แผนงาน Schedule: ลบข้อมูลเดิมในช่องสีเหลือง แล้วกรอกรายการงาน (สูงสุด 60 รายการ) เลือกหมวดจาก Drop-down รหัส WBS จะสร้างให้เอง
B26: 3) น้ำหนักงาน: กรอก 'น้ำหนักกำหนดเอง' หรือกรอก 'มูลค่า BOQ' อย่างเดียวแล้วระบบคำนวณน้ำหนักจากสัดส่วนมูลค่าให้ • รวมต้องได้ 100% (ดูช่องตรวจสอบใน Dashboard)
B27: 4) กรอกวันเริ่ม-เสร็จตามแผนเดิม (Baseline) – เมื่อได้รับอนุมัติแผนแล้ว ไม่ควรแก้ Baseline อีก ถ้าแผนเปลี่ยนให้ใช้คอลัมน์ Revised
B28: 5) ชีต S-Curve และ ขยายเวลา EOT: ลบข้อมูลเดิมในช่องสีเหลือง
B30: 4. ขั้นตอนอัปเดตทุกงวด / Periodic Update Routine
B31: 1) ตั้งค่า Setup → เปลี่ยน 'วันที่ตรวจวัดผลงาน (Status Date)'
B32: 2) แผนงาน Schedule → กรอกวันเริ่มจริง วันเสร็จจริง (เว้นว่างถ้ายังไม่เสร็จ) และ % ความคืบหน้าของแต่ละรายการ
B33: 3) S-Curve → ที่แถวสีส้ม กรอก Actual % สะสม (คัดลอกค่าจากแถวรวม คอลัมน์ '% งานนี้' ในชีตแผนงาน), AC ต้นทุนจริงในงวด และเงินเบิกจ่ายในงวด
B34: 4) ขยายเวลา EOT → บันทึกเหตุการณ์ล่าช้าใหม่ / อัปเดตผลพิจารณา
B35: 5) รายงาน Report → กรอกปัญหาและแนวทางแก้ไข แล้วสั่งพิมพ์ (A4 แนวตั้ง 2 หน้า)
... B38: 5. ความหมายของคอลัมน์ในชีตแผนงาน / Schedule Columns
B39: คอลัมน์ / Column | C39: ความหมาย / Meaning | D39: วิธีคำนวณ / How calculated
B40: WBS | C40: รหัสโครงสร้างงาน: เลขหมวด.ลำดับในหมวด เช่น 2.3 = หมวดที่ 2 รายการที่ 3 | D40: อัตโนมัติจากหมวดที่เลือก
B41: น้ำหนักที่ใช้ / Weight Used | C41: สัดส่วนความสำคัญของงานเทียบทั้งโครงการ ใช้ถ่วงน้ำหนักผลงาน | D41: ใช้น้ำหนักกำหนดเอง ถ้าไม่มีใช้ BOQ ÷ BOQ รวม
B42: งบประมาณ / Budget | C42: มูลค่างานของรายการตามสัดส่วนสัญญา | D42: น้ำหนัก × มูลค่าสัญญา
B43: BASELINE แผนเดิม | C43: แผนตามสัญญาที่ได้รับอนุมัติ ใช้เป็นเกณฑ์วัดผลตลอดโครงการ | D43: กรอกเอง
B44: REVISED แผนเร่งรัด | C44: แผนปรับปรุง/แผนเร่งรัดเพื่อกู้สถานการณ์ (Recovery Plan) – ไม่บังคับ | D44: ถ้าเว้นว่าง ระบบใช้ค่า Baseline
B45: % งานนี้ / % Complete | C45: ความคืบหน้าของรายการนั้นเอง (ไม่ใช่ % ของโครงการ) | D45: กรอกเอง จากการวัดหน้างาน
B46: % แผน ณ Status | C46: รายการนี้ควรเสร็จกี่ % ณ วันตรวจวัด | D46: กระจายเชิงเส้นตามวันเริ่ม-เสร็จแผน
B47: PV / EV / SV / SPI | C47: มูลค่างานตามแผน / มูลค่างานที่ทำได้ / ผลต่าง / ดัชนีเวลา ระดับรายการ | D47: ดูคำอธิบายในหัวข้อ 6
B48: คาดว่าเสร็จ / Forecast Finish | C48: วันที่คาดว่ารายการนี้จะเสร็จ | D48: เสร็จแล้ว = วันเสร็จจริง • กำลังทำ = คาดจากอัตราที่ทำได้ • ยังไม่เริ่ม = MAX(แผน, วันนี้ + ระยะเวลางาน)
B49: ล่าช้า (วัน) / Delay vs BL | C49: คาดว่าเสร็จช้ากว่าแผนเดิมกี่วัน (+ ช้า, − เร็ว) | D49: Forecast Finish − Baseline Finish
B50: สถานะ / Status | C50: Completed / Completed Late / Not Due / On Track / Behind / Overdue | D50: เทียบ % จริงกับ % แผน และวันที่
B52: 6. อภิธานศัพท์ตัวชี้วัด / KPI Glossary
B53: ตัวชี้วัด / KPI | C53: ความหมาย / Meaning | D53: สูตรและการแปลผล / Formula & Interpretation
B54: S-Curve | C54: กราฟความก้าวหน้าสะสมตามเวลา มีรูปตัว S เพราะช่วงต้นและท้ายโครงการงานเดินช้า ช่วงกลางเร็ว | D54: เส้นจริงต่ำกว่าเส้นแผน = ล่าช้า • ระยะห่างแนวนอน = ช้ากี่วัน
B55: Baseline / Revised / Forecast | C55: แผนเดิมตามสัญญา / แผนเร่งรัด / เส้นคาดการณ์จากผลงานจริงล่าสุดไปถึงวันคาดว่าเสร็จ | D55: Forecast ลากเส้นตรงจากจุดจริงล่าสุดไปถึง 100% ณ วันคาดว่าแล้วเสร็จ
B56: Data Date | C56: วันที่ของข้อมูลผลงานจริงที่ใช้คำนวณ | D56: ถ้าไม่ตรงกับ Status Date (แสดงสีแดง) แปลว่ายังไม่ได้อัปเดตผลงานจริงล่าสุด
B57: BAC – Budget at Completion | C57: งบประมาณ/มูลค่างานทั้งหมด | D57: เท่ากับมูลค่าสัญญา
B58: PV – Planned Value | C58: มูลค่างานที่ควรทำได้ตามแผน ณ วันที่วัด | D58: % แผน × BAC
B59: EV – Earned Value | C59: มูลค่างานที่ทำได้จริง (คิดตามราคาในสัญญา) | D59: % จริง × BAC
B60: AC – Actual Cost | C60: ต้นทุนที่จ่ายไปจริงเพื่อให้ได้งานนั้น (ค่าวัสดุ ค่าแรง ค่าผู้รับเหมาช่วง ฯลฯ) | D60: กรอกในชีต S-Curve • ถ้าเป็นฝั่งผู้ว่าจ้าง อาจใช้ยอดเงินที่จ่ายจริง
B61: SV – Schedule Variance | C61: ผลต่างด้านเวลาในรูปเงิน | D61: EV − PV • ติดลบ = งานช้ากว่าแผน
B62: CV – Cost Variance | C62: ผลต่างด้านต้นทุน | D62: EV − AC • ติดลบ = ใช้เงินมากกว่ามูลค่างานที่ได้
B63: SPI – Schedule Performance Index | C63: ประสิทธิภาพด้านเวลา | D63: EV ÷ PV • ≥1.00 ตามแผน • 0.90–0.99 เฝ้าระวัง • <0.90 ล่าช้ามาก
B64: CPI – Cost Performance Index | C64: ประสิทธิภาพด้านต้นทุน | D64: EV ÷ AC • ≥1.00 ดี • <1.00 ใช้เงินเกิน (เช่น 0.85 = ได้งาน 85 สตางค์ต่อเงิน 1 บาท)
... B78: Look-ahead | C78: แผนงานล่วงหน้าระยะสั้น ใช้ประชุมหน้างานรายสัปดาห์ | D78: แสดงงานที่ยังไม่เสร็จและต้องเริ่มภายใน X วัน
B80: 7. หมายเหตุเกี่ยวกับข้อมูลตั้งต้นในไฟล์นี้ / Notes on Pre-filled Data
B81: • แผนงาน 17 รายการ น้ำหนักงาน วันตามแผน ผลงานจริงสะสมถึง 30-Apr-26 และเงินเบิกจ่าย ถอดจากเอกสาร PDF ที่ผู้ใช้ส่งมา • ชื่องานเขียนแบบย่อ • มูลค่า BOQ และมูลค่าสัญญาอ่านได้ไม่ชัด กรุณาตรวจสอบ
B82: • การจัดหมวดงาน (WBS ระดับ 1) เป็นการจัดตัวอย่าง แก้ไขได้ในชีต ตั้งค่า Setup
B83: • อัตราค่าปรับ 0.10%/วัน และขั้นต่ำ 100 บาท เป็นค่าตัวอย่าง ต้องแก้ให้ตรงตามสัญญา
B84: • % แผนคำนวณแบบกระจายเชิงเส้น จึงต่างจากเอกสารเดิมเล็กน้อย (ณ 30-Apr-26 ได้ ~20.8% เทียบกับ 22.73%)
B85: • เส้น Forecast ในกราฟจะแสดงถึงสุดแกนเวลาเท่านั้น ถ้าวันคาดว่าเสร็จอยู่ไกลกว่านั้น เส้นจะหยุดก่อนถึง 100%
B86: • ยังไม่มีข้อมูล AC (ต้นทุนจริง) และ % จริงรายรายการ – ตัวชี้วัดด้านต้นทุนและรายการที่ล่าช้าจะแสดงผลเมื่อกรอกข้อมูลแล้ว
B87: • ความจุ: 60 รายการงาน • 10 หมวด • 80 งวด (รอบ 10 วัน ≈ 26 เดือน) • 50 เหตุการณ์ขยายเวลา
B88: • ข้อจำกัด: ไฟล์นี้ไม่วิเคราะห์ความสัมพันธ์ระหว่างงาน (Critical Path) – ถ้าต้องการ ควรใช้ร่วมกับ MS Project หรือ Primavera P6
B90: รายงานต่อคณะกรรมการตรวจรับพัสดุ (รายสัปดาห์) / Weekly Committee Report
B91: ชุดรายงานนี้มี 3 ชีต (แท็บสีม่วง): งวดงาน Installments • บันทึกสัปดาห์ Weekly Log • รายงานกรรมการ Weekly (พิมพ์ได้ในรูปแบบบันทึกข้อความ)
B92: ครั้งแรก: (1) ชีตงวดงาน – กรอกงวดงานตามสัญญา: เนื้องาน, ผลงานสะสมที่กำหนด (ถ้ามี), กำหนดเสร็จ, จำนวนเงิน • ยอดรวมต้องเท่ามูลค่าสัญญา
... B108: – สถานะแดง = เลยกำหนดหรือเหลือไม่เกิน 14 วัน • ใช้ร่วมกับแอปเช็คลิสต์วัสดุ กฟภ.: ตรวจด้วยแอป → บันทึกเลขที่เอกสารและผลตรวจ AI ลงทะเบียนนี้

Sheet ตั้งค่า Setup
B1: ตั้งค่าโครงการ / Project Setup
B2: กรอกเฉพาะช่องสีเหลือง • Fill in yellow cells only
B3: รายการ / Item | C3: ค่า / Value | D3: หมายเหตุ / Note
B4: ชื่อโครงการ (ไทย) / Project name (TH) | C4: โครงการก่อสร้างอาคาร (แก้ไขชื่อได้)
B5: ชื่อโครงการ (อังกฤษ) / Project name (EN) | C5: Building Construction Project
B6: ผู้ว่าจ้าง / Employer
B7: ผู้รับจ้าง / Contractor
B8: เลขที่สัญญา / Contract No.
B9: มูลค่าสัญญา / Contract Value = BAC (บาท) | C9: 12108000 | D9: อ่านจากเอกสารแผนงาน (Summary) – กรุณาตรวจสอบกับสัญญา
B10: วันเริ่มสัญญา / Commencement Date | C10: 46073 | D10: จากเอกสารแผนงาน 20-Feb-26
B11: ระยะเวลาสัญญา / Contract Duration (วัน/days) | C11: 270 | D11: จากเอกสารแผนงาน 270 วัน
B12: วันสิ้นสุดตามสัญญาเดิม / Original Completion | C12: =C10+C11-1 -> 46342 | D12: นับวันเริ่มเป็นวันที่ 1 (เอกสารระบุ 17-Nov-26 – พิมพ์ทับได้)
B13: ขยายเวลาที่อนุมัติแล้ว / Approved EOT (วัน) | C13: =SUM('ขยายเวลา EOT'!$J$8:$J$57) -> 0 | D13: ดึงจากชีต ขยายเวลา EOT อัตโนมัติ
B14: วันสิ้นสุดหลังขยายเวลา / Revised Completion | C14: =C12+C13 -> 46342 | D14: วันสิ้นสุดสัญญาเดิม + วันขยายเวลาที่อนุมัติ
B15: วันที่ตรวจวัดผลงาน / Status Date | C15: 46293 | D15: เปลี่ยนทุกครั้งที่อัปเดตรายงาน
B16: รอบตัดงวด S-Curve / Reporting Period | C16: ทุก 10 วัน / 10-day | D16: ทุก 10 วัน (ตัดวันที่ 10, 20, สิ้นเดือน) / รายสัปดาห์ / รายเดือน
B17: อัตราค่าปรับต่อวัน / LD Rate (% of contract per day) | C17: 0.001 | D17: ตัวอย่าง 0.10% – กรุณาใส่อัตราตามสัญญาจริง
B18: ค่าปรับขั้นต่ำต่อวัน / Minimum LD per day (บาท) | C18: 100 | D18: ตามที่สัญญากำหนด (ถ้าไม่มีใส่ 0)
B19: เกณฑ์เตือนค่าปรับสะสม / LD Warning Threshold | C19: 0.1 | D19: หลายสัญญากำหนดให้ผู้ว่าจ้างพิจารณาบอกเลิกได้เมื่อค่าปรับเกิน 10%
B20: ช่วงแผนงานล่วงหน้า / Look-ahead (วัน/days) | C20: 30 | D20: ใช้ในรายงานประจำงวด
B21: รายงานงวดที่ / Report No. | C21: 1
B22: ผู้จัดทำรายงาน / Prepared by
B24: หมวดงาน (WBS ระดับ 1) / Work Categories | C24: ชื่อหมวด / Category name | D24: หมายเหตุ
B25: เลขหมวด = ลำดับในตาราง (ใช้สร้างรหัส WBS เช่น 2.3)
B26: หมวดที่ 1 | C26: งานเตรียมการ / Preliminaries | D26: ตัวอย่างการจัดหมวดจากแผนงานเดิม – แก้ไขได้
B27: หมวดที่ 2 | C27: งานโครงสร้าง / Structural Works
B28: หมวดที่ 3 | C28: งานสถาปัตยกรรม / Architectural Works
B29: หมวดที่ 4 | C29: งานระบบ / MEP Works
B30: หมวดที่ 5 | C30: งานภายนอกและทดสอบระบบ / External & Commissioning
B31: หมวดที่ 6
B32: หมวดที่ 7
B33: หมวดที่ 8
B34: หมวดที่ 9
B35: หมวดที่ 10
B36: หมวดที่ 11
B37: หมวดที่ 12
B38: หมวดที่ 13
B39: หมวดที่ 14
B40: หมวดที่ 15
B41: หมวดที่ 16
B42: หมวดที่ 17
... B67: ตัวช่วยคำนวณแกนเวลา (อัตโนมัติ) / Timeline helper
B68: วันเริ่มแกนเวลา | C68: =MIN(C10,IF(COUNT('แผนงาน Schedule'!$H$7:$H$66)>0,MIN('แผนงาน Schedule'!$H$7:$H$66),C10),IF(COUNT('แผนงาน Schedule'!$K$7:$K$66)>0,MIN('แผนงาน Schedule'!$K$7:$K$66),C10),IF(COUNT('แผนงาน Schedule'!$M$7:$M$66)>0,MIN('แผนงาน Schedule'!$M$7:$M$66),C10)) -> 46072
B69: วันสิ้นสุดแกนเวลา | C69: =MAX(C14,C15,MAX('แผนงาน Schedule'!$I$7:$I$66),MAX('แผนงาน Schedule'!$L$7:$L$66),MAX('แผนงาน Schedule'!$N$7:$N$66),MAX('แผนงาน Schedule'!$V$7:$V$66)) -> 46346

Sheet Dashboard
B1: แดชบอร์ดควบคุมโครงการ / Project Control Dashboard
B2: คำนวณอัตโนมัติทั้งหมด • All values are calculated
B3: ข้อมูลอ้างอิง / Reference | C3: ค่า / Value | D3: ความหมาย / Meaning
B4: โครงการ / Project | C4: ='ตั้งค่า Setup'!C4 -> โครงการก่อสร้างอาคาร (แก้ไขชื่อได้)
B5: วันที่ตรวจวัด / Status Date | C5: ='ตั้งค่า Setup'!$C$15 -> 46293
B6: แหล่งข้อมูลผลงานจริง / Actual Data Source | C6: =IF(COUNT('แผนงาน Schedule'!$O$7:$O$66)>0,"ชีตแผนงาน (รายรายการ)","ชีต S-Curve (ค่าสะสมล่าสุด)") -> ชีต S-Curve (ค่าสะสมล่าสุด) | D6: ถ้ากรอก % จริงรายรายการ จะใช้ข้อมูลรายรายการก่อน
B7: ข้อมูลจริง ณ วันที่ / Data Date | C7: =IF(COUNT('แผนงาน Schedule'!$O$7:$O$66)>0,'ตั้งค่า Setup'!$C$15,IFERROR(INDEX('S-Curve'!$C$7:$C$86,MATCH(9.99E+307,'S-Curve'!$F$7:$F$86)),'ตั้งค่า Setup'!$C$15)) -> 46142 | D7: ถ้าไม่ตรงวันที่ตรวจวัด (สีแดง) = ยังไม่อัปเดตผลงานจริงล่าสุด
B8: ด้านเวลา / SCHEDULE PERFORMANCE | C8: ค่า / Value | D8: ความหมาย / Meaning
B9: วันเริ่มสัญญา / Commencement | C9: ='ตั้งค่า Setup'!$C$10 -> 46073
B10: วันสิ้นสุดสัญญาเดิม / Original Completion | C10: ='ตั้งค่า Setup'!C12 -> 46342
B11: ขยายเวลาที่อนุมัติ / Approved EOT (วัน) | C11: ='ตั้งค่า Setup'!C13 -> 0 | D11: จากทะเบียนขยายเวลา
B12: วันสิ้นสุดหลังขยายเวลา / Revised Completion | C12: ='ตั้งค่า Setup'!$C$14 -> 46342
B13: วันที่ดำเนินการแล้ว / Days Elapsed | C13: ='ตั้งค่า Setup'!$C$15-'ตั้งค่า Setup'!$C$10+1 -> 221 | D13: ณ วันที่ตรวจวัด นับวันเริ่มเป็นวันที่ 1
B14: % เวลาที่ใช้ไป / Time Elapsed | C14: =IFERROR(C13/(C12-C9+1),0) -> 0.81851852 | D14: เทียบกับระยะเวลารวมหลังขยายเวลา
B15: วันคงเหลือ / Days Remaining | C15: =C12-C5 -> 49 | D15: ติดลบ = เลยกำหนดสัญญาแล้ว
B16: % แผนเดิม / Baseline Planned % | C16: =SUMPRODUCT('แผนงาน Schedule'!$F$7:$F$66,('แผนงาน Schedule'!$I$7:$I$66<=C7)+('แผนงาน Schedule'!$H$7:$H$66<=C7)*('แผนงาน Schedule'!$I$7:$I$66>C7)*(C7-'แผนงาน Schedule'!$H$7:$H$66+1)/('แผนงาน Schedule'!$I$7:$I$66-'แผนงาน Schedule'!$H$7:$H$66+1)) -> 0.20820323 | D16: ผลงานที่ควรทำได้ตามแผนสัญญา ณ Data Date
B17: % แผนเร่งรัด / Revised Planned % | C17: =IF(C63,SUMPRODUCT('แผนงาน Schedule'!$F$7:$F$66,('แผนงาน Schedule'!$AA$7:$AA$66<=C7)+('แผนงาน Schedule'!$Z$7:$Z$66<=C7)*('แผนงาน Schedule'!$AA$7:$AA$66>C7)*(C7-'แผนงาน Schedule'!$Z$7:$Z$66+1)/('แผนงาน Schedule'!$AA$7:$AA$66-'แผนงาน Schedule'!$Z$7:$Z$66+1)),C16) -> 0.20820323 | D17: ถ้ายังไม่มีแผนเร่งรัด จะเท่ากับแผนเดิม
B18: ผลต่างเทียบแผนเร่งรัด / Variance vs Revised | C18: =C19-C17 -> -0.15690323 | D18: ใช้ติดตามว่าเดินตามแผนเร่งรัดได้หรือไม่
B19: % ผลงานจริง / Actual % | C19: =IF(COUNT('แผนงาน Schedule'!$O$7:$O$66)>0,'แผนงาน Schedule'!$O$67,IFERROR(INDEX('S-Curve'!$F$7:$F$86,MATCH(9.99E+307,'S-Curve'!$F$7:$F$86)),0)) -> 0.0513
B20: ผลต่าง / Variance (Actual − Baseline) | C20: =C19-C16 -> -0.15690323 | D20: ติดลบ = ช้ากว่าแผน
B21: ผลต่างคิดเป็นวัน / Variance in Days | C21: =C20*C69 -> -42.363871 | D21: ผลต่าง % × ระยะเวลาสัญญา (วิธีรายงานแบบไทย)
B22: SPI (ดัชนีเวลา) | C22: =IFERROR(C37/C36,0) -> 0.24639388 | D22: EV ÷ PV • ≥1 ตามแผน / 0.9–1 เฝ้าระวัง / <0.9 ล่าช้ามาก
B23: Earned Schedule – ES (วัน) | C23: =C68 -> 22.27852 | D23: งานที่ทำได้จริง เท่ากับแผนของวันที่เท่าใด (นับจากวันเริ่ม)
B24: Actual Time – AT (วัน) | C24: =C7-C9+1 -> 70 | D24: เวลาที่ใช้จริงถึง Data Date
B25: SV(t) – ช้ากว่าแผนจริง (วัน) | C25: =C23-C24 -> -47.72148 | D25: ติดลบ = ช้ากว่าแผนกี่วัน (แม่นกว่า SPI ในช่วงท้ายโครงการ)
B26: SPI(t) (ดัชนีเวลาเชิงวัน) | C26: =IFERROR(C23/C24,0) -> 0.31826457 | D26: ES ÷ AT
B27: คาดการณ์วันแล้วเสร็จ / Forecast Completion | C27: =IF(C19>=1,C7,IF(COUNT('แผนงาน Schedule'!$O$7:$O$66)>0,MAX('แผนงาน Schedule'!$V$7:$V$66),IFERROR(C9+ROUND(C69/C26,0)-1,"-"))) -> 46920 | D27: ถ้ามี % รายรายการ ใช้วันเสร็จคาดการณ์รายงาน • ถ้าไม่มี ใช้ IEAC(t) = ระยะเวลา ÷ SPI(t)
B28: คาดว่าล่าช้ากว่าสัญญา / Forecast Delay (วัน) | C28: =IFERROR(MAX(0,C27-C12),"-") -> 578 | D28: เทียบกับวันสิ้นสุดหลังขยายเวลา
B29: อัตราผลงานจริงเฉลี่ย / Actual Rate (%/วัน) | C29: =IFERROR(C19/C24,0) -> 0.00073285714
B30: อัตราที่ต้องทำ / Required Rate (%/วัน) | C30: =IF(C19>=1,0,IF(C12-C7>0,(1-C19)/(C12-C7),"เลยกำหนดแล้ว")) -> 0.0047435 | D30: เพื่อให้เสร็จทันวันสิ้นสุดหลังขยายเวลา
B31: ต้องเร่งงาน / Acceleration Needed (เท่า) | C31: =IFERROR(C30/C29,"-") -> 6.4726121 | D31: เท่าของอัตราผลงานปัจจุบัน
B32: สถานะโครงการ / Overall Status | C32: =IF(C19>=1,"แล้วเสร็จ / Completed",IF(C22>=1,"ตามแผน / On Track",IF(C22>=0.9,"เฝ้าระวัง / At Risk","ล่าช้ามาก / Critical Delay"))) -> ล่าช้ามาก / Critical Delay
B33: จำนวนรายการที่ล่าช้า / Items Behind | C33: =COUNTIF('แผนงาน Schedule'!$X$7:$X$66,"*ล่าช้า*")+COUNTIF('แผนงาน Schedule'!$X$7:$X$66,"*เกินกำหนด*") -> 15 | D33: จากชีตแผนงาน (ต้องกรอก % รายรายการ)
B34: ด้านต้นทุน / COST PERFORMANCE (EVM) | C34: ค่า / Value | D34: ความหมาย / Meaning
B35: BAC – งบประมาณรวม / Budget at Completion | C35: ='ตั้งค่า Setup'!$C$9 -> 12108000 | D35: มูลค่าสัญญา
B36: PV – มูลค่างานตามแผน / Planned Value | C36: =C16*C35 -> 2520924.7 | D36: มูลค่างานที่ควรทำได้ตามแผน
B37: EV – มูลค่างานที่ทำได้จริง / Earned Value | C37: =C19*C35 -> 621140.4 | D37: มูลค่างานที่ทำเสร็จจริง (ตามราคาสัญญา)
B38: AC – ต้นทุนจริงสะสม / Actual Cost | C38: =SUMIFS('S-Curve'!$K$7:$K$86,'S-Curve'!$C$7:$C$86,"<="&C7) -> 0 | D38: เงินที่จ่ายไปจริง (กรอกในชีต S-Curve) • ถ้าเป็น 0 จะไม่คำนวณ CPI
B39: SV – ผลต่างด้านเวลา (บาท) / Schedule Variance | C39: =C37-C36 -> -1899784.3 | D39: EV − PV • ติดลบ = งานช้ากว่าแผน
B40: CV – ผลต่างด้านต้นทุน / Cost Variance | C40: =IF(C38>0,C37-C38,"-") -> - | D40: EV − AC • ติดลบ = ใช้เงินเกินมูลค่างานที่ได้
B41: CPI (ดัชนีต้นทุน) | C41: =IF(C38>0,C37/C38,"-") -> - | D41: EV ÷ AC • <1 = ใช้เงินเกิน
B42: EAC – ประมาณการต้นทุนเมื่อแล้วเสร็จ | C42: =IF(C38>0,C35/C41,"-") -> - | D42: BAC ÷ CPI
B43: ETC – ต้นทุนที่ต้องใช้อีก | C43: =IF(C38>0,C42-C38,"-") -> - | D43: EAC − AC
B44: VAC – กำไร/ขาดทุนจากงบ | C44: =IF(C38>0,C35-C42,"-") -> - | D44: BAC − EAC • ติดลบ = คาดว่าเกินงบ
B45: TCPI – ประสิทธิภาพที่ต้องทำให้ได้ | C45: =IF(C38>0,IFERROR((C35-C37)/(C35-C38),"-"),"-") -> - | D45: (BAC − EV) ÷ (BAC − AC) • >1.1 = ยากที่จะอยู่ในงบ
B46: เงินเบิกจ่ายสะสม / Certified Payment | C46: =SUMIFS('S-Curve'!$M$7:$M$86,'S-Curve'!$C$7:$C$86,"<="&C5) -> 621140.4 | D46: จากชีต S-Curve
B47: % เบิกจ่ายต่อมูลค่าสัญญา | C47: =IFERROR(C46/C35,0) -> 0.0513
B48: ขยายเวลาและค่าปรับ / EOT & LIQUIDATED DAMAGES | C48: ค่า / Value | D48: ความหมาย / Meaning
B49: ขอขยายเวลารวม / EOT Claimed (วัน) | C49: =SUM('ขยายเวลา EOT'!$F$8:$F$57) -> 0
B50: อนุมัติแล้ว / EOT Approved (วัน) | C50: =SUM('ขยายเวลา EOT'!$J$8:$J$57) -> 0
B51: รอพิจารณา / EOT Pending (วัน) | C51: =SUMIF('ขยายเวลา EOT'!$I$8:$I$57,"รอพิจารณา / Pending",'ขยายเวลา EOT'!$F$8:$F$57) -> 0 | D51: ติดตามผลให้ได้ข้อยุติก่อนครบสัญญา
B52: ค่าปรับต่อวัน / LD per Day (บาท) | C52: =MAX('ตั้งค่า Setup'!C18,'ตั้งค่า Setup'!C17*C35) -> 12108 | D52: MAX(ค่าปรับขั้นต่ำ, อัตรา × มูลค่าสัญญา)
B53: วันที่ถูกปรับแล้ว / LD Days to Date | C53: =MAX(0,C5-C12) -> 0 | D53: ณ วันที่ตรวจวัด
B54: ค่าปรับเกิดขึ้นแล้ว / LD Incurred (บาท) | C54: =C53*C52 -> 0
B55: ค่าปรับคาดการณ์ / Forecast LD (บาท) | C55: =IFERROR(C28*C52,0) -> 6998424 | D55: ถ้าเสร็จตามวันคาดการณ์
B56: ค่าปรับคาดการณ์ % ของสัญญา | C56: =IFERROR(C55/C35,0) -> 0.578
B57: สัญญาณเตือนค่าปรับ / LD Alert | C57: =IF(C56>'ตั้งค่า Setup'!C19,"⚠ เกินเกณฑ์ "&TEXT('ตั้งค่า Setup'!C19,"0%")&" – ความเสี่ยงถูกบอกเลิกสัญญา",IF(C56>0,"⚠ มีค่าปรับคาดการณ์","✓ ไม่มีค่าปรับคาดการณ์")) -> ⚠ เกินเกณฑ์ 10% – ความเสี่ยงถูกบอกเลิกสัญญา
B58: ตรวจสอบน้ำหนักงานรวม / Weight Check | C58: =IF(ABS('แผนงาน Schedule'!$F$67-1)<0.0001,"✓ ครบ 100%","⚠ น้ำหนักรวม = "&TEXT('แผนงาน Schedule'!$F$67,"0.00%")) -> ✓ ครบ 100% | D58: ต้องเท่ากับ 100%
B61: ตัวช่วยคำนวณ (อัตโนมัติ) / Calculation helpers
B62: N = จำนวนงวดที่ Baseline ≤ Actual | C62: =COUNTIF('S-Curve'!$D$7:$D$86,"<="&C19) -> 3
B63: มีแผนเร่งรัดหรือไม่ (TRUE/FALSE) | C63: =COUNT('แผนงาน Schedule'!$K$7:$K$66)+COUNT('แผนงาน Schedule'!$L$7:$L$66)>0 -> FALSE
B64: จำนวนงวดทั้งหมด | C64: =COUNT('S-Curve'!$D$7:$D$86) -> 28
B65: วันที่ ES (Earned Schedule date) | C65: =IF(C62=0,'ตั้งค่า Setup'!$C$68-1+IFERROR(C19/INDEX('S-Curve'!$D$7:$D$86,1),0)*(INDEX('S-Curve'!$C$7:$C$86,1)-'ตั้งค่า Setup'!$C$68+1),IF(C62>=C64,INDEX('S-Curve'!$C$7:$C$86,C64),INDEX('S-Curve'!$C$7:$C$86,C62)+IF(INDEX('S-Curve'!$D$7:$D$86,C62+1)>INDEX('S-Curve'!$D$7:$D$86,C62),(C19-INDEX('S-Curve'!$D$7:$D$86,C62))/(INDEX('S-Curve'!$D$7:$D$86,C62+1)-INDEX('S-Curve'!$D$7:$D$86,C62))*(INDEX('S-Curve'!$C$7:$C$86,C62+1)-INDEX('S-Curve'!$C$7:$C$86,C62)),0))) -> 46094.279
B68: ES (วัน) | C68: =MAX(0,C65-C9+1) -> 22.27852
B69: ระยะเวลาสัญญาเดิม (วัน) | C69: ='ตั้งค่า Setup'!$C$11 -> 270

Sheet รายงาน Report
B1: รายงานความก้าวหน้าโครงการ / PROJECT PROGRESS REPORT
B2: โครงการ / Project: | D2: ='ตั้งค่า Setup'!C4&IF('ตั้งค่า Setup'!C5<>""," ("&'ตั้งค่า Setup'!C5&")","") -> โครงการก่อสร้างอาคาร (แก้ไขชื่อได้) (Building Construction Project) | G2: รายงานงวดที่ / Report No.: | I2: ='ตั้งค่า Setup'!C21 -> 1
B3: ผู้ว่าจ้าง / Employer: | D3: ='ตั้งค่า Setup'!C6&"" | G3: วันที่ตรวจวัด / Status Date: | I3: ='ตั้งค่า Setup'!$C$15 -> 46293
B4: ผู้รับจ้าง / Contractor: | D4: ='ตั้งค่า Setup'!C7&"" | G4: เลขที่สัญญา / Contract No.: | I4: ='ตั้งค่า Setup'!C8&""
B6: 1. สรุปผลการดำเนินงาน / Executive Summary
B7: ระยะเวลาที่ใช้ไป / Time Elapsed | D7: =Dashboard!C14 -> 0.81851852
B8: แผนเดิม / Baseline Planned | D8: =Dashboard!C16 -> 0.20820323
B9: แผนเร่งรัด / Revised Planned | D9: =Dashboard!C17 -> 0.20820323
B10: ผลงานจริง / Actual Progress | D10: =Dashboard!C19 -> 0.0513
B11: ผลต่าง / Variance | D11: =Dashboard!C20 -> -0.15690323
B12: SPI | SPI(t) | D12: =TEXT(Dashboard!C22,"0.00")&" | "&TEXT(Dashboard!C26,"0.00") -> 0.25 | 0.32
B13: ช้ากว่าแผน / SV(t) (วัน) | D13: =Dashboard!C25 -> -47.72148
B14: คาดว่าแล้วเสร็จ / Forecast Completion | D14: =Dashboard!C27 -> 46920
B15: คาดว่าล่าช้า / Forecast Delay (วัน) | D15: =Dashboard!C28 -> 578
B16: ค่าปรับคาดการณ์ / Forecast LD (฿) | D16: =Dashboard!C55 -> 6998424
B17: CPI (ดัชนีต้นทุน) | D17: =Dashboard!C41 -> -
B18: สถานะ / Status | D18: =Dashboard!C32 -> ล่าช้ามาก / Critical Delay
B19: ข้อมูลจริง ณ / Data Date | D19: =Dashboard!C7 -> 46142
B21: 2. ความก้าวหน้าตามหมวดงาน / Progress by WBS Category
B22: หมวด No. | C22: หมวดงาน / Category | D22: น้ำหนัก Weight | E22: แผน ณ Data Date Planned | F22: จริง Actual | G22: ผลต่าง Variance | H22: SPI | I22: ผลงานแผน (% โครงการ) | J22: ผลงานจริง (% โครงการ)
B23: =IF('ตั้งค่า Setup'!$C$26="","",1) -> 1 | C23: =IF('ตั้งค่า Setup'!$C$26="","",'ตั้งค่า Setup'!$C$26) -> งานเตรียมการ / Preliminaries | D23: =IF(C23="","",SUMIF('แผนงาน Schedule'!$B$7:$B$66,C23,'แผนงาน Schedule'!$F$7:$F$66)) -> 0.0811 | E23: =IF(OR(C23="",N(D23)=0),"",I23/D23) -> 1 | F23: =IF(OR(C23="",N(D23)=0),"",J23/D23) -> 0 | G23: =IF(E23="","",F23-E23) -> -1 | H23: =IF(OR(E23="",N(E23)=0),"",F23/E23) -> 0 | I23: =IF(C23="","",SUMPRODUCT(('แผนงาน Schedule'!$B$7:$B$66=C23)*'แผนงาน Schedule'!$F$7:$F$66*(('แผนงาน Schedule'!$I$7:$I$66<=Dashboard!$C$7)+('แผนงาน Schedule'!$H$7:$H$66<=Dashboard!$C$7)*('แผนงาน Schedule'!$I$7:$I$66>Dashboard!$C$7)*(Dashboard!$C$7-'แผนงาน Schedule'!$H$7:$H$66+1)/('แผนงาน Schedule'!$I$7:$I$66-'แผนงาน Schedule'!$H$7:$H$66+1)))) -> 0.0811 | J23: =IF(C23="","",SUMPRODUCT(('แผนงาน Schedule'!$B$7:$B$66=C23)*'แผนงาน Schedule'!$F$7:$F$66*'แผนงาน Schedule'!$O$7:$O$66)) -> 0
B24: =IF('ตั้งค่า Setup'!$C$27="","",2) -> 2 | C24: =IF('ตั้งค่า Setup'!$C$27="","",'ตั้งค่า Setup'!$C$27) -> งานโครงสร้าง / Structural Works | D24: =IF(C24="","",SUMIF('แผนงาน Schedule'!$B$7:$B$66,C24,'แผนงาน Schedule'!$F$7:$F$66)) -> 0.285 | E24: =IF(OR(C24="",N(D24)=0),"",I24/D24) -> 0.44597623 | F24: =IF(OR(C24="",N(D24)=0),"",J24/D24) -> 0 | G24: =IF(E24="","",F24-E24) -> -0.44597623 | H24: =IF(OR(E24="",N(E24)=0),"",F24/E24) -> 0 | I24: =IF(C24="","",SUMPRODUCT(('แผนงาน Schedule'!$B$7:$B$66=C24)*'แผนงาน Schedule'!$F$7:$F$66*(('แผนงาน Schedule'!$I$7:$I$66<=Dashboard!$C$7)+('แผนงาน Schedule'!$H$7:$H$66<=Dashboard!$C$7)*('แผนงาน Schedule'!$I$7:$I$66>Dashboard!$C$7)*(Dashboard!$C$7-'แผนงาน Schedule'!$H$7:$H$66+1)/('แผนงาน Schedule'!$I$7:$I$66-'แผนงาน Schedule'!$H$7:$H$66+1)))) -> 0.12710323 | J24: =IF(C24="","",SUMPRODUCT(('แผนงาน Schedule'!$B$7:$B$66=C24)*'แผนงาน Schedule'!$F$7:$F$66*'แผนงาน Schedule'!$O$7:$O$66)) -> 0
B25: =IF('ตั้งค่า Setup'!$C$28="","",3) -> 3 | C25: =IF('ตั้งค่า Setup'!$C$28="","",'ตั้งค่า Setup'!$C$28) -> งานสถาปัตยกรรม / Architectural Works | D25: =IF(C25="","",SUMIF('แผนงาน Schedule'!$B$7:$B$66,C25,'แผนงาน Schedule'!$F$7:$F$66)) -> 0.2407 | E25: =IF(OR(C25="",N(D25)=0),"",I25/D25) -> 0 | F25: =IF(OR(C25="",N(D25)=0),"",J25/D25) -> 0 | G25: =IF(E25="","",F25-E25) -> 0 | H25: =IF(OR(E25="",N(E25)=0),"",F25/E25) | I25: =IF(C25="","",SUMPRODUCT(('แผนงาน Schedule'!$B$7:$B$66=C25)*'แผนงาน Schedule'!$F$7:$F$66*(('แผนงาน Schedule'!$I$7:$I$66<=Dashboard!$C$7)+('แผนงาน Schedule'!$H$7:$H$66<=Dashboard!$C$7)*('แผนงาน Schedule'!$I$7:$I$66>Dashboard!$C$7)*(Dashboard!$C$7-'แผนงาน Schedule'!$H$7:$H$66+1)/('แผนงาน Schedule'!$I$7:$I$66-'แผนงาน Schedule'!$H$7:$H$66+1)))) -> 0 | J25: =IF(C25="","",SUMPRODUCT(('แผนงาน Schedule'!$B$7:$B$66=C25)*'แผนงาน Schedule'!$F$7:$F$66*'แผนงาน Schedule'!$O$7:$O$66)) -> 0
B26: =IF('ตั้งค่า Setup'!$C$29="","",4) -> 4 | C26: =IF('ตั้งค่า Setup'!$C$29="","",'ตั้งค่า Setup'!$C$29) -> งานระบบ / MEP Works | D26: =IF(C26="","",SUMIF('แผนงาน Schedule'!$B$7:$B$66,C26,'แผนงาน Schedule'!$F$7:$F$66)) -> 0.2769 | E26: =IF(OR(C26="",N(D26)=0),"",I26/D26) -> 0 | F26: =IF(OR(C26="",N(D26)=0),"",J26/D26) -> 0 | G26: =IF(E26="","",F26-E26) -> 0 | H26: =IF(OR(E26="",N(E26)=0),"",F26/E26) | I26: =IF(C26="","",SUMPRODUCT(('แผนงาน Schedule'!$B$7:$B$66=C26)*'แผนงาน Schedule'!$F$7:$F$66*(('แผนงาน Schedule'!$I$7:$I$66<=Dashboard!$C$7)+('แผนงาน Schedule'!$H$7:$H$66<=Dashboard!$C$7)*('แผนงาน Schedule'!$I$7:$I$66>Dashboard!$C$7)*(Dashboard!$C$7-'แผนงาน Schedule'!$H$7:$H$66+1)/('แผนงาน Schedule'!$I$7:$I$66-'แผนงาน Schedule'!$H$7:$H$66+1)))) -> 0 | J26: =IF(C26="","",SUMPRODUCT(('แผนงาน Schedule'!$B$7:$B$66=C26)*'แผนงาน Schedule'!$F$7:$F$66*'แผนงาน Schedule'!$O$7:$O$66)) -> 0
B27: =IF('ตั้งค่า Setup'!$C$30="","",5) -> 5 | C27: =IF('ตั้งค่า Setup'!$C$30="","",'ตั้งค่า Setup'!$C$30) -> งานภายนอกและทดสอบระบบ / External & Commissioning | D27: =IF(C27="","",SUMIF('แผนงาน Schedule'!$B$7:$B$66,C27,'แผนงาน Schedule'!$F$7:$F$66)) -> 0.1163 | E27: =IF(OR(C27="",N(D27)=0),"",I27/D27) -> 0 | F27: =IF(OR(C27="",N(D27)=0),"",J27/D27) -> 0 | G27: =IF(E27="","",F27-E27) -> 0 | H27: =IF(OR(E27="",N(E27)=0),"",F27/E27) | I27: =IF(C27="","",SUMPRODUCT(('แผนงาน Schedule'!$B$7:$B$66=C27)*'แผนงาน Schedule'!$F$7:$F$66*(('แผนงาน Schedule'!$I$7:$I$66<=Dashboard!$C$7)+('แผนงาน Schedule'!$H$7:$H$66<=Dashboard!$C$7)*('แผนงาน Schedule'!$I$7:$I$66>Dashboard!$C$7)*(Dashboard!$C$7-'แผนงาน Schedule'!$H$7:$H$66+1)/('แผนงาน Schedule'!$I$7:$I$66-'แผนงาน Schedule'!$H$7:$H$66+1)))) -> 0 | J27: =IF(C27="","",SUMPRODUCT(('แผนงาน Schedule'!$B$7:$B$66=C27)*'แผนงาน Schedule'!$F$7:$F$66*'แผนงาน Schedule'!$O$7:$O$66)) -> 0
B28: =IF('ตั้งค่า Setup'!$C$31="","",6) | C28: =IF('ตั้งค่า Setup'!$C$31="","",'ตั้งค่า Setup'!$C$31) | D28: =IF(C28="","",SUMIF('แผนงาน Schedule'!$B$7:$B$66,C28,'แผนงาน Schedule'!$F$7:$F$66)) | E28: =IF(OR(C28="",N(D28)=0),"",I28/D28) | F28: =IF(OR(C28="",N(D28)=0),"",J28/D28) | G28: =IF(E28="","",F28-E28) | H28: =IF(OR(E28="",N(E28)=0),"",F28/E28) | I28: =IF(C28="","",SUMPRODUCT(('แผนงาน Schedule'!$B$7:$B$66=C28)*'แผนงาน Schedule'!$F$7:$F$66*(('แผนงาน Schedule'!$I$7:$I$66<=Dashboard!$C$7)+('แผนงาน Schedule'!$H$7:$H$66<=Dashboard!$C$7)*('แผนงาน Schedule'!$I$7:$I$66>Dashboard!$C$7)*(Dashboard!$C$7-'แผนงาน Schedule'!$H$7:$H$66+1)/('แผนงาน Schedule'!$I$7:$I$66-'แผนงาน Schedule'!$H$7:$H$66+1)))) | J28: =IF(C28="","",SUMPRODUCT(('แผนงาน Schedule'!$B$7:$B$66=C28)*'แผนงาน Schedule'!$F$7:$F$66*'แผนงาน Schedule'!$O$7:$O$66))
B29: =IF('ตั้งค่า Setup'!$C$32="","",7) | C29: =IF('ตั้งค่า Setup'!$C$32="","",'ตั้งค่า Setup'!$C$32) | D29: =IF(C29="","",SUMIF('แผนงาน Schedule'!$B$7:$B$66,C29,'แผนงาน Schedule'!$F$7:$F$66)) | E29: =IF(OR(C29="",N(D29)=0),"",I29/D29) | F29: =IF(OR(C29="",N(D29)=0),"",J29/D29) | G29: =IF(E29="","",F29-E29) | H29: =IF(OR(E29="",N(E29)=0),"",F29/E29) | I29: =IF(C29="","",SUMPRODUCT(('แผนงาน Schedule'!$B$7:$B$66=C29)*'แผนงาน Schedule'!$F$7:$F$66*(('แผนงาน Schedule'!$I$7:$I$66<=Dashboard!$C$7)+('แผนงาน Schedule'!$H$7:$H$66<=Dashboard!$C$7)*('แผนงาน Schedule'!$I$7:$I$66>Dashboard!$C$7)*(Dashboard!$C$7-'แผนงาน Schedule'!$H$7:$H$66+1)/('แผนงาน Schedule'!$I$7:$I$66-'แผนงาน Schedule'!$H$7:$H$66+1)))) | J29: =IF(C29="","",SUMPRODUCT(('แผนงาน Schedule'!$B$7:$B$66=C29)*'แผนงาน Schedule'!$F$7:$F$66*'แผนงาน Schedule'!$O$7:$O$66))
B30: =IF('ตั้งค่า Setup'!$C$33="","",8) | C30: =IF('ตั้งค่า Setup'!$C$33="","",'ตั้งค่า Setup'!$C$33) | D30: =IF(C30="","",SUMIF('แผนงาน Schedule'!$B$7:$B$66,C30,'แผนงาน Schedule'!$F$7:$F$66)) | E30: =IF(OR(C30="",N(D30)=0),"",I30/D30) | F30: =IF(OR(C30="",N(D30)=0),"",J30/D30) | G30: =IF(E30="","",F30-E30) | H30: =IF(OR(E30="",N(E30)=0),"",F30/E30) | I30: =IF(C30="","",SUMPRODUCT(('แผนงาน Schedule'!$B$7:$B$66=C30)*'แผนงาน Schedule'!$F$7:$F$66*(('แผนงาน Schedule'!$I$7:$I$66<=Dashboard!$C$7)+('แผนงาน Schedule'!$H$7:$H$66<=Dashboard!$C$7)*('แผนงาน Schedule'!$I$7:$I$66>Dashboard!$C$7)*(Dashboard!$C$7-'แผนงาน Schedule'!$H$7:$H$66+1)/('แผนงาน Schedule'!$I$7:$I$66-'แผนงาน Schedule'!$H$7:$H$66+1)))) | J30: =IF(C30="","",SUMPRODUCT(('แผนงาน Schedule'!$B$7:$B$66=C30)*'แผนงาน Schedule'!$F$7:$F$66*'แผนงาน Schedule'!$O$7:$O$66))
B31: =IF('ตั้งค่า Setup'!$C$34="","",9) | C31: =IF('ตั้งค่า Setup'!$C$34="","",'ตั้งค่า Setup'!$C$34) | D31: =IF(C31="","",SUMIF('แผนงาน Schedule'!$B$7:$B$66,C31,'แผนงาน Schedule'!$F$7:$F$66)) | E31: =IF(OR(C31="",N(D31)=0),"",I31/D31) | F31: =IF(OR(C31="",N(D31)=0),"",J31/D31) | G31: =IF(E31="","",F31-E31) | H31: =IF(OR(E31="",N(E31)=0),"",F31/E31) | I31: =IF(C31="","",SUMPRODUCT(('แผนงาน Schedule'!$B$7:$B$66=C31)*'แผนงาน Schedule'!$F$7:$F$66*(('แผนงาน Schedule'!$I$7:$I$66<=Dashboard!$C$7)+('แผนงาน Schedule'!$H$7:$H$66<=Dashboard!$C$7)*('แผนงาน Schedule'!$I$7:$I$66>Dashboard!$C$7)*(Dashboard!$C$7-'แผนงาน Schedule'!$H$7:$H$66+1)/('แผนงาน Schedule'!$I$7:$I$66-'แผนงาน Schedule'!$H$7:$H$66+1)))) | J31: =IF(C31="","",SUMPRODUCT(('แผนงาน Schedule'!$B$7:$B$66=C31)*'แผนงาน Schedule'!$F$7:$F$66*'แผนงาน Schedule'!$O$7:$O$66))
B32: =IF('ตั้งค่า Setup'!$C$35="","",10) | C32: =IF('ตั้งค่า Setup'!$C$35="","",'ตั้งค่า Setup'!$C$35) | D32: =IF(C32="","",SUMIF('แผนงาน Schedule'!$B$7:$B$66,C32,'แผนงาน Schedule'!$F$7:$F$66)) | E32: =IF(OR(C32="",N(D32)=0),"",I32/D32) | F32: =IF(OR(C32="",N(D32)=0),"",J32/D32) | G32: =IF(E32="","",F32-E32) | H32: =IF(OR(E32="",N(E32)=0),"",F32/E32) | I32: =IF(C32="","",SUMPRODUCT(('แผนงาน Schedule'!$B$7:$B$66=C32)*'แผนงาน Schedule'!$F$7:$F$66*(('แผนงาน Schedule'!$I$7:$I$66<=Dashboard!$C$7)+('แผนงาน Schedule'!$H$7:$H$66<=Dashboard!$C$7)*('แผนงาน Schedule'!$I$7:$I$66>Dashboard!$C$7)*(Dashboard!$C$7-'แผนงาน Schedule'!$H$7:$H$66+1)/('แผนงาน Schedule'!$I$7:$I$66-'แผนงาน Schedule'!$H$7:$H$66+1)))) | J32: =IF(C32="","",SUMPRODUCT(('แผนงาน Schedule'!$B$7:$B$66=C32)*'แผนงาน Schedule'!$F$7:$F$66*'แผนงาน Schedule'!$O$7:$O$66))
B33: =IF('ตั้งค่า Setup'!$C$36="","",11) | C33: =IF('ตั้งค่า Setup'!$C$36="","",'ตั้งค่า Setup'!$C$36) | D33: =IF(C33="","",SUMIF('แผนงาน Schedule'!$B$7:$B$66,C33,'แผนงาน Schedule'!$F$7:$F$66)) | E33: =IF(OR(C33="",N(D33)=0),"",I33/D33) | F33: =IF(OR(C33="",N(D33)=0),"",J33/D33) | G33: =IF(E33="","",F33-E33) | H33: =IF(OR(E33="",N(E33)=0),"",F33/E33) | I33: =IF(C33="","",SUMPRODUCT(('แผนงาน Schedule'!$B$7:$B$66=C33)*'แผนงาน Schedule'!$F$7:$F$66*(('แผนงาน Schedule'!$I$7:$I$66<=Dashboard!$C$7)+('แผนงาน Schedule'!$H$7:$H$66<=Dashboard!$C$7)*('แผนงาน Schedule'!$I$7:$I$66>Dashboard!$C$7)*(Dashboard!$C$7-'แผนงาน Schedule'!$H$7:$H$66+1)/('แผนงาน Schedule'!$I$7:$I$66-'แผนงาน Schedule'!$H$7:$H$66+1)))) | J33: =IF(C33="","",SUMPRODUCT(('แผนงาน Schedule'!$B$7:$B$66=C33)*'แผนงาน Schedule'!$F$7:$F$66*'แผนงาน Schedule'!$O$7:$O$66))
B34: =IF('ตั้งค่า Setup'!$C$37="","",12) | C34: =IF('ตั้งค่า Setup'!$C$37="","",'ตั้งค่า Setup'!$C$37) | D34: =IF(C34="","",SUMIF('แผนงาน Schedule'!$B$7:$B$66,C34,'แผนงาน Schedule'!$F$7:$F$66)) | E34: =IF(OR(C34="",N(D34)=0),"",I34/D34) | F34: =IF(OR(C34="",N(D34)=0),"",J34/D34) | G34: =IF(E34="","",F34-E34) | H34: =IF(OR(E34="",N(E34)=0),"",F34/E34) | I34: =IF(C34="","",SUMPRODUCT(('แผนงาน Schedule'!$B$7:$B$66=C34)*'แผนงาน Schedule'!$F$7:$F$66*(('แผนงาน Schedule'!$I$7:$I$66<=Dashboard!$C$7)+('แผนงาน Schedule'!$H$7:$H$66<=Dashboard!$C$7)*('แผนงาน Schedule'!$I$7:$I$66>Dashboard!$C$7)*(Dashboard!$C$7-'แผนงาน Schedule'!$H$7:$H$66+1)/('แผนงาน Schedule'!$I$7:$I$66-'แผนงาน Schedule'!$H$7:$H$66+1)))) | J34: =IF(C34="","",SUMPRODUCT(('แผนงาน Schedule'!$B$7:$B$66=C34)*'แผนงาน Schedule'!$F$7:$F$66*'แผนงาน Schedule'!$O$7:$O$66))
B35: =IF('ตั้งค่า Setup'!$C$38="","",13) | C35: =IF('ตั้งค่า Setup'!$C$38="","",'ตั้งค่า Setup'!$C$38) | D35: =IF(C35="","",SUMIF('แผนงาน Schedule'!$B$7:$B$66,C35,'แผนงาน Schedule'!$F$7:$F$66)) | E35: =IF(OR(C35="",N(D35)=0),"",I35/D35) | F35: =IF(OR(C35="",N(D35)=0),"",J35/D35) | G35: =IF(E35="","",F35-E35) | H35: =IF(OR(E35="",N(E35)=0),"",F35/E35) | I35: =IF(C35="","",SUMPRODUCT(('แผนงาน Schedule'!$B$7:$B$66=C35)*'แผนงาน Schedule'!$F$7:$F$66*(('แผนงาน Schedule'!$I$7:$I$66<=Dashboard!$C$7)+('แผนงาน Schedule'!$H$7:$H$66<=Dashboard!$C$7)*('แผนงาน Schedule'!$I$7:$I$66>Dashboard!$C$7)*(Dashboard!$C$7-'แผนงาน Schedule'!$H$7:$H$66+1)/('แผนงาน Schedule'!$I$7:$I$66-'แผนงาน Schedule'!$H$7:$H$66+1)))) | J35: =IF(C35="","",SUMPRODUCT(('แผนงาน Schedule'!$B$7:$B$66=C35)*'แผนงาน Schedule'!$F$7:$F$66*'แผนงาน Schedule'!$O$7:$O$66))
B36: =IF('ตั้งค่า Setup'!$C$39="","",14) | C36: =IF('ตั้งค่า Setup'!$C$39="","",'ตั้งค่า Setup'!$C$39) | D36: =IF(C36="","",SUMIF('แผนงาน Schedule'!$B$7:$B$66,C36,'แผนงาน Schedule'!$F$7:$F$66)) | E36: =IF(OR(C36="",N(D36)=0),"",I36/D36) | F36: =IF(OR(C36="",N(D36)=0),"",J36/D36) | G36: =IF(E36="","",F36-E36) | H36: =IF(OR(E36="",N(E36)=0),"",F36/E36) | I36: =IF(C36="","",SUMPRODUCT(('แผนงาน Schedule'!$B$7:$B$66=C36)*'แผนงาน Schedule'!$F$7:$F$66*(('แผนงาน Schedule'!$I$7:$I$66<=Dashboard!$C$7)+('แผนงาน Schedule'!$H$7:$H$66<=Dashboard!$C$7)*('แผนงาน Schedule'!$I$7:$I$66>Dashboard!$C$7)*(Dashboard!$C$7-'แผนงาน Schedule'!$H$7:$H$66+1)/('แผนงาน Schedule'!$I$7:$I$66-'แผนงาน Schedule'!$H$7:$H$66+1)))) | J36: =IF(C36="","",SUMPRODUCT(('แผนงาน Schedule'!$B$7:$B$66=C36)*'แผนงาน Schedule'!$F$7:$F$66*'แผนงาน Schedule'!$O$7:$O$66))
B37: =IF('ตั้งค่า Setup'!$C$40="","",15) | C37: =IF('ตั้งค่า Setup'!$C$40="","",'ตั้งค่า Setup'!$C$40) | D37: =IF(C37="","",SUMIF('แผนงาน Schedule'!$B$7:$B$66,C37,'แผนงาน Schedule'!$F$7:$F$66)) | E37: =IF(OR(C37="",N(D37)=0),"",I37/D37) | F37: =IF(OR(C37="",N(D37)=0),"",J37/D37) | G37: =IF(E37="","",F37-E37) | H37: =IF(OR(E37="",N(E37)=0),"",F37/E37) | I37: =IF(C37="","",SUMPRODUCT(('แผนงาน Schedule'!$B$7:$B$66=C37)*'แผนงาน Schedule'!$F$7:$F$66*(('แผนงาน Schedule'!$I$7:$I$66<=Dashboard!$C$7)+('แผนงาน Schedule'!$H$7:$H$66<=Dashboard!$C$7)*('แผนงาน Schedule'!$I$7:$I$66>Dashboard!$C$7)*(Dashboard!$C$7-'แผนงาน Schedule'!$H$7:$H$66+1)/('แผนงาน Schedule'!$I$7:$I$66-'แผนงาน Schedule'!$H$7:$H$66+1)))) | J37: =IF(C37="","",SUMPRODUCT(('แผนงาน Schedule'!$B$7:$B$66=C37)*'แผนงาน Schedule'!$F$7:$F$66*'แผนงาน Schedule'!$O$7:$O$66))
B38: =IF('ตั้งค่า Setup'!$C$41="","",16) | C38: =IF('ตั้งค่า Setup'!$C$41="","",'ตั้งค่า Setup'!$C$41) | D38: =IF(C38="","",SUMIF('แผนงาน Schedule'!$B$7:$B$66,C38,'แผนงาน Schedule'!$F$7:$F$66)) | E38: =IF(OR(C38="",N(D38)=0),"",I38/D38) | F38: =IF(OR(C38="",N(D38)=0),"",J38/D38) | G38: =IF(E38="","",F38-E38) | H38: =IF(OR(E38="",N(E38)=0),"",F38/E38) | I38: =IF(C38="","",SUMPRODUCT(('แผนงาน Schedule'!$B$7:$B$66=C38)*'แผนงาน Schedule'!$F$7:$F$66*(('แผนงาน Schedule'!$I$7:$I$66<=Dashboard!$C$7)+('แผนงาน Schedule'!$H$7:$H$66<=Dashboard!$C$7)*('แผนงาน Schedule'!$I$7:$I$66>Dashboard!$C$7)*(Dashboard!$C$7-'แผนงาน Schedule'!$H$7:$H$66+1)/('แผนงาน Schedule'!$I$7:$I$66-'แผนงาน Schedule'!$H$7:$H$66+1)))) | J38: =IF(C38="","",SUMPRODUCT(('แผนงาน Schedule'!$B$7:$B$66=C38)*'แผนงาน Schedule'!$F$7:$F$66*'แผนงาน Schedule'!$O$7:$O$66))
B39: =IF('ตั้งค่า Setup'!$C$42="","",17) | C39: =IF('ตั้งค่า Setup'!$C$42="","",'ตั้งค่า Setup'!$C$42) | D39: =IF(C39="","",SUMIF('แผนงาน Schedule'!$B$7:$B$66,C39,'แผนงาน Schedule'!$F$7:$F$66)) | E39: =IF(OR(C39="",N(D39)=0),"",I39/D39) | F39: =IF(OR(C39="",N(D39)=0),"",J39/D39) | G39: =IF(E39="","",F39-E39) | H39: =IF(OR(E39="",N(E39)=0),"",F39/E39) | I39: =IF(C39="","",SUMPRODUCT(('แผนงาน Schedule'!$B$7:$B$66=C39)*'แผนงาน Schedule'!$F$7:$F$66*(('แผนงาน Schedule'!$I$7:$I$66<=Dashboard!$C$7)+('แผนงาน Schedule'!$H$7:$H$66<=Dashboard!$C$7)*('แผนงาน Schedule'!$I$7:$I$66>Dashboard!$C$7)*(Dashboard!$C$7-'แผนงาน Schedule'!$H$7:$H$66+1)/('แผนงาน Schedule'!$I$7:$I$66-'แผนงาน Schedule'!$H$7:$H$66+1)))) | J39: =IF(C39="","",SUMPRODUCT(('แผนงาน Schedule'!$B$7:$B$66=C39)*'แผนงาน Schedule'!$F$7:$F$66*'แผนงาน Schedule'!$O$7:$O$66))
B40: =IF('ตั้งค่า Setup'!$C$43="","",18) | C40: =IF('ตั้งค่า Setup'!$C$43="","",'ตั้งค่า Setup'!$C$43) | D40: =IF(C40="","",SUMIF('แผนงาน Schedule'!$B$7:$B$66,C40,'แผนงาน Schedule'!$F$7:$F$66)) | E40: =IF(OR(C40="",N(D40)=0),"",I40/D40) | F40: =IF(OR(C40="",N(D40)=0),"",J40/D40) | G40: =IF(E40="","",F40-E40) | H40: =IF(OR(E40="",N(E40)=0),"",F40/E40) | I40: =IF(C40="","",SUMPRODUCT(('แผนงาน Schedule'!$B$7:$B$66=C40)*'แผนงาน Schedule'!$F$7:$F$66*(('แผนงาน Schedule'!$I$7:$I$66<=Dashboard!$C$7)+('แผนงาน Schedule'!$H$7:$H$66<=Dashboard!$C$7)*('แผนงาน Schedule'!$I$7:$I$66>Dashboard!$C$7)*(Dashboard!$C$7-'แผนงาน Schedule'!$H$7:$H$66+1)/('แผนงาน Schedule'!$I$7:$I$66-'แผนงาน Schedule'!$H$7:$H$66+1)))) | J40: =IF(C40="","",SUMPRODUCT(('แผนงาน Schedule'!$B$7:$B$66=C40)*'แผนงาน Schedule'!$F$7:$F$66*'แผนงาน Schedule'!$O$7:$O$66))
B41: =IF('ตั้งค่า Setup'!$C$44="","",19) | C41: =IF('ตั้งค่า Setup'!$C$44="","",'ตั้งค่า Setup'!$C$44) | D41: =IF(C41="","",SUMIF('แผนงาน Schedule'!$B$7:$B$66,C41,'แผนงาน Schedule'!$F$7:$F$66)) | E41: =IF(OR(C41="",N(D41)=0),"",I41/D41) | F41: =IF(OR(C41="",N(D41)=0),"",J41/D41) | G41: =IF(E41="","",F41-E41) | H41: =IF(OR(E41="",N(E41)=0),"",F41/E41) | I41: =IF(C41="","",SUMPRODUCT(('แผนงาน Schedule'!$B$7:$B$66=C41)*'แผนงาน Schedule'!$F$7:$F$66*(('แผนงาน Schedule'!$I$7:$I$66<=Dashboard!$C$7)+('แผนงาน Schedule'!$H$7:$H$66<=Dashboard!$C$7)*('แผนงาน Schedule'!$I$7:$I$66>Dashboard!$C$7)*(Dashboard!$C$7-'แผนงาน Schedule'!$H$7:$H$66+1)/('แผนงาน Schedule'!$I$7:$I$66-'แผนงาน Schedule'!$H$7:$H$66+1)))) | J41: =IF(C41="","",SUMPRODUCT(('แผนงาน Schedule'!$B$7:$B$66=C41)*'แผนงาน Schedule'!$F$7:$F$66*'แผนงาน Schedule'!$O$7:$O$66))
B42: =IF('ตั้งค่า Setup'!$C$45="","",20) | C42: =IF('ตั้งค่า Setup'!$C$45="","",'ตั้งค่า Setup'!$C$45) | D42: =IF(C42="","",SUMIF('แผนงาน Schedule'!$B$7:$B$66,C42,'แผนงาน Schedule'!$F$7:$F$66)) | E42: =IF(OR(C42="",N(D42)=0),"",I42/D42) | F42: =IF(OR(C42="",N(D42)=0),"",J42/D42) | G42: =IF(E42="","",F42-E42) | H42: =IF(OR(E42="",N(E42)=0),"",F42/E42) | I42: =IF(C42="","",SUMPRODUCT(('แผนงาน Schedule'!$B$7:$B$66=C42)*'แผนงาน Schedule'!$F$7:$F$66*(('แผนงาน Schedule'!$I$7:$I$66<=Dashboard!$C$7)+('แผนงาน Schedule'!$H$7:$H$66<=Dashboard!$C$7)*('แผนงาน Schedule'!$I$7:$I$66>Dashboard!$C$7)*(Dashboard!$C$7-'แผนงาน Schedule'!$H$7:$H$66+1)/('แผนงาน Schedule'!$I$7:$I$66-'แผนงาน Schedule'!$H$7:$H$66+1)))) | J42: =IF(C42="","",SUMPRODUCT(('แผนงาน Schedule'!$B$7:$B$66=C42)*'แผนงาน Schedule'!$F$7:$F$66*'แผนงาน Schedule'!$O$7:$O$66))
B43: =IF('ตั้งค่า Setup'!$C$46="","",21) | C43: =IF('ตั้งค่า Setup'!$C$46="","",'ตั้งค่า Setup'!$C$46) | D43: =IF(C43="","",SUMIF('แผนงาน Schedule'!$B$7:$B$66,C43,'แผนงาน Schedule'!$F$7:$F$66)) | E43: =IF(OR(C43="",N(D43)=0),"",I43/D43) | F43: =IF(OR(C43="",N(D43)=0),"",J43/D43) | G43: =IF(E43="","",F43-E43) | H43: =IF(OR(E43="",N(E43)=0),"",F43/E43) | I43: =IF(C43="","",SUMPRODUCT(('แผนงาน Schedule'!$B$7:$B$66=C43)*'แผนงาน Schedule'!$F$7:$F$66*(('แผนงาน Schedule'!$I$7:$I$66<=Dashboard!$C$7)+('แผนงาน Schedule'!$H$7:$H$66<=Dashboard!$C$7)*('แผนงาน Schedule'!$I$7:$I$66>Dashboard!$C$7)*(Dashboard!$C$7-'แผนงาน Schedule'!$H$7:$H$66+1)/('แผนงาน Schedule'!$I$7:$I$66-'แผนงาน Schedule'!$H$7:$H$66+1)))) | J43: =IF(C43="","",SUMPRODUCT(('แผนงาน Schedule'!$B$7:$B$66=C43)*'แผนงาน Schedule'!$F$7:$F$66*'แผนงาน Schedule'!$O$7:$O$66))
B44: =IF('ตั้งค่า Setup'!$C$47="","",22) | C44: =IF('ตั้งค่า Setup'!$C$47="","",'ตั้งค่า Setup'!$C$47) | D44: =IF(C44="","",SUMIF('แผนงาน Schedule'!$B$7:$B$66,C44,'แผนงาน Schedule'!$F$7:$F$66)) | E44: =IF(OR(C44="",N(D44)=0),"",I44/D44) | F44: =IF(OR(C44="",N(D44)=0),"",J44/D44) | G44: =IF(E44="","",F44-E44) | H44: =IF(OR(E44="",N(E44)=0),"",F44/E44) | I44: =IF(C44="","",SUMPRODUCT(('แผนงาน Schedule'!$B$7:$B$66=C44)*'แผนงาน Schedule'!$F$7:$F$66*(('แผนงาน Schedule'!$I$7:$I$66<=Dashboard!$C$7)+('แผนงาน Schedule'!$H$7:$H$66<=Dashboard!$C$7)*('แผนงาน Schedule'!$I$7:$I$66>Dashboard!$C$7)*(Dashboard!$C$7-'แผนงาน Schedule'!$H$7:$H$66+1)/('แผนงาน Schedule'!$I$7:$I$66-'แผนงาน Schedule'!$H$7:$H$66+1)))) | J44: =IF(C44="","",SUMPRODUCT(('แผนงาน Schedule'!$B$7:$B$66=C44)*'แผนงาน Schedule'!$F$7:$F$66*'แผนงาน Schedule'!$O$7:$O$66))
B45: =IF('ตั้งค่า Setup'!$C$48="","",23) | C45: =IF('ตั้งค่า Setup'!$C$48="","",'ตั้งค่า Setup'!$C$48) | D45: =IF(C45="","",SUMIF('แผนงาน Schedule'!$B$7:$B$66,C45,'แผนงาน Schedule'!$F$7:$F$66)) | E45: =IF(OR(C45="",N(D45)=0),"",I45/D45) | F45: =IF(OR(C45="",N(D45)=0),"",J45/D45) | G45: =IF(E45="","",F45-E45) | H45: =IF(OR(E45="",N(E45)=0),"",F45/E45) | I45: =IF(C45="","",SUMPRODUCT(('แผนงาน Schedule'!$B$7:$B$66=C45)*'แผนงาน Schedule'!$F$7:$F$66*(('แผนงาน Schedule'!$I$7:$I$66<=Dashboard!$C$7)+('แผนงาน Schedule'!$H$7:$H$66<=Dashboard!$C$7)*('แผนงาน Schedule'!$I$7:$I$66>Dashboard!$C$7)*(Dashboard!$C$7-'แผนงาน Schedule'!$H$7:$H$66+1)/('แผนงาน Schedule'!$I$7:$I$66-'แผนงาน Schedule'!$H$7:$H$66+1)))) | J45: =IF(C45="","",SUMPRODUCT(('แผนงาน Schedule'!$B$7:$B$66=C45)*'แผนงาน Schedule'!$F$7:$F$66*'แผนงาน Schedule'!$O$7:$O$66))
B46: =IF('ตั้งค่า Setup'!$C$49="","",24) | C46: =IF('ตั้งค่า Setup'!$C$49="","",'ตั้งค่า Setup'!$C$49) | D46: =IF(C46="","",SUMIF('แผนงาน Schedule'!$B$7:$B$66,C46,'แผนงาน Schedule'!$F$7:$F$66)) | E46: =IF(OR(C46="",N(D46)=0),"",I46/D46) | F46: =IF(OR(C46="",N(D46)=0),"",J46/D46) | G46: =IF(E46="","",F46-E46) | H46: =IF(OR(E46="",N(E46)=0),"",F46/E46) | I46: =IF(C46="","",SUMPRODUCT(('แผนงาน Schedule'!$B$7:$B$66=C46)*'แผนงาน Schedule'!$F$7:$F$66*(('แผนงาน Schedule'!$I$7:$I$66<=Dashboard!$C$7)+('แผนงาน Schedule'!$H$7:$H$66<=Dashboard!$C$7)*('แผนงาน Schedule'!$I$7:$I$66>Dashboard!$C$7)*(Dashboard!$C$7-'แผนงาน Schedule'!$H$7:$H$66+1)/('แผนงาน Schedule'!$I$7:$I$66-'แผนงาน Schedule'!$H$7:$H$66+1)))) | J46: =IF(C46="","",SUMPRODUCT(('แผนงาน Schedule'!$B$7:$B$66=C46)*'แผนงาน Schedule'!$F$7:$F$66*'แผนงาน Schedule'!$O$7:$O$66))
B47: =IF('ตั้งค่า Setup'!$C$50="","",25) | C47: =IF('ตั้งค่า Setup'!$C$50="","",'ตั้งค่า Setup'!$C$50) | D47: =IF(C47="","",SUMIF('แผนงาน Schedule'!$B$7:$B$66,C47,'แผนงาน Schedule'!$F$7:$F$66)) | E47: =IF(OR(C47="",N(D47)=0),"",I47/D47) | F47: =IF(OR(C47="",N(D47)=0),"",J47/D47) | G47: =IF(E47="","",F47-E47) | H47: =IF(OR(E47="",N(E47)=0),"",F47/E47) | I47: =IF(C47="","",SUMPRODUCT(('แผนงาน Schedule'!$B$7:$B$66=C47)*'แผนงาน Schedule'!$F$7:$F$66*(('แผนงาน Schedule'!$I$7:$I$66<=Dashboard!$C$7)+('แผนงาน Schedule'!$H$7:$H$66<=Dashboard!$C$7)*('แผนงาน Schedule'!$I$7:$I$66>Dashboard!$C$7)*(Dashboard!$C$7-'แผนงาน Schedule'!$H$7:$H$66+1)/('แผนงาน Schedule'!$I$7:$I$66-'แผนงาน Schedule'!$H$7:$H$66+1)))) | J47: =IF(C47="","",SUMPRODUCT(('แผนงาน Schedule'!$B$7:$B$66=C47)*'แผนงาน Schedule'!$F$7:$F$66*'แผนงาน Schedule'!$O$7:$O$66))
B48: =IF('ตั้งค่า Setup'!$C$51="","",26) | C48: =IF('ตั้งค่า Setup'!$C$51="","",'ตั้งค่า Setup'!$C$51) | D48: =IF(C48="","",SUMIF('แผนงาน Schedule'!$B$7:$B$66,C48,'แผนงาน Schedule'!$F$7:$F$66)) | E48: =IF(OR(C48="",N(D48)=0),"",I48/D48) | F48: =IF(OR(C48="",N(D48)=0),"",J48/D48) | G48: =IF(E48="","",F48-E48) | H48: =IF(OR(E48="",N(E48)=0),"",F48/E48) | I48: =IF(C48="","",SUMPRODUCT(('แผนงาน Schedule'!$B$7:$B$66=C48)*'แผนงาน Schedule'!$F$7:$F$66*(('แผนงาน Schedule'!$I$7:$I$66<=Dashboard!$C$7)+('แผนงาน Schedule'!$H$7:$H$66<=Dashboard!$C$7)*('แผนงาน Schedule'!$I$7:$I$66>Dashboard!$C$7)*(Dashboard!$C$7-'แผนงาน Schedule'!$H$7:$H$66+1)/('แผนงาน Schedule'!$I$7:$I$66-'แผนงาน Schedule'!$H$7:$H$66+1)))) | J48: =IF(C48="","",SUMPRODUCT(('แผนงาน Schedule'!$B$7:$B$66=C48)*'แผนงาน Schedule'!$F$7:$F$66*'แผนงาน Schedule'!$O$7:$O$66))
B49: =IF('ตั้งค่า Setup'!$C$52="","",27) | C49: =IF('ตั้งค่า Setup'!$C$52="","",'ตั้งค่า Setup'!$C$52) | D49: =IF(C49="","",SUMIF('แผนงาน Schedule'!$B$7:$B$66,C49,'แผนงาน Schedule'!$F$7:$F$66)) | E49: =IF(OR(C49="",N(D49)=0),"",I49/D49) | F49: =IF(OR(C49="",N(D49)=0),"",J49/D49) | G49: =IF(E49="","",F49-E49) | H49: =IF(OR(E49="",N(E49)=0),"",F49/E49) | I49: =IF(C49="","",SUMPRODUCT(('แผนงาน Schedule'!$B$7:$B$66=C49)*'แผนงาน Schedule'!$F$7:$F$66*(('แผนงาน Schedule'!$I$7:$I$66<=Dashboard!$C$7)+('แผนงาน Schedule'!$H$7:$H$66<=Dashboard!$C$7)*('แผนงาน Schedule'!$I$7:$I$66>Dashboard!$C$7)*(Dashboard!$C$7-'แผนงาน Schedule'!$H$7:$H$66+1)/('แผนงาน Schedule'!$I$7:$I$66-'แผนงาน Schedule'!$H$7:$H$66+1)))) | J49: =IF(C49="","",SUMPRODUCT(('แผนงาน Schedule'!$B$7:$B$66=C49)*'แผนงาน Schedule'!$F$7:$F$66*'แผนงาน Schedule'!$O$7:$O$66))
B50: =IF('ตั้งค่า Setup'!$C$53="","",28) | C50: =IF('ตั้งค่า Setup'!$C$53="","",'ตั้งค่า Setup'!$C$53) | D50: =IF(C50="","",SUMIF('แผนงาน Schedule'!$B$7:$B$66,C50,'แผนงาน Schedule'!$F$7:$F$66)) | E50: =IF(OR(C50="",N(D50)=0),"",I50/D50) | F50: =IF(OR(C50="",N(D50)=0),"",J50/D50) | G50: =IF(E50="","",F50-E50) | H50: =IF(OR(E50="",N(E50)=0),"",F50/E50) | I50: =IF(C50="","",SUMPRODUCT(('แผนงาน Schedule'!$B$7:$B$66=C50)*'แผนงาน Schedule'!$F$7:$F$66*(('แผนงาน Schedule'!$I$7:$I$66<=Dashboard!$C$7)+('แผนงาน Schedule'!$H$7:$H$66<=Dashboard!$C$7)*('แผนงาน Schedule'!$I$7:$I$66>Dashboard!$C$7)*(Dashboard!$C$7-'แผนงาน Schedule'!$H$7:$H$66+1)/('แผนงาน Schedule'!$I$7:$I$66-'แผนงาน Schedule'!$H$7:$H$66+1)))) | J50: =IF(C50="","",SUMPRODUCT(('แผนงาน Schedule'!$B$7:$B$66=C50)*'แผนงาน Schedule'!$F$7:$F$66*'แผนงาน Schedule'!$O$7:$O$66))
B51: =IF('ตั้งค่า Setup'!$C$54="","",29) | C51: =IF('ตั้งค่า Setup'!$C$54="","",'ตั้งค่า Setup'!$C$54) | D51: =IF(C51="","",SUMIF('แผนงาน Schedule'!$B$7:$B$66,C51,'แผนงาน Schedule'!$F$7:$F$66)) | E51: =IF(OR(C51="",N(D51)=0),"",I51/D51) | F51: =IF(OR(C51="",N(D51)=0),"",J51/D51) | G51: =IF(E51="","",F51-E51) | H51: =IF(OR(E51="",N(E51)=0),"",F51/E51) | I51: =IF(C51="","",SUMPRODUCT(('แผนงาน Schedule'!$B$7:$B$66=C51)*'แผนงาน Schedule'!$F$7:$F$66*(('แผนงาน Schedule'!$I$7:$I$66<=Dashboard!$C$7)+('แผนงาน Schedule'!$H$7:$H$66<=Dashboard!$C$7)*('แผนงาน Schedule'!$I$7:$I$66>Dashboard!$C$7)*(Dashboard!$C$7-'แผนงาน Schedule'!$H$7:$H$66+1)/('แผนงาน Schedule'!$I$7:$I$66-'แผนงาน Schedule'!$H$7:$H$66+1)))) | J51: =IF(C51="","",SUMPRODUCT(('แผนงาน Schedule'!$B$7:$B$66=C51)*'แผนงาน Schedule'!$F$7:$F$66*'แผนงาน Schedule'!$O$7:$O$66))
B52: =IF('ตั้งค่า Setup'!$C$55="","",30) | C52: =IF('ตั้งค่า Setup'!$C$55="","",'ตั้งค่า Setup'!$C$55) | D52: =IF(C52="","",SUMIF('แผนงาน Schedule'!$B$7:$B$66,C52,'แผนงาน Schedule'!$F$7:$F$66)) | E52: =IF(OR(C52="",N(D52)=0),"",I52/D52) | F52: =IF(OR(C52="",N(D52)=0),"",J52/D52) | G52: =IF(E52="","",F52-E52) | H52: =IF(OR(E52="",N(E52)=0),"",F52/E52) | I52: =IF(C52="","",SUMPRODUCT(('แผนงาน Schedule'!$B$7:$B$66=C52)*'แผนงาน Schedule'!$F$7:$F$66*(('แผนงาน Schedule'!$I$7:$I$66<=Dashboard!$C$7)+('แผนงาน Schedule'!$H$7:$H$66<=Dashboard!$C$7)*('แผนงาน Schedule'!$I$7:$I$66>Dashboard!$C$7)*(Dashboard!$C$7-'แผนงาน Schedule'!$H$7:$H$66+1)/('แผนงาน Schedule'!$I$7:$I$66-'แผนงาน Schedule'!$H$7:$H$66+1)))) | J52: =IF(C52="","",SUMPRODUCT(('แผนงาน Schedule'!$B$7:$B$66=C52)*'แผนงาน Schedule'!$F$7:$F$66*'แผนงาน Schedule'!$O$7:$O$66))
B53: =IF('ตั้งค่า Setup'!$C$56="","",31) | C53: =IF('ตั้งค่า Setup'!$C$56="","",'ตั้งค่า Setup'!$C$56) | D53: =IF(C53="","",SUMIF('แผนงาน Schedule'!$B$7:$B$66,C53,'แผนงาน Schedule'!$F$7:$F$66)) | E53: =IF(OR(C53="",N(D53)=0),"",I53/D53) | F53: =IF(OR(C53="",N(D53)=0),"",J53/D53) | G53: =IF(E53="","",F53-E53) | H53: =IF(OR(E53="",N(E53)=0),"",F53/E53) | I53: =IF(C53="","",SUMPRODUCT(('แผนงาน Schedule'!$B$7:$B$66=C53)*'แผนงาน Schedule'!$F$7:$F$66*(('แผนงาน Schedule'!$I$7:$I$66<=Dashboard!$C$7)+('แผนงาน Schedule'!$H$7:$H$66<=Dashboard!$C$7)*('แผนงาน Schedule'!$I$7:$I$66>Dashboard!$C$7)*(Dashboard!$C$7-'แผนงาน Schedule'!$H$7:$H$66+1)/('แผนงาน Schedule'!$I$7:$I$66-'แผนงาน Schedule'!$H$7:$H$66+1)))) | J53: =IF(C53="","",SUMPRODUCT(('แผนงาน Schedule'!$B$7:$B$66=C53)*'แผนงาน Schedule'!$F$7:$F$66*'แผนงาน Schedule'!$O$7:$O$66))
B54: =IF('ตั้งค่า Setup'!$C$57="","",32) | C54: =IF('ตั้งค่า Setup'!$C$57="","",'ตั้งค่า Setup'!$C$57) | D54: =IF(C54="","",SUMIF('แผนงาน Schedule'!$B$7:$B$66,C54,'แผนงาน Schedule'!$F$7:$F$66)) | E54: =IF(OR(C54="",N(D54)=0),"",I54/D54) | F54: =IF(OR(C54="",N(D54)=0),"",J54/D54) | G54: =IF(E54="","",F54-E54) | H54: =IF(OR(E54="",N(E54)=0),"",F54/E54) | I54: =IF(C54="","",SUMPRODUCT(('แผนงาน Schedule'!$B$7:$B$66=C54)*'แผนงาน Schedule'!$F$7:$F$66*(('แผนงาน Schedule'!$I$7:$I$66<=Dashboard!$C$7)+('แผนงาน Schedule'!$H$7:$H$66<=Dashboard!$C$7)*('แผนงาน Schedule'!$I$7:$I$66>Dashboard!$C$7)*(Dashboard!$C$7-'แผนงาน Schedule'!$H$7:$H$66+1)/('แผนงาน Schedule'!$I$7:$I$66-'แผนงาน Schedule'!$H$7:$H$66+1)))) | J54: =IF(C54="","",SUMPRODUCT(('แผนงาน Schedule'!$B$7:$B$66=C54)*'แผนงาน Schedule'!$F$7:$F$66*'แผนงาน Schedule'!$O$7:$O$66))
B55: =IF('ตั้งค่า Setup'!$C$58="","",33) | C55: =IF('ตั้งค่า Setup'!$C$58="","",'ตั้งค่า Setup'!$C$58) | D55: =IF(C55="","",SUMIF('แผนงาน Schedule'!$B$7:$B$66,C55,'แผนงาน Schedule'!$F$7:$F$66)) | E55: =IF(OR(C55="",N(D55)=0),"",I55/D55) | F55: =IF(OR(C55="",N(D55)=0),"",J55/D55) | G55: =IF(E55="","",F55-E55) | H55: =IF(OR(E55="",N(E55)=0),"",F55/E55) | I55: =IF(C55="","",SUMPRODUCT(('แผนงาน Schedule'!$B$7:$B$66=C55)*'แผนงาน Schedule'!$F$7:$F$66*(('แผนงาน Schedule'!$I$7:$I$66<=Dashboard!$C$7)+('แผนงาน Schedule'!$H$7:$H$66<=Dashboard!$C$7)*('แผนงาน Schedule'!$I$7:$I$66>Dashboard!$C$7)*(Dashboard!$C$7-'แผนงาน Schedule'!$H$7:$H$66+1)/('แผนงาน Schedule'!$I$7:$I$66-'แผนงาน Schedule'!$H$7:$H$66+1)))) | J55: =IF(C55="","",SUMPRODUCT(('แผนงาน Schedule'!$B$7:$B$66=C55)*'แผนงาน Schedule'!$F$7:$F$66*'แผนงาน Schedule'!$O$7:$O$66))
B56: =IF('ตั้งค่า Setup'!$C$59="","",34) | C56: =IF('ตั้งค่า Setup'!$C$59="","",'ตั้งค่า Setup'!$C$59) | D56: =IF(C56="","",SUMIF('แผนงาน Schedule'!$B$7:$B$66,C56,'แผนงาน Schedule'!$F$7:$F$66)) | E56: =IF(OR(C56="",N(D56)=0),"",I56/D56) | F56: =IF(OR(C56="",N(D56)=0),"",J56/D56) | G56: =IF(E56="","",F56-E56) | H56: =IF(OR(E56="",N(E56)=0),"",F56/E56) | I56: =IF(C56="","",SUMPRODUCT(('แผนงาน Schedule'!$B$7:$B$66=C56)*'แผนงาน Schedule'!$F$7:$F$66*(('แผนงาน Schedule'!$I$7:$I$66<=Dashboard!$C$7)+('แผนงาน Schedule'!$H$7:$H$66<=Dashboard!$C$7)*('แผนงาน Schedule'!$I$7:$I$66>Dashboard!$C$7)*(Dashboard!$C$7-'แผนงาน Schedule'!$H$7:$H$66+1)/('แผนงาน Schedule'!$I$7:$I$66-'แผนงาน Schedule'!$H$7:$H$66+1)))) | J56: =IF(C56="","",SUMPRODUCT(('แผนงาน Schedule'!$B$7:$B$66=C56)*'แผนงาน Schedule'!$F$7:$F$66*'แผนงาน Schedule'!$O$7:$O$66))
B57: =IF('ตั้งค่า Setup'!$C$60="","",35) | C57: =IF('ตั้งค่า Setup'!$C$60="","",'ตั้งค่า Setup'!$C$60) | D57: =IF(C57="","",SUMIF('แผนงาน Schedule'!$B$7:$B$66,C57,'แผนงาน Schedule'!$F$7:$F$66)) | E57: =IF(OR(C57="",N(D57)=0),"",I57/D57) | F57: =IF(OR(C57="",N(D57)=0),"",J57/D57) | G57: =IF(E57="","",F57-E57) | H57: =IF(OR(E57="",N(E57)=0),"",F57/E57) | I57: =IF(C57="","",SUMPRODUCT(('แผนงาน Schedule'!$B$7:$B$66=C57)*'แผนงาน Schedule'!$F$7:$F$66*(('แผนงาน Schedule'!$I$7:$I$66<=Dashboard!$C$7)+('แผนงาน Schedule'!$H$7:$H$66<=Dashboard!$C$7)*('แผนงาน Schedule'!$I$7:$I$66>Dashboard!$C$7)*(Dashboard!$C$7-'แผนงาน Schedule'!$H$7:$H$66+1)/('แผนงาน Schedule'!$I$7:$I$66-'แผนงาน Schedule'!$H$7:$H$66+1)))) | J57: =IF(C57="","",SUMPRODUCT(('แผนงาน Schedule'!$B$7:$B$66=C57)*'แผนงาน Schedule'!$F$7:$F$66*'แผนงาน Schedule'!$O$7:$O$66))
B58: =IF('ตั้งค่า Setup'!$C$61="","",36) | C58: =IF('ตั้งค่า Setup'!$C$61="","",'ตั้งค่า Setup'!$C$61) | D58: =IF(C58="","",SUMIF('แผนงาน Schedule'!$B$7:$B$66,C58,'แผนงาน Schedule'!$F$7:$F$66)) | E58: =IF(OR(C58="",N(D58)=0),"",I58/D58) | F58: =IF(OR(C58="",N(D58)=0),"",J58/D58) | G58: =IF(E58="","",F58-E58) | H58: =IF(OR(E58="",N(E58)=0),"",F58/E58) | I58: =IF(C58="","",SUMPRODUCT(('แผนงาน Schedule'!$B$7:$B$66=C58)*'แผนงาน Schedule'!$F$7:$F$66*(('แผนงาน Schedule'!$I$7:$I$66<=Dashboard!$C$7)+('แผนงาน Schedule'!$H$7:$H$66<=Dashboard!$C$7)*('แผนงาน Schedule'!$I$7:$I$66>Dashboard!$C$7)*(Dashboard!$C$7-'แผนงาน Schedule'!$H$7:$H$66+1)/('แผนงาน Schedule'!$I$7:$I$66-'แผนงาน Schedule'!$H$7:$H$66+1)))) | J58: =IF(C58="","",SUMPRODUCT(('แผนงาน Schedule'!$B$7:$B$66=C58)*'แผนงาน Schedule'!$F$7:$F$66*'แผนงาน Schedule'!$O$7:$O$66))
B59: =IF('ตั้งค่า Setup'!$C$62="","",37) | C59: =IF('ตั้งค่า Setup'!$C$62="","",'ตั้งค่า Setup'!$C$62) | D59: =IF(C59="","",SUMIF('แผนงาน Schedule'!$B$7:$B$66,C59,'แผนงาน Schedule'!$F$7:$F$66)) | E59: =IF(OR(C59="",N(D59)=0),"",I59/D59) | F59: =IF(OR(C59="",N(D59)=0),"",J59/D59) | G59: =IF(E59="","",F59-E59) | H59: =IF(OR(E59="",N(E59)=0),"",F59/E59) | I59: =IF(C59="","",SUMPRODUCT(('แผนงาน Schedule'!$B$7:$B$66=C59)*'แผนงาน Schedule'!$F$7:$F$66*(('แผนงาน Schedule'!$I$7:$I$66<=Dashboard!$C$7)+('แผนงาน Schedule'!$H$7:$H$66<=Dashboard!$C$7)*('แผนงาน Schedule'!$I$7:$I$66>Dashboard!$C$7)*(Dashboard!$C$7-'แผนงาน Schedule'!$H$7:$H$66+1)/('แผนงาน Schedule'!$I$7:$I$66-'แผนงาน Schedule'!$H$7:$H$66+1)))) | J59: =IF(C59="","",SUMPRODUCT(('แผนงาน Schedule'!$B$7:$B$66=C59)*'แผนงาน Schedule'!$F$7:$F$66*'แผนงาน Schedule'!$O$7:$O$66))
B60: =IF('ตั้งค่า Setup'!$C$63="","",38) | C60: =IF('ตั้งค่า Setup'!$C$63="","",'ตั้งค่า Setup'!$C$63) | D60: =IF(C60="","",SUMIF('แผนงาน Schedule'!$B$7:$B$66,C60,'แผนงาน Schedule'!$F$7:$F$66)) | E60: =IF(OR(C60="",N(D60)=0),"",I60/D60) | F60: =IF(OR(C60="",N(D60)=0),"",J60/D60) | G60: =IF(E60="","",F60-E60) | H60: =IF(OR(E60="",N(E60)=0),"",F60/E60) | I60: =IF(C60="","",SUMPRODUCT(('แผนงาน Schedule'!$B$7:$B$66=C60)*'แผนงาน Schedule'!$F$7:$F$66*(('แผนงาน Schedule'!$I$7:$I$66<=Dashboard!$C$7)+('แผนงาน Schedule'!$H$7:$H$66<=Dashboard!$C$7)*('แผนงาน Schedule'!$I$7:$I$66>Dashboard!$C$7)*(Dashboard!$C$7-'แผนงาน Schedule'!$H$7:$H$66+1)/('แผนงาน Schedule'!$I$7:$I$66-'แผนงาน Schedule'!$H$7:$H$66+1)))) | J60: =IF(C60="","",SUMPRODUCT(('แผนงาน Schedule'!$B$7:$B$66=C60)*'แผนงาน Schedule'!$F$7:$F$66*'แผนงาน Schedule'!$O$7:$O$66))
B61: =IF('ตั้งค่า Setup'!$C$64="","",39) | C61: =IF('ตั้งค่า Setup'!$C$64="","",'ตั้งค่า Setup'!$C$64) | D61: =IF(C61="","",SUMIF('แผนงาน Schedule'!$B$7:$B$66,C61,'แผนงาน Schedule'!$F$7:$F$66)) | E61: =IF(OR(C61="",N(D61)=0),"",I61/D61) | F61: =IF(OR(C61="",N(D61)=0),"",J61/D61) | G61: =IF(E61="","",F61-E61) | H61: =IF(OR(E61="",N(E61)=0),"",F61/E61) | I61: =IF(C61="","",SUMPRODUCT(('แผนงาน Schedule'!$B$7:$B$66=C61)*'แผนงาน Schedule'!$F$7:$F$66*(('แผนงาน Schedule'!$I$7:$I$66<=Dashboard!$C$7)+('แผนงาน Schedule'!$H$7:$H$66<=Dashboard!$C$7)*('แผนงาน Schedule'!$I$7:$I$66>Dashboard!$C$7)*(Dashboard!$C$7-'แผนงาน Schedule'!$H$7:$H$66+1)/('แผนงาน Schedule'!$I$7:$I$66-'แผนงาน Schedule'!$H$7:$H$66+1)))) | J61: =IF(C61="","",SUMPRODUCT(('แผนงาน Schedule'!$B$7:$B$66=C61)*'แผนงาน Schedule'!$F$7:$F$66*'แผนงาน Schedule'!$O$7:$O$66))
B62: =IF('ตั้งค่า Setup'!$C$65="","",40) | C62: =IF('ตั้งค่า Setup'!$C$65="","",'ตั้งค่า Setup'!$C$65) | D62: =IF(C62="","",SUMIF('แผนงาน Schedule'!$B$7:$B$66,C62,'แผนงาน Schedule'!$F$7:$F$66)) | E62: =IF(OR(C62="",N(D62)=0),"",I62/D62) | F62: =IF(OR(C62="",N(D62)=0),"",J62/D62) | G62: =IF(E62="","",F62-E62) | H62: =IF(OR(E62="",N(E62)=0),"",F62/E62) | I62: =IF(C62="","",SUMPRODUCT(('แผนงาน Schedule'!$B$7:$B$66=C62)*'แผนงาน Schedule'!$F$7:$F$66*(('แผนงาน Schedule'!$I$7:$I$66<=Dashboard!$C$7)+('แผนงาน Schedule'!$H$7:$H$66<=Dashboard!$C$7)*('แผนงาน Schedule'!$I$7:$I$66>Dashboard!$C$7)*(Dashboard!$C$7-'แผนงาน Schedule'!$H$7:$H$66+1)/('แผนงาน Schedule'!$I$7:$I$66-'แผนงาน Schedule'!$H$7:$H$66+1)))) | J62: =IF(C62="","",SUMPRODUCT(('แผนงาน Schedule'!$B$7:$B$66=C62)*'แผนงาน Schedule'!$F$7:$F$66*'แผนงาน Schedule'!$O$7:$O$66))
C63: รวม / TOTAL | D63: =SUM(D23:D62) -> 1 | E63: =I63 -> 0.20820323 | F63: =J63 -> 0 | G63: =F63-E63 -> -0.20820323 | H63: =IFERROR(F63/E63,"") -> 0 | I63: =SUM(I23:I62) -> 0.20820323 | J63: =SUM(J23:J62) -> 0
B64: หมายเหตุ: ผลงานจริงรายหมวดคำนวณจาก % รายรายการในชีตแผนงาน (ถ้ายังไม่กรอกจะแสดง 0)
B66: 3. รายการที่ล่าช้ามากที่สุด / Top 5 Delayed Items
B67: อันดับ | C67: WBS / รายการงาน | D67: เสร็จตามแผน BL Finish | E67: คาดว่าเสร็จ Forecast | F67: ล่าช้า (วัน) Delay | G67: % จริง Actual | H67: สถานะ / Status | J67: หมายเหตุ / Remarks
B68: =IF(L68="","",1) -> 1 | C68: =IF(L68="","",INDEX('แผนงาน Schedule'!$A$7:$A$66,L68)&" "&INDEX('แผนงาน Schedule'!$C$7:$C$66,L68)) -> 1.1 งานเตรียมการ ติดตั้งป้ายโครงการ และรื้อถอนระบบเดิม | D68: =IF(L68="","",INDEX('แผนงาน Schedule'!$I$7:$I$66,L68)) -> 46087 | E68: =IF(L68="","",INDEX('แผนงาน Schedule'!$V$7:$V$66,L68)) -> 46308 | F68: =IF(L68="","",INDEX('แผนงาน Schedule'!$W$7:$W$66,L68)) -> 221 | G68: =IF(L68="","",N(INDEX('แผนงาน Schedule'!$O$7:$O$66,L68))) -> 0 | H68: =IF(L68="","",INDEX('แผนงาน Schedule'!$X$7:$X$66,L68)) -> เกินกำหนด / Overdue | J68: =IF(L68="","",INDEX('แผนงาน Schedule'!$Y$7:$Y$66,L68)&"") | L68: =IFERROR(MATCH(LARGE('แผนงาน Schedule'!$AB$7:$AB$66,1),'แผนงาน Schedule'!$AB$7:$AB$66,0),"") -> 1
B69: =IF(L69="","",2) -> 2 | C69: =IF(L69="","",INDEX('แผนงาน Schedule'!$A$7:$A$66,L69)&" "&INDEX('แผนงาน Schedule'!$C$7:$C$66,L69)) -> 1.2 ก่อสร้างสำนักงานชั่วคราวและจัดเตรียมอุปกรณ์สำนักงาน | D69: =IF(L69="","",INDEX('แผนงาน Schedule'!$I$7:$I$66,L69)) -> 46127 | E69: =IF(L69="","",INDEX('แผนงาน Schedule'!$V$7:$V$66,L69)) -> 46337 | F69: =IF(L69="","",INDEX('แผนงาน Schedule'!$W$7:$W$66,L69)) -> 210 | G69: =IF(L69="","",N(INDEX('แผนงาน Schedule'!$O$7:$O$66,L69))) -> 0 | H69: =IF(L69="","",INDEX('แผนงาน Schedule'!$X$7:$X$66,L69)) -> เกินกำหนด / Overdue | J69: =IF(L69="","",INDEX('แผนงาน Schedule'!$Y$7:$Y$66,L69)&"") | L69: =IFERROR(MATCH(LARGE('แผนงาน Schedule'!$AB$7:$AB$66,2),'แผนงาน Schedule'!$AB$7:$AB$66,0),"") -> 2
B70: =IF(L70="","",3) -> 3 | C70: =IF(L70="","",INDEX('แผนงาน Schedule'!$A$7:$A$66,L70)&" "&INDEX('แผนงาน Schedule'!$C$7:$C$66,L70)) -> 1.3 งานรื้อถอนโครงสร้างเดิมและเตรียมพื้นที่ติดตั้งใหม่ | D70: =IF(L70="","",INDEX('แผนงาน Schedule'!$I$7:$I$66,L70)) -> 46132 | E70: =IF(L70="","",INDEX('แผนงาน Schedule'!$V$7:$V$66,L70)) -> 46333 | F70: =IF(L70="","",INDEX('แผนงาน Schedule'!$W$7:$W$66,L70)) -> 201 | G70: =IF(L70="","",N(INDEX('แผนงาน Schedule'!$O$7:$O$66,L70))) -> 0 | H70: =IF(L70="","",INDEX('แผนงาน Schedule'!$X$7:$X$66,L70)) -> เกินกำหนด / Overdue | J70: =IF(L70="","",INDEX('แผนงาน Schedule'!$Y$7:$Y$66,L70)&"") | L70: =IFERROR(MATCH(LARGE('แผนงาน Schedule'!$AB$7:$AB$66,3),'แผนงาน Schedule'!$AB$7:$AB$66,0),"") -> 3
B71: =IF(L71="","",4) -> 4 | C71: =IF(L71="","",INDEX('แผนงาน Schedule'!$A$7:$A$66,L71)&" "&INDEX('แผนงาน Schedule'!$C$7:$C$66,L71)) -> 2.1 งานฐานราก คานคอดิน พื้นชั้น 1 และเสาชั้น 1 | D71: =IF(L71="","",INDEX('แผนงาน Schedule'!$I$7:$I$66,L71)) -> 46142 | E71: =IF(L71="","",INDEX('แผนงาน Schedule'!$V$7:$V$66,L71)) -> 46339 | F71: =IF(L71="","",INDEX('แผนงาน Schedule'!$W$7:$W$66,L71)) -> 197 | G71: =IF(L71="","",N(INDEX('แผนงาน Schedule'!$O$7:$O$66,L71))) -> 0 | H71: =IF(L71="","",INDEX('แผนงาน Schedule'!$X$7:$X$66,L71)) -> เกินกำหนด / Overdue | J71: =IF(L71="","",INDEX('แผนงาน Schedule'!$Y$7:$Y$66,L71)&"") | L71: =IFERROR(MATCH(LARGE('แผนงาน Schedule'!$AB$7:$AB$66,4),'แผนงาน Schedule'!$AB$7:$AB$66,0),"") -> 4
B72: =IF(L72="","",5) -> 5 | C72: =IF(L72="","",INDEX('แผนงาน Schedule'!$A$7:$A$66,L72)&" "&INDEX('แผนงาน Schedule'!$C$7:$C$66,L72)) -> 2.2 งานวาง SLEEVE/เดินท่อฝังในโครงสร้าง และโครงสร้างชั้น 1–2 | D72: =IF(L72="","",INDEX('แผนงาน Schedule'!$I$7:$I$66,L72)) -> 46157 | E72: =IF(L72="","",INDEX('แผนงาน Schedule'!$V$7:$V$66,L72)) -> 46323 | F72: =IF(L72="","",INDEX('แผนงาน Schedule'!$W$7:$W$66,L72)) -> 166 | G72: =IF(L72="","",N(INDEX('แผนงาน Schedule'!$O$7:$O$66,L72))) -> 0 | H72: =IF(L72="","",INDEX('แผนงาน Schedule'!$X$7:$X$66,L72)) -> เกินกำหนด / Overdue | J72: =IF(L72="","",INDEX('แผนงาน Schedule'!$Y$7:$Y$66,L72)&"") | L72: =IFERROR(MATCH(LARGE('แผนงาน Schedule'!$AB$7:$AB$66,5),'แผนงาน Schedule'!$AB$7:$AB$66,0),"") -> 5
B74: ="4. แผนงานล่วงหน้า "&'ตั้งค่า Setup'!$C$20&" วัน (งานค้างและงานที่ต้องเริ่ม) / "&'ตั้งค่า Setup'!$C$20&"-Day Look-ahead" -> 4. แผนงานล่วงหน้า 30 วัน (งานค้างและงานที่ต้องเริ่ม) / 30-Day Look-ahead
B75: ลำดับ | C75: WBS / รายการงาน | D75: เริ่ม (แผนใช้งาน) Start | E75: เสร็จ (แผนใช้งาน) Finish | F75: % จริง Actual | G75: คาดว่าเสร็จ Forecast | H75: สถานะ / Status | J75: หมายเหตุ / Remarks
B76: =IF(L76="","",1) -> 1 | C76: =IF(L76="","",INDEX('แผนงาน Schedule'!$A$7:$A$66,L76)&" "&INDEX('แผนงาน Schedule'!$C$7:$C$66,L76)) -> 1.1 งานเตรียมการ ติดตั้งป้ายโครงการ และรื้อถอนระบบเดิม | D76: =IF(L76="","",INDEX('แผนงาน Schedule'!$Z$7:$Z$66,L76)) -> 46072 | E76: =IF(L76="","",INDEX('แผนงาน Schedule'!$AA$7:$AA$66,L76)) -> 46087 | F76: =IF(L76="","",N(INDEX('แผนงาน Schedule'!$O$7:$O$66,L76))) -> 0 | G76: =IF(L76="","",INDEX('แผนงาน Schedule'!$V$7:$V$66,L76)) -> 46308 | H76: =IF(L76="","",INDEX('แผนงาน Schedule'!$X$7:$X$66,L76)) -> เกินกำหนด / Overdue | J76: =IF(L76="","",INDEX('แผนงาน Schedule'!$Y$7:$Y$66,L76)&"") | L76: =IFERROR(MATCH(1,'แผนงาน Schedule'!$AD$7:$AD$66,0),"") -> 1
B77: =IF(L77="","",2) -> 2 | C77: =IF(L77="","",INDEX('แผนงาน Schedule'!$A$7:$A$66,L77)&" "&INDEX('แผนงาน Schedule'!$C$7:$C$66,L77)) -> 1.2 ก่อสร้างสำนักงานชั่วคราวและจัดเตรียมอุปกรณ์สำนักงาน | D77: =IF(L77="","",INDEX('แผนงาน Schedule'!$Z$7:$Z$66,L77)) -> 46083 | E77: =IF(L77="","",INDEX('แผนงาน Schedule'!$AA$7:$AA$66,L77)) -> 46127 | F77: =IF(L77="","",N(INDEX('แผนงาน Schedule'!$O$7:$O$66,L77))) -> 0 | G77: =IF(L77="","",INDEX('แผนงาน Schedule'!$V$7:$V$66,L77)) -> 46337 | H77: =IF(L77="","",INDEX('แผนงาน Schedule'!$X$7:$X$66,L77)) -> เกินกำหนด / Overdue | J77: =IF(L77="","",INDEX('แผนงาน Schedule'!$Y$7:$Y$66,L77)&"") | L77: =IFERROR(MATCH(2,'แผนงาน Schedule'!$AD$7:$AD$66,0),"") -> 2
B78: =IF(L78="","",3) -> 3 | C78: =IF(L78="","",INDEX('แผนงาน Schedule'!$A$7:$A$66,L78)&" "&INDEX('แผนงาน Schedule'!$C$7:$C$66,L78)) -> 1.3 งานรื้อถอนโครงสร้างเดิมและเตรียมพื้นที่ติดตั้งใหม่ | D78: =IF(L78="","",INDEX('แผนงาน Schedule'!$Z$7:$Z$66,L78)) -> 46092 | E78: =IF(L78="","",INDEX('แผนงาน Schedule'!$AA$7:$AA$66,L78)) -> 46132 | F78: =IF(L78="","",N(INDEX('แผนงาน Schedule'!$O$7:$O$66,L78))) -> 0 | G78: =IF(L78="","",INDEX('แผนงาน Schedule'!$V$7:$V$66,L78)) -> 46333 | H78: =IF(L78="","",INDEX('แผนงาน Schedule'!$X$7:$X$66,L78)) -> เกินกำหนด / Overdue | J78: =IF(L78="","",INDEX('แผนงาน Schedule'!$Y$7:$Y$66,L78)&"") | L78: =IFERROR(MATCH(3,'แผนงาน Schedule'!$AD$7:$AD$66,0),"") -> 3
B79: =IF(L79="","",4) -> 4 | C79: =IF(L79="","",INDEX('แผนงาน Schedule'!$A$7:$A$66,L79)&" "&INDEX('แผนงาน Schedule'!$C$7:$C$66,L79)) -> 2.1 งานฐานราก คานคอดิน พื้นชั้น 1 และเสาชั้น 1 | D79: =IF(L79="","",INDEX('แผนงาน Schedule'!$Z$7:$Z$66,L79)) -> 46096 | E79: =IF(L79="","",INDEX('แผนงาน Schedule'!$AA$7:$AA$66,L79)) -> 46142 | F79: =IF(L79="","",N(INDEX('แผนงาน Schedule'!$O$7:$O$66,L79))) -> 0 | G79: =IF(L79="","",INDEX('แผนงาน Schedule'!$V$7:$V$66,L79)) -> 46339 | H79: =IF(L79="","",INDEX('แผนงาน Schedule'!$X$7:$X$66,L79)) -> เกินกำหนด / Overdue | J79: =IF(L79="","",INDEX('แผนงาน Schedule'!$Y$7:$Y$66,L79)&"") | L79: =IFERROR(MATCH(4,'แผนงาน Schedule'!$AD$7:$AD$66,0),"") -> 4
B80: =IF(L80="","",5) -> 5 | C80: =IF(L80="","",INDEX('แผนงาน Schedule'!$A$7:$A$66,L80)&" "&INDEX('แผนงาน Schedule'!$C$7:$C$66,L80)) -> 2.2 งานวาง SLEEVE/เดินท่อฝังในโครงสร้าง และโครงสร้างชั้น 1–2 | D80: =IF(L80="","",INDEX('แผนงาน Schedule'!$Z$7:$Z$66,L80)) -> 46127 | E80: =IF(L80="","",INDEX('แผนงาน Schedule'!$AA$7:$AA$66,L80)) -> 46157 | F80: =IF(L80="","",N(INDEX('แผนงาน Schedule'!$O$7:$O$66,L80))) -> 0 | G80: =IF(L80="","",INDEX('แผนงาน Schedule'!$V$7:$V$66,L80)) -> 46323 | H80: =IF(L80="","",INDEX('แผนงาน Schedule'!$X$7:$X$66,L80)) -> เกินกำหนด / Overdue | J80: =IF(L80="","",INDEX('แผนงาน Schedule'!$Y$7:$Y$66,L80)&"") | L80: =IFERROR(MATCH(5,'แผนงาน Schedule'!$AD$7:$AD$66,0),"") -> 5
B81: =IF(L81="","",6) -> 6 | C81: =IF(L81="","",INDEX('แผนงาน Schedule'!$A$7:$A$66,L81)&" "&INDEX('แผนงาน Schedule'!$C$7:$C$66,L81)) -> 2.3 งานคานและพื้นชั้น 2 พร้อมวาง SLEEVE ชั้น 2 | D81: =IF(L81="","",INDEX('แผนงาน Schedule'!$Z$7:$Z$66,L81)) -> 46153 | E81: =IF(L81="","",INDEX('แผนงาน Schedule'!$AA$7:$AA$66,L81)) -> 46178 | F81: =IF(L81="","",N(INDEX('แผนงาน Schedule'!$O$7:$O$66,L81))) -> 0 | G81: =IF(L81="","",INDEX('แผนงาน Schedule'!$V$7:$V$66,L81)) -> 46318 | H81: =IF(L81="","",INDEX('แผนงาน Schedule'!$X$7:$X$66,L81)) -> เกินกำหนด / Overdue | J81: =IF(L81="","",INDEX('แผนงาน Schedule'!$Y$7:$Y$66,L81)&"") | L81: =IFERROR(MATCH(6,'แผนงาน Schedule'!$AD$7:$AD$66,0),"") -> 6
B82: =IF(L82="","",7) -> 7 | C82: =IF(L82="","",INDEX('แผนงาน Schedule'!$A$7:$A$66,L82)&" "&INDEX('แผนงาน Schedule'!$C$7:$C$66,L82)) -> 2.4 งานโครงสร้างหลังคาและมุงหลังคา | D82: =IF(L82="","",INDEX('แผนงาน Schedule'!$Z$7:$Z$66,L82)) -> 46174 | E82: =IF(L82="","",INDEX('แผนงาน Schedule'!$AA$7:$AA$66,L82)) -> 46198 | F82: =IF(L82="","",N(INDEX('แผนงาน Schedule'!$O$7:$O$66,L82))) -> 0 | G82: =IF(L82="","",INDEX('แผนงาน Schedule'!$V$7:$V$66,L82)) -> 46317 | H82: =IF(L82="","",INDEX('แผนงาน Schedule'!$X$7:$X$66,L82)) -> เกินกำหนด / Overdue | J82: =IF(L82="","",INDEX('แผนงาน Schedule'!$Y$7:$Y$66,L82)&"") | L82: =IFERROR(MATCH(7,'แผนงาน Schedule'!$AD$7:$AD$66,0),"") -> 7
B83: =IF(L83="","",8) -> 8 | C83: =IF(L83="","",INDEX('แผนงาน Schedule'!$A$7:$A$66,L83)&" "&INDEX('แผนงาน Schedule'!$C$7:$C$66,L83)) -> 3.1 งานผนัง/โครงเคร่า ติดตั้งฉนวน PU Foam และรางน้ำ | D83: =IF(L83="","",INDEX('แผนงาน Schedule'!$Z$7:$Z$66,L83)) -> 46188 | E83: =IF(L83="","",INDEX('แผนงาน Schedule'!$AA$7:$AA$66,L83)) -> 46218 | F83: =IF(L83="","",N(INDEX('แผนงาน Schedule'!$O$7:$O$66,L83))) -> 0 | G83: =IF(L83="","",INDEX('แผนงาน Schedule'!$V$7:$V$66,L83)) -> 46323 | H83: =IF(L83="","",INDEX('แผนงาน Schedule'!$X$7:$X$66,L83)) -> เกินกำหนด / Overdue | J83: =IF(L83="","",INDEX('แผนงาน Schedule'!$Y$7:$Y$66,L83)&"") | L83: =IFERROR(MATCH(8,'แผนงาน Schedule'!$AD$7:$AD$66,0),"") -> 8
B84: =IF(L84="","",9) -> 9 | C84: =IF(L84="","",INDEX('แผนงาน Schedule'!$A$7:$A$66,L84)&" "&INDEX('แผนงาน Schedule'!$C$7:$C$66,L84)) -> 4.1 งานเดินท่อประปา ท่อน้ำทิ้ง และงานระบบในผนัง | D84: =IF(L84="","",INDEX('แผนงาน Schedule'!$Z$7:$Z$66,L84)) -> 46214 | E84: =IF(L84="","",INDEX('แผนงาน Schedule'!$AA$7:$AA$66,L84)) -> 46233 | F84: =IF(L84="","",N(INDEX('แผนงาน Schedule'!$O$7:$O$66,L84))) -> 0 | G84: =IF(L84="","",INDEX('แผนงาน Schedule'!$V$7:$V$66,L84)) -> 46312 | H84: =IF(L84="","",INDEX('แผนงาน Schedule'!$X$7:$X$66,L84)) -> เกินกำหนด / Overdue | J84: =IF(L84="","",INDEX('แผนงาน Schedule'!$Y$7:$Y$66,L84)&"") | L84: =IFERROR(MATCH(9,'แผนงาน Schedule'!$AD$7:$AD$66,0),"") -> 9
B85: =IF(L85="","",10) -> 10 | C85: =IF(L85="","",INDEX('แผนงาน Schedule'!$A$7:$A$66,L85)&" "&INDEX('แผนงาน Schedule'!$C$7:$C$66,L85)) -> 3.2 งานฉาบปูน ฝ้าเพดาน ปูพื้น และทาสีภายใน-ภายนอก | D85: =IF(L85="","",INDEX('แผนงาน Schedule'!$Z$7:$Z$66,L85)) -> 46204 | E85: =IF(L85="","",INDEX('แผนงาน Schedule'!$AA$7:$AA$66,L85)) -> 46249 | F85: =IF(L85="","",N(INDEX('แผนงาน Schedule'!$O$7:$O$66,L85))) -> 0 | G85: =IF(L85="","",INDEX('แผนงาน Schedule'!$V$7:$V$66,L85)) -> 46338 | H85: =IF(L85="","",INDEX('แผนงาน Schedule'!$X$7:$X$66,L85)) -> เกินกำหนด / Overdue | J85: =IF(L85="","",INDEX('แผนงาน Schedule'!$Y$7:$Y$66,L85)&"") | L85: =IFERROR(MATCH(10,'แผนงาน Schedule'!$AD$7:$AD$66,0),"") -> 10
B87: 5. การขยายเวลาและค่าปรับ / Extension of Time & Liquidated Damages
B88: ขอขยายเวลารวม / Claimed | D88: =Dashboard!C49 -> 0 | F88: อนุมัติแล้ว / Approved | I88: =Dashboard!C50 -> 0
B89: รอพิจารณา / Pending | D89: =Dashboard!C51 -> 0 | F89: วันสิ้นสุดหลังขยายเวลา / Revised Completion | I89: =Dashboard!C12 -> 46342
B90: ค่าปรับต่อวัน / LD per Day (฿) | D90: =Dashboard!C52 -> 12108 | F90: ค่าปรับเกิดขึ้นแล้ว / LD Incurred (฿) | I90: =Dashboard!C54 -> 0
B91: ค่าปรับคาดการณ์ / Forecast LD (฿) | D91: =Dashboard!C55 -> 6998424 | F91: สัญญาณเตือน / Alert | I91: =Dashboard!C57 -> ⚠ เกินเกณฑ์ 10% – ความเสี่ยงถูกบอกเลิกสัญญา
B93: 6. ปัญหา อุปสรรค และแนวทางแก้ไข / Issues, Risks & Corrective Actions
B94: ลำดับ | C94: ปัญหา / Issue | G94: แนวทางแก้ไข / ผู้รับผิดชอบ / กำหนดเสร็จ
B95: 1
B96: 2
B97: 3
B98: 4
B99: 5
B102: ลงชื่อ .................................... | D102: =IF('ตั้งค่า Setup'!C22<>"",'ตั้งค่า Setup'!C22,"") | E102: ลงชื่อ .................................... | H102: ลงชื่อ ....................................
B103: (....................................) | E103: (....................................) | H103: (....................................)
B104: ผู้จัดทำ / Prepared by | E104: ผู้ตรวจสอบ / Checked by | H104: ผู้อนุมัติ / Approved by
B105: วันที่ ........../........../.......... | E105: วันที่ ........../........../.......... | H105: วันที่ ........../........../..........

Sheet งวดงาน Installments
A1: งวดงานตามสัญญา / Contract Payment Installments
A2: กรอกตามงวดงานที่ระบุในสัญญา/TOR • ระบบแสดงสถานะ ความล่าช้า และเช็คว่าผลงานถึงเกณฑ์ของงวดแล้วหรือยัง
A3: ตัวอย่างการกรอก: 1 | งานฐานรากและโครงสร้างชั้น 1 แล้วเสร็จ | 25% | 30-Apr-26 | 3,000,000 | ส่งมอบ 28-Apr-26 | ตรวจรับ 5-May-26
A6: งวดที่ No. | B6: เนื้องานที่ต้องแล้วเสร็จในงวด Scope of Installment | C6: ผลงานสะสม ที่กำหนด (%) | D6: กำหนดแล้วเสร็จ Due Date | E6: จำนวนเงิน (บาท) Amount | F6: % ของ ค่าจ้าง | G6: วันที่ส่งมอบงาน Submitted | H6: วันที่ตรวจรับ Accepted | I6: เบิกจ่ายแล้ว (บาท) | J6: ผลงานปัจจุบัน เทียบเกณฑ์ | K6: สถานะ Status | L6: ล่าช้า (วัน) | M6: หมายเหตุ Remarks
F7: =IF(E7="","",E7/'ตั้งค่า Setup'!$C$9) | I7: =IF(OR(E7="",H7=""),"",E7) | J7: =IF(OR(B7="",C7=""),"",IF(Dashboard!$C$19>=C7,"✓ ถึงเกณฑ์แล้ว","ยังขาด "&TEXT(C7-Dashboard!$C$19,"0.00%"))) | K7: =IF(B7="","",IF(H7<>"","ตรวจรับแล้ว",IF(G7<>"","ส่งมอบแล้ว รอตรวจรับ",IF(D7="","-",IF('ตั้งค่า Setup'!$C$15>D7,"เกินกำหนด",IF(D7-'ตั้งค่า Setup'!$C$15<=14,"ใกล้ครบกำหนด (≤14 วัน)","ยังไม่ถึงกำหนด")))))) | L7: =IF(OR(B7="",D7=""),"",MAX(0,IF(G7<>"",G7,IF(H7<>"",H7,'ตั้งค่า Setup'!$C$15))-D7))
F8: =IF(E8="","",E8/'ตั้งค่า Setup'!$C$9) | I8: =IF(OR(E8="",H8=""),"",E8) | J8: =IF(OR(B8="",C8=""),"",IF(Dashboard!$C$19>=C8,"✓ ถึงเกณฑ์แล้ว","ยังขาด "&TEXT(C8-Dashboard!$C$19,"0.00%"))) | K8: =IF(B8="","",IF(H8<>"","ตรวจรับแล้ว",IF(G8<>"","ส่งมอบแล้ว รอตรวจรับ",IF(D8="","-",IF('ตั้งค่า Setup'!$C$15>D8,"เกินกำหนด",IF(D8-'ตั้งค่า Setup'!$C$15<=14,"ใกล้ครบกำหนด (≤14 วัน)","ยังไม่ถึงกำหนด")))))) | L8: =IF(OR(B8="",D8=""),"",MAX(0,IF(G8<>"",G8,IF(H8<>"",H8,'ตั้งค่า Setup'!$C$15))-D8))
F9: =IF(E9="","",E9/'ตั้งค่า Setup'!$C$9) | I9: =IF(OR(E9="",H9=""),"",E9) | J9: =IF(OR(B9="",C9=""),"",IF(Dashboard!$C$19>=C9,"✓ ถึงเกณฑ์แล้ว","ยังขาด "&TEXT(C9-Dashboard!$C$19,"0.00%"))) | K9: =IF(B9="","",IF(H9<>"","ตรวจรับแล้ว",IF(G9<>"","ส่งมอบแล้ว รอตรวจรับ",IF(D9="","-",IF('ตั้งค่า Setup'!$C$15>D9,"เกินกำหนด",IF(D9-'ตั้งค่า Setup'!$C$15<=14,"ใกล้ครบกำหนด (≤14 วัน)","ยังไม่ถึงกำหนด")))))) | L9: =IF(OR(B9="",D9=""),"",MAX(0,IF(G9<>"",G9,IF(H9<>"",H9,'ตั้งค่า Setup'!$C$15))-D9))
F10: =IF(E10="","",E10/'ตั้งค่า Setup'!$C$9) | I10: =IF(OR(E10="",H10=""),"",E10) | J10: =IF(OR(B10="",C10=""),"",IF(Dashboard!$C$19>=C10,"✓ ถึงเกณฑ์แล้ว","ยังขาด "&TEXT(C10-Dashboard!$C$19,"0.00%"))) | K10: =IF(B10="","",IF(H10<>"","ตรวจรับแล้ว",IF(G10<>"","ส่งมอบแล้ว รอตรวจรับ",IF(D10="","-",IF('ตั้งค่า Setup'!$C$15>D10,"เกินกำหนด",IF(D10-'ตั้งค่า Setup'!$C$15<=14,"ใกล้ครบกำหนด (≤14 วัน)","ยังไม่ถึงกำหนด")))))) | L10: =IF(OR(B10="",D10=""),"",MAX(0,IF(G10<>"",G10,IF(H10<>"",H10,'ตั้งค่า Setup'!$C$15))-D10))
F11: =IF(E11="","",E11/'ตั้งค่า Setup'!$C$9) | I11: =IF(OR(E11="",H11=""),"",E11) | J11: =IF(OR(B11="",C11=""),"",IF(Dashboard!$C$19>=C11,"✓ ถึงเกณฑ์แล้ว","ยังขาด "&TEXT(C11-Dashboard!$C$19,"0.00%"))) | K11: =IF(B11="","",IF(H11<>"","ตรวจรับแล้ว",IF(G11<>"","ส่งมอบแล้ว รอตรวจรับ",IF(D11="","-",IF('ตั้งค่า Setup'!$C$15>D11,"เกินกำหนด",IF(D11-'ตั้งค่า Setup'!$C$15<=14,"ใกล้ครบกำหนด (≤14 วัน)","ยังไม่ถึงกำหนด")))))) | L11: =IF(OR(B11="",D11=""),"",MAX(0,IF(G11<>"",G11,IF(H11<>"",H11,'ตั้งค่า Setup'!$C$15))-D11))
F12: =IF(E12="","",E12/'ตั้งค่า Setup'!$C$9) | I12: =IF(OR(E12="",H12=""),"",E12) | J12: =IF(OR(B12="",C12=""),"",IF(Dashboard!$C$19>=C12,"✓ ถึงเกณฑ์แล้ว","ยังขาด "&TEXT(C12-Dashboard!$C$19,"0.00%"))) | K12: =IF(B12="","",IF(H12<>"","ตรวจรับแล้ว",IF(G12<>"","ส่งมอบแล้ว รอตรวจรับ",IF(D12="","-",IF('ตั้งค่า Setup'!$C$15>D12,"เกินกำหนด",IF(D12-'ตั้งค่า Setup'!$C$15<=14,"ใกล้ครบกำหนด (≤14 วัน)","ยังไม่ถึงกำหนด")))))) | L12: =IF(OR(B12="",D12=""),"",MAX(0,IF(G12<>"",G12,IF(H12<>"",H12,'ตั้งค่า Setup'!$C$15))-D12))
F13: =IF(E13="","",E13/'ตั้งค่า Setup'!$C$9) | I13: =IF(OR(E13="",H13=""),"",E13) | J13: =IF(OR(B13="",C13=""),"",IF(Dashboard!$C$19>=C13,"✓ ถึงเกณฑ์แล้ว","ยังขาด "&TEXT(C13-Dashboard!$C$19,"0.00%"))) | K13: =IF(B13="","",IF(H13<>"","ตรวจรับแล้ว",IF(G13<>"","ส่งมอบแล้ว รอตรวจรับ",IF(D13="","-",IF('ตั้งค่า Setup'!$C$15>D13,"เกินกำหนด",IF(D13-'ตั้งค่า Setup'!$C$15<=14,"ใกล้ครบกำหนด (≤14 วัน)","ยังไม่ถึงกำหนด")))))) | L13: =IF(OR(B13="",D13=""),"",MAX(0,IF(G13<>"",G13,IF(H13<>"",H13,'ตั้งค่า Setup'!$C$15))-D13))
F14: =IF(E14="","",E14/'ตั้งค่า Setup'!$C$9) | I14: =IF(OR(E14="",H14=""),"",E14) | J14: =IF(OR(B14="",C14=""),"",IF(Dashboard!$C$19>=C14,"✓ ถึงเกณฑ์แล้ว","ยังขาด "&TEXT(C14-Dashboard!$C$19,"0.00%"))) | K14: =IF(B14="","",IF(H14<>"","ตรวจรับแล้ว",IF(G14<>"","ส่งมอบแล้ว รอตรวจรับ",IF(D14="","-",IF('ตั้งค่า Setup'!$C$15>D14,"เกินกำหนด",IF(D14-'ตั้งค่า Setup'!$C$15<=14,"ใกล้ครบกำหนด (≤14 วัน)","ยังไม่ถึงกำหนด")))))) | L14: =IF(OR(B14="",D14=""),"",MAX(0,IF(G14<>"",G14,IF(H14<>"",H14,'ตั้งค่า Setup'!$C$15))-D14))
F15: =IF(E15="","",E15/'ตั้งค่า Setup'!$C$9) | I15: =IF(OR(E15="",H15=""),"",E15) | J15: =IF(OR(B15="",C15=""),"",IF(Dashboard!$C$19>=C15,"✓ ถึงเกณฑ์แล้ว","ยังขาด "&TEXT(C15-Dashboard!$C$19,"0.00%"))) | K15: =IF(B15="","",IF(H15<>"","ตรวจรับแล้ว",IF(G15<>"","ส่งมอบแล้ว รอตรวจรับ",IF(D15="","-",IF('ตั้งค่า Setup'!$C$15>D15,"เกินกำหนด",IF(D15-'ตั้งค่า Setup'!$C$15<=14,"ใกล้ครบกำหนด (≤14 วัน)","ยังไม่ถึงกำหนด")))))) | L15: =IF(OR(B15="",D15=""),"",MAX(0,IF(G15<>"",G15,IF(H15<>"",H15,'ตั้งค่า Setup'!$C$15))-D15))
F16: =IF(E16="","",E16/'ตั้งค่า Setup'!$C$9) | I16: =IF(OR(E16="",H16=""),"",E16) | J16: =IF(OR(B16="",C16=""),"",IF(Dashboard!$C$19>=C16,"✓ ถึงเกณฑ์แล้ว","ยังขาด "&TEXT(C16-Dashboard!$C$19,"0.00%"))) | K16: =IF(B16="","",IF(H16<>"","ตรวจรับแล้ว",IF(G16<>"","ส่งมอบแล้ว รอตรวจรับ",IF(D16="","-",IF('ตั้งค่า Setup'!$C$15>D16,"เกินกำหนด",IF(D16-'ตั้งค่า Setup'!$C$15<=14,"ใกล้ครบกำหนด (≤14 วัน)","ยังไม่ถึงกำหนด")))))) | L16: =IF(OR(B16="",D16=""),"",MAX(0,IF(G16<>"",G16,IF(H16<>"",H16,'ตั้งค่า Setup'!$C$15))-D16))
F17: =IF(E17="","",E17/'ตั้งค่า Setup'!$C$9) | I17: =IF(OR(E17="",H17=""),"",E17) | J17: =IF(OR(B17="",C17=""),"",IF(Dashboard!$C$19>=C17,"✓ ถึงเกณฑ์แล้ว","ยังขาด "&TEXT(C17-Dashboard!$C$19,"0.00%"))) | K17: =IF(B17="","",IF(H17<>"","ตรวจรับแล้ว",IF(G17<>"","ส่งมอบแล้ว รอตรวจรับ",IF(D17="","-",IF('ตั้งค่า Setup'!$C$15>D17,"เกินกำหนด",IF(D17-'ตั้งค่า Setup'!$C$15<=14,"ใกล้ครบกำหนด (≤14 วัน)","ยังไม่ถึงกำหนด")))))) | L17: =IF(OR(B17="",D17=""),"",MAX(0,IF(G17<>"",G17,IF(H17<>"",H17,'ตั้งค่า Setup'!$C$15))-D17))
F18: =IF(E18="","",E18/'ตั้งค่า Setup'!$C$9) | I18: =IF(OR(E18="",H18=""),"",E18) | J18: =IF(OR(B18="",C18=""),"",IF(Dashboard!$C$19>=C18,"✓ ถึงเกณฑ์แล้ว","ยังขาด "&TEXT(C18-Dashboard!$C$19,"0.00%"))) | K18: =IF(B18="","",IF(H18<>"","ตรวจรับแล้ว",IF(G18<>"","ส่งมอบแล้ว รอตรวจรับ",IF(D18="","-",IF('ตั้งค่า Setup'!$C$15>D18,"เกินกำหนด",IF(D18-'ตั้งค่า Setup'!$C$15<=14,"ใกล้ครบกำหนด (≤14 วัน)","ยังไม่ถึงกำหนด")))))) | L18: =IF(OR(B18="",D18=""),"",MAX(0,IF(G18<>"",G18,IF(H18<>"",H18,'ตั้งค่า Setup'!$C$15))-D18))
... F26: =IF(E26="","",E26/'ตั้งค่า Setup'!$C$9) | I26: =IF(OR(E26="",H26=""),"",E26) | J26: =IF(OR(B26="",C26=""),"",IF(Dashboard!$C$19>=C26,"✓ ถึงเกณฑ์แล้ว","ยังขาด "&TEXT(C26-Dashboard!$C$19,"0.00%"))) | K26: =IF(B26="","",IF(H26<>"","ตรวจรับแล้ว",IF(G26<>"","ส่งมอบแล้ว รอตรวจรับ",IF(D26="","-",IF('ตั้งค่า Setup'!$C$15>D26,"เกินกำหนด",IF(D26-'ตั้งค่า Setup'!$C$15<=14,"ใกล้ครบกำหนด (≤14 วัน)","ยังไม่ถึงกำหนด")))))) | L26: =IF(OR(B26="",D26=""),"",MAX(0,IF(G26<>"",G26,IF(H26<>"",H26,'ตั้งค่า Setup'!$C$15))-D26))
B27: รวม / TOTAL | E27: =SUM(E7:E26) -> 0 | F27: =SUM(F7:F26) -> 0 | I27: =SUM(I7:I26) -> 0 | K27: =IF(COUNT(E7:E26)=0,"",IF(ABS(E27-'ตั้งค่า Setup'!$C$9)<1,"✓ ตรงกับมูลค่าสัญญา","⚠ ต่างจากมูลค่าสัญญา "&TEXT(E27-'ตั้งค่า Setup'!$C$9,"#,##0")))

Sheet บันทึกสัปดาห์ Weekly Log
A1: บันทึกผลการปฏิบัติงานประจำสัปดาห์ / Weekly Site Log
A2: กรอกทุกสัปดาห์ 1 แถว • ข้อมูลในแถวของสัปดาห์ที่เลือกจะไปแสดงในชีต รายงานกรรมการ Weekly อัตโนมัติ
B3: ข้อมูลสำหรับหนังสือรายงาน / Memo Details | C3: ค่า / Value | D3: หมายเหตุ
B4: ส่วนราชการ / หน่วยงาน
B5: เลขที่หนังสือ (ที่) | D5: เช่น กท 1234/2569
B6: วันที่ลงนามสัญญา | D6: ใช้ในย่อหน้าอ้างถึงสัญญา
B7: ชื่อผู้ควบคุมงาน | D7: ผู้ลงนามในรายงาน
B8: ตำแหน่งผู้ควบคุมงาน | C8: ผู้ควบคุมงาน
B9: ประธานกรรมการตรวจรับพัสดุ
B10: กรรมการตรวจรับพัสดุ คนที่ 1
B11: กรรมการตรวจรับพัสดุ คนที่ 2
B12: รายงานสัปดาห์ที่ (เลือก) | C12: =MAX(1,INT(('ตั้งค่า Setup'!$C$15-'ตั้งค่า Setup'!$C$10+1)/7)) -> 31 | D12: ค่าเริ่มต้น = สัปดาห์ล่าสุดที่ครบ 7 วันแล้ว (พิมพ์ทับได้)
B13: วันที่ออกรายงาน | C13: ='ตั้งค่า Setup'!$C$15 -> 46293 | D13: ค่าเริ่มต้น = Status Date (พิมพ์ทับได้)
A15: ตารางบันทึกรายสัปดาห์ (แถวสีส้ม = สัปดาห์ที่เลือกรายงาน) • ช่วงวันที่คำนวณจากวันเริ่มสัญญา ทุก 7 วัน
A16: สัปดาห์ ที่ | B16: จาก From | C16: ถึง To | D16: % แผน สะสม | E16: % จริง สะสม (กรอก) | F16: ผลงาน สัปดาห์นี้ | G16: ผลต่าง (จริง−แผน) | H16: คนงานเฉลี่ย (คน/วัน) | I16: เครื่องจักรหลัก Machinery | J16: วันทำงาน / หยุด-ฝนตก | K16: งานที่ดำเนินการในสัปดาห์นี้ Work Done This Week | L16: แผนงานสัปดาห์หน้า Plan Next Week | M16: วัสดุเข้าหน่วยงาน / การทดสอบ Materials & Tests | N16: ปัญหา อุปสรรค Issues | O16: ความเห็นผู้ควบคุมงาน Supervisor's Opinion
A17: =IF('ตั้งค่า Setup'!$C$10+7*0>MAX('ตั้งค่า Setup'!$C$69,'ตั้งค่า Setup'!$C$15)+7,"",1) -> 1 | B17: =IF(A17="","",'ตั้งค่า Setup'!$C$10+7*0) -> 46073 | C17: =IF(A17="","",B17+6) -> 46079 | D17: =IF(A17="","",SUMPRODUCT('แผนงาน Schedule'!$F$7:$F$66,('แผนงาน Schedule'!$I$7:$I$66<=C17)+('แผนงาน Schedule'!$H$7:$H$66<=C17)*('แผนงาน Schedule'!$I$7:$I$66>C17)*(C17-'แผนงาน Schedule'!$H$7:$H$66+1)/('แผนงาน Schedule'!$I$7:$I$66-'แผนงาน Schedule'!$H$7:$H$66+1))) -> 0.02015 | F17: =IF(E17="","",E17-0) | G17: =IF(OR(E17="",D17=""),"",E17-D17)
A18: =IF('ตั้งค่า Setup'!$C$10+7*1>MAX('ตั้งค่า Setup'!$C$69,'ตั้งค่า Setup'!$C$15)+7,"",2) -> 2 | B18: =IF(A18="","",'ตั้งค่า Setup'!$C$10+7*1) -> 46080 | C18: =IF(A18="","",B18+6) -> 46086 | D18: =IF(A18="","",SUMPRODUCT('แผนงาน Schedule'!$F$7:$F$66,('แผนงาน Schedule'!$I$7:$I$66<=C18)+('แผนงาน Schedule'!$H$7:$H$66<=C18)*('แผนงาน Schedule'!$I$7:$I$66>C18)*(C18-'แผนงาน Schedule'!$H$7:$H$66+1)/('แผนงาน Schedule'!$I$7:$I$66-'แผนงาน Schedule'!$H$7:$H$66+1))) -> 0.039514583 | F18: =IF(E18="","",E18-N(E17)) | G18: =IF(OR(E18="",D18=""),"",E18-D18)
A19: =IF('ตั้งค่า Setup'!$C$10+7*2>MAX('ตั้งค่า Setup'!$C$69,'ตั้งค่า Setup'!$C$15)+7,"",3) -> 3 | B19: =IF(A19="","",'ตั้งค่า Setup'!$C$10+7*2) -> 46087 | C19: =IF(A19="","",B19+6) -> 46093 | D19: =IF(A19="","",SUMPRODUCT('แผนงาน Schedule'!$F$7:$F$66,('แผนงาน Schedule'!$I$7:$I$66<=C19)+('แผนงาน Schedule'!$H$7:$H$66<=C19)*('แผนงาน Schedule'!$I$7:$I$66>C19)*(C19-'แผนงาน Schedule'!$H$7:$H$66+1)/('แผนงาน Schedule'!$I$7:$I$66-'แผนงาน Schedule'!$H$7:$H$66+1))) -> 0.046105691 | F19: =IF(E19="","",E19-N(E18)) | G19: =IF(OR(E19="",D19=""),"",E19-D19)
A20: =IF('ตั้งค่า Setup'!$C$10+7*3>MAX('ตั้งค่า Setup'!$C$69,'ตั้งค่า Setup'!$C$15)+7,"",4) -> 4 | B20: =IF(A20="","",'ตั้งค่า Setup'!$C$10+7*3) -> 46094 | C20: =IF(A20="","",B20+6) -> 46100 | D20: =IF(A20="","",SUMPRODUCT('แผนงาน Schedule'!$F$7:$F$66,('แผนงาน Schedule'!$I$7:$I$66<=C20)+('แผนงาน Schedule'!$H$7:$H$66<=C20)*('แผนงาน Schedule'!$I$7:$I$66>C20)*(C20-'แผนงาน Schedule'!$H$7:$H$66+1)/('แผนงาน Schedule'!$I$7:$I$66-'แผนงาน Schedule'!$H$7:$H$66+1))) -> 0.062881993 | F20: =IF(E20="","",E20-N(E19)) | G20: =IF(OR(E20="",D20=""),"",E20-D20)
A21: =IF('ตั้งค่า Setup'!$C$10+7*4>MAX('ตั้งค่า Setup'!$C$69,'ตั้งค่า Setup'!$C$15)+7,"",5) -> 5 | B21: =IF(A21="","",'ตั้งค่า Setup'!$C$10+7*4) -> 46101 | C21: =IF(A21="","",B21+6) -> 46107 | D21: =IF(A21="","",SUMPRODUCT('แผนงาน Schedule'!$F$7:$F$66,('แผนงาน Schedule'!$I$7:$I$66<=C21)+('แผนงาน Schedule'!$H$7:$H$66<=C21)*('แผนงาน Schedule'!$I$7:$I$66>C21)*(C21-'แผนงาน Schedule'!$H$7:$H$66+1)/('แผนงาน Schedule'!$I$7:$I$66-'แผนงาน Schedule'!$H$7:$H$66+1))) -> 0.083700848 | F21: =IF(E21="","",E21-N(E20)) | G21: =IF(OR(E21="",D21=""),"",E21-D21)
A22: =IF('ตั้งค่า Setup'!$C$10+7*5>MAX('ตั้งค่า Setup'!$C$69,'ตั้งค่า Setup'!$C$15)+7,"",6) -> 6 | B22: =IF(A22="","",'ตั้งค่า Setup'!$C$10+7*5) -> 46108 | C22: =IF(A22="","",B22+6) -> 46114 | D22: =IF(A22="","",SUMPRODUCT('แผนงาน Schedule'!$F$7:$F$66,('แผนงาน Schedule'!$I$7:$I$66<=C22)+('แผนงาน Schedule'!$H$7:$H$66<=C22)*('แผนงาน Schedule'!$I$7:$I$66>C22)*(C22-'แผนงาน Schedule'!$H$7:$H$66+1)/('แผนงาน Schedule'!$I$7:$I$66-'แผนงาน Schedule'!$H$7:$H$66+1))) -> 0.1045197 | F22: =IF(E22="","",E22-N(E21)) | G22: =IF(OR(E22="",D22=""),"",E22-D22)
A23: =IF('ตั้งค่า Setup'!$C$10+7*6>MAX('ตั้งค่า Setup'!$C$69,'ตั้งค่า Setup'!$C$15)+7,"",7) -> 7 | B23: =IF(A23="","",'ตั้งค่า Setup'!$C$10+7*6) -> 46115 | C23: =IF(A23="","",B23+6) -> 46121 | D23: =IF(A23="","",SUMPRODUCT('แผนงาน Schedule'!$F$7:$F$66,('แผนงาน Schedule'!$I$7:$I$66<=C23)+('แผนงาน Schedule'!$H$7:$H$66<=C23)*('แผนงาน Schedule'!$I$7:$I$66>C23)*(C23-'แผนงาน Schedule'!$H$7:$H$66+1)/('แผนงาน Schedule'!$I$7:$I$66-'แผนงาน Schedule'!$H$7:$H$66+1))) -> 0.12533856 | F23: =IF(E23="","",E23-N(E22)) | G23: =IF(OR(E23="",D23=""),"",E23-D23)
A24: =IF('ตั้งค่า Setup'!$C$10+7*7>MAX('ตั้งค่า Setup'!$C$69,'ตั้งค่า Setup'!$C$15)+7,"",8) -> 8 | B24: =IF(A24="","",'ตั้งค่า Setup'!$C$10+7*7) -> 46122 | C24: =IF(A24="","",B24+6) -> 46128 | D24: =IF(A24="","",SUMPRODUCT('แผนงาน Schedule'!$F$7:$F$66,('แผนงาน Schedule'!$I$7:$I$66<=C24)+('แผนงาน Schedule'!$H$7:$H$66<=C24)*('แผนงาน Schedule'!$I$7:$I$66>C24)*(C24-'แผนงาน Schedule'!$H$7:$H$66+1)/('แผนงาน Schedule'!$I$7:$I$66-'แผนงาน Schedule'!$H$7:$H$66+1))) -> 0.14973698 | F24: =IF(E24="","",E24-N(E23)) | G24: =IF(OR(E24="",D24=""),"",E24-D24)
A25: =IF('ตั้งค่า Setup'!$C$10+7*8>MAX('ตั้งค่า Setup'!$C$69,'ตั้งค่า Setup'!$C$15)+7,"",9) -> 9 | B25: =IF(A25="","",'ตั้งค่า Setup'!$C$10+7*8) -> 46129 | C25: =IF(A25="","",B25+6) -> 46135 | D25: =IF(A25="","",SUMPRODUCT('แผนงาน Schedule'!$F$7:$F$66,('แผนงาน Schedule'!$I$7:$I$66<=C25)+('แผนงาน Schedule'!$H$7:$H$66<=C25)*('แผนงาน Schedule'!$I$7:$I$66>C25)*(C25-'แผนงาน Schedule'!$H$7:$H$66+1)/('แผนงาน Schedule'!$I$7:$I$66-'แผนงาน Schedule'!$H$7:$H$66+1))) -> 0.18000913 | F25: =IF(E25="","",E25-N(E24)) | G25: =IF(OR(E25="",D25=""),"",E25-D25)
A26: =IF('ตั้งค่า Setup'!$C$10+7*9>MAX('ตั้งค่า Setup'!$C$69,'ตั้งค่า Setup'!$C$15)+7,"",10) -> 10 | B26: =IF(A26="","",'ตั้งค่า Setup'!$C$10+7*9) -> 46136 | C26: =IF(A26="","",B26+6) -> 46142 | D26: =IF(A26="","",SUMPRODUCT('แผนงาน Schedule'!$F$7:$F$66,('แผนงาน Schedule'!$I$7:$I$66<=C26)+('แผนงาน Schedule'!$H$7:$H$66<=C26)*('แผนงาน Schedule'!$I$7:$I$66>C26)*(C26-'แผนงาน Schedule'!$H$7:$H$66+1)/('แผนงาน Schedule'!$I$7:$I$66-'แผนงาน Schedule'!$H$7:$H$66+1))) -> 0.20820323 | F26: =IF(E26="","",E26-N(E25)) | G26: =IF(OR(E26="",D26=""),"",E26-D26)
A27: =IF('ตั้งค่า Setup'!$C$10+7*10>MAX('ตั้งค่า Setup'!$C$69,'ตั้งค่า Setup'!$C$15)+7,"",11) -> 11 | B27: =IF(A27="","",'ตั้งค่า Setup'!$C$10+7*10) -> 46143 | C27: =IF(A27="","",B27+6) -> 46149 | D27: =IF(A27="","",SUMPRODUCT('แผนงาน Schedule'!$F$7:$F$66,('แผนงาน Schedule'!$I$7:$I$66<=C27)+('แผนงาน Schedule'!$H$7:$H$66<=C27)*('แผนงาน Schedule'!$I$7:$I$66>C27)*(C27-'แผนงาน Schedule'!$H$7:$H$66+1)/('แผนงาน Schedule'!$I$7:$I$66-'แผนงาน Schedule'!$H$7:$H$66+1))) -> 0.22224839 | F27: =IF(E27="","",E27-N(E26)) | G27: =IF(OR(E27="",D27=""),"",E27-D27)
A28: =IF('ตั้งค่า Setup'!$C$10+7*11>MAX('ตั้งค่า Setup'!$C$69,'ตั้งค่า Setup'!$C$15)+7,"",12) -> 12 | B28: =IF(A28="","",'ตั้งค่า Setup'!$C$10+7*11) -> 46150 | C28: =IF(A28="","",B28+6) -> 46156 | D28: =IF(A28="","",SUMPRODUCT('แผนงาน Schedule'!$F$7:$F$66,('แผนงาน Schedule'!$I$7:$I$66<=C28)+('แผนงาน Schedule'!$H$7:$H$66<=C28)*('แผนงาน Schedule'!$I$7:$I$66>C28)*(C28-'แผนงาน Schedule'!$H$7:$H$66+1)/('แผนงาน Schedule'!$I$7:$I$66-'แผนงาน Schedule'!$H$7:$H$66+1))) -> 0.24612432 | F28: =IF(E28="","",E28-N(E27)) | G28: =IF(OR(E28="",D28=""),"",E28-D28)
A29: =IF('ตั้งค่า Setup'!$C$10+7*12>MAX('ตั้งค่า Setup'!$C$69,'ตั้งค่า Setup'!$C$15)+7,"",13) -> 13 | B29: =IF(A29="","",'ตั้งค่า Setup'!$C$10+7*12) -> 46157 | C29: =IF(A29="","",B29+6) -> 46163 | D29: =IF(A29="","",SUMPRODUCT('แผนงาน Schedule'!$F$7:$F$66,('แผนงาน Schedule'!$I$7:$I$66<=C29)+('แผนงาน Schedule'!$H$7:$H$66<=C29)*('แผนงาน Schedule'!$I$7:$I$66>C29)*(C29-'แผนงาน Schedule'!$H$7:$H$66+1)/('แผนงาน Schedule'!$I$7:$I$66-'แผนงาน Schedule'!$H$7:$H$66+1))) -> 0.26533462 | F29: =IF(E29="","",E29-N(E28)) | G29: =IF(OR(E29="",D29=""),"",E29-D29)
A30: =IF('ตั้งค่า Setup'!$C$10+7*13>MAX('ตั้งค่า Setup'!$C$69,'ตั้งค่า Setup'!$C$15)+7,"",14) -> 14 | B30: =IF(A30="","",'ตั้งค่า Setup'!$C$10+7*13) -> 46164 | C30: =IF(A30="","",B30+6) -> 46170 | D30: =IF(A30="","",SUMPRODUCT('แผนงาน Schedule'!$F$7:$F$66,('แผนงาน Schedule'!$I$7:$I$66<=C30)+('แผนงาน Schedule'!$H$7:$H$66<=C30)*('แผนงาน Schedule'!$I$7:$I$66>C30)*(C30-'แผนงาน Schedule'!$H$7:$H$66+1)/('แผนงาน Schedule'!$I$7:$I$66-'แผนงาน Schedule'!$H$7:$H$66+1))) -> 0.28253846 | F30: =IF(E30="","",E30-N(E29)) | G30: =IF(OR(E30="",D30=""),"",E30-D30)
A31: =IF('ตั้งค่า Setup'!$C$10+7*14>MAX('ตั้งค่า Setup'!$C$69,'ตั้งค่า Setup'!$C$15)+7,"",15) -> 15 | B31: =IF(A31="","",'ตั้งค่า Setup'!$C$10+7*14) -> 46171 | C31: =IF(A31="","",B31+6) -> 46177 | D31: =IF(A31="","",SUMPRODUCT('แผนงาน Schedule'!$F$7:$F$66,('แผนงาน Schedule'!$I$7:$I$66<=C31)+('แผนงาน Schedule'!$H$7:$H$66<=C31)*('แผนงาน Schedule'!$I$7:$I$66>C31)*(C31-'แผนงาน Schedule'!$H$7:$H$66+1)/('แผนงาน Schedule'!$I$7:$I$66-'แผนงาน Schedule'!$H$7:$H$66+1))) -> 0.30996631 | F31: =IF(E31="","",E31-N(E30)) | G31: =IF(OR(E31="",D31=""),"",E31-D31)
A32: =IF('ตั้งค่า Setup'!$C$10+7*15>MAX('ตั้งค่า Setup'!$C$69,'ตั้งค่า Setup'!$C$15)+7,"",16) -> 16 | B32: =IF(A32="","",'ตั้งค่า Setup'!$C$10+7*15) -> 46178 | C32: =IF(A32="","",B32+6) -> 46184 | D32: =IF(A32="","",SUMPRODUCT('แผนงาน Schedule'!$F$7:$F$66,('แผนงาน Schedule'!$I$7:$I$66<=C32)+('แผนงาน Schedule'!$H$7:$H$66<=C32)*('แผนงาน Schedule'!$I$7:$I$66>C32)*(C32-'แผนงาน Schedule'!$H$7:$H$66+1)/('แผนงาน Schedule'!$I$7:$I$66-'แผนงาน Schedule'!$H$7:$H$66+1))) -> 0.330316 | F32: =IF(E32="","",E32-N(E31)) | G32: =IF(OR(E32="",D32=""),"",E32-D32)
A33: =IF('ตั้งค่า Setup'!$C$10+7*16>MAX('ตั้งค่า Setup'!$C$69,'ตั้งค่า Setup'!$C$15)+7,"",17) -> 17 | B33: =IF(A33="","",'ตั้งค่า Setup'!$C$10+7*16) -> 46185 | C33: =IF(A33="","",B33+6) -> 46191 | D33: =IF(A33="","",SUMPRODUCT('แผนงาน Schedule'!$F$7:$F$66,('แผนงาน Schedule'!$I$7:$I$66<=C33)+('แผนงาน Schedule'!$H$7:$H$66<=C33)*('แผนงาน Schedule'!$I$7:$I$66>C33)*(C33-'แผนงาน Schedule'!$H$7:$H$66+1)/('แผนงาน Schedule'!$I$7:$I$66-'แผนงาน Schedule'!$H$7:$H$66+1))) -> 0.35623381 | F33: =IF(E33="","",E33-N(E32)) | G33: =IF(OR(E33="",D33=""),"",E33-D33)
A34: =IF('ตั้งค่า Setup'!$C$10+7*17>MAX('ตั้งค่า Setup'!$C$69,'ตั้งค่า Setup'!$C$15)+7,"",18) -> 18 | B34: =IF(A34="","",'ตั้งค่า Setup'!$C$10+7*17) -> 46192 | C34: =IF(A34="","",B34+6) -> 46198 | D34: =IF(A34="","",SUMPRODUCT('แผนงาน Schedule'!$F$7:$F$66,('แผนงาน Schedule'!$I$7:$I$66<=C34)+('แผนงาน Schedule'!$H$7:$H$66<=C34)*('แผนงาน Schedule'!$I$7:$I$66>C34)*(C34-'แผนงาน Schedule'!$H$7:$H$66+1)/('แผนงาน Schedule'!$I$7:$I$66-'แผนงาน Schedule'!$H$7:$H$66+1))) -> 0.38817097 | F34: =IF(E34="","",E34-N(E33)) | G34: =IF(OR(E34="",D34=""),"",E34-D34)
A35: =IF('ตั้งค่า Setup'!$C$10+7*18>MAX('ตั้งค่า Setup'!$C$69,'ตั้งค่า Setup'!$C$15)+7,"",19) -> 19 | B35: =IF(A35="","",'ตั้งค่า Setup'!$C$10+7*18) -> 46199 | C35: =IF(A35="","",B35+6) -> 46205 | D35: =IF(A35="","",SUMPRODUCT('แผนงาน Schedule'!$F$7:$F$66,('แผนงาน Schedule'!$I$7:$I$66<=C35)+('แผนงาน Schedule'!$H$7:$H$66<=C35)*('แผนงาน Schedule'!$I$7:$I$66>C35)*(C35-'แผนงาน Schedule'!$H$7:$H$66+1)/('แผนงาน Schedule'!$I$7:$I$66-'แผนงาน Schedule'!$H$7:$H$66+1))) -> 0.40634656 | F35: =IF(E35="","",E35-N(E34)) | G35: =IF(OR(E35="",D35=""),"",E35-D35)
A36: =IF('ตั้งค่า Setup'!$C$10+7*19>MAX('ตั้งค่า Setup'!$C$69,'ตั้งค่า Setup'!$C$15)+7,"",20) -> 20 | B36: =IF(A36="","",'ตั้งค่า Setup'!$C$10+7*19) -> 46206 | C36: =IF(A36="","",B36+6) -> 46212 | D36: =IF(A36="","",SUMPRODUCT('แผนงาน Schedule'!$F$7:$F$66,('แผนงาน Schedule'!$I$7:$I$66<=C36)+('แผนงาน Schedule'!$H$7:$H$66<=C36)*('แผนงาน Schedule'!$I$7:$I$66>C36)*(C36-'แผนงาน Schedule'!$H$7:$H$66+1)/('แผนงาน Schedule'!$I$7:$I$66-'แผนงาน Schedule'!$H$7:$H$66+1))) -> 0.43484825 | F36: =IF(E36="","",E36-N(E35)) | G36: =IF(OR(E36="",D36=""),"",E36-D36)
A37: =IF('ตั้งค่า Setup'!$C$10+7*20>MAX('ตั้งค่า Setup'!$C$69,'ตั้งค่า Setup'!$C$15)+7,"",21) -> 21 | B37: =IF(A37="","",'ตั้งค่า Setup'!$C$10+7*20) -> 46213 | C37: =IF(A37="","",B37+6) -> 46219 | D37: =IF(A37="","",SUMPRODUCT('แผนงาน Schedule'!$F$7:$F$66,('แผนงาน Schedule'!$I$7:$I$66<=C37)+('แผนงาน Schedule'!$H$7:$H$66<=C37)*('แผนงาน Schedule'!$I$7:$I$66>C37)*(C37-'แผนงาน Schedule'!$H$7:$H$66+1)/('แผนงาน Schedule'!$I$7:$I$66-'แผนงาน Schedule'!$H$7:$H$66+1))) -> 0.49079098 | F37: =IF(E37="","",E37-N(E36)) | G37: =IF(OR(E37="",D37=""),"",E37-D37)
A38: =IF('ตั้งค่า Setup'!$C$10+7*21>MAX('ตั้งค่า Setup'!$C$69,'ตั้งค่า Setup'!$C$15)+7,"",22) -> 22 | B38: =IF(A38="","",'ตั้งค่า Setup'!$C$10+7*21) -> 46220 | C38: =IF(A38="","",B38+6) -> 46226 | D38: =IF(A38="","",SUMPRODUCT('แผนงาน Schedule'!$F$7:$F$66,('แผนงาน Schedule'!$I$7:$I$66<=C38)+('แผนงาน Schedule'!$H$7:$H$66<=C38)*('แผนงาน Schedule'!$I$7:$I$66>C38)*(C38-'แผนงาน Schedule'!$H$7:$H$66+1)/('แผนงาน Schedule'!$I$7:$I$66-'แผนงาน Schedule'!$H$7:$H$66+1))) -> 0.5485179 | F38: =IF(E38="","",E38-N(E37)) | G38: =IF(OR(E38="",D38=""),"",E38-D38)
A39: =IF('ตั้งค่า Setup'!$C$10+7*22>MAX('ตั้งค่า Setup'!$C$69,'ตั้งค่า Setup'!$C$15)+7,"",23) -> 23 | B39: =IF(A39="","",'ตั้งค่า Setup'!$C$10+7*22) -> 46227 | C39: =IF(A39="","",B39+6) -> 46233 | D39: =IF(A39="","",SUMPRODUCT('แผนงาน Schedule'!$F$7:$F$66,('แผนงาน Schedule'!$I$7:$I$66<=C39)+('แผนงาน Schedule'!$H$7:$H$66<=C39)*('แผนงาน Schedule'!$I$7:$I$66>C39)*(C39-'แผนงาน Schedule'!$H$7:$H$66+1)/('แผนงาน Schedule'!$I$7:$I$66-'แผนงาน Schedule'!$H$7:$H$66+1))) -> 0.60603701 | F39: =IF(E39="","",E39-N(E38)) | G39: =IF(OR(E39="",D39=""),"",E39-D39)
A40: =IF('ตั้งค่า Setup'!$C$10+7*23>MAX('ตั้งค่า Setup'!$C$69,'ตั้งค่า Setup'!$C$15)+7,"",24) -> 24 | B40: =IF(A40="","",'ตั้งค่า Setup'!$C$10+7*23) -> 46234 | C40: =IF(A40="","",B40+6) -> 46240 | D40: =IF(A40="","",SUMPRODUCT('แผนงาน Schedule'!$F$7:$F$66,('แผนงาน Schedule'!$I$7:$I$66<=C40)+('แผนงาน Schedule'!$H$7:$H$66<=C40)*('แผนงาน Schedule'!$I$7:$I$66>C40)*(C40-'แผนงาน Schedule'!$H$7:$H$66+1)/('แผนงาน Schedule'!$I$7:$I$66-'แผนงาน Schedule'!$H$7:$H$66+1))) -> 0.64864612 | F40: =IF(E40="","",E40-N(E39)) | G40: =IF(OR(E40="",D40=""),"",E40-D40)
A41: =IF('ตั้งค่า Setup'!$C$10+7*24>MAX('ตั้งค่า Setup'!$C$69,'ตั้งค่า Setup'!$C$15)+7,"",25) -> 25 | B41: =IF(A41="","",'ตั้งค่า Setup'!$C$10+7*24) -> 46241 | C41: =IF(A41="","",B41+6) -> 46247 | D41: =IF(A41="","",SUMPRODUCT('แผนงาน Schedule'!$F$7:$F$66,('แผนงาน Schedule'!$I$7:$I$66<=C41)+('แผนงาน Schedule'!$H$7:$H$66<=C41)*('แผนงาน Schedule'!$I$7:$I$66>C41)*(C41-'แผนงาน Schedule'!$H$7:$H$66+1)/('แผนงาน Schedule'!$I$7:$I$66-'แผนงาน Schedule'!$H$7:$H$66+1))) -> 0.69125524 | F41: =IF(E41="","",E41-N(E40)) | G41: =IF(OR(E41="",D41=""),"",E41-D41)
A42: =IF('ตั้งค่า Setup'!$C$10+7*25>MAX('ตั้งค่า Setup'!$C$69,'ตั้งค่า Setup'!$C$15)+7,"",26) -> 26 | B42: =IF(A42="","",'ตั้งค่า Setup'!$C$10+7*25) -> 46248 | C42: =IF(A42="","",B42+6) -> 46254 | D42: =IF(A42="","",SUMPRODUCT('แผนงาน Schedule'!$F$7:$F$66,('แผนงาน Schedule'!$I$7:$I$66<=C42)+('แผนงาน Schedule'!$H$7:$H$66<=C42)*('แผนงาน Schedule'!$I$7:$I$66>C42)*(C42-'แผนงาน Schedule'!$H$7:$H$66+1)/('แผนงาน Schedule'!$I$7:$I$66-'แผนงาน Schedule'!$H$7:$H$66+1))) -> 0.71672406 | F42: =IF(E42="","",E42-N(E41)) | G42: =IF(OR(E42="",D42=""),"",E42-D42)
A43: =IF('ตั้งค่า Setup'!$C$10+7*26>MAX('ตั้งค่า Setup'!$C$69,'ตั้งค่า Setup'!$C$15)+7,"",27) -> 27 | B43: =IF(A43="","",'ตั้งค่า Setup'!$C$10+7*26) -> 46255 | C43: =IF(A43="","",B43+6) -> 46261 | D43: =IF(A43="","",SUMPRODUCT('แผนงาน Schedule'!$F$7:$F$66,('แผนงาน Schedule'!$I$7:$I$66<=C43)+('แผนงาน Schedule'!$H$7:$H$66<=C43)*('แผนงาน Schedule'!$I$7:$I$66>C43)*(C43-'แผนงาน Schedule'!$H$7:$H$66+1)/('แผนงาน Schedule'!$I$7:$I$66-'แผนงาน Schedule'!$H$7:$H$66+1))) -> 0.75160222 | F43: =IF(E43="","",E43-N(E42)) | G43: =IF(OR(E43="",D43=""),"",E43-D43)
A44: =IF('ตั้งค่า Setup'!$C$10+7*27>MAX('ตั้งค่า Setup'!$C$69,'ตั้งค่า Setup'!$C$15)+7,"",28) -> 28 | B44: =IF(A44="","",'ตั้งค่า Setup'!$C$10+7*27) -> 46262 | C44: =IF(A44="","",B44+6) -> 46268 | D44: =IF(A44="","",SUMPRODUCT('แผนงาน Schedule'!$F$7:$F$66,('แผนงาน Schedule'!$I$7:$I$66<=C44)+('แผนงาน Schedule'!$H$7:$H$66<=C44)*('แผนงาน Schedule'!$I$7:$I$66>C44)*(C44-'แผนงาน Schedule'!$H$7:$H$66+1)/('แผนงาน Schedule'!$I$7:$I$66-'แผนงาน Schedule'!$H$7:$H$66+1))) -> 0.78455818 | F44: =IF(E44="","",E44-N(E43)) | G44: =IF(OR(E44="",D44=""),"",E44-D44)
A45: =IF('ตั้งค่า Setup'!$C$10+7*28>MAX('ตั้งค่า Setup'!$C$69,'ตั้งค่า Setup'!$C$15)+7,"",29) -> 29 | B45: =IF(A45="","",'ตั้งค่า Setup'!$C$10+7*28) -> 46269 | C45: =IF(A45="","",B45+6) -> 46275 | D45: =IF(A45="","",SUMPRODUCT('แผนงาน Schedule'!$F$7:$F$66,('แผนงาน Schedule'!$I$7:$I$66<=C45)+('แผนงาน Schedule'!$H$7:$H$66<=C45)*('แผนงาน Schedule'!$I$7:$I$66>C45)*(C45-'แผนงาน Schedule'!$H$7:$H$66+1)/('แผนงาน Schedule'!$I$7:$I$66-'แผนงาน Schedule'!$H$7:$H$66+1))) -> 0.8198 | F45: =IF(E45="","",E45-N(E44)) | G45: =IF(OR(E45="",D45=""),"",E45-D45)
A46: =IF('ตั้งค่า Setup'!$C$10+7*29>MAX('ตั้งค่า Setup'!$C$69,'ตั้งค่า Setup'!$C$15)+7,"",30) -> 30 | B46: =IF(A46="","",'ตั้งค่า Setup'!$C$10+7*29) -> 46276 | C46: =IF(A46="","",B46+6) -> 46282 | D46: =IF(A46="","",SUMPRODUCT('แผนงาน Schedule'!$F$7:$F$66,('แผนงาน Schedule'!$I$7:$I$66<=C46)+('แผนงาน Schedule'!$H$7:$H$66<=C46)*('แผนงาน Schedule'!$I$7:$I$66>C46)*(C46-'แผนงาน Schedule'!$H$7:$H$66+1)/('แผนงาน Schedule'!$I$7:$I$66-'แผนงาน Schedule'!$H$7:$H$66+1))) -> 0.83471 | F46: =IF(E46="","",E46-N(E45)) | G46: =IF(OR(E46="",D46=""),"",E46-D46)
A47: =IF('ตั้งค่า Setup'!$C$10+7*30>MAX('ตั้งค่า Setup'!$C$69,'ตั้งค่า Setup'!$C$15)+7,"",31) -> 31 | B47: =IF(A47="","",'ตั้งค่า Setup'!$C$10+7*30) -> 46283 | C47: =IF(A47="","",B47+6) -> 46289 | D47: =IF(A47="","",SUMPRODUCT('แผนงาน Schedule'!$F$7:$F$66,('แผนงาน Schedule'!$I$7:$I$66<=C47)+('แผนงาน Schedule'!$H$7:$H$66<=C47)*('แผนงาน Schedule'!$I$7:$I$66>C47)*(C47-'แผนงาน Schedule'!$H$7:$H$66+1)/('แผนงาน Schedule'!$I$7:$I$66-'แผนงาน Schedule'!$H$7:$H$66+1))) -> 0.84962 | F47: =IF(E47="","",E47-N(E46)) | G47: =IF(OR(E47="",D47=""),"",E47-D47)
A48: =IF('ตั้งค่า Setup'!$C$10+7*31>MAX('ตั้งค่า Setup'!$C$69,'ตั้งค่า Setup'!$C$15)+7,"",32) -> 32 | B48: =IF(A48="","",'ตั้งค่า Setup'!$C$10+7*31) -> 46290 | C48: =IF(A48="","",B48+6) -> 46296 | D48: =IF(A48="","",SUMPRODUCT('แผนงาน Schedule'!$F$7:$F$66,('แผนงาน Schedule'!$I$7:$I$66<=C48)+('แผนงาน Schedule'!$H$7:$H$66<=C48)*('แผนงาน Schedule'!$I$7:$I$66>C48)*(C48-'แผนงาน Schedule'!$H$7:$H$66+1)/('แผนงาน Schedule'!$I$7:$I$66-'แผนงาน Schedule'!$H$7:$H$66+1))) -> 0.86453 | F48: =IF(E48="","",E48-N(E47)) | G48: =IF(OR(E48="",D48=""),"",E48-D48)
A49: =IF('ตั้งค่า Setup'!$C$10+7*32>MAX('ตั้งค่า Setup'!$C$69,'ตั้งค่า Setup'!$C$15)+7,"",33) -> 33 | B49: =IF(A49="","",'ตั้งค่า Setup'!$C$10+7*32) -> 46297 | C49: =IF(A49="","",B49+6) -> 46303 | D49: =IF(A49="","",SUMPRODUCT('แผนงาน Schedule'!$F$7:$F$66,('แผนงาน Schedule'!$I$7:$I$66<=C49)+('แผนงาน Schedule'!$H$7:$H$66<=C49)*('แผนงาน Schedule'!$I$7:$I$66>C49)*(C49-'แผนงาน Schedule'!$H$7:$H$66+1)/('แผนงาน Schedule'!$I$7:$I$66-'แผนงาน Schedule'!$H$7:$H$66+1))) -> 0.87944 | F49: =IF(E49="","",E49-N(E48)) | G49: =IF(OR(E49="",D49=""),"",E49-D49)
A50: =IF('ตั้งค่า Setup'!$C$10+7*33>MAX('ตั้งค่า Setup'!$C$69,'ตั้งค่า Setup'!$C$15)+7,"",34) -> 34 | B50: =IF(A50="","",'ตั้งค่า Setup'!$C$10+7*33) -> 46304 | C50: =IF(A50="","",B50+6) -> 46310 | D50: =IF(A50="","",SUMPRODUCT('แผนงาน Schedule'!$F$7:$F$66,('แผนงาน Schedule'!$I$7:$I$66<=C50)+('แผนงาน Schedule'!$H$7:$H$66<=C50)*('แผนงาน Schedule'!$I$7:$I$66>C50)*(C50-'แผนงาน Schedule'!$H$7:$H$66+1)/('แผนงาน Schedule'!$I$7:$I$66-'แผนงาน Schedule'!$H$7:$H$66+1))) -> 0.8860027 | F50: =IF(E50="","",E50-N(E49)) | G50: =IF(OR(E50="",D50=""),"",E50-D50)
A51: =IF('ตั้งค่า Setup'!$C$10+7*34>MAX('ตั้งค่า Setup'!$C$69,'ตั้งค่า Setup'!$C$15)+7,"",35) -> 35 | B51: =IF(A51="","",'ตั้งค่า Setup'!$C$10+7*34) -> 46311 | C51: =IF(A51="","",B51+6) -> 46317 | D51: =IF(A51="","",SUMPRODUCT('แผนงาน Schedule'!$F$7:$F$66,('แผนงาน Schedule'!$I$7:$I$66<=C51)+('แผนงาน Schedule'!$H$7:$H$66<=C51)*('แผนงาน Schedule'!$I$7:$I$66>C51)*(C51-'แผนงาน Schedule'!$H$7:$H$66+1)/('แผนงาน Schedule'!$I$7:$I$66-'แผนงาน Schedule'!$H$7:$H$66+1))) -> 0.90212162 | F51: =IF(E51="","",E51-N(E50)) | G51: =IF(OR(E51="",D51=""),"",E51-D51)
A52: =IF('ตั้งค่า Setup'!$C$10+7*35>MAX('ตั้งค่า Setup'!$C$69,'ตั้งค่า Setup'!$C$15)+7,"",36) -> 36 | B52: =IF(A52="","",'ตั้งค่า Setup'!$C$10+7*35) -> 46318 | C52: =IF(A52="","",B52+6) -> 46324 | D52: =IF(A52="","",SUMPRODUCT('แผนงาน Schedule'!$F$7:$F$66,('แผนงาน Schedule'!$I$7:$I$66<=C52)+('แผนงาน Schedule'!$H$7:$H$66<=C52)*('แผนงาน Schedule'!$I$7:$I$66>C52)*(C52-'แผนงาน Schedule'!$H$7:$H$66+1)/('แผนงาน Schedule'!$I$7:$I$66-'แผนงาน Schedule'!$H$7:$H$66+1))) -> 0.91824054 | F52: =IF(E52="","",E52-N(E51)) | G52: =IF(OR(E52="",D52=""),"",E52-D52)
A53: =IF('ตั้งค่า Setup'!$C$10+7*36>MAX('ตั้งค่า Setup'!$C$69,'ตั้งค่า Setup'!$C$15)+7,"",37) -> 37 | B53: =IF(A53="","",'ตั้งค่า Setup'!$C$10+7*36) -> 46325 | C53: =IF(A53="","",B53+6) -> 46331 | D53: =IF(A53="","",SUMPRODUCT('แผนงาน Schedule'!$F$7:$F$66,('แผนงาน Schedule'!$I$7:$I$66<=C53)+('แผนงาน Schedule'!$H$7:$H$66<=C53)*('แผนงาน Schedule'!$I$7:$I$66>C53)*(C53-'แผนงาน Schedule'!$H$7:$H$66+1)/('แผนงาน Schedule'!$I$7:$I$66-'แผนงาน Schedule'!$H$7:$H$66+1))) -> 0.94407821 | F53: =IF(E53="","",E53-N(E52)) | G53: =IF(OR(E53="",D53=""),"",E53-D53)
A54: =IF('ตั้งค่า Setup'!$C$10+7*37>MAX('ตั้งค่า Setup'!$C$69,'ตั้งค่า Setup'!$C$15)+7,"",38) -> 38 | B54: =IF(A54="","",'ตั้งค่า Setup'!$C$10+7*37) -> 46332 | C54: =IF(A54="","",B54+6) -> 46338 | D54: =IF(A54="","",SUMPRODUCT('แผนงาน Schedule'!$F$7:$F$66,('แผนงาน Schedule'!$I$7:$I$66<=C54)+('แผนงาน Schedule'!$H$7:$H$66<=C54)*('แผนงาน Schedule'!$I$7:$I$66>C54)*(C54-'แผนงาน Schedule'!$H$7:$H$66+1)/('แผนงาน Schedule'!$I$7:$I$66-'แผนงาน Schedule'!$H$7:$H$66+1))) -> 0.97380338 | F54: =IF(E54="","",E54-N(E53)) | G54: =IF(OR(E54="",D54=""),"",E54-D54)
A55: =IF('ตั้งค่า Setup'!$C$10+7*38>MAX('ตั้งค่า Setup'!$C$69,'ตั้งค่า Setup'!$C$15)+7,"",39) -> 39 | B55: =IF(A55="","",'ตั้งค่า Setup'!$C$10+7*38) -> 46339 | C55: =IF(A55="","",B55+6) -> 46345 | D55: =IF(A55="","",SUMPRODUCT('แผนงาน Schedule'!$F$7:$F$66,('แผนงาน Schedule'!$I$7:$I$66<=C55)+('แผนงาน Schedule'!$H$7:$H$66<=C55)*('แผนงาน Schedule'!$I$7:$I$66>C55)*(C55-'แผนงาน Schedule'!$H$7:$H$66+1)/('แผนงาน Schedule'!$I$7:$I$66-'แผนงาน Schedule'!$H$7:$H$66+1))) -> 0.9976973 | F55: =IF(E55="","",E55-N(E54)) | G55: =IF(OR(E55="",D55=""),"",E55-D55)
A56: =IF('ตั้งค่า Setup'!$C$10+7*39>MAX('ตั้งค่า Setup'!$C$69,'ตั้งค่า Setup'!$C$15)+7,"",40) -> 40 | B56: =IF(A56="","",'ตั้งค่า Setup'!$C$10+7*39) -> 46346 | C56: =IF(A56="","",B56+6) -> 46352 | D56: =IF(A56="","",SUMPRODUCT('แผนงาน Schedule'!$F$7:$F$66,('แผนงาน Schedule'!$I$7:$I$66<=C56)+('แผนงาน Schedule'!$H$7:$H$66<=C56)*('แผนงาน Schedule'!$I$7:$I$66>C56)*(C56-'แผนงาน Schedule'!$H$7:$H$66+1)/('แผนงาน Schedule'!$I$7:$I$66-'แผนงาน Schedule'!$H$7:$H$66+1))) -> 1 | F56: =IF(E56="","",E56-N(E55)) | G56: =IF(OR(E56="",D56=""),"",E56-D56)
A57: =IF('ตั้งค่า Setup'!$C$10+7*40>MAX('ตั้งค่า Setup'!$C$69,'ตั้งค่า Setup'!$C$15)+7,"",41) -> 41 | B57: =IF(A57="","",'ตั้งค่า Setup'!$C$10+7*40) -> 46353 | C57: =IF(A57="","",B57+6) -> 46359 | D57: =IF(A57="","",SUMPRODUCT('แผนงาน Schedule'!$F$7:$F$66,('แผนงาน Schedule'!$I$7:$I$66<=C57)+('แผนงาน Schedule'!$H$7:$H$66<=C57)*('แผนงาน Schedule'!$I$7:$I$66>C57)*(C57-'แผนงาน Schedule'!$H$7:$H$66+1)/('แผนงาน Schedule'!$I$7:$I$66-'แผนงาน Schedule'!$H$7:$H$66+1))) -> 1 | F57: =IF(E57="","",E57-N(E56)) | G57: =IF(OR(E57="",D57=""),"",E57-D57)
A58: =IF('ตั้งค่า Setup'!$C$10+7*41>MAX('ตั้งค่า Setup'!$C$69,'ตั้งค่า Setup'!$C$15)+7,"",42) | B58: =IF(A58="","",'ตั้งค่า Setup'!$C$10+7*41) | C58: =IF(A58="","",B58+6) | D58: =IF(A58="","",SUMPRODUCT('แผนงาน Schedule'!$F$7:$F$66,('แผนงาน Schedule'!$I$7:$I$66<=C58)+('แผนงาน Schedule'!$H$7:$H$66<=C58)*('แผนงาน Schedule'!$I$7:$I$66>C58)*(C58-'แผนงาน Schedule'!$H$7:$H$66+1)/('แผนงาน Schedule'!$I$7:$I$66-'แผนงาน Schedule'!$H$7:$H$66+1))) | F58: =IF(E58="","",E58-N(E57)) | G58: =IF(OR(E58="",D58=""),"",E58-D58)
A59: =IF('ตั้งค่า Setup'!$C$10+7*42>MAX('ตั้งค่า Setup'!$C$69,'ตั้งค่า Setup'!$C$15)+7,"",43) | B59: =IF(A59="","",'ตั้งค่า Setup'!$C$10+7*42) | C59: =IF(A59="","",B59+6) | D59: =IF(A59="","",SUMPRODUCT('แผนงาน Schedule'!$F$7:$F$66,('แผนงาน Schedule'!$I$7:$I$66<=C59)+('แผนงาน Schedule'!$H$7:$H$66<=C59)*('แผนงาน Schedule'!$I$7:$I$66>C59)*(C59-'แผนงาน Schedule'!$H$7:$H$66+1)/('แผนงาน Schedule'!$I$7:$I$66-'แผนงาน Schedule'!$H$7:$H$66+1))) | F59: =IF(E59="","",E59-N(E58)) | G59: =IF(OR(E59="",D59=""),"",E59-D59)
A60: =IF('ตั้งค่า Setup'!$C$10+7*43>MAX('ตั้งค่า Setup'!$C$69,'ตั้งค่า Setup'!$C$15)+7,"",44) | B60: =IF(A60="","",'ตั้งค่า Setup'!$C$10+7*43) | C60: =IF(A60="","",B60+6) | D60: =IF(A60="","",SUMPRODUCT('แผนงาน Schedule'!$F$7:$F$66,('แผนงาน Schedule'!$I$7:$I$66<=C60)+('แผนงาน Schedule'!$H$7:$H$66<=C60)*('แผนงาน Schedule'!$I$7:$I$66>C60)*(C60-'แผนงาน Schedule'!$H$7:$H$66+1)/('แผนงาน Schedule'!$I$7:$I$66-'แผนงาน Schedule'!$H$7:$H$66+1))) | F60: =IF(E60="","",E60-N(E59)) | G60: =IF(OR(E60="",D60=""),"",E60-D60)
A61: =IF('ตั้งค่า Setup'!$C$10+7*44>MAX('ตั้งค่า Setup'!$C$69,'ตั้งค่า Setup'!$C$15)+7,"",45) | B61: =IF(A61="","",'ตั้งค่า Setup'!$C$10+7*44) | C61: =IF(A61="","",B61+6) | D61: =IF(A61="","",SUMPRODUCT('แผนงาน Schedule'!$F$7:$F$66,('แผนงาน Schedule'!$I$7:$I$66<=C61)+('แผนงาน Schedule'!$H$7:$H$66<=C61)*('แผนงาน Schedule'!$I$7:$I$66>C61)*(C61-'แผนงาน Schedule'!$H$7:$H$66+1)/('แผนงาน Schedule'!$I$7:$I$66-'แผนงาน Schedule'!$H$7:$H$66+1))) | F61: =IF(E61="","",E61-N(E60)) | G61: =IF(OR(E61="",D61=""),"",E61-D61)
A62: =IF('ตั้งค่า Setup'!$C$10+7*45>MAX('ตั้งค่า Setup'!$C$69,'ตั้งค่า Setup'!$C$15)+7,"",46) | B62: =IF(A62="","",'ตั้งค่า Setup'!$C$10+7*45) | C62: =IF(A62="","",B62+6) | D62: =IF(A62="","",SUMPRODUCT('แผนงาน Schedule'!$F$7:$F$66,('แผนงาน Schedule'!$I$7:$I$66<=C62)+('แผนงาน Schedule'!$H$7:$H$66<=C62)*('แผนงาน Schedule'!$I$7:$I$66>C62)*(C62-'แผนงาน Schedule'!$H$7:$H$66+1)/('แผนงาน Schedule'!$I$7:$I$66-'แผนงาน Schedule'!$H$7:$H$66+1))) | F62: =IF(E62="","",E62-N(E61)) | G62: =IF(OR(E62="",D62=""),"",E62-D62)
A63: =IF('ตั้งค่า Setup'!$C$10+7*46>MAX('ตั้งค่า Setup'!$C$69,'ตั้งค่า Setup'!$C$15)+7,"",47) | B63: =IF(A63="","",'ตั้งค่า Setup'!$C$10+7*46) | C63: =IF(A63="","",B63+6) | D63: =IF(A63="","",SUMPRODUCT('แผนงาน Schedule'!$F$7:$F$66,('แผนงาน Schedule'!$I$7:$I$66<=C63)+('แผนงาน Schedule'!$H$7:$H$66<=C63)*('แผนงาน Schedule'!$I$7:$I$66>C63)*(C63-'แผนงาน Schedule'!$H$7:$H$66+1)/('แผนงาน Schedule'!$I$7:$I$66-'แผนงาน Schedule'!$H$7:$H$66+1))) | F63: =IF(E63="","",E63-N(E62)) | G63: =IF(OR(E63="",D63=""),"",E63-D63)
A64: =IF('ตั้งค่า Setup'!$C$10+7*47>MAX('ตั้งค่า Setup'!$C$69,'ตั้งค่า Setup'!$C$15)+7,"",48) | B64: =IF(A64="","",'ตั้งค่า Setup'!$C$10+7*47) | C64: =IF(A64="","",B64+6) | D64: =IF(A64="","",SUMPRODUCT('แผนงาน Schedule'!$F$7:$F$66,('แผนงาน Schedule'!$I$7:$I$66<=C64)+('แผนงาน Schedule'!$H$7:$H$66<=C64)*('แผนงาน Schedule'!$I$7:$I$66>C64)*(C64-'แผนงาน Schedule'!$H$7:$H$66+1)/('แผนงาน Schedule'!$I$7:$I$66-'แผนงาน Schedule'!$H$7:$H$66+1))) | F64: =IF(E64="","",E64-N(E63)) | G64: =IF(OR(E64="",D64=""),"",E64-D64)
A65: =IF('ตั้งค่า Setup'!$C$10+7*48>MAX('ตั้งค่า Setup'!$C$69,'ตั้งค่า Setup'!$C$15)+7,"",49) | B65: =IF(A65="","",'ตั้งค่า Setup'!$C$10+7*48) | C65: =IF(A65="","",B65+6) | D65: =IF(A65="","",SUMPRODUCT('แผนงาน Schedule'!$F$7:$F$66,('แผนงาน Schedule'!$I$7:$I$66<=C65)+('แผนงาน Schedule'!$H$7:$H$66<=C65)*('แผนงาน Schedule'!$I$7:$I$66>C65)*(C65-'แผนงาน Schedule'!$H$7:$H$66+1)/('แผนงาน Schedule'!$I$7:$I$66-'แผนงาน Schedule'!$H$7:$H$66+1))) | F65: =IF(E65="","",E65-N(E64)) | G65: =IF(OR(E65="",D65=""),"",E65-D65)
A66: =IF('ตั้งค่า Setup'!$C$10+7*49>MAX('ตั้งค่า Setup'!$C$69,'ตั้งค่า Setup'!$C$15)+7,"",50) | B66: =IF(A66="","",'ตั้งค่า Setup'!$C$10+7*49) | C66: =IF(A66="","",B66+6) | D66: =IF(A66="","",SUMPRODUCT('แผนงาน Schedule'!$F$7:$F$66,('แผนงาน Schedule'!$I$7:$I$66<=C66)+('แผนงาน Schedule'!$H$7:$H$66<=C66)*('แผนงาน Schedule'!$I$7:$I$66>C66)*(C66-'แผนงาน Schedule'!$H$7:$H$66+1)/('แผนงาน Schedule'!$I$7:$I$66-'แผนงาน Schedule'!$H$7:$H$66+1))) | F66: =IF(E66="","",E66-N(E65)) | G66: =IF(OR(E66="",D66=""),"",E66-D66)
A67: =IF('ตั้งค่า Setup'!$C$10+7*50>MAX('ตั้งค่า Setup'!$C$69,'ตั้งค่า Setup'!$C$15)+7,"",51) | B67: =IF(A67="","",'ตั้งค่า Setup'!$C$10+7*50) | C67: =IF(A67="","",B67+6) | D67: =IF(A67="","",SUMPRODUCT('แผนงาน Schedule'!$F$7:$F$66,('แผนงาน Schedule'!$I$7:$I$66<=C67)+('แผนงาน Schedule'!$H$7:$H$66<=C67)*('แผนงาน Schedule'!$I$7:$I$66>C67)*(C67-'แผนงาน Schedule'!$H$7:$H$66+1)/('แผนงาน Schedule'!$I$7:$I$66-'แผนงาน Schedule'!$H$7:$H$66+1))) | F67: =IF(E67="","",E67-N(E66)) | G67: =IF(OR(E67="",D67=""),"",E67-D67)
A68: =IF('ตั้งค่า Setup'!$C$10+7*51>MAX('ตั้งค่า Setup'!$C$69,'ตั้งค่า Setup'!$C$15)+7,"",52) | B68: =IF(A68="","",'ตั้งค่า Setup'!$C$10+7*51) | C68: =IF(A68="","",B68+6) | D68: =IF(A68="","",SUMPRODUCT('แผนงาน Schedule'!$F$7:$F$66,('แผนงาน Schedule'!$I$7:$I$66<=C68)+('แผนงาน Schedule'!$H$7:$H$66<=C68)*('แผนงาน Schedule'!$I$7:$I$66>C68)*(C68-'แผนงาน Schedule'!$H$7:$H$66+1)/('แผนงาน Schedule'!$I$7:$I$66-'แผนงาน Schedule'!$H$7:$H$66+1))) | F68: =IF(E68="","",E68-N(E67)) | G68: =IF(OR(E68="",D68=""),"",E68-D68)
A69: =IF('ตั้งค่า Setup'!$C$10+7*52>MAX('ตั้งค่า Setup'!$C$69,'ตั้งค่า Setup'!$C$15)+7,"",53) | B69: =IF(A69="","",'ตั้งค่า Setup'!$C$10+7*52) | C69: =IF(A69="","",B69+6) | D69: =IF(A69="","",SUMPRODUCT('แผนงาน Schedule'!$F$7:$F$66,('แผนงาน Schedule'!$I$7:$I$66<=C69)+('แผนงาน Schedule'!$H$7:$H$66<=C69)*('แผนงาน Schedule'!$I$7:$I$66>C69)*(C69-'แผนงาน Schedule'!$H$7:$H$66+1)/('แผนงาน Schedule'!$I$7:$I$66-'แผนงาน Schedule'!$H$7:$H$66+1))) | F69: =IF(E69="","",E69-N(E68)) | G69: =IF(OR(E69="",D69=""),"",E69-D69)
A70: =IF('ตั้งค่า Setup'!$C$10+7*53>MAX('ตั้งค่า Setup'!$C$69,'ตั้งค่า Setup'!$C$15)+7,"",54) | B70: =IF(A70="","",'ตั้งค่า Setup'!$C$10+7*53) | C70: =IF(A70="","",B70+6) | D70: =IF(A70="","",SUMPRODUCT('แผนงาน Schedule'!$F$7:$F$66,('แผนงาน Schedule'!$I$7:$I$66<=C70)+('แผนงาน Schedule'!$H$7:$H$66<=C70)*('แผนงาน Schedule'!$I$7:$I$66>C70)*(C70-'แผนงาน Schedule'!$H$7:$H$66+1)/('แผนงาน Schedule'!$I$7:$I$66-'แผนงาน Schedule'!$H$7:$H$66+1))) | F70: =IF(E70="","",E70-N(E69)) | G70: =IF(OR(E70="",D70=""),"",E70-D70)
A71: =IF('ตั้งค่า Setup'!$C$10+7*54>MAX('ตั้งค่า Setup'!$C$69,'ตั้งค่า Setup'!$C$15)+7,"",55) | B71: =IF(A71="","",'ตั้งค่า Setup'!$C$10+7*54) | C71: =IF(A71="","",B71+6) | D71: =IF(A71="","",SUMPRODUCT('แผนงาน Schedule'!$F$7:$F$66,('แผนงาน Schedule'!$I$7:$I$66<=C71)+('แผนงาน Schedule'!$H$7:$H$66<=C71)*('แผนงาน Schedule'!$I$7:$I$66>C71)*(C71-'แผนงาน Schedule'!$H$7:$H$66+1)/('แผนงาน Schedule'!$I$7:$I$66-'แผนงาน Schedule'!$H$7:$H$66+1))) | F71: =IF(E71="","",E71-N(E70)) | G71: =IF(OR(E71="",D71=""),"",E71-D71)
A72: =IF('ตั้งค่า Setup'!$C$10+7*55>MAX('ตั้งค่า Setup'!$C$69,'ตั้งค่า Setup'!$C$15)+7,"",56) | B72: =IF(A72="","",'ตั้งค่า Setup'!$C$10+7*55) | C72: =IF(A72="","",B72+6) | D72: =IF(A72="","",SUMPRODUCT('แผนงาน Schedule'!$F$7:$F$66,('แผนงาน Schedule'!$I$7:$I$66<=C72)+('แผนงาน Schedule'!$H$7:$H$66<=C72)*('แผนงาน Schedule'!$I$7:$I$66>C72)*(C72-'แผนงาน Schedule'!$H$7:$H$66+1)/('แผนงาน Schedule'!$I$7:$I$66-'แผนงาน Schedule'!$H$7:$H$66+1))) | F72: =IF(E72="","",E72-N(E71)) | G72: =IF(OR(E72="",D72=""),"",E72-D72)
A73: =IF('ตั้งค่า Setup'!$C$10+7*56>MAX('ตั้งค่า Setup'!$C$69,'ตั้งค่า Setup'!$C$15)+7,"",57) | B73: =IF(A73="","",'ตั้งค่า Setup'!$C$10+7*56) | C73: =IF(A73="","",B73+6) | D73: =IF(A73="","",SUMPRODUCT('แผนงาน Schedule'!$F$7:$F$66,('แผนงาน Schedule'!$I$7:$I$66<=C73)+('แผนงาน Schedule'!$H$7:$H$66<=C73)*('แผนงาน Schedule'!$I$7:$I$66>C73)*(C73-'แผนงาน Schedule'!$H$7:$H$66+1)/('แผนงาน Schedule'!$I$7:$I$66-'แผนงาน Schedule'!$H$7:$H$66+1))) | F73: =IF(E73="","",E73-N(E72)) | G73: =IF(OR(E73="",D73=""),"",E73-D73)
A74: =IF('ตั้งค่า Setup'!$C$10+7*57>MAX('ตั้งค่า Setup'!$C$69,'ตั้งค่า Setup'!$C$15)+7,"",58) | B74: =IF(A74="","",'ตั้งค่า Setup'!$C$10+7*57) | C74: =IF(A74="","",B74+6) | D74: =IF(A74="","",SUMPRODUCT('แผนงาน Schedule'!$F$7:$F$66,('แผนงาน Schedule'!$I$7:$I$66<=C74)+('แผนงาน Schedule'!$H$7:$H$66<=C74)*('แผนงาน Schedule'!$I$7:$I$66>C74)*(C74-'แผนงาน Schedule'!$H$7:$H$66+1)/('แผนงาน Schedule'!$I$7:$I$66-'แผนงาน Schedule'!$H$7:$H$66+1))) | F74: =IF(E74="","",E74-N(E73)) | G74: =IF(OR(E74="",D74=""),"",E74-D74)
A75: =IF('ตั้งค่า Setup'!$C$10+7*58>MAX('ตั้งค่า Setup'!$C$69,'ตั้งค่า Setup'!$C$15)+7,"",59) | B75: =IF(A75="","",'ตั้งค่า Setup'!$C$10+7*58) | C75: =IF(A75="","",B75+6) | D75: =IF(A75="","",SUMPRODUCT('แผนงาน Schedule'!$F$7:$F$66,('แผนงาน Schedule'!$I$7:$I$66<=C75)+('แผนงาน Schedule'!$H$7:$H$66<=C75)*('แผนงาน Schedule'!$I$7:$I$66>C75)*(C75-'แผนงาน Schedule'!$H$7:$H$66+1)/('แผนงาน Schedule'!$I$7:$I$66-'แผนงาน Schedule'!$H$7:$H$66+1))) | F75: =IF(E75="","",E75-N(E74)) | G75: =IF(OR(E75="",D75=""),"",E75-D75)
A76: =IF('ตั้งค่า Setup'!$C$10+7*59>MAX('ตั้งค่า Setup'!$C$69,'ตั้งค่า Setup'!$C$15)+7,"",60) | B76: =IF(A76="","",'ตั้งค่า Setup'!$C$10+7*59) | C76: =IF(A76="","",B76+6) | D76: =IF(A76="","",SUMPRODUCT('แผนงาน Schedule'!$F$7:$F$66,('แผนงาน Schedule'!$I$7:$I$66<=C76)+('แผนงาน Schedule'!$H$7:$H$66<=C76)*('แผนงาน Schedule'!$I$7:$I$66>C76)*(C76-'แผนงาน Schedule'!$H$7:$H$66+1)/('แผนงาน Schedule'!$I$7:$I$66-'แผนงาน Schedule'!$H$7:$H$66+1))) | F76: =IF(E76="","",E76-N(E75)) | G76: =IF(OR(E76="",D76=""),"",E76-D76)
A77: =IF('ตั้งค่า Setup'!$C$10+7*60>MAX('ตั้งค่า Setup'!$C$69,'ตั้งค่า Setup'!$C$15)+7,"",61) | B77: =IF(A77="","",'ตั้งค่า Setup'!$C$10+7*60) | C77: =IF(A77="","",B77+6) | D77: =IF(A77="","",SUMPRODUCT('แผนงาน Schedule'!$F$7:$F$66,('แผนงาน Schedule'!$I$7:$I$66<=C77)+('แผนงาน Schedule'!$H$7:$H$66<=C77)*('แผนงาน Schedule'!$I$7:$I$66>C77)*(C77-'แผนงาน Schedule'!$H$7:$H$66+1)/('แผนงาน Schedule'!$I$7:$I$66-'แผนงาน Schedule'!$H$7:$H$66+1))) | F77: =IF(E77="","",E77-N(E76)) | G77: =IF(OR(E77="",D77=""),"",E77-D77)
A78: =IF('ตั้งค่า Setup'!$C$10+7*61>MAX('ตั้งค่า Setup'!$C$69,'ตั้งค่า Setup'!$C$15)+7,"",62) | B78: =IF(A78="","",'ตั้งค่า Setup'!$C$10+7*61) | C78: =IF(A78="","",B78+6) | D78: =IF(A78="","",SUMPRODUCT('แผนงาน Schedule'!$F$7:$F$66,('แผนงาน Schedule'!$I$7:$I$66<=C78)+('แผนงาน Schedule'!$H$7:$H$66<=C78)*('แผนงาน Schedule'!$I$7:$I$66>C78)*(C78-'แผนงาน Schedule'!$H$7:$H$66+1)/('แผนงาน Schedule'!$I$7:$I$66-'แผนงาน Schedule'!$H$7:$H$66+1))) | F78: =IF(E78="","",E78-N(E77)) | G78: =IF(OR(E78="",D78=""),"",E78-D78)
A79: =IF('ตั้งค่า Setup'!$C$10+7*62>MAX('ตั้งค่า Setup'!$C$69,'ตั้งค่า Setup'!$C$15)+7,"",63) | B79: =IF(A79="","",'ตั้งค่า Setup'!$C$10+7*62) | C79: =IF(A79="","",B79+6) | D79: =IF(A79="","",SUMPRODUCT('แผนงาน Schedule'!$F$7:$F$66,('แผนงาน Schedule'!$I$7:$I$66<=C79)+('แผนงาน Schedule'!$H$7:$H$66<=C79)*('แผนงาน Schedule'!$I$7:$I$66>C79)*(C79-'แผนงาน Schedule'!$H$7:$H$66+1)/('แผนงาน Schedule'!$I$7:$I$66-'แผนงาน Schedule'!$H$7:$H$66+1))) | F79: =IF(E79="","",E79-N(E78)) | G79: =IF(OR(E79="",D79=""),"",E79-D79)
A80: =IF('ตั้งค่า Setup'!$C$10+7*63>MAX('ตั้งค่า Setup'!$C$69,'ตั้งค่า Setup'!$C$15)+7,"",64) | B80: =IF(A80="","",'ตั้งค่า Setup'!$C$10+7*63) | C80: =IF(A80="","",B80+6) | D80: =IF(A80="","",SUMPRODUCT('แผนงาน Schedule'!$F$7:$F$66,('แผนงาน Schedule'!$I$7:$I$66<=C80)+('แผนงาน Schedule'!$H$7:$H$66<=C80)*('แผนงาน Schedule'!$I$7:$I$66>C80)*(C80-'แผนงาน Schedule'!$H$7:$H$66+1)/('แผนงาน Schedule'!$I$7:$I$66-'แผนงาน Schedule'!$H$7:$H$66+1))) | F80: =IF(E80="","",E80-N(E79)) | G80: =IF(OR(E80="",D80=""),"",E80-D80)
A81: =IF('ตั้งค่า Setup'!$C$10+7*64>MAX('ตั้งค่า Setup'!$C$69,'ตั้งค่า Setup'!$C$15)+7,"",65) | B81: =IF(A81="","",'ตั้งค่า Setup'!$C$10+7*64) | C81: =IF(A81="","",B81+6) | D81: =IF(A81="","",SUMPRODUCT('แผนงาน Schedule'!$F$7:$F$66,('แผนงาน Schedule'!$I$7:$I$66<=C81)+('แผนงาน Schedule'!$H$7:$H$66<=C81)*('แผนงาน Schedule'!$I$7:$I$66>C81)*(C81-'แผนงาน Schedule'!$H$7:$H$66+1)/('แผนงาน Schedule'!$I$7:$I$66-'แผนงาน Schedule'!$H$7:$H$66+1))) | F81: =IF(E81="","",E81-N(E80)) | G81: =IF(OR(E81="",D81=""),"",E81-D81)
A82: =IF('ตั้งค่า Setup'!$C$10+7*65>MAX('ตั้งค่า Setup'!$C$69,'ตั้งค่า Setup'!$C$15)+7,"",66) | B82: =IF(A82="","",'ตั้งค่า Setup'!$C$10+7*65) | C82: =IF(A82="","",B82+6) | D82: =IF(A82="","",SUMPRODUCT('แผนงาน Schedule'!$F$7:$F$66,('แผนงาน Schedule'!$I$7:$I$66<=C82)+('แผนงาน Schedule'!$H$7:$H$66<=C82)*('แผนงาน Schedule'!$I$7:$I$66>C82)*(C82-'แผนงาน Schedule'!$H$7:$H$66+1)/('แผนงาน Schedule'!$I$7:$I$66-'แผนงาน Schedule'!$H$7:$H$66+1))) | F82: =IF(E82="","",E82-N(E81)) | G82: =IF(OR(E82="",D82=""),"",E82-D82)
A83: =IF('ตั้งค่า Setup'!$C$10+7*66>MAX('ตั้งค่า Setup'!$C$69,'ตั้งค่า Setup'!$C$15)+7,"",67) | B83: =IF(A83="","",'ตั้งค่า Setup'!$C$10+7*66) | C83: =IF(A83="","",B83+6) | D83: =IF(A83="","",SUMPRODUCT('แผนงาน Schedule'!$F$7:$F$66,('แผนงาน Schedule'!$I$7:$I$66<=C83)+('แผนงาน Schedule'!$H$7:$H$66<=C83)*('แผนงาน Schedule'!$I$7:$I$66>C83)*(C83-'แผนงาน Schedule'!$H$7:$H$66+1)/('แผนงาน Schedule'!$I$7:$I$66-'แผนงาน Schedule'!$H$7:$H$66+1))) | F83: =IF(E83="","",E83-N(E82)) | G83: =IF(OR(E83="",D83=""),"",E83-D83)
A84: =IF('ตั้งค่า Setup'!$C$10+7*67>MAX('ตั้งค่า Setup'!$C$69,'ตั้งค่า Setup'!$C$15)+7,"",68) | B84: =IF(A84="","",'ตั้งค่า Setup'!$C$10+7*67) | C84: =IF(A84="","",B84+6) | D84: =IF(A84="","",SUMPRODUCT('แผนงาน Schedule'!$F$7:$F$66,('แผนงาน Schedule'!$I$7:$I$66<=C84)+('แผนงาน Schedule'!$H$7:$H$66<=C84)*('แผนงาน Schedule'!$I$7:$I$66>C84)*(C84-'แผนงาน Schedule'!$H$7:$H$66+1)/('แผนงาน Schedule'!$I$7:$I$66-'แผนงาน Schedule'!$H$7:$H$66+1))) | F84: =IF(E84="","",E84-N(E83)) | G84: =IF(OR(E84="",D84=""),"",E84-D84)
A85: =IF('ตั้งค่า Setup'!$C$10+7*68>MAX('ตั้งค่า Setup'!$C$69,'ตั้งค่า Setup'!$C$15)+7,"",69) | B85: =IF(A85="","",'ตั้งค่า Setup'!$C$10+7*68) | C85: =IF(A85="","",B85+6) | D85: =IF(A85="","",SUMPRODUCT('แผนงาน Schedule'!$F$7:$F$66,('แผนงาน Schedule'!$I$7:$I$66<=C85)+('แผนงาน Schedule'!$H$7:$H$66<=C85)*('แผนงาน Schedule'!$I$7:$I$66>C85)*(C85-'แผนงาน Schedule'!$H$7:$H$66+1)/('แผนงาน Schedule'!$I$7:$I$66-'แผนงาน Schedule'!$H$7:$H$66+1))) | F85: =IF(E85="","",E85-N(E84)) | G85: =IF(OR(E85="",D85=""),"",E85-D85)
A86: =IF('ตั้งค่า Setup'!$C$10+7*69>MAX('ตั้งค่า Setup'!$C$69,'ตั้งค่า Setup'!$C$15)+7,"",70) | B86: =IF(A86="","",'ตั้งค่า Setup'!$C$10+7*69) | C86: =IF(A86="","",B86+6) | D86: =IF(A86="","",SUMPRODUCT('แผนงาน Schedule'!$F$7:$F$66,('แผนงาน Schedule'!$I$7:$I$66<=C86)+('แผนงาน Schedule'!$H$7:$H$66<=C86)*('แผนงาน Schedule'!$I$7:$I$66>C86)*(C86-'แผนงาน Schedule'!$H$7:$H$66+1)/('แผนงาน Schedule'!$I$7:$I$66-'แผนงาน Schedule'!$H$7:$H$66+1))) | F86: =IF(E86="","",E86-N(E85)) | G86: =IF(OR(E86="",D86=""),"",E86-D86)
A87: =IF('ตั้งค่า Setup'!$C$10+7*70>MAX('ตั้งค่า Setup'!$C$69,'ตั้งค่า Setup'!$C$15)+7,"",71) | B87: =IF(A87="","",'ตั้งค่า Setup'!$C$10+7*70) | C87: =IF(A87="","",B87+6) | D87: =IF(A87="","",SUMPRODUCT('แผนงาน Schedule'!$F$7:$F$66,('แผนงาน Schedule'!$I$7:$I$66<=C87)+('แผนงาน Schedule'!$H$7:$H$66<=C87)*('แผนงาน Schedule'!$I$7:$I$66>C87)*(C87-'แผนงาน Schedule'!$H$7:$H$66+1)/('แผนงาน Schedule'!$I$7:$I$66-'แผนงาน Schedule'!$H$7:$H$66+1))) | F87: =IF(E87="","",E87-N(E86)) | G87: =IF(OR(E87="",D87=""),"",E87-D87)
A88: =IF('ตั้งค่า Setup'!$C$10+7*71>MAX('ตั้งค่า Setup'!$C$69,'ตั้งค่า Setup'!$C$15)+7,"",72) | B88: =IF(A88="","",'ตั้งค่า Setup'!$C$10+7*71) | C88: =IF(A88="","",B88+6) | D88: =IF(A88="","",SUMPRODUCT('แผนงาน Schedule'!$F$7:$F$66,('แผนงาน Schedule'!$I$7:$I$66<=C88)+('แผนงาน Schedule'!$H$7:$H$66<=C88)*('แผนงาน Schedule'!$I$7:$I$66>C88)*(C88-'แผนงาน Schedule'!$H$7:$H$66+1)/('แผนงาน Schedule'!$I$7:$I$66-'แผนงาน Schedule'!$H$7:$H$66+1))) | F88: =IF(E88="","",E88-N(E87)) | G88: =IF(OR(E88="",D88=""),"",E88-D88)
A89: =IF('ตั้งค่า Setup'!$C$10+7*72>MAX('ตั้งค่า Setup'!$C$69,'ตั้งค่า Setup'!$C$15)+7,"",73) | B89: =IF(A89="","",'ตั้งค่า Setup'!$C$10+7*72) | C89: =IF(A89="","",B89+6) | D89: =IF(A89="","",SUMPRODUCT('แผนงาน Schedule'!$F$7:$F$66,('แผนงาน Schedule'!$I$7:$I$66<=C89)+('แผนงาน Schedule'!$H$7:$H$66<=C89)*('แผนงาน Schedule'!$I$7:$I$66>C89)*(C89-'แผนงาน Schedule'!$H$7:$H$66+1)/('แผนงาน Schedule'!$I$7:$I$66-'แผนงาน Schedule'!$H$7:$H$66+1))) | F89: =IF(E89="","",E89-N(E88)) | G89: =IF(OR(E89="",D89=""),"",E89-D89)
A90: =IF('ตั้งค่า Setup'!$C$10+7*73>MAX('ตั้งค่า Setup'!$C$69,'ตั้งค่า Setup'!$C$15)+7,"",74) | B90: =IF(A90="","",'ตั้งค่า Setup'!$C$10+7*73) | C90: =IF(A90="","",B90+6) | D90: =IF(A90="","",SUMPRODUCT('แผนงาน Schedule'!$F$7:$F$66,('แผนงาน Schedule'!$I$7:$I$66<=C90)+('แผนงาน Schedule'!$H$7:$H$66<=C90)*('แผนงาน Schedule'!$I$7:$I$66>C90)*(C90-'แผนงาน Schedule'!$H$7:$H$66+1)/('แผนงาน Schedule'!$I$7:$I$66-'แผนงาน Schedule'!$H$7:$H$66+1))) | F90: =IF(E90="","",E90-N(E89)) | G90: =IF(OR(E90="",D90=""),"",E90-D90)
A91: =IF('ตั้งค่า Setup'!$C$10+7*74>MAX('ตั้งค่า Setup'!$C$69,'ตั้งค่า Setup'!$C$15)+7,"",75) | B91: =IF(A91="","",'ตั้งค่า Setup'!$C$10+7*74) | C91: =IF(A91="","",B91+6) | D91: =IF(A91="","",SUMPRODUCT('แผนงาน Schedule'!$F$7:$F$66,('แผนงาน Schedule'!$I$7:$I$66<=C91)+('แผนงาน Schedule'!$H$7:$H$66<=C91)*('แผนงาน Schedule'!$I$7:$I$66>C91)*(C91-'แผนงาน Schedule'!$H$7:$H$66+1)/('แผนงาน Schedule'!$I$7:$I$66-'แผนงาน Schedule'!$H$7:$H$66+1))) | F91: =IF(E91="","",E91-N(E90)) | G91: =IF(OR(E91="",D91=""),"",E91-D91)
A92: =IF('ตั้งค่า Setup'!$C$10+7*75>MAX('ตั้งค่า Setup'!$C$69,'ตั้งค่า Setup'!$C$15)+7,"",76) | B92: =IF(A92="","",'ตั้งค่า Setup'!$C$10+7*75) | C92: =IF(A92="","",B92+6) | D92: =IF(A92="","",SUMPRODUCT('แผนงาน Schedule'!$F$7:$F$66,('แผนงาน Schedule'!$I$7:$I$66<=C92)+('แผนงาน Schedule'!$H$7:$H$66<=C92)*('แผนงาน Schedule'!$I$7:$I$66>C92)*(C92-'แผนงาน Schedule'!$H$7:$H$66+1)/('แผนงาน Schedule'!$I$7:$I$66-'แผนงาน Schedule'!$H$7:$H$66+1))) | F92: =IF(E92="","",E92-N(E91)) | G92: =IF(OR(E92="",D92=""),"",E92-D92)
A93: =IF('ตั้งค่า Setup'!$C$10+7*76>MAX('ตั้งค่า Setup'!$C$69,'ตั้งค่า Setup'!$C$15)+7,"",77) | B93: =IF(A93="","",'ตั้งค่า Setup'!$C$10+7*76) | C93: =IF(A93="","",B93+6) | D93: =IF(A93="","",SUMPRODUCT('แผนงาน Schedule'!$F$7:$F$66,('แผนงาน Schedule'!$I$7:$I$66<=C93)+('แผนงาน Schedule'!$H$7:$H$66<=C93)*('แผนงาน Schedule'!$I$7:$I$66>C93)*(C93-'แผนงาน Schedule'!$H$7:$H$66+1)/('แผนงาน Schedule'!$I$7:$I$66-'แผนงาน Schedule'!$H$7:$H$66+1))) | F93: =IF(E93="","",E93-N(E92)) | G93: =IF(OR(E93="",D93=""),"",E93-D93)
A94: =IF('ตั้งค่า Setup'!$C$10+7*77>MAX('ตั้งค่า Setup'!$C$69,'ตั้งค่า Setup'!$C$15)+7,"",78) | B94: =IF(A94="","",'ตั้งค่า Setup'!$C$10+7*77) | C94: =IF(A94="","",B94+6) | D94: =IF(A94="","",SUMPRODUCT('แผนงาน Schedule'!$F$7:$F$66,('แผนงาน Schedule'!$I$7:$I$66<=C94)+('แผนงาน Schedule'!$H$7:$H$66<=C94)*('แผนงาน Schedule'!$I$7:$I$66>C94)*(C94-'แผนงาน Schedule'!$H$7:$H$66+1)/('แผนงาน Schedule'!$I$7:$I$66-'แผนงาน Schedule'!$H$7:$H$66+1))) | F94: =IF(E94="","",E94-N(E93)) | G94: =IF(OR(E94="",D94=""),"",E94-D94)
A95: =IF('ตั้งค่า Setup'!$C$10+7*78>MAX('ตั้งค่า Setup'!$C$69,'ตั้งค่า Setup'!$C$15)+7,"",79) | B95: =IF(A95="","",'ตั้งค่า Setup'!$C$10+7*78) | C95: =IF(A95="","",B95+6) | D95: =IF(A95="","",SUMPRODUCT('แผนงาน Schedule'!$F$7:$F$66,('แผนงาน Schedule'!$I$7:$I$66<=C95)+('แผนงาน Schedule'!$H$7:$H$66<=C95)*('แผนงาน Schedule'!$I$7:$I$66>C95)*(C95-'แผนงาน Schedule'!$H$7:$H$66+1)/('แผนงาน Schedule'!$I$7:$I$66-'แผนงาน Schedule'!$H$7:$H$66+1))) | F95: =IF(E95="","",E95-N(E94)) | G95: =IF(OR(E95="",D95=""),"",E95-D95)
A96: =IF('ตั้งค่า Setup'!$C$10+7*79>MAX('ตั้งค่า Setup'!$C$69,'ตั้งค่า Setup'!$C$15)+7,"",80) | B96: =IF(A96="","",'ตั้งค่า Setup'!$C$10+7*79) | C96: =IF(A96="","",B96+6) | D96: =IF(A96="","",SUMPRODUCT('แผนงาน Schedule'!$F$7:$F$66,('แผนงาน Schedule'!$I$7:$I$66<=C96)+('แผนงาน Schedule'!$H$7:$H$66<=C96)*('แผนงาน Schedule'!$I$7:$I$66>C96)*(C96-'แผนงาน Schedule'!$H$7:$H$66+1)/('แผนงาน Schedule'!$I$7:$I$66-'แผนงาน Schedule'!$H$7:$H$66+1))) | F96: =IF(E96="","",E96-N(E95)) | G96: =IF(OR(E96="",D96=""),"",E96-D96)
A97: =IF('ตั้งค่า Setup'!$C$10+7*80>MAX('ตั้งค่า Setup'!$C$69,'ตั้งค่า Setup'!$C$15)+7,"",81) | B97: =IF(A97="","",'ตั้งค่า Setup'!$C$10+7*80) | C97: =IF(A97="","",B97+6) | D97: =IF(A97="","",SUMPRODUCT('แผนงาน Schedule'!$F$7:$F$66,('แผนงาน Schedule'!$I$7:$I$66<=C97)+('แผนงาน Schedule'!$H$7:$H$66<=C97)*('แผนงาน Schedule'!$I$7:$I$66>C97)*(C97-'แผนงาน Schedule'!$H$7:$H$66+1)/('แผนงาน Schedule'!$I$7:$I$66-'แผนงาน Schedule'!$H$7:$H$66+1))) | F97: =IF(E97="","",E97-N(E96)) | G97: =IF(OR(E97="",D97=""),"",E97-D97)
A98: =IF('ตั้งค่า Setup'!$C$10+7*81>MAX('ตั้งค่า Setup'!$C$69,'ตั้งค่า Setup'!$C$15)+7,"",82) | B98: =IF(A98="","",'ตั้งค่า Setup'!$C$10+7*81) | C98: =IF(A98="","",B98+6) | D98: =IF(A98="","",SUMPRODUCT('แผนงาน Schedule'!$F$7:$F$66,('แผนงาน Schedule'!$I$7:$I$66<=C98)+('แผนงาน Schedule'!$H$7:$H$66<=C98)*('แผนงาน Schedule'!$I$7:$I$66>C98)*(C98-'แผนงาน Schedule'!$H$7:$H$66+1)/('แผนงาน Schedule'!$I$7:$I$66-'แผนงาน Schedule'!$H$7:$H$66+1))) | F98: =IF(E98="","",E98-N(E97)) | G98: =IF(OR(E98="",D98=""),"",E98-D98)
A99: =IF('ตั้งค่า Setup'!$C$10+7*82>MAX('ตั้งค่า Setup'!$C$69,'ตั้งค่า Setup'!$C$15)+7,"",83) | B99: =IF(A99="","",'ตั้งค่า Setup'!$C$10+7*82) | C99: =IF(A99="","",B99+6) | D99: =IF(A99="","",SUMPRODUCT('แผนงาน Schedule'!$F$7:$F$66,('แผนงาน Schedule'!$I$7:$I$66<=C99)+('แผนงาน Schedule'!$H$7:$H$66<=C99)*('แผนงาน Schedule'!$I$7:$I$66>C99)*(C99-'แผนงาน Schedule'!$H$7:$H$66+1)/('แผนงาน Schedule'!$I$7:$I$66-'แผนงาน Schedule'!$H$7:$H$66+1))) | F99: =IF(E99="","",E99-N(E98)) | G99: =IF(OR(E99="",D99=""),"",E99-D99)
A100: =IF('ตั้งค่า Setup'!$C$10+7*83>MAX('ตั้งค่า Setup'!$C$69,'ตั้งค่า Setup'!$C$15)+7,"",84) | B100: =IF(A100="","",'ตั้งค่า Setup'!$C$10+7*83) | C100: =IF(A100="","",B100+6) | D100: =IF(A100="","",SUMPRODUCT('แผนงาน Schedule'!$F$7:$F$66,('แผนงาน Schedule'!$I$7:$I$66<=C100)+('แผนงาน Schedule'!$H$7:$H$66<=C100)*('แผนงาน Schedule'!$I$7:$I$66>C100)*(C100-'แผนงาน Schedule'!$H$7:$H$66+1)/('แผนงาน Schedule'!$I$7:$I$66-'แผนงาน Schedule'!$H$7:$H$66+1))) | F100: =IF(E100="","",E100-N(E99)) | G100: =IF(OR(E100="",D100=""),"",E100-D100)
A101: =IF('ตั้งค่า Setup'!$C$10+7*84>MAX('ตั้งค่า Setup'!$C$69,'ตั้งค่า Setup'!$C$15)+7,"",85) | B101: =IF(A101="","",'ตั้งค่า Setup'!$C$10+7*84) | C101: =IF(A101="","",B101+6) | D101: =IF(A101="","",SUMPRODUCT('แผนงาน Schedule'!$F$7:$F$66,('แผนงาน Schedule'!$I$7:$I$66<=C101)+('แผนงาน Schedule'!$H$7:$H$66<=C101)*('แผนงาน Schedule'!$I$7:$I$66>C101)*(C101-'แผนงาน Schedule'!$H$7:$H$66+1)/('แผนงาน Schedule'!$I$7:$I$66-'แผนงาน Schedule'!$H$7:$H$66+1))) | F101: =IF(E101="","",E101-N(E100)) | G101: =IF(OR(E101="",D101=""),"",E101-D101)
...

Sheet รายงานกรรมการ Weekly
B1: บันทึกข้อความ
B2: ส่วนราชการ | C2: ='บันทึกสัปดาห์ Weekly Log'!C4&""
B3: ที่ | C3: ='บันทึกสัปดาห์ Weekly Log'!C5&"" | G3: วันที่ | H3: =IF(N('บันทึกสัปดาห์ Weekly Log'!$C$13)=0,"-",DAY('บันทึกสัปดาห์ Weekly Log'!$C$13)&" "&CHOOSE(MONTH('บันทึกสัปดาห์ Weekly Log'!$C$13),"มกราคม","กุมภาพันธ์","มีนาคม","เมษายน","พฤษภาคม","มิถุนายน","กรกฎาคม","สิงหาคม","กันยายน","ตุลาคม","พฤศจิกายน","ธันวาคม")&" "&(YEAR('บันทึกสัปดาห์ Weekly Log'!$C$13)+543)) -> 28 กันยายน 2569
B4: เรื่อง | C4: ="รายงานผลการปฏิบัติงานของผู้รับจ้าง ประจำสัปดาห์ที่ "&'บันทึกสัปดาห์ Weekly Log'!$C$12&" ("&IF(N(INDEX('บันทึกสัปดาห์ Weekly Log'!$B$17:$B$120,'บันทึกสัปดาห์ Weekly Log'!$C$12))=0,"-",DAY(INDEX('บันทึกสัปดาห์ Weekly Log'!$B$17:$B$120,'บันทึกสัปดาห์ Weekly Log'!$C$12))&" "&CHOOSE(MONTH(INDEX('บันทึกสัปดาห์ Weekly Log'!$B$17:$B$120,'บันทึกสัปดาห์ Weekly Log'!$C$12)),"ม.ค.","ก.พ.","มี.ค.","เม.ย.","พ.ค.","มิ.ย.","ก.ค.","ส.ค.","ก.ย.","ต.ค.","พ.ย.","ธ.ค.")&" "&RIGHT(YEAR(INDEX('บันทึกสัปดาห์ Weekly Log'!$B$17:$B$120,'บันทึกสัปดาห์ Weekly Log'!$C$12))+543,2))&" – "&IF(N(INDEX('บันทึกสัปดาห์ Weekly Log'!$C$17:$C$120,'บันทึกสัปดาห์ Weekly Log'!$C$12))=0,"-",DAY(INDEX('บันทึกสัปดาห์ Weekly Log'!$C$17:$C$120,'บันทึกสัปดาห์ Weekly Log'!$C$12))&" "&CHOOSE(MONTH(INDEX('บันทึกสัปดาห์ Weekly Log'!$C$17:$C$120,'บันทึกสัปดาห์ Weekly Log'!$C$12)),"ม.ค.","ก.พ.","มี.ค.","เม.ย.","พ.ค.","มิ.ย.","ก.ค.","ส.ค.","ก.ย.","ต.ค.","พ.ย.","ธ.ค.")&" "&RIGHT(YEAR(INDEX('บันทึกสัปดาห์ Weekly Log'!$C$17:$C$120,'บันทึกสัปดาห์ Weekly Log'!$C$12))+543,2))&")" -> รายงานผลการปฏิบัติงานของผู้รับจ้าง ประจำสัปดาห์ที่ 31 (18 ก.ย. 69 – 24 ก.ย. 69)
B5: เรียน | C5: ประธานกรรมการตรวจรับพัสดุ
B6: =" ตามที่ "&IF('ตั้งค่า Setup'!C6="","(ผู้ว่าจ้าง)",'ตั้งค่า Setup'!C6)&" ได้ทำสัญญาจ้าง "&IF('ตั้งค่า Setup'!C7="","(ผู้รับจ้าง)",'ตั้งค่า Setup'!C7)&" ดำเนินการ"&'ตั้งค่า Setup'!C4&" ตามสัญญาเลขที่ "&IF('ตั้งค่า Setup'!C8="","……",'ตั้งค่า Setup'!C8)&" ลงวันที่ "&IF(N('บันทึกสัปดาห์ Weekly Log'!$C$6)=0,"……",IF(N('บันทึกสัปดาห์ Weekly Log'!$C$6)=0,"-",DAY('บันทึกสัปดาห์ Weekly Log'!$C$6)&" "&CHOOSE(MONTH('บันทึกสัปดาห์ Weekly Log'!$C$6),"มกราคม","กุมภาพันธ์","มีนาคม","เมษายน","พฤษภาคม","มิถุนายน","กรกฎาคม","สิงหาคม","กันยายน","ตุลาคม","พฤศจิกายน","ธันวาคม")&" "&(YEAR('บันทึกสัปดาห์ Weekly Log'!$C$6)+543)))&" วงเงิน "&TEXT('ตั้งค่า Setup'!$C$9,"#,##0.00")&" บาท"&" ระยะเวลาดำเนินการ "&'ตั้งค่า Setup'!$C$11&" วัน เริ่มสัญญาวันที่ "&IF(N('ตั้งค่า Setup'!$C$10)=0,"-",DAY('ตั้งค่า Setup'!$C$10)&" "&CHOOSE(MONTH('ตั้งค่า Setup'!$C$10),"มกราคม","กุมภาพันธ์","มีนาคม","เมษายน","พฤษภาคม","มิถุนายน","กรกฎาคม","สิงหาคม","กันยายน","ตุลาคม","พฤศจิกายน","ธันวาคม")&" "&(YEAR('ตั้งค่า Setup'!$C$10)+543))&" สิ้นสุดสัญญาวันที่ "&IF(N('ตั้งค่า Setup'!$C$14)=0,"-",DAY('ตั้งค่า Setup'!$C$14)&" "&CHOOSE(MONTH('ตั้งค่า Setup'!$C$14),"มกราคม","กุมภาพันธ์","มีนาคม","เมษายน","พฤษภาคม","มิถุนายน","กรกฎาคม","สิงหาคม","กันยายน","ตุลาคม","พฤศจิกายน","ธันวาคม")&" "&(YEAR('ตั้งค่า Setup'!$C$14)+543))&IF('ตั้งค่า Setup'!$C$13>0," (รวมการขยายเวลา "&'ตั้งค่า Setup'!$C$13&" วัน)","")&" นั้น"&CHAR(10)&" ข้าพเจ้าในฐานะผู้ควบคุมงาน ขอรายงานผลการปฏิบัติงานของผู้รับจ้าง ประจำสัปดาห์ที่ "&'บันทึกสัปดาห์ Weekly Log'!$C$12&" ดังนี้" -> ตามที่ (ผู้ว่าจ้าง) ได้ทำสัญญาจ้าง (ผู้รับจ้าง) ดำเนินการโครงการก่อสร้างอาคาร (แก้ไขชื่อได้) ตามสัญญาเลขที่ …… ลงวันที่ …… วงเงิน 12,108,000.00 บาท ระยะเวลาดำเนินการ 270 วัน เริ่มสัญญาวันที่ 20 กุมภาพันธ์ 2569 สิ้นสุดสัญญาวันที่ 16 พฤศจิกายน 2569 นั้น ข้าพเจ้าในฐานะผู้ควบคุมงาน ขอรายงานผลการปฏิบัติงานของผู้รับจ้าง ประจำสัปดาห์ที่ 31 ดังนี้
B8: 1. ความก้าวหน้าของงาน ณ สิ้นสัปดาห์
B9: ผลงานตามแผนสะสม | D9: =INDEX('บันทึกสัปดาห์ Weekly Log'!$D$17:$D$120,'บันทึกสัปดาห์ Weekly Log'!$C$12) -> 0.84962
B10: ผลงานจริงสะสม | D10: =IF(INDEX('บันทึกสัปดาห์ Weekly Log'!$E$17:$E$120,'บันทึกสัปดาห์ Weekly Log'!$C$12)="","ยังไม่กรอก",INDEX('บันทึกสัปดาห์ Weekly Log'!$E$17:$E$120,'บันทึกสัปดาห์ Weekly Log'!$C$12)) -> ยังไม่กรอก
B11: ผลงานเร็ว (+) / ช้า (−) กว่าแผน | D11: =IF(INDEX('บันทึกสัปดาห์ Weekly Log'!$E$17:$E$120,'บันทึกสัปดาห์ Weekly Log'!$C$12)="","-",INDEX('บันทึกสัปดาห์ Weekly Log'!$E$17:$E$120,'บันทึกสัปดาห์ Weekly Log'!$C$12)-INDEX('บันทึกสัปดาห์ Weekly Log'!$D$17:$D$120,'บันทึกสัปดาห์ Weekly Log'!$C$12)) -> -
B12: คิดเป็นจำนวนวัน | D12: =IF(INDEX('บันทึกสัปดาห์ Weekly Log'!$E$17:$E$120,'บันทึกสัปดาห์ Weekly Log'!$C$12)="","-",ROUND((INDEX('บันทึกสัปดาห์ Weekly Log'!$E$17:$E$120,'บันทึกสัปดาห์ Weekly Log'!$C$12)-INDEX('บันทึกสัปดาห์ Weekly Log'!$D$17:$D$120,'บันทึกสัปดาห์ Weekly Log'!$C$12))*'ตั้งค่า Setup'!$C$11,0)) -> -
B13: ผลงานที่ทำได้ในสัปดาห์นี้ | D13: =IF(INDEX('บันทึกสัปดาห์ Weekly Log'!$E$17:$E$120,'บันทึกสัปดาห์ Weekly Log'!$C$12)="","-",INDEX('บันทึกสัปดาห์ Weekly Log'!$F$17:$F$120,'บันทึกสัปดาห์ Weekly Log'!$C$12)) -> -
B14: ผลงานสัปดาห์ที่แล้ว | D14: =IF('บันทึกสัปดาห์ Weekly Log'!$C$12<=1,"-",IF(INDEX('บันทึกสัปดาห์ Weekly Log'!$F$17:$F$120,'บันทึกสัปดาห์ Weekly Log'!$C$12-1)="","-",INDEX('บันทึกสัปดาห์ Weekly Log'!$F$17:$F$120,'บันทึกสัปดาห์ Weekly Log'!$C$12-1))) -> -
B15: ระยะเวลาดำเนินการแล้ว | D15: =(INDEX('บันทึกสัปดาห์ Weekly Log'!$C$17:$C$120,'บันทึกสัปดาห์ Weekly Log'!$C$12)-'ตั้งค่า Setup'!$C$10+1)&" วัน ("&TEXT((INDEX('บันทึกสัปดาห์ Weekly Log'!$C$17:$C$120,'บันทึกสัปดาห์ Weekly Log'!$C$12)-'ตั้งค่า Setup'!$C$10+1)/('ตั้งค่า Setup'!$C$14-'ตั้งค่า Setup'!$C$10+1),"0.0%")&")" -> 217 วัน (80.4%)
B16: ระยะเวลาคงเหลือตามสัญญา | D16: =IF('ตั้งค่า Setup'!$C$14-INDEX('บันทึกสัปดาห์ Weekly Log'!$C$17:$C$120,'บันทึกสัปดาห์ Weekly Log'!$C$12)>=0,('ตั้งค่า Setup'!$C$14-INDEX('บันทึกสัปดาห์ Weekly Log'!$C$17:$C$120,'บันทึกสัปดาห์ Weekly Log'!$C$12))&" วัน","เลยกำหนด "&(INDEX('บันทึกสัปดาห์ Weekly Log'!$C$17:$C$120,'บันทึกสัปดาห์ Weekly Log'!$C$12)-'ตั้งค่า Setup'!$C$14)&" วัน") -> 53 วัน
B17: สถานะ | D17: =IF(INDEX('บันทึกสัปดาห์ Weekly Log'!$E$17:$E$120,'บันทึกสัปดาห์ Weekly Log'!$C$12)="","-",IF(INDEX('บันทึกสัปดาห์ Weekly Log'!$E$17:$E$120,'บันทึกสัปดาห์ Weekly Log'!$C$12)>=INDEX('บันทึกสัปดาห์ Weekly Log'!$D$17:$D$120,'บันทึกสัปดาห์ Weekly Log'!$C$12),"เป็นไปตามแผน / เร็วกว่าแผน",IF(INDEX('บันทึกสัปดาห์ Weekly Log'!$E$17:$E$120,'บันทึกสัปดาห์ Weekly Log'!$C$12)/INDEX('บันทึกสัปดาห์ Weekly Log'!$D$17:$D$120,'บันทึกสัปดาห์ Weekly Log'!$C$12)>=0.9,"ล่าช้ากว่าแผนเล็กน้อย","ล่าช้ากว่าแผนมาก"))) -> -
B19: 2. ความก้าวหน้าตามงวดงานในสัญญา
B20: งวด | C20: เนื้องาน | D20: กำหนดเสร็จ | E20: จำนวนเงิน (บาท) | G20: เกณฑ์ผลงาน | H20: สถานะ | J20: ล่าช้า (วัน)
B21: ='งวดงาน Installments'!A7&"" | C21: ='งวดงาน Installments'!B7&"" | D21: =IF('งวดงาน Installments'!D7="","",IF(N('งวดงาน Installments'!D7)=0,"-",DAY('งวดงาน Installments'!D7)&" "&CHOOSE(MONTH('งวดงาน Installments'!D7),"ม.ค.","ก.พ.","มี.ค.","เม.ย.","พ.ค.","มิ.ย.","ก.ค.","ส.ค.","ก.ย.","ต.ค.","พ.ย.","ธ.ค.")&" "&RIGHT(YEAR('งวดงาน Installments'!D7)+543,2))) | E21: =IF('งวดงาน Installments'!E7="","",'งวดงาน Installments'!E7) | G21: ='งวดงาน Installments'!J7&"" | H21: ='งวดงาน Installments'!K7&"" | J21: =IF('งวดงาน Installments'!L7="","",'งวดงาน Installments'!L7)
B22: ='งวดงาน Installments'!A8&"" | C22: ='งวดงาน Installments'!B8&"" | D22: =IF('งวดงาน Installments'!D8="","",IF(N('งวดงาน Installments'!D8)=0,"-",DAY('งวดงาน Installments'!D8)&" "&CHOOSE(MONTH('งวดงาน Installments'!D8),"ม.ค.","ก.พ.","มี.ค.","เม.ย.","พ.ค.","มิ.ย.","ก.ค.","ส.ค.","ก.ย.","ต.ค.","พ.ย.","ธ.ค.")&" "&RIGHT(YEAR('งวดงาน Installments'!D8)+543,2))) | E22: =IF('งวดงาน Installments'!E8="","",'งวดงาน Installments'!E8) | G22: ='งวดงาน Installments'!J8&"" | H22: ='งวดงาน Installments'!K8&"" | J22: =IF('งวดงาน Installments'!L8="","",'งวดงาน Installments'!L8)
B23: ='งวดงาน Installments'!A9&"" | C23: ='งวดงาน Installments'!B9&"" | D23: =IF('งวดงาน Installments'!D9="","",IF(N('งวดงาน Installments'!D9)=0,"-",DAY('งวดงาน Installments'!D9)&" "&CHOOSE(MONTH('งวดงาน Installments'!D9),"ม.ค.","ก.พ.","มี.ค.","เม.ย.","พ.ค.","มิ.ย.","ก.ค.","ส.ค.","ก.ย.","ต.ค.","พ.ย.","ธ.ค.")&" "&RIGHT(YEAR('งวดงาน Installments'!D9)+543,2))) | E23: =IF('งวดงาน Installments'!E9="","",'งวดงาน Installments'!E9) | G23: ='งวดงาน Installments'!J9&"" | H23: ='งวดงาน Installments'!K9&"" | J23: =IF('งวดงาน Installments'!L9="","",'งวดงาน Installments'!L9)
B24: ='งวดงาน Installments'!A10&"" | C24: ='งวดงาน Installments'!B10&"" | D24: =IF('งวดงาน Installments'!D10="","",IF(N('งวดงาน Installments'!D10)=0,"-",DAY('งวดงาน Installments'!D10)&" "&CHOOSE(MONTH('งวดงาน Installments'!D10),"ม.ค.","ก.พ.","มี.ค.","เม.ย.","พ.ค.","มิ.ย.","ก.ค.","ส.ค.","ก.ย.","ต.ค.","พ.ย.","ธ.ค.")&" "&RIGHT(YEAR('งวดงาน Installments'!D10)+543,2))) | E24: =IF('งวดงาน Installments'!E10="","",'งวดงาน Installments'!E10) | G24: ='งวดงาน Installments'!J10&"" | H24: ='งวดงาน Installments'!K10&"" | J24: =IF('งวดงาน Installments'!L10="","",'งวดงาน Installments'!L10)
B25: ='งวดงาน Installments'!A11&"" | C25: ='งวดงาน Installments'!B11&"" | D25: =IF('งวดงาน Installments'!D11="","",IF(N('งวดงาน Installments'!D11)=0,"-",DAY('งวดงาน Installments'!D11)&" "&CHOOSE(MONTH('งวดงาน Installments'!D11),"ม.ค.","ก.พ.","มี.ค.","เม.ย.","พ.ค.","มิ.ย.","ก.ค.","ส.ค.","ก.ย.","ต.ค.","พ.ย.","ธ.ค.")&" "&RIGHT(YEAR('งวดงาน Installments'!D11)+543,2))) | E25: =IF('งวดงาน Installments'!E11="","",'งวดงาน Installments'!E11) | G25: ='งวดงาน Installments'!J11&"" | H25: ='งวดงาน Installments'!K11&"" | J25: =IF('งวดงาน Installments'!L11="","",'งวดงาน Installments'!L11)
B26: ='งวดงาน Installments'!A12&"" | C26: ='งวดงาน Installments'!B12&"" | D26: =IF('งวดงาน Installments'!D12="","",IF(N('งวดงาน Installments'!D12)=0,"-",DAY('งวดงาน Installments'!D12)&" "&CHOOSE(MONTH('งวดงาน Installments'!D12),"ม.ค.","ก.พ.","มี.ค.","เม.ย.","พ.ค.","มิ.ย.","ก.ค.","ส.ค.","ก.ย.","ต.ค.","พ.ย.","ธ.ค.")&" "&RIGHT(YEAR('งวดงาน Installments'!D12)+543,2))) | E26: =IF('งวดงาน Installments'!E12="","",'งวดงาน Installments'!E12) | G26: ='งวดงาน Installments'!J12&"" | H26: ='งวดงาน Installments'!K12&"" | J26: =IF('งวดงาน Installments'!L12="","",'งวดงาน Installments'!L12)
B27: ='งวดงาน Installments'!A13&"" | C27: ='งวดงาน Installments'!B13&"" | D27: =IF('งวดงาน Installments'!D13="","",IF(N('งวดงาน Installments'!D13)=0,"-",DAY('งวดงาน Installments'!D13)&" "&CHOOSE(MONTH('งวดงาน Installments'!D13),"ม.ค.","ก.พ.","มี.ค.","เม.ย.","พ.ค.","มิ.ย.","ก.ค.","ส.ค.","ก.ย.","ต.ค.","พ.ย.","ธ.ค.")&" "&RIGHT(YEAR('งวดงาน Installments'!D13)+543,2))) | E27: =IF('งวดงาน Installments'!E13="","",'งวดงาน Installments'!E13) | G27: ='งวดงาน Installments'!J13&"" | H27: ='งวดงาน Installments'!K13&"" | J27: =IF('งวดงาน Installments'!L13="","",'งวดงาน Installments'!L13)
B28: ='งวดงาน Installments'!A14&"" | C28: ='งวดงาน Installments'!B14&"" | D28: =IF('งวดงาน Installments'!D14="","",IF(N('งวดงาน Installments'!D14)=0,"-",DAY('งวดงาน Installments'!D14)&" "&CHOOSE(MONTH('งวดงาน Installments'!D14),"ม.ค.","ก.พ.","มี.ค.","เม.ย.","พ.ค.","มิ.ย.","ก.ค.","ส.ค.","ก.ย.","ต.ค.","พ.ย.","ธ.ค.")&" "&RIGHT(YEAR('งวดงาน Installments'!D14)+543,2))) | E28: =IF('งวดงาน Installments'!E14="","",'งวดงาน Installments'!E14) | G28: ='งวดงาน Installments'!J14&"" | H28: ='งวดงาน Installments'!K14&"" | J28: =IF('งวดงาน Installments'!L14="","",'งวดงาน Installments'!L14)
B29: ='งวดงาน Installments'!A15&"" | C29: ='งวดงาน Installments'!B15&"" | D29: =IF('งวดงาน Installments'!D15="","",IF(N('งวดงาน Installments'!D15)=0,"-",DAY('งวดงาน Installments'!D15)&" "&CHOOSE(MONTH('งวดงาน Installments'!D15),"ม.ค.","ก.พ.","มี.ค.","เม.ย.","พ.ค.","มิ.ย.","ก.ค.","ส.ค.","ก.ย.","ต.ค.","พ.ย.","ธ.ค.")&" "&RIGHT(YEAR('งวดงาน Installments'!D15)+543,2))) | E29: =IF('งวดงาน Installments'!E15="","",'งวดงาน Installments'!E15) | G29: ='งวดงาน Installments'!J15&"" | H29: ='งวดงาน Installments'!K15&"" | J29: =IF('งวดงาน Installments'!L15="","",'งวดงาน Installments'!L15)
B30: ='งวดงาน Installments'!A16&"" | C30: ='งวดงาน Installments'!B16&"" | D30: =IF('งวดงาน Installments'!D16="","",IF(N('งวดงาน Installments'!D16)=0,"-",DAY('งวดงาน Installments'!D16)&" "&CHOOSE(MONTH('งวดงาน Installments'!D16),"ม.ค.","ก.พ.","มี.ค.","เม.ย.","พ.ค.","มิ.ย.","ก.ค.","ส.ค.","ก.ย.","ต.ค.","พ.ย.","ธ.ค.")&" "&RIGHT(YEAR('งวดงาน Installments'!D16)+543,2))) | E30: =IF('งวดงาน Installments'!E16="","",'งวดงาน Installments'!E16) | G30: ='งวดงาน Installments'!J16&"" | H30: ='งวดงาน Installments'!K16&"" | J30: =IF('งวดงาน Installments'!L16="","",'งวดงาน Installments'!L16)
B31: =IF(COUNTA('งวดงาน Installments'!B7:B26)=0,"(ยังไม่ได้กรอกข้อมูลงวดงาน – กรอกที่ชีต งวดงาน Installments)","") -> (ยังไม่ได้กรอกข้อมูลงวดงาน – กรอกที่ชีต งวดงาน Installments)
B33: 3. ผลการดำเนินงาน
B34: 3.1 งานที่ดำเนินการในสัปดาห์นี้
B35: =IF(INDEX('บันทึกสัปดาห์ Weekly Log'!$K$17:$K$120,'บันทึกสัปดาห์ Weekly Log'!$C$12)="","-",INDEX('บันทึกสัปดาห์ Weekly Log'!$K$17:$K$120,'บันทึกสัปดาห์ Weekly Log'!$C$12)) -> -
B36: ="3.2 งานที่อยู่ระหว่างดำเนินการ / ต้องดำเนินการภายใน "&'ตั้งค่า Setup'!$C$20&" วัน" -> 3.2 งานที่อยู่ระหว่างดำเนินการ / ต้องดำเนินการภายใน 30 วัน
B37: ลำดับ | C37: WBS / รายการงาน | D37: กำหนดเสร็จ | E37: % ผลงาน | G37: คาดว่าเสร็จ | H37: สถานะ
B38: =IF(L38="","",1) -> 1 | C38: =IF(L38="","",INDEX('แผนงาน Schedule'!$A$7:$A$66,L38)&" "&INDEX('แผนงาน Schedule'!$C$7:$C$66,L38)) -> 1.1 งานเตรียมการ ติดตั้งป้ายโครงการ และรื้อถอนระบบเดิม | D38: =IF(L38="","",IF(N(INDEX('แผนงาน Schedule'!$AA$7:$AA$66,L38))=0,"-",DAY(INDEX('แผนงาน Schedule'!$AA$7:$AA$66,L38))&" "&CHOOSE(MONTH(INDEX('แผนงาน Schedule'!$AA$7:$AA$66,L38)),"ม.ค.","ก.พ.","มี.ค.","เม.ย.","พ.ค.","มิ.ย.","ก.ค.","ส.ค.","ก.ย.","ต.ค.","พ.ย.","ธ.ค.")&" "&RIGHT(YEAR(INDEX('แผนงาน Schedule'!$AA$7:$AA$66,L38))+543,2))) -> 6 มี.ค. 69 | E38: =IF(L38="","",N(INDEX('แผนงาน Schedule'!$O$7:$O$66,L38))) -> 0 | G38: =IF(L38="","",IF(N(INDEX('แผนงาน Schedule'!$V$7:$V$66,L38))=0,"-",DAY(INDEX('แผนงาน Schedule'!$V$7:$V$66,L38))&" "&CHOOSE(MONTH(INDEX('แผนงาน Schedule'!$V$7:$V$66,L38)),"ม.ค.","ก.พ.","มี.ค.","เม.ย.","พ.ค.","มิ.ย.","ก.ค.","ส.ค.","ก.ย.","ต.ค.","พ.ย.","ธ.ค.")&" "&RIGHT(YEAR(INDEX('แผนงาน Schedule'!$V$7:$V$66,L38))+543,2))) -> 13 ต.ค. 69 | H38: =IF(L38="","",INDEX('แผนงาน Schedule'!$X$7:$X$66,L38)) -> เกินกำหนด / Overdue | L38: =IFERROR(MATCH(1,'แผนงาน Schedule'!$AD$7:$AD$66,0),"") -> 1
B39: =IF(L39="","",2) -> 2 | C39: =IF(L39="","",INDEX('แผนงาน Schedule'!$A$7:$A$66,L39)&" "&INDEX('แผนงาน Schedule'!$C$7:$C$66,L39)) -> 1.2 ก่อสร้างสำนักงานชั่วคราวและจัดเตรียมอุปกรณ์สำนักงาน | D39: =IF(L39="","",IF(N(INDEX('แผนงาน Schedule'!$AA$7:$AA$66,L39))=0,"-",DAY(INDEX('แผนงาน Schedule'!$AA$7:$AA$66,L39))&" "&CHOOSE(MONTH(INDEX('แผนงาน Schedule'!$AA$7:$AA$66,L39)),"ม.ค.","ก.พ.","มี.ค.","เม.ย.","พ.ค.","มิ.ย.","ก.ค.","ส.ค.","ก.ย.","ต.ค.","พ.ย.","ธ.ค.")&" "&RIGHT(YEAR(INDEX('แผนงาน Schedule'!$AA$7:$AA$66,L39))+543,2))) -> 15 เม.ย. 69 | E39: =IF(L39="","",N(INDEX('แผนงาน Schedule'!$O$7:$O$66,L39))) -> 0 | G39: =IF(L39="","",IF(N(INDEX('แผนงาน Schedule'!$V$7:$V$66,L39))=0,"-",DAY(INDEX('แผนงาน Schedule'!$V$7:$V$66,L39))&" "&CHOOSE(MONTH(INDEX('แผนงาน Schedule'!$V$7:$V$66,L39)),"ม.ค.","ก.พ.","มี.ค.","เม.ย.","พ.ค.","มิ.ย.","ก.ค.","ส.ค.","ก.ย.","ต.ค.","พ.ย.","ธ.ค.")&" "&RIGHT(YEAR(INDEX('แผนงาน Schedule'!$V$7:$V$66,L39))+543,2))) -> 11 พ.ย. 69 | H39: =IF(L39="","",INDEX('แผนงาน Schedule'!$X$7:$X$66,L39)) -> เกินกำหนด / Overdue | L39: =IFERROR(MATCH(2,'แผนงาน Schedule'!$AD$7:$AD$66,0),"") -> 2
B40: =IF(L40="","",3) -> 3 | C40: =IF(L40="","",INDEX('แผนงาน Schedule'!$A$7:$A$66,L40)&" "&INDEX('แผนงาน Schedule'!$C$7:$C$66,L40)) -> 1.3 งานรื้อถอนโครงสร้างเดิมและเตรียมพื้นที่ติดตั้งใหม่ | D40: =IF(L40="","",IF(N(INDEX('แผนงาน Schedule'!$AA$7:$AA$66,L40))=0,"-",DAY(INDEX('แผนงาน Schedule'!$AA$7:$AA$66,L40))&" "&CHOOSE(MONTH(INDEX('แผนงาน Schedule'!$AA$7:$AA$66,L40)),"ม.ค.","ก.พ.","มี.ค.","เม.ย.","พ.ค.","มิ.ย.","ก.ค.","ส.ค.","ก.ย.","ต.ค.","พ.ย.","ธ.ค.")&" "&RIGHT(YEAR(INDEX('แผนงาน Schedule'!$AA$7:$AA$66,L40))+543,2))) -> 20 เม.ย. 69 | E40: =IF(L40="","",N(INDEX('แผนงาน Schedule'!$O$7:$O$66,L40))) -> 0 | G40: =IF(L40="","",IF(N(INDEX('แผนงาน Schedule'!$V$7:$V$66,L40))=0,"-",DAY(INDEX('แผนงาน Schedule'!$V$7:$V$66,L40))&" "&CHOOSE(MONTH(INDEX('แผนงาน Schedule'!$V$7:$V$66,L40)),"ม.ค.","ก.พ.","มี.ค.","เม.ย.","พ.ค.","มิ.ย.","ก.ค.","ส.ค.","ก.ย.","ต.ค.","พ.ย.","ธ.ค.")&" "&RIGHT(YEAR(INDEX('แผนงาน Schedule'!$V$7:$V$66,L40))+543,2))) -> 7 พ.ย. 69 | H40: =IF(L40="","",INDEX('แผนงาน Schedule'!$X$7:$X$66,L40)) -> เกินกำหนด / Overdue | L40: =IFERROR(MATCH(3,'แผนงาน Schedule'!$AD$7:$AD$66,0),"") -> 3
B41: =IF(L41="","",4) -> 4 | C41: =IF(L41="","",INDEX('แผนงาน Schedule'!$A$7:$A$66,L41)&" "&INDEX('แผนงาน Schedule'!$C$7:$C$66,L41)) -> 2.1 งานฐานราก คานคอดิน พื้นชั้น 1 และเสาชั้น 1 | D41: =IF(L41="","",IF(N(INDEX('แผนงาน Schedule'!$AA$7:$AA$66,L41))=0,"-",DAY(INDEX('แผนงาน Schedule'!$AA$7:$AA$66,L41))&" "&CHOOSE(MONTH(INDEX('แผนงาน Schedule'!$AA$7:$AA$66,L41)),"ม.ค.","ก.พ.","มี.ค.","เม.ย.","พ.ค.","มิ.ย.","ก.ค.","ส.ค.","ก.ย.","ต.ค.","พ.ย.","ธ.ค.")&" "&RIGHT(YEAR(INDEX('แผนงาน Schedule'!$AA$7:$AA$66,L41))+543,2))) -> 30 เม.ย. 69 | E41: =IF(L41="","",N(INDEX('แผนงาน Schedule'!$O$7:$O$66,L41))) -> 0 | G41: =IF(L41="","",IF(N(INDEX('แผนงาน Schedule'!$V$7:$V$66,L41))=0,"-",DAY(INDEX('แผนงาน Schedule'!$V$7:$V$66,L41))&" "&CHOOSE(MONTH(INDEX('แผนงาน Schedule'!$V$7:$V$66,L41)),"ม.ค.","ก.พ.","มี.ค.","เม.ย.","พ.ค.","มิ.ย.","ก.ค.","ส.ค.","ก.ย.","ต.ค.","พ.ย.","ธ.ค.")&" "&RIGHT(YEAR(INDEX('แผนงาน Schedule'!$V$7:$V$66,L41))+543,2))) -> 13 พ.ย. 69 | H41: =IF(L41="","",INDEX('แผนงาน Schedule'!$X$7:$X$66,L41)) -> เกินกำหนด / Overdue | L41: =IFERROR(MATCH(4,'แผนงาน Schedule'!$AD$7:$AD$66,0),"") -> 4
B42: =IF(L42="","",5) -> 5 | C42: =IF(L42="","",INDEX('แผนงาน Schedule'!$A$7:$A$66,L42)&" "&INDEX('แผนงาน Schedule'!$C$7:$C$66,L42)) -> 2.2 งานวาง SLEEVE/เดินท่อฝังในโครงสร้าง และโครงสร้างชั้น 1–2 | D42: =IF(L42="","",IF(N(INDEX('แผนงาน Schedule'!$AA$7:$AA$66,L42))=0,"-",DAY(INDEX('แผนงาน Schedule'!$AA$7:$AA$66,L42))&" "&CHOOSE(MONTH(INDEX('แผนงาน Schedule'!$AA$7:$AA$66,L42)),"ม.ค.","ก.พ.","มี.ค.","เม.ย.","พ.ค.","มิ.ย.","ก.ค.","ส.ค.","ก.ย.","ต.ค.","พ.ย.","ธ.ค.")&" "&RIGHT(YEAR(INDEX('แผนงาน Schedule'!$AA$7:$AA$66,L42))+543,2))) -> 15 พ.ค. 69 | E42: =IF(L42="","",N(INDEX('แผนงาน Schedule'!$O$7:$O$66,L42))) -> 0 | G42: =IF(L42="","",IF(N(INDEX('แผนงาน Schedule'!$V$7:$V$66,L42))=0,"-",DAY(INDEX('แผนงาน Schedule'!$V$7:$V$66,L42))&" "&CHOOSE(MONTH(INDEX('แผนงาน Schedule'!$V$7:$V$66,L42)),"ม.ค.","ก.พ.","มี.ค.","เม.ย.","พ.ค.","มิ.ย.","ก.ค.","ส.ค.","ก.ย.","ต.ค.","พ.ย.","ธ.ค.")&" "&RIGHT(YEAR(INDEX('แผนงาน Schedule'!$V$7:$V$66,L42))+543,2))) -> 28 ต.ค. 69 | H42: =IF(L42="","",INDEX('แผนงาน Schedule'!$X$7:$X$66,L42)) -> เกินกำหนด / Overdue | L42: =IFERROR(MATCH(5,'แผนงาน Schedule'!$AD$7:$AD$66,0),"") -> 5
B43: =IF(L43="","",6) -> 6 | C43: =IF(L43="","",INDEX('แผนงาน Schedule'!$A$7:$A$66,L43)&" "&INDEX('แผนงาน Schedule'!$C$7:$C$66,L43)) -> 2.3 งานคานและพื้นชั้น 2 พร้อมวาง SLEEVE ชั้น 2 | D43: =IF(L43="","",IF(N(INDEX('แผนงาน Schedule'!$AA$7:$AA$66,L43))=0,"-",DAY(INDEX('แผนงาน Schedule'!$AA$7:$AA$66,L43))&" "&CHOOSE(MONTH(INDEX('แผนงาน Schedule'!$AA$7:$AA$66,L43)),"ม.ค.","ก.พ.","มี.ค.","เม.ย.","พ.ค.","มิ.ย.","ก.ค.","ส.ค.","ก.ย.","ต.ค.","พ.ย.","ธ.ค.")&" "&RIGHT(YEAR(INDEX('แผนงาน Schedule'!$AA$7:$AA$66,L43))+543,2))) -> 5 มิ.ย. 69 | E43: =IF(L43="","",N(INDEX('แผนงาน Schedule'!$O$7:$O$66,L43))) -> 0 | G43: =IF(L43="","",IF(N(INDEX('แผนงาน Schedule'!$V$7:$V$66,L43))=0,"-",DAY(INDEX('แผนงาน Schedule'!$V$7:$V$66,L43))&" "&CHOOSE(MONTH(INDEX('แผนงาน Schedule'!$V$7:$V$66,L43)),"ม.ค.","ก.พ.","มี.ค.","เม.ย.","พ.ค.","มิ.ย.","ก.ค.","ส.ค.","ก.ย.","ต.ค.","พ.ย.","ธ.ค.")&" "&RIGHT(YEAR(INDEX('แผนงาน Schedule'!$V$7:$V$66,L43))+543,2))) -> 23 ต.ค. 69 | H43: =IF(L43="","",INDEX('แผนงาน Schedule'!$X$7:$X$66,L43)) -> เกินกำหนด / Overdue | L43: =IFERROR(MATCH(6,'แผนงาน Schedule'!$AD$7:$AD$66,0),"") -> 6
B44: =IF(L44="","",7) -> 7 | C44: =IF(L44="","",INDEX('แผนงาน Schedule'!$A$7:$A$66,L44)&" "&INDEX('แผนงาน Schedule'!$C$7:$C$66,L44)) -> 2.4 งานโครงสร้างหลังคาและมุงหลังคา | D44: =IF(L44="","",IF(N(INDEX('แผนงาน Schedule'!$AA$7:$AA$66,L44))=0,"-",DAY(INDEX('แผนงาน Schedule'!$AA$7:$AA$66,L44))&" "&CHOOSE(MONTH(INDEX('แผนงาน Schedule'!$AA$7:$AA$66,L44)),"ม.ค.","ก.พ.","มี.ค.","เม.ย.","พ.ค.","มิ.ย.","ก.ค.","ส.ค.","ก.ย.","ต.ค.","พ.ย.","ธ.ค.")&" "&RIGHT(YEAR(INDEX('แผนงาน Schedule'!$AA$7:$AA$66,L44))+543,2))) -> 25 มิ.ย. 69 | E44: =IF(L44="","",N(INDEX('แผนงาน Schedule'!$O$7:$O$66,L44))) -> 0 | G44: =IF(L44="","",IF(N(INDEX('แผนงาน Schedule'!$V$7:$V$66,L44))=0,"-",DAY(INDEX('แผนงาน Schedule'!$V$7:$V$66,L44))&" "&CHOOSE(MONTH(INDEX('แผนงาน Schedule'!$V$7:$V$66,L44)),"ม.ค.","ก.พ.","มี.ค.","เม.ย.","พ.ค.","มิ.ย.","ก.ค.","ส.ค.","ก.ย.","ต.ค.","พ.ย.","ธ.ค.")&" "&RIGHT(YEAR(INDEX('แผนงาน Schedule'!$V$7:$V$66,L44))+543,2))) -> 22 ต.ค. 69 | H44: =IF(L44="","",INDEX('แผนงาน Schedule'!$X$7:$X$66,L44)) -> เกินกำหนด / Overdue | L44: =IFERROR(MATCH(7,'แผนงาน Schedule'!$AD$7:$AD$66,0),"") -> 7
B45: =IF(L45="","",8) -> 8 | C45: =IF(L45="","",INDEX('แผนงาน Schedule'!$A$7:$A$66,L45)&" "&INDEX('แผนงาน Schedule'!$C$7:$C$66,L45)) -> 3.1 งานผนัง/โครงเคร่า ติดตั้งฉนวน PU Foam และรางน้ำ | D45: =IF(L45="","",IF(N(INDEX('แผนงาน Schedule'!$AA$7:$AA$66,L45))=0,"-",DAY(INDEX('แผนงาน Schedule'!$AA$7:$AA$66,L45))&" "&CHOOSE(MONTH(INDEX('แผนงาน Schedule'!$AA$7:$AA$66,L45)),"ม.ค.","ก.พ.","มี.ค.","เม.ย.","พ.ค.","มิ.ย.","ก.ค.","ส.ค.","ก.ย.","ต.ค.","พ.ย.","ธ.ค.")&" "&RIGHT(YEAR(INDEX('แผนงาน Schedule'!$AA$7:$AA$66,L45))+543,2))) -> 15 ก.ค. 69 | E45: =IF(L45="","",N(INDEX('แผนงาน Schedule'!$O$7:$O$66,L45))) -> 0 | G45: =IF(L45="","",IF(N(INDEX('แผนงาน Schedule'!$V$7:$V$66,L45))=0,"-",DAY(INDEX('แผนงาน Schedule'!$V$7:$V$66,L45))&" "&CHOOSE(MONTH(INDEX('แผนงาน Schedule'!$V$7:$V$66,L45)),"ม.ค.","ก.พ.","มี.ค.","เม.ย.","พ.ค.","มิ.ย.","ก.ค.","ส.ค.","ก.ย.","ต.ค.","พ.ย.","ธ.ค.")&" "&RIGHT(YEAR(INDEX('แผนงาน Schedule'!$V$7:$V$66,L45))+543,2))) -> 28 ต.ค. 69 | H45: =IF(L45="","",INDEX('แผนงาน Schedule'!$X$7:$X$66,L45)) -> เกินกำหนด / Overdue | L45: =IFERROR(MATCH(8,'แผนงาน Schedule'!$AD$7:$AD$66,0),"") -> 8
B46: 3.3 แผนงานสัปดาห์หน้า
B47: =IF(INDEX('บันทึกสัปดาห์ Weekly Log'!$L$17:$L$120,'บันทึกสัปดาห์ Weekly Log'!$C$12)="","-",INDEX('บันทึกสัปดาห์ Weekly Log'!$L$17:$L$120,'บันทึกสัปดาห์ Weekly Log'!$C$12)) -> -
B49: 4. ข้อมูลการปฏิบัติงานในหน่วยงาน
B50: จำนวนคนงานเฉลี่ย | D50: =IF(INDEX('บันทึกสัปดาห์ Weekly Log'!$H$17:$H$120,'บันทึกสัปดาห์ Weekly Log'!$C$12)="","-",INDEX('บันทึกสัปดาห์ Weekly Log'!$H$17:$H$120,'บันทึกสัปดาห์ Weekly Log'!$C$12)&" คน/วัน") -> -
B51: เครื่องจักร/เครื่องมือหลัก | D51: =IF(INDEX('บันทึกสัปดาห์ Weekly Log'!$I$17:$I$120,'บันทึกสัปดาห์ Weekly Log'!$C$12)="","-",INDEX('บันทึกสัปดาห์ Weekly Log'!$I$17:$I$120,'บันทึกสัปดาห์ Weekly Log'!$C$12)) -> -
B52: วันทำงาน / วันหยุด-ฝนตก | D52: =IF(INDEX('บันทึกสัปดาห์ Weekly Log'!$J$17:$J$120,'บันทึกสัปดาห์ Weekly Log'!$C$12)="","-",INDEX('บันทึกสัปดาห์ Weekly Log'!$J$17:$J$120,'บันทึกสัปดาห์ Weekly Log'!$C$12)) -> -
B53: วัสดุเข้าหน่วยงาน / การทดสอบ | D53: =IF(INDEX('บันทึกสัปดาห์ Weekly Log'!$M$17:$M$120,'บันทึกสัปดาห์ Weekly Log'!$C$12)="","-",INDEX('บันทึกสัปดาห์ Weekly Log'!$M$17:$M$120,'บันทึกสัปดาห์ Weekly Log'!$C$12)) -> -
B55: 5. ปัญหา อุปสรรค และการขยายเวลา
B56: =IF(INDEX('บันทึกสัปดาห์ Weekly Log'!$N$17:$N$120,'บันทึกสัปดาห์ Weekly Log'!$C$12)="","-",INDEX('บันทึกสัปดาห์ Weekly Log'!$N$17:$N$120,'บันทึกสัปดาห์ Weekly Log'!$C$12)) -> -
B57: ="การขอขยายเวลา: ขอรวม "&Dashboard!C49&" วัน • อนุมัติแล้ว "&Dashboard!C50&" วัน • รอพิจารณา "&Dashboard!C51&" วัน • วันสิ้นสุดสัญญาปัจจุบัน "&IF(N('ตั้งค่า Setup'!$C$14)=0,"-",DAY('ตั้งค่า Setup'!$C$14)&" "&CHOOSE(MONTH('ตั้งค่า Setup'!$C$14),"มกราคม","กุมภาพันธ์","มีนาคม","เมษายน","พฤษภาคม","มิถุนายน","กรกฎาคม","สิงหาคม","กันยายน","ตุลาคม","พฤศจิกายน","ธันวาคม")&" "&(YEAR('ตั้งค่า Setup'!$C$14)+543)) -> การขอขยายเวลา: ขอรวม 0 วัน • อนุมัติแล้ว 0 วัน • รอพิจารณา 0 วัน • วันสิ้นสุดสัญญาปัจจุบัน 16 พฤศจิกายน 2569
B58: ="ค่าปรับ: "&IF(Dashboard!C54>0,"เกิดขึ้นแล้ว "&TEXT(Dashboard!C54,"#,##0")&" บาท • ","")&Dashboard!C57 -> ค่าปรับ: ⚠ เกินเกณฑ์ 10% – ความเสี่ยงถูกบอกเลิกสัญญา
B60: 6. ความเห็นของผู้ควบคุมงาน
B61: =IF(INDEX('บันทึกสัปดาห์ Weekly Log'!$O$17:$O$120,'บันทึกสัปดาห์ Weekly Log'!$C$12)="","-",INDEX('บันทึกสัปดาห์ Weekly Log'!$O$17:$O$120,'บันทึกสัปดาห์ Weekly Log'!$C$12)) -> -
B63: จึงเรียนมาเพื่อโปรดทราบ
G65: ลงชื่อ ..........................................
G66: ="("&IF('บันทึกสัปดาห์ Weekly Log'!C7="","..........................................",'บันทึกสัปดาห์ Weekly Log'!C7)&")" -> (..........................................)
G67: ="ตำแหน่ง "&'บันทึกสัปดาห์ Weekly Log'!C8 -> ตำแหน่ง ผู้ควบคุมงาน
G68: ผู้ควบคุมงาน
B71: 7. ความเห็นของคณะกรรมการตรวจรับพัสดุ
B72: ☐ รับทราบ ☐ ให้ผู้รับจ้างเร่งรัดงาน ☐ อื่นๆ ......................................................................................
B76: ลงชื่อ ............................. | E76: ลงชื่อ ............................. | H76: ลงชื่อ .............................
B77: ="("&IF('บันทึกสัปดาห์ Weekly Log'!C9="",".............................",'บันทึกสัปดาห์ Weekly Log'!C9)&")" -> (.............................) | E77: ="("&IF('บันทึกสัปดาห์ Weekly Log'!C10="",".............................",'บันทึกสัปดาห์ Weekly Log'!C10)&")" -> (.............................) | H77: ="("&IF('บันทึกสัปดาห์ Weekly Log'!C11="",".............................",'บันทึกสัปดาห์ Weekly Log'!C11)&")" -> (.............................)
B78: ประธานกรรมการ | E78: กรรมการ | H78: กรรมการ
B79: วันที่ ......./......./....... | E79: วันที่ ......./......./....... | H79: วันที่ ......./......./.......
B82: ="ภาพถ่ายประกอบรายงาน ประจำสัปดาห์ที่ "&'บันทึกสัปดาห์ Weekly Log'!$C$12 -> ภาพถ่ายประกอบรายงาน ประจำสัปดาห์ที่ 31
B83: วิธีใส่รูป: คลิกที่กรอบ → แทรก (Insert) → รูปภาพ → ย่อขนาดให้พอดีกรอบ • พิมพ์คำอธิบายใต้รูปในช่องสีเหลือง
B85: รูปที่ 1 | F85: รูปที่ 2
B100: รูปที่ 3 | F100: รูปที่ 4
B115: รูปที่ 5 | F115: รูปที่ 6

Sheet งานเพิ่มลด VO
A1: ทะเบียนงานเพิ่ม-ลด / Variation Order (VO) Register
A2: บันทึกการแก้ไขเปลี่ยนแปลงสัญญา • เฉพาะรายการ 'อนุมัติ' จึงนำไปปรับมูลค่าสัญญา • มูลค่าสัญญาเดิม (Baseline) ในชีตตั้งค่ายังคงไว้เพื่อวัดผล
A3: มูลค่าสัญญาเดิม (บาท) | C3: ='ตั้งค่า Setup'!$C$9 -> 12108000 | E3: รอพิจารณา: | F3: =COUNTIF(H10:H59,"รอพิจารณา")&" รายการ • "&TEXT(SUMIF(H10:H59,"รอพิจารณา",G10:G59),"#,##0")&" บาท" -> 0 รายการ • 0 บาท
A4: งานเพิ่มที่อนุมัติ (บาท) | C4: =SUMIFS(L10:L59,L10:L59,">0") -> 0 | E4: ข้อควรทราบ: | F4: งานเพิ่มที่อนุมัติ ควรเพิ่มเป็นรายการใหม่ในชีตแผนงาน (พร้อมมูลค่า BOQ และวันแผน) เพื่อให้ S-Curve และผลงานรวมงานเพิ่มด้วย
A5: งานลดที่อนุมัติ (บาท) | C5: =SUMIFS(L10:L59,L10:L59,"<0") -> 0 | F5: ผลกระทบต่อระยะเวลา (ถ้ามี) ให้บันทึกขอขยายเวลาในชีต ขยายเวลา EOT
A6: มูลค่าสัญญาปัจจุบัน (บาท) | C6: =C3+C4+C5 -> 12108000
A7: % เปลี่ยนแปลงสุทธิ | C7: =IFERROR((C6-C3)/C3,0) -> 0
A9: ลำดับ | B9: เลขที่ VO / หนังสือ | C9: วันที่ | D9: รายละเอียดงานที่เปลี่ยนแปลง | E9: WBS ที่ เกี่ยวข้อง | F9: ประเภท | G9: จำนวนเงินที่เสนอ (บาท) | H9: ผลพิจารณา | I9: จำนวนเงิน ที่อนุมัติ (บาท) | J9: วันที่ อนุมัติ | K9: ผลต่อเวลา (วัน) | L9: มูลค่าสุทธิ เข้าสัญญา (บาท) | M9: หมายเหตุ
A10: =IF(D10="","",COUNTA(D$10:D10)) | L10: =IF(OR(D10="",H10<>"อนุมัติ"),0,IF(F10="งานลด",-N(I10),N(I10))) -> 0
A11: =IF(D11="","",COUNTA(D$10:D11)) | L11: =IF(OR(D11="",H11<>"อนุมัติ"),0,IF(F11="งานลด",-N(I11),N(I11))) -> 0
A12: =IF(D12="","",COUNTA(D$10:D12)) | L12: =IF(OR(D12="",H12<>"อนุมัติ"),0,IF(F12="งานลด",-N(I12),N(I12))) -> 0
A13: =IF(D13="","",COUNTA(D$10:D13)) | L13: =IF(OR(D13="",H13<>"อนุมัติ"),0,IF(F13="งานลด",-N(I13),N(I13))) -> 0
A14: =IF(D14="","",COUNTA(D$10:D14)) | L14: =IF(OR(D14="",H14<>"อนุมัติ"),0,IF(F14="งานลด",-N(I14),N(I14))) -> 0
A15: =IF(D15="","",COUNTA(D$10:D15)) | L15: =IF(OR(D15="",H15<>"อนุมัติ"),0,IF(F15="งานลด",-N(I15),N(I15))) -> 0
A16: =IF(D16="","",COUNTA(D$10:D16)) | L16: =IF(OR(D16="",H16<>"อนุมัติ"),0,IF(F16="งานลด",-N(I16),N(I16))) -> 0
A17: =IF(D17="","",COUNTA(D$10:D17)) | L17: =IF(OR(D17="",H17<>"อนุมัติ"),0,IF(F17="งานลด",-N(I17),N(I17))) -> 0
A18: =IF(D18="","",COUNTA(D$10:D18)) | L18: =IF(OR(D18="",H18<>"อนุมัติ"),0,IF(F18="งานลด",-N(I18),N(I18))) -> 0
A19: =IF(D19="","",COUNTA(D$10:D19)) | L19: =IF(OR(D19="",H19<>"อนุมัติ"),0,IF(F19="งานลด",-N(I19),N(I19))) -> 0
A20: =IF(D20="","",COUNTA(D$10:D20)) | L20: =IF(OR(D20="",H20<>"อนุมัติ"),0,IF(F20="งานลด",-N(I20),N(I20))) -> 0
A21: =IF(D21="","",COUNTA(D$10:D21)) | L21: =IF(OR(D21="",H21<>"อนุมัติ"),0,IF(F21="งานลด",-N(I21),N(I21))) -> 0
... A59: =IF(D59="","",COUNTA(D$10:D59)) | L59: =IF(OR(D59="",H59<>"อนุมัติ"),0,IF(F59="งานลด",-N(I59),N(I59))) -> 0

Sheet เงินงวด Payment
A1: คำนวณเงินงวด / Payment Certificate: เงินล่วงหน้า • เงินประกันผลงาน • ค่า K
A2: ดึงงวดงานจากชีต งวดงาน Installments • กรอกดัชนีราคาเดือนส่งมอบงาน (It) เพื่อคำนวณค่า K • ตรวจสอบอัตราทั้งหมดกับเงื่อนไขในสัญญา
A3: เงื่อนไขสัญญา | D3: ค่า | F3: สูตรค่า K | H3: สัมประสิทธิ์ | I3: Io (ฐาน) | J3: ดัชนี | L3: สรุป | N3: บาท
A4: มูลค่าสัญญาปัจจุบัน (รวม VO อนุมัติ) | D4: ='งานเพิ่มลด VO'!C6 -> 12108000 | F4: ค่าคงที่ a | H4: 0.25 | L4: เงินล่วงหน้าคงเหลือ (หลังงวดที่ตรวจรับแล้ว) | N4: =D6-SUMIF(Q15:Q34,"ตรวจรับแล้ว",M15:M34) -> 1816200
A5: เงินล่วงหน้า (% ของสัญญาเดิม) | D5: 0.15 | F5: It/Io | H5: 0.15 | I5: 100 | J5: ดัชนีราคาผู้บริโภคทั่วไป | L5: เงินประกันผลงานที่ถูกหักแล้ว (งวดที่ตรวจรับแล้ว) | N5: =SUMIF(Q15:Q34,"ตรวจรับแล้ว",N15:N34) -> 0
A6: จำนวนเงินล่วงหน้าที่รับ (บาท) | D6: ='ตั้งค่า Setup'!$C$9*D5 -> 1816200 | F6: Ct/Co | H6: 0.1 | I6: 100 | J6: ดัชนีราคาซีเมนต์ | L6: ยอดจ่ายสุทธิสะสม (งวดที่ตรวจรับแล้ว) | N6: =SUMIF(Q15:Q34,"ตรวจรับแล้ว",P15:P34) -> 0
A7: หักเงินประกันผลงาน (% ต่องวด) | D7: 0.05 | F7: Mt/Mo | H7: 0.4 | I7: 100 | J7: ดัชนีราคาวัสดุก่อสร้าง
A8: เกณฑ์ค่า K (คิดเฉพาะส่วนที่เกิน ±) | D8: 0.04 | F8: St/So | H8: 0.1 | I8: 100 | J8: ดัชนีราคาเหล็ก
A9: ใช้ค่า K ในสัญญานี้หรือไม่ | D9: ใช้ | F9: (ว่าง) | H9: 0
A10: ผลรวมสัมประสิทธิ์ (ต้อง = 1.00) | D10: =H4+SUM(H5:H9) -> 1 | F10: ตัวอย่างสูตรงานอาคาร K = 0.25 + 0.15It/Io + 0.10Ct/Co + 0.40Mt/Mo + 0.10St/So • Io = ดัชนีเดือนเปิดซอง • ต้องใช้สูตรตามที่ระบุในสัญญา
A14: งวด | B14: วันที่ส่งมอบ /ตรวจรับ | C14: จำนวนเงิน ตามสัญญา | D14: VO ที่รวม ในงวดนี้ | E14: มูลค่างานงวด | F14: It1 | G14: It2 | H14: It3 | I14: It4 | J14: It5 | K14: ค่า K | L14: เงินเพิ่ม(+)/ลด(−) ค่า K | M14: หักเงิน ล่วงหน้า | N14: หักเงินประกัน ผลงาน | O14: หักค่าปรับ | P14: ยอดจ่ายสุทธิ | Q14: สถานะงวด
A15: =IF('งวดงาน Installments'!B7="","",'งวดงาน Installments'!A7) | B15: =IF(A15="","",IF('งวดงาน Installments'!H7<>"",'งวดงาน Installments'!H7,IF('งวดงาน Installments'!G7<>"",'งวดงาน Installments'!G7,""))) | C15: =IF(A15="","",N('งวดงาน Installments'!E7)) | E15: =IF(A15="","",C15+N(D15)) | K15: =IF(OR(A15="",$D$9<>"ใช้",OR(COUNT(F15:J15)=0,AND($H$5>0,F15=""),AND($H$6>0,G15=""),AND($H$7>0,H15=""),AND($H$8>0,I15=""),AND($H$9>0,J15=""))),"",$H$4+IF($I$5>0,$H$5*F15/$I$5,0)+IF($I$6>0,$H$6*G15/$I$6,0)+IF($I$7>0,$H$7*H15/$I$7,0)+IF($I$8>0,$H$8*I15/$I$8,0)+IF($I$9>0,$H$9*J15/$I$9,0)) | L15: =IF(K15="","",IF(K15>1+$D$8,E15*(K15-1-$D$8),IF(K15<1-$D$8,E15*(K15-1+$D$8),0))) | M15: =IF(A15="","",E15*$D$5) | N15: =IF(A15="","",E15*$D$7) | P15: =IF(A15="","",E15+N(L15)-M15-N15-N(O15)) | Q15: =IF(A15="","",'งวดงาน Installments'!K7)
A16: =IF('งวดงาน Installments'!B8="","",'งวดงาน Installments'!A8) | B16: =IF(A16="","",IF('งวดงาน Installments'!H8<>"",'งวดงาน Installments'!H8,IF('งวดงาน Installments'!G8<>"",'งวดงาน Installments'!G8,""))) | C16: =IF(A16="","",N('งวดงาน Installments'!E8)) | E16: =IF(A16="","",C16+N(D16)) | K16: =IF(OR(A16="",$D$9<>"ใช้",OR(COUNT(F16:J16)=0,AND($H$5>0,F16=""),AND($H$6>0,G16=""),AND($H$7>0,H16=""),AND($H$8>0,I16=""),AND($H$9>0,J16=""))),"",$H$4+IF($I$5>0,$H$5*F16/$I$5,0)+IF($I$6>0,$H$6*G16/$I$6,0)+IF($I$7>0,$H$7*H16/$I$7,0)+IF($I$8>0,$H$8*I16/$I$8,0)+IF($I$9>0,$H$9*J16/$I$9,0)) | L16: =IF(K16="","",IF(K16>1+$D$8,E16*(K16-1-$D$8),IF(K16<1-$D$8,E16*(K16-1+$D$8),0))) | M16: =IF(A16="","",E16*$D$5) | N16: =IF(A16="","",E16*$D$7) | P16: =IF(A16="","",E16+N(L16)-M16-N16-N(O16)) | Q16: =IF(A16="","",'งวดงาน Installments'!K8)
A17: =IF('งวดงาน Installments'!B9="","",'งวดงาน Installments'!A9) | B17: =IF(A17="","",IF('งวดงาน Installments'!H9<>"",'งวดงาน Installments'!H9,IF('งวดงาน Installments'!G9<>"",'งวดงาน Installments'!G9,""))) | C17: =IF(A17="","",N('งวดงาน Installments'!E9)) | E17: =IF(A17="","",C17+N(D17)) | K17: =IF(OR(A17="",$D$9<>"ใช้",OR(COUNT(F17:J17)=0,AND($H$5>0,F17=""),AND($H$6>0,G17=""),AND($H$7>0,H17=""),AND($H$8>0,I17=""),AND($H$9>0,J17=""))),"",$H$4+IF($I$5>0,$H$5*F17/$I$5,0)+IF($I$6>0,$H$6*G17/$I$6,0)+IF($I$7>0,$H$7*H17/$I$7,0)+IF($I$8>0,$H$8*I17/$I$8,0)+IF($I$9>0,$H$9*J17/$I$9,0)) | L17: =IF(K17="","",IF(K17>1+$D$8,E17*(K17-1-$D$8),IF(K17<1-$D$8,E17*(K17-1+$D$8),0))) | M17: =IF(A17="","",E17*$D$5) | N17: =IF(A17="","",E17*$D$7) | P17: =IF(A17="","",E17+N(L17)-M17-N17-N(O17)) | Q17: =IF(A17="","",'งวดงาน Installments'!K9)
A18: =IF('งวดงาน Installments'!B10="","",'งวดงาน Installments'!A10) | B18: =IF(A18="","",IF('งวดงาน Installments'!H10<>"",'งวดงาน Installments'!H10,IF('งวดงาน Installments'!G10<>"",'งวดงาน Installments'!G10,""))) | C18: =IF(A18="","",N('งวดงาน Installments'!E10)) | E18: =IF(A18="","",C18+N(D18)) | K18: =IF(OR(A18="",$D$9<>"ใช้",OR(COUNT(F18:J18)=0,AND($H$5>0,F18=""),AND($H$6>0,G18=""),AND($H$7>0,H18=""),AND($H$8>0,I18=""),AND($H$9>0,J18=""))),"",$H$4+IF($I$5>0,$H$5*F18/$I$5,0)+IF($I$6>0,$H$6*G18/$I$6,0)+IF($I$7>0,$H$7*H18/$I$7,0)+IF($I$8>0,$H$8*I18/$I$8,0)+IF($I$9>0,$H$9*J18/$I$9,0)) | L18: =IF(K18="","",IF(K18>1+$D$8,E18*(K18-1-$D$8),IF(K18<1-$D$8,E18*(K18-1+$D$8),0))) | M18: =IF(A18="","",E18*$D$5) | N18: =IF(A18="","",E18*$D$7) | P18: =IF(A18="","",E18+N(L18)-M18-N18-N(O18)) | Q18: =IF(A18="","",'งวดงาน Installments'!K10)
A19: =IF('งวดงาน Installments'!B11="","",'งวดงาน Installments'!A11) | B19: =IF(A19="","",IF('งวดงาน Installments'!H11<>"",'งวดงาน Installments'!H11,IF('งวดงาน Installments'!G11<>"",'งวดงาน Installments'!G11,""))) | C19: =IF(A19="","",N('งวดงาน Installments'!E11)) | E19: =IF(A19="","",C19+N(D19)) | K19: =IF(OR(A19="",$D$9<>"ใช้",OR(COUNT(F19:J19)=0,AND($H$5>0,F19=""),AND($H$6>0,G19=""),AND($H$7>0,H19=""),AND($H$8>0,I19=""),AND($H$9>0,J19=""))),"",$H$4+IF($I$5>0,$H$5*F19/$I$5,0)+IF($I$6>0,$H$6*G19/$I$6,0)+IF($I$7>0,$H$7*H19/$I$7,0)+IF($I$8>0,$H$8*I19/$I$8,0)+IF($I$9>0,$H$9*J19/$I$9,0)) | L19: =IF(K19="","",IF(K19>1+$D$8,E19*(K19-1-$D$8),IF(K19<1-$D$8,E19*(K19-1+$D$8),0))) | M19: =IF(A19="","",E19*$D$5) | N19: =IF(A19="","",E19*$D$7) | P19: =IF(A19="","",E19+N(L19)-M19-N19-N(O19)) | Q19: =IF(A19="","",'งวดงาน Installments'!K11)
A20: =IF('งวดงาน Installments'!B12="","",'งวดงาน Installments'!A12) | B20: =IF(A20="","",IF('งวดงาน Installments'!H12<>"",'งวดงาน Installments'!H12,IF('งวดงาน Installments'!G12<>"",'งวดงาน Installments'!G12,""))) | C20: =IF(A20="","",N('งวดงาน Installments'!E12)) | E20: =IF(A20="","",C20+N(D20)) | K20: =IF(OR(A20="",$D$9<>"ใช้",OR(COUNT(F20:J20)=0,AND($H$5>0,F20=""),AND($H$6>0,G20=""),AND($H$7>0,H20=""),AND($H$8>0,I20=""),AND($H$9>0,J20=""))),"",$H$4+IF($I$5>0,$H$5*F20/$I$5,0)+IF($I$6>0,$H$6*G20/$I$6,0)+IF($I$7>0,$H$7*H20/$I$7,0)+IF($I$8>0,$H$8*I20/$I$8,0)+IF($I$9>0,$H$9*J20/$I$9,0)) | L20: =IF(K20="","",IF(K20>1+$D$8,E20*(K20-1-$D$8),IF(K20<1-$D$8,E20*(K20-1+$D$8),0))) | M20: =IF(A20="","",E20*$D$5) | N20: =IF(A20="","",E20*$D$7) | P20: =IF(A20="","",E20+N(L20)-M20-N20-N(O20)) | Q20: =IF(A20="","",'งวดงาน Installments'!K12)
A21: =IF('งวดงาน Installments'!B13="","",'งวดงาน Installments'!A13) | B21: =IF(A21="","",IF('งวดงาน Installments'!H13<>"",'งวดงาน Installments'!H13,IF('งวดงาน Installments'!G13<>"",'งวดงาน Installments'!G13,""))) | C21: =IF(A21="","",N('งวดงาน Installments'!E13)) | E21: =IF(A21="","",C21+N(D21)) | K21: =IF(OR(A21="",$D$9<>"ใช้",OR(COUNT(F21:J21)=0,AND($H$5>0,F21=""),AND($H$6>0,G21=""),AND($H$7>0,H21=""),AND($H$8>0,I21=""),AND($H$9>0,J21=""))),"",$H$4+IF($I$5>0,$H$5*F21/$I$5,0)+IF($I$6>0,$H$6*G21/$I$6,0)+IF($I$7>0,$H$7*H21/$I$7,0)+IF($I$8>0,$H$8*I21/$I$8,0)+IF($I$9>0,$H$9*J21/$I$9,0)) | L21: =IF(K21="","",IF(K21>1+$D$8,E21*(K21-1-$D$8),IF(K21<1-$D$8,E21*(K21-1+$D$8),0))) | M21: =IF(A21="","",E21*$D$5) | N21: =IF(A21="","",E21*$D$7) | P21: =IF(A21="","",E21+N(L21)-M21-N21-N(O21)) | Q21: =IF(A21="","",'งวดงาน Installments'!K13)
A22: =IF('งวดงาน Installments'!B14="","",'งวดงาน Installments'!A14) | B22: =IF(A22="","",IF('งวดงาน Installments'!H14<>"",'งวดงาน Installments'!H14,IF('งวดงาน Installments'!G14<>"",'งวดงาน Installments'!G14,""))) | C22: =IF(A22="","",N('งวดงาน Installments'!E14)) | E22: =IF(A22="","",C22+N(D22)) | K22: =IF(OR(A22="",$D$9<>"ใช้",OR(COUNT(F22:J22)=0,AND($H$5>0,F22=""),AND($H$6>0,G22=""),AND($H$7>0,H22=""),AND($H$8>0,I22=""),AND($H$9>0,J22=""))),"",$H$4+IF($I$5>0,$H$5*F22/$I$5,0)+IF($I$6>0,$H$6*G22/$I$6,0)+IF($I$7>0,$H$7*H22/$I$7,0)+IF($I$8>0,$H$8*I22/$I$8,0)+IF($I$9>0,$H$9*J22/$I$9,0)) | L22: =IF(K22="","",IF(K22>1+$D$8,E22*(K22-1-$D$8),IF(K22<1-$D$8,E22*(K22-1+$D$8),0))) | M22: =IF(A22="","",E22*$D$5) | N22: =IF(A22="","",E22*$D$7) | P22: =IF(A22="","",E22+N(L22)-M22-N22-N(O22)) | Q22: =IF(A22="","",'งวดงาน Installments'!K14)
A23: =IF('งวดงาน Installments'!B15="","",'งวดงาน Installments'!A15) | B23: =IF(A23="","",IF('งวดงาน Installments'!H15<>"",'งวดงาน Installments'!H15,IF('งวดงาน Installments'!G15<>"",'งวดงาน Installments'!G15,""))) | C23: =IF(A23="","",N('งวดงาน Installments'!E15)) | E23: =IF(A23="","",C23+N(D23)) | K23: =IF(OR(A23="",$D$9<>"ใช้",OR(COUNT(F23:J23)=0,AND($H$5>0,F23=""),AND($H$6>0,G23=""),AND($H$7>0,H23=""),AND($H$8>0,I23=""),AND($H$9>0,J23=""))),"",$H$4+IF($I$5>0,$H$5*F23/$I$5,0)+IF($I$6>0,$H$6*G23/$I$6,0)+IF($I$7>0,$H$7*H23/$I$7,0)+IF($I$8>0,$H$8*I23/$I$8,0)+IF($I$9>0,$H$9*J23/$I$9,0)) | L23: =IF(K23="","",IF(K23>1+$D$8,E23*(K23-1-$D$8),IF(K23<1-$D$8,E23*(K23-1+$D$8),0))) | M23: =IF(A23="","",E23*$D$5) | N23: =IF(A23="","",E23*$D$7) | P23: =IF(A23="","",E23+N(L23)-M23-N23-N(O23)) | Q23: =IF(A23="","",'งวดงาน Installments'!K15)
A24: =IF('งวดงาน Installments'!B16="","",'งวดงาน Installments'!A16) | B24: =IF(A24="","",IF('งวดงาน Installments'!H16<>"",'งวดงาน Installments'!H16,IF('งวดงาน Installments'!G16<>"",'งวดงาน Installments'!G16,""))) | C24: =IF(A24="","",N('งวดงาน Installments'!E16)) | E24: =IF(A24="","",C24+N(D24)) | K24: =IF(OR(A24="",$D$9<>"ใช้",OR(COUNT(F24:J24)=0,AND($H$5>0,F24=""),AND($H$6>0,G24=""),AND($H$7>0,H24=""),AND($H$8>0,I24=""),AND($H$9>0,J24=""))),"",$H$4+IF($I$5>0,$H$5*F24/$I$5,0)+IF($I$6>0,$H$6*G24/$I$6,0)+IF($I$7>0,$H$7*H24/$I$7,0)+IF($I$8>0,$H$8*I24/$I$8,0)+IF($I$9>0,$H$9*J24/$I$9,0)) | L24: =IF(K24="","",IF(K24>1+$D$8,E24*(K24-1-$D$8),IF(K24<1-$D$8,E24*(K24-1+$D$8),0))) | M24: =IF(A24="","",E24*$D$5) | N24: =IF(A24="","",E24*$D$7) | P24: =IF(A24="","",E24+N(L24)-M24-N24-N(O24)) | Q24: =IF(A24="","",'งวดงาน Installments'!K16)
A25: =IF('งวดงาน Installments'!B17="","",'งวดงาน Installments'!A17) | B25: =IF(A25="","",IF('งวดงาน Installments'!H17<>"",'งวดงาน Installments'!H17,IF('งวดงาน Installments'!G17<>"",'งวดงาน Installments'!G17,""))) | C25: =IF(A25="","",N('งวดงาน Installments'!E17)) | E25: =IF(A25="","",C25+N(D25)) | K25: =IF(OR(A25="",$D$9<>"ใช้",OR(COUNT(F25:J25)=0,AND($H$5>0,F25=""),AND($H$6>0,G25=""),AND($H$7>0,H25=""),AND($H$8>0,I25=""),AND($H$9>0,J25=""))),"",$H$4+IF($I$5>0,$H$5*F25/$I$5,0)+IF($I$6>0,$H$6*G25/$I$6,0)+IF($I$7>0,$H$7*H25/$I$7,0)+IF($I$8>0,$H$8*I25/$I$8,0)+IF($I$9>0,$H$9*J25/$I$9,0)) | L25: =IF(K25="","",IF(K25>1+$D$8,E25*(K25-1-$D$8),IF(K25<1-$D$8,E25*(K25-1+$D$8),0))) | M25: =IF(A25="","",E25*$D$5) | N25: =IF(A25="","",E25*$D$7) | P25: =IF(A25="","",E25+N(L25)-M25-N25-N(O25)) | Q25: =IF(A25="","",'งวดงาน Installments'!K17)
A26: =IF('งวดงาน Installments'!B18="","",'งวดงาน Installments'!A18) | B26: =IF(A26="","",IF('งวดงาน Installments'!H18<>"",'งวดงาน Installments'!H18,IF('งวดงาน Installments'!G18<>"",'งวดงาน Installments'!G18,""))) | C26: =IF(A26="","",N('งวดงาน Installments'!E18)) | E26: =IF(A26="","",C26+N(D26)) | K26: =IF(OR(A26="",$D$9<>"ใช้",OR(COUNT(F26:J26)=0,AND($H$5>0,F26=""),AND($H$6>0,G26=""),AND($H$7>0,H26=""),AND($H$8>0,I26=""),AND($H$9>0,J26=""))),"",$H$4+IF($I$5>0,$H$5*F26/$I$5,0)+IF($I$6>0,$H$6*G26/$I$6,0)+IF($I$7>0,$H$7*H26/$I$7,0)+IF($I$8>0,$H$8*I26/$I$8,0)+IF($I$9>0,$H$9*J26/$I$9,0)) | L26: =IF(K26="","",IF(K26>1+$D$8,E26*(K26-1-$D$8),IF(K26<1-$D$8,E26*(K26-1+$D$8),0))) | M26: =IF(A26="","",E26*$D$5) | N26: =IF(A26="","",E26*$D$7) | P26: =IF(A26="","",E26+N(L26)-M26-N26-N(O26)) | Q26: =IF(A26="","",'งวดงาน Installments'!K18)
... A34: =IF('งวดงาน Installments'!B26="","",'งวดงาน Installments'!A26) | B34: =IF(A34="","",IF('งวดงาน Installments'!H26<>"",'งวดงาน Installments'!H26,IF('งวดงาน Installments'!G26<>"",'งวดงาน Installments'!G26,""))) | C34: =IF(A34="","",N('งวดงาน Installments'!E26)) | E34: =IF(A34="","",C34+N(D34)) | K34: =IF(OR(A34="",$D$9<>"ใช้",OR(COUNT(F34:J34)=0,AND($H$5>0,F34=""),AND($H$6>0,G34=""),AND($H$7>0,H34=""),AND($H$8>0,I34=""),AND($H$9>0,J34=""))),"",$H$4+IF($I$5>0,$H$5*F34/$I$5,0)+IF($I$6>0,$H$6*G34/$I$6,0)+IF($I$7>0,$H$7*H34/$I$7,0)+IF($I$8>0,$H$8*I34/$I$8,0)+IF($I$9>0,$H$9*J34/$I$9,0)) | L34: =IF(K34="","",IF(K34>1+$D$8,E34*(K34-1-$D$8),IF(K34<1-$D$8,E34*(K34-1+$D$8),0))) | M34: =IF(A34="","",E34*$D$5) | N34: =IF(A34="","",E34*$D$7) | P34: =IF(A34="","",E34+N(L34)-M34-N34-N(O34)) | Q34: =IF(A34="","",'งวดงาน Installments'!K26)
A35: รวม | C35: =SUM(C15:C34) -> 0 | D35: =SUM(D15:D34) -> 0 | E35: =SUM(E15:E34) -> 0 | L35: =SUM(L15:L34) -> 0 | M35: =SUM(M15:M34) -> 0 | N35: =SUM(N15:N34) -> 0 | O35: =SUM(O15:O34) -> 0 | P35: =SUM(P15:P34) -> 0
A36: สูตร: ค่า K เงินเพิ่ม/ลด = มูลค่างานงวด × (K − 1 ∓ เกณฑ์) เฉพาะเมื่อ K เปลี่ยนเกินเกณฑ์ • หักเงินล่วงหน้าตามสัดส่วน = มูลค่างานงวด × % เงินล่วงหน้า • ยอดสุทธิยังไม่รวมภาษีมูลค่าเพิ่ม/ภาษีหัก ณ ที่จ่าย – ปรับตามสัญญาและระเบียบของหน่วยงาน

Sheet ขออนุมัติวัสดุ Submittal
A1: ทะเบียนขออนุมัติวัสดุ / Material Submittal Register (เชื่อมกับแผนงาน)
A2: เลือก WBS ที่ใช้วัสดุ → ระบบดึงวันเริ่มงาน แล้วคำนวณวันที่ต้องได้รับอนุมัติ = วันเริ่มงาน − ระยะเวลาสั่งผลิต/จัดส่ง • ผลตรวจจากแอปเช็คลิสต์วัสดุ กฟภ. ใส่ในคอลัมน์ผลตรวจ AI
B3: ทั้งหมด | E3: อนุมัติ | H3: รอพิจารณา / ขอเอกสารเพิ่ม | K3: ไม่อนุมัติ | N3: ⚠ เสี่ยงกระทบแผนงาน
B4: =COUNTA(D9:D108) -> 0 | E4: =COUNTIF(K9:K108,"อนุมัติ") -> 0 | H4: =COUNTIF(K9:K108,"รอพิจารณา")+COUNTIF(K9:K108,"ขอเอกสารเพิ่มเติม") -> 0 | K4: =COUNTIF(K9:K108,"ไม่อนุมัติ") -> 0 | N4: =COUNTIF(N9:N108,"⚠*") -> 0
A6: ลำดับการใช้งาน: ตรวจสเปกด้วยแอปเช็คลิสต์วัสดุ กฟภ. → บันทึกผลลงทะเบียนนี้ → ติดตามจนได้รับอนุมัติก่อนวันที่กำหนด
A8: ลำดับ | B8: เลขที่เอกสาร ขออนุมัติ | C8: หมวดตามรายการ ประกอบแบบ | D8: รายการวัสดุ | E8: ยี่ห้อ / รุ่น ที่เสนอ | F8: WBS ที่ใช้วัสดุ | G8: เริ่มงาน ตามแผน | H8: ระยะเวลา สั่งผลิต (วัน) | I8: ต้องอนุมัติ ภายใน | J8: วันที่ยื่น | K8: ผลพิจารณา | L8: วันที่ อนุมัติ | M8: ผลตรวจ AI (จากแอป) | N8: สถานะความเสี่ยง | O8: หมายเหตุ
A9: =IF(D9="","",COUNTA(D$9:D9)) | G9: =IF(F9="","",IFERROR(INDEX('แผนงาน Schedule'!$Z$7:$Z$66,MATCH(F9&"",'แผนงาน Schedule'!$A$7:$A$66,0)),"ไม่พบ WBS")) | I9: =IF(OR(D9="",NOT(ISNUMBER(G9))),"",G9-N(H9)) | N9: =IF(D9="","",IF(K9="อนุมัติ","✓ อนุมัติแล้ว พร้อมใช้",IF(K9="ไม่อนุมัติ","⚠ ไม่อนุมัติ – ต้องเสนอใหม่"&IF(ISNUMBER(I9),IF(I9>='ตั้งค่า Setup'!$C$15," (เหลือ "&(I9-'ตั้งค่า Setup'!$C$15)&" วัน)"," (เลยกำหนด "&('ตั้งค่า Setup'!$C$15-I9)&" วัน)"),""),IF(NOT(ISNUMBER(I9)),"ติดตาม",IF(I9<'ตั้งค่า Setup'!$C$15,"⚠ เลยกำหนดอนุมัติ "&('ตั้งค่า Setup'!$C$15-I9)&" วัน – กระทบแผนงาน",IF(I9-'ตั้งค่า Setup'!$C$15<=14,"⚠ ต้องอนุมัติภายใน "&(I9-'ตั้งค่า Setup'!$C$15)&" วัน","ติดตาม (เหลือ "&(I9-'ตั้งค่า Setup'!$C$15)&" วัน)"))))))
A10: =IF(D10="","",COUNTA(D$9:D10)) | G10: =IF(F10="","",IFERROR(INDEX('แผนงาน Schedule'!$Z$7:$Z$66,MATCH(F10&"",'แผนงาน Schedule'!$A$7:$A$66,0)),"ไม่พบ WBS")) | I10: =IF(OR(D10="",NOT(ISNUMBER(G10))),"",G10-N(H10)) | N10: =IF(D10="","",IF(K10="อนุมัติ","✓ อนุมัติแล้ว พร้อมใช้",IF(K10="ไม่อนุมัติ","⚠ ไม่อนุมัติ – ต้องเสนอใหม่"&IF(ISNUMBER(I10),IF(I10>='ตั้งค่า Setup'!$C$15," (เหลือ "&(I10-'ตั้งค่า Setup'!$C$15)&" วัน)"," (เลยกำหนด "&('ตั้งค่า Setup'!$C$15-I10)&" วัน)"),""),IF(NOT(ISNUMBER(I10)),"ติดตาม",IF(I10<'ตั้งค่า Setup'!$C$15,"⚠ เลยกำหนดอนุมัติ "&('ตั้งค่า Setup'!$C$15-I10)&" วัน – กระทบแผนงาน",IF(I10-'ตั้งค่า Setup'!$C$15<=14,"⚠ ต้องอนุมัติภายใน "&(I10-'ตั้งค่า Setup'!$C$15)&" วัน","ติดตาม (เหลือ "&(I10-'ตั้งค่า Setup'!$C$15)&" วัน)"))))))
A11: =IF(D11="","",COUNTA(D$9:D11)) | G11: =IF(F11="","",IFERROR(INDEX('แผนงาน Schedule'!$Z$7:$Z$66,MATCH(F11&"",'แผนงาน Schedule'!$A$7:$A$66,0)),"ไม่พบ WBS")) | I11: =IF(OR(D11="",NOT(ISNUMBER(G11))),"",G11-N(H11)) | N11: =IF(D11="","",IF(K11="อนุมัติ","✓ อนุมัติแล้ว พร้อมใช้",IF(K11="ไม่อนุมัติ","⚠ ไม่อนุมัติ – ต้องเสนอใหม่"&IF(ISNUMBER(I11),IF(I11>='ตั้งค่า Setup'!$C$15," (เหลือ "&(I11-'ตั้งค่า Setup'!$C$15)&" วัน)"," (เลยกำหนด "&('ตั้งค่า Setup'!$C$15-I11)&" วัน)"),""),IF(NOT(ISNUMBER(I11)),"ติดตาม",IF(I11<'ตั้งค่า Setup'!$C$15,"⚠ เลยกำหนดอนุมัติ "&('ตั้งค่า Setup'!$C$15-I11)&" วัน – กระทบแผนงาน",IF(I11-'ตั้งค่า Setup'!$C$15<=14,"⚠ ต้องอนุมัติภายใน "&(I11-'ตั้งค่า Setup'!$C$15)&" วัน","ติดตาม (เหลือ "&(I11-'ตั้งค่า Setup'!$C$15)&" วัน)"))))))
A12: =IF(D12="","",COUNTA(D$9:D12)) | G12: =IF(F12="","",IFERROR(INDEX('แผนงาน Schedule'!$Z$7:$Z$66,MATCH(F12&"",'แผนงาน Schedule'!$A$7:$A$66,0)),"ไม่พบ WBS")) | I12: =IF(OR(D12="",NOT(ISNUMBER(G12))),"",G12-N(H12)) | N12: =IF(D12="","",IF(K12="อนุมัติ","✓ อนุมัติแล้ว พร้อมใช้",IF(K12="ไม่อนุมัติ","⚠ ไม่อนุมัติ – ต้องเสนอใหม่"&IF(ISNUMBER(I12),IF(I12>='ตั้งค่า Setup'!$C$15," (เหลือ "&(I12-'ตั้งค่า Setup'!$C$15)&" วัน)"," (เลยกำหนด "&('ตั้งค่า Setup'!$C$15-I12)&" วัน)"),""),IF(NOT(ISNUMBER(I12)),"ติดตาม",IF(I12<'ตั้งค่า Setup'!$C$15,"⚠ เลยกำหนดอนุมัติ "&('ตั้งค่า Setup'!$C$15-I12)&" วัน – กระทบแผนงาน",IF(I12-'ตั้งค่า Setup'!$C$15<=14,"⚠ ต้องอนุมัติภายใน "&(I12-'ตั้งค่า Setup'!$C$15)&" วัน","ติดตาม (เหลือ "&(I12-'ตั้งค่า Setup'!$C$15)&" วัน)"))))))
A13: =IF(D13="","",COUNTA(D$9:D13)) | G13: =IF(F13="","",IFERROR(INDEX('แผนงาน Schedule'!$Z$7:$Z$66,MATCH(F13&"",'แผนงาน Schedule'!$A$7:$A$66,0)),"ไม่พบ WBS")) | I13: =IF(OR(D13="",NOT(ISNUMBER(G13))),"",G13-N(H13)) | N13: =IF(D13="","",IF(K13="อนุมัติ","✓ อนุมัติแล้ว พร้อมใช้",IF(K13="ไม่อนุมัติ","⚠ ไม่อนุมัติ – ต้องเสนอใหม่"&IF(ISNUMBER(I13),IF(I13>='ตั้งค่า Setup'!$C$15," (เหลือ "&(I13-'ตั้งค่า Setup'!$C$15)&" วัน)"," (เลยกำหนด "&('ตั้งค่า Setup'!$C$15-I13)&" วัน)"),""),IF(NOT(ISNUMBER(I13)),"ติดตาม",IF(I13<'ตั้งค่า Setup'!$C$15,"⚠ เลยกำหนดอนุมัติ "&('ตั้งค่า Setup'!$C$15-I13)&" วัน – กระทบแผนงาน",IF(I13-'ตั้งค่า Setup'!$C$15<=14,"⚠ ต้องอนุมัติภายใน "&(I13-'ตั้งค่า Setup'!$C$15)&" วัน","ติดตาม (เหลือ "&(I13-'ตั้งค่า Setup'!$C$15)&" วัน)"))))))
A14: =IF(D14="","",COUNTA(D$9:D14)) | G14: =IF(F14="","",IFERROR(INDEX('แผนงาน Schedule'!$Z$7:$Z$66,MATCH(F14&"",'แผนงาน Schedule'!$A$7:$A$66,0)),"ไม่พบ WBS")) | I14: =IF(OR(D14="",NOT(ISNUMBER(G14))),"",G14-N(H14)) | N14: =IF(D14="","",IF(K14="อนุมัติ","✓ อนุมัติแล้ว พร้อมใช้",IF(K14="ไม่อนุมัติ","⚠ ไม่อนุมัติ – ต้องเสนอใหม่"&IF(ISNUMBER(I14),IF(I14>='ตั้งค่า Setup'!$C$15," (เหลือ "&(I14-'ตั้งค่า Setup'!$C$15)&" วัน)"," (เลยกำหนด "&('ตั้งค่า Setup'!$C$15-I14)&" วัน)"),""),IF(NOT(ISNUMBER(I14)),"ติดตาม",IF(I14<'ตั้งค่า Setup'!$C$15,"⚠ เลยกำหนดอนุมัติ "&('ตั้งค่า Setup'!$C$15-I14)&" วัน – กระทบแผนงาน",IF(I14-'ตั้งค่า Setup'!$C$15<=14,"⚠ ต้องอนุมัติภายใน "&(I14-'ตั้งค่า Setup'!$C$15)&" วัน","ติดตาม (เหลือ "&(I14-'ตั้งค่า Setup'!$C$15)&" วัน)"))))))
A15: =IF(D15="","",COUNTA(D$9:D15)) | G15: =IF(F15="","",IFERROR(INDEX('แผนงาน Schedule'!$Z$7:$Z$66,MATCH(F15&"",'แผนงาน Schedule'!$A$7:$A$66,0)),"ไม่พบ WBS")) | I15: =IF(OR(D15="",NOT(ISNUMBER(G15))),"",G15-N(H15)) | N15: =IF(D15="","",IF(K15="อนุมัติ","✓ อนุมัติแล้ว พร้อมใช้",IF(K15="ไม่อนุมัติ","⚠ ไม่อนุมัติ – ต้องเสนอใหม่"&IF(ISNUMBER(I15),IF(I15>='ตั้งค่า Setup'!$C$15," (เหลือ "&(I15-'ตั้งค่า Setup'!$C$15)&" วัน)"," (เลยกำหนด "&('ตั้งค่า Setup'!$C$15-I15)&" วัน)"),""),IF(NOT(ISNUMBER(I15)),"ติดตาม",IF(I15<'ตั้งค่า Setup'!$C$15,"⚠ เลยกำหนดอนุมัติ "&('ตั้งค่า Setup'!$C$15-I15)&" วัน – กระทบแผนงาน",IF(I15-'ตั้งค่า Setup'!$C$15<=14,"⚠ ต้องอนุมัติภายใน "&(I15-'ตั้งค่า Setup'!$C$15)&" วัน","ติดตาม (เหลือ "&(I15-'ตั้งค่า Setup'!$C$15)&" วัน)"))))))
A16: =IF(D16="","",COUNTA(D$9:D16)) | G16: =IF(F16="","",IFERROR(INDEX('แผนงาน Schedule'!$Z$7:$Z$66,MATCH(F16&"",'แผนงาน Schedule'!$A$7:$A$66,0)),"ไม่พบ WBS")) | I16: =IF(OR(D16="",NOT(ISNUMBER(G16))),"",G16-N(H16)) | N16: =IF(D16="","",IF(K16="อนุมัติ","✓ อนุมัติแล้ว พร้อมใช้",IF(K16="ไม่อนุมัติ","⚠ ไม่อนุมัติ – ต้องเสนอใหม่"&IF(ISNUMBER(I16),IF(I16>='ตั้งค่า Setup'!$C$15," (เหลือ "&(I16-'ตั้งค่า Setup'!$C$15)&" วัน)"," (เลยกำหนด "&('ตั้งค่า Setup'!$C$15-I16)&" วัน)"),""),IF(NOT(ISNUMBER(I16)),"ติดตาม",IF(I16<'ตั้งค่า Setup'!$C$15,"⚠ เลยกำหนดอนุมัติ "&('ตั้งค่า Setup'!$C$15-I16)&" วัน – กระทบแผนงาน",IF(I16-'ตั้งค่า Setup'!$C$15<=14,"⚠ ต้องอนุมัติภายใน "&(I16-'ตั้งค่า Setup'!$C$15)&" วัน","ติดตาม (เหลือ "&(I16-'ตั้งค่า Setup'!$C$15)&" วัน)"))))))
A17: =IF(D17="","",COUNTA(D$9:D17)) | G17: =IF(F17="","",IFERROR(INDEX('แผนงาน Schedule'!$Z$7:$Z$66,MATCH(F17&"",'แผนงาน Schedule'!$A$7:$A$66,0)),"ไม่พบ WBS")) | I17: =IF(OR(D17="",NOT(ISNUMBER(G17))),"",G17-N(H17)) | N17: =IF(D17="","",IF(K17="อนุมัติ","✓ อนุมัติแล้ว พร้อมใช้",IF(K17="ไม่อนุมัติ","⚠ ไม่อนุมัติ – ต้องเสนอใหม่"&IF(ISNUMBER(I17),IF(I17>='ตั้งค่า Setup'!$C$15," (เหลือ "&(I17-'ตั้งค่า Setup'!$C$15)&" วัน)"," (เลยกำหนด "&('ตั้งค่า Setup'!$C$15-I17)&" วัน)"),""),IF(NOT(ISNUMBER(I17)),"ติดตาม",IF(I17<'ตั้งค่า Setup'!$C$15,"⚠ เลยกำหนดอนุมัติ "&('ตั้งค่า Setup'!$C$15-I17)&" วัน – กระทบแผนงาน",IF(I17-'ตั้งค่า Setup'!$C$15<=14,"⚠ ต้องอนุมัติภายใน "&(I17-'ตั้งค่า Setup'!$C$15)&" วัน","ติดตาม (เหลือ "&(I17-'ตั้งค่า Setup'!$C$15)&" วัน)"))))))
A18: =IF(D18="","",COUNTA(D$9:D18)) | G18: =IF(F18="","",IFERROR(INDEX('แผนงาน Schedule'!$Z$7:$Z$66,MATCH(F18&"",'แผนงาน Schedule'!$A$7:$A$66,0)),"ไม่พบ WBS")) | I18: =IF(OR(D18="",NOT(ISNUMBER(G18))),"",G18-N(H18)) | N18: =IF(D18="","",IF(K18="อนุมัติ","✓ อนุมัติแล้ว พร้อมใช้",IF(K18="ไม่อนุมัติ","⚠ ไม่อนุมัติ – ต้องเสนอใหม่"&IF(ISNUMBER(I18),IF(I18>='ตั้งค่า Setup'!$C$15," (เหลือ "&(I18-'ตั้งค่า Setup'!$C$15)&" วัน)"," (เลยกำหนด "&('ตั้งค่า Setup'!$C$15-I18)&" วัน)"),""),IF(NOT(ISNUMBER(I18)),"ติดตาม",IF(I18<'ตั้งค่า Setup'!$C$15,"⚠ เลยกำหนดอนุมัติ "&('ตั้งค่า Setup'!$C$15-I18)&" วัน – กระทบแผนงาน",IF(I18-'ตั้งค่า Setup'!$C$15<=14,"⚠ ต้องอนุมัติภายใน "&(I18-'ตั้งค่า Setup'!$C$15)&" วัน","ติดตาม (เหลือ "&(I18-'ตั้งค่า Setup'!$C$15)&" วัน)"))))))
A19: =IF(D19="","",COUNTA(D$9:D19)) | G19: =IF(F19="","",IFERROR(INDEX('แผนงาน Schedule'!$Z$7:$Z$66,MATCH(F19&"",'แผนงาน Schedule'!$A$7:$A$66,0)),"ไม่พบ WBS")) | I19: =IF(OR(D19="",NOT(ISNUMBER(G19))),"",G19-N(H19)) | N19: =IF(D19="","",IF(K19="อนุมัติ","✓ อนุมัติแล้ว พร้อมใช้",IF(K19="ไม่อนุมัติ","⚠ ไม่อนุมัติ – ต้องเสนอใหม่"&IF(ISNUMBER(I19),IF(I19>='ตั้งค่า Setup'!$C$15," (เหลือ "&(I19-'ตั้งค่า Setup'!$C$15)&" วัน)"," (เลยกำหนด "&('ตั้งค่า Setup'!$C$15-I19)&" วัน)"),""),IF(NOT(ISNUMBER(I19)),"ติดตาม",IF(I19<'ตั้งค่า Setup'!$C$15,"⚠ เลยกำหนดอนุมัติ "&('ตั้งค่า Setup'!$C$15-I19)&" วัน – กระทบแผนงาน",IF(I19-'ตั้งค่า Setup'!$C$15<=14,"⚠ ต้องอนุมัติภายใน "&(I19-'ตั้งค่า Setup'!$C$15)&" วัน","ติดตาม (เหลือ "&(I19-'ตั้งค่า Setup'!$C$15)&" วัน)"))))))
A20: =IF(D20="","",COUNTA(D$9:D20)) | G20: =IF(F20="","",IFERROR(INDEX('แผนงาน Schedule'!$Z$7:$Z$66,MATCH(F20&"",'แผนงาน Schedule'!$A$7:$A$66,0)),"ไม่พบ WBS")) | I20: =IF(OR(D20="",NOT(ISNUMBER(G20))),"",G20-N(H20)) | N20: =IF(D20="","",IF(K20="อนุมัติ","✓ อนุมัติแล้ว พร้อมใช้",IF(K20="ไม่อนุมัติ","⚠ ไม่อนุมัติ – ต้องเสนอใหม่"&IF(ISNUMBER(I20),IF(I20>='ตั้งค่า Setup'!$C$15," (เหลือ "&(I20-'ตั้งค่า Setup'!$C$15)&" วัน)"," (เลยกำหนด "&('ตั้งค่า Setup'!$C$15-I20)&" วัน)"),""),IF(NOT(ISNUMBER(I20)),"ติดตาม",IF(I20<'ตั้งค่า Setup'!$C$15,"⚠ เลยกำหนดอนุมัติ "&('ตั้งค่า Setup'!$C$15-I20)&" วัน – กระทบแผนงาน",IF(I20-'ตั้งค่า Setup'!$C$15<=14,"⚠ ต้องอนุมัติภายใน "&(I20-'ตั้งค่า Setup'!$C$15)&" วัน","ติดตาม (เหลือ "&(I20-'ตั้งค่า Setup'!$C$15)&" วัน)"))))))
... A108: =IF(D108="","",COUNTA(D$9:D108)) | G108: =IF(F108="","",IFERROR(INDEX('แผนงาน Schedule'!$Z$7:$Z$66,MATCH(F108&"",'แผนงาน Schedule'!$A$7:$A$66,0)),"ไม่พบ WBS")) | I108: =IF(OR(D108="",NOT(ISNUMBER(G108))),"",G108-N(H108)) | N108: =IF(D108="","",IF(K108="อนุมัติ","✓ อนุมัติแล้ว พร้อมใช้",IF(K108="ไม่อนุมัติ","⚠ ไม่อนุมัติ – ต้องเสนอใหม่"&IF(ISNUMBER(I108),IF(I108>='ตั้งค่า Setup'!$C$15," (เหลือ "&(I108-'ตั้งค่า Setup'!$C$15)&" วัน)"," (เลยกำหนด "&('ตั้งค่า Setup'!$C$15-I108)&" วัน)"),""),IF(NOT(ISNUMBER(I108)),"ติดตาม",IF(I108<'ตั้งค่า Setup'!$C$15,"⚠ เลยกำหนดอนุมัติ "&('ตั้งค่า Setup'!$C$15-I108)&" วัน – กระทบแผนงาน",IF(I108-'ตั้งค่า Setup'!$C$15<=14,"⚠ ต้องอนุมัติภายใน "&(I108-'ตั้งค่า Setup'!$C$15)&" วัน","ติดตาม (เหลือ "&(I108-'ตั้งค่า Setup'!$C$15)&" วัน)"))))))

Sheet แผนงาน Schedule
A1: แผนงานและผลการดำเนินงาน / Schedule & Progress (WBS)
A2: Baseline = แผนตามสัญญา (ห้ามแก้หลังอนุมัติ) • Revised = แผนเร่งรัด (ไม่บังคับ) • Actual = ผลงานจริง • Gantt: ฟ้า=Baseline ส้ม=Actual เขียว=Actual ตรงช่วง Baseline
A3: Status Date: | C3: ='ตั้งค่า Setup'!$C$15 -> 46293
A5: รายการงาน / WORK ITEMS | E5: น้ำหนัก / WEIGHT | H5: BASELINE แผนเดิม | K5: REVISED แผนเร่งรัด | M5: ACTUAL ผลงานจริง | P5: ANALYSIS การวิเคราะห์ | AF5: =INDEX('S-Curve'!$B$7:$B$86,1) -> 46072 | AG5: =INDEX('S-Curve'!$B$7:$B$86,2) -> 46074 | AH5: =INDEX('S-Curve'!$B$7:$B$86,3) -> 46082 | AI5: =INDEX('S-Curve'!$B$7:$B$86,4) -> 46092 | AJ5: =INDEX('S-Curve'!$B$7:$B$86,5) -> 46102 | AK5: =INDEX('S-Curve'!$B$7:$B$86,6) -> 46113 | AL5: =INDEX('S-Curve'!$B$7:$B$86,7) -> 46123 | AM5: =INDEX('S-Curve'!$B$7:$B$86,8) -> 46133 | AN5: =INDEX('S-Curve'!$B$7:$B$86,9) -> 46143 | AO5: =INDEX('S-Curve'!$B$7:$B$86,10) -> 46153 | AP5: =INDEX('S-Curve'!$B$7:$B$86,11) -> 46163 | AQ5: =INDEX('S-Curve'!$B$7:$B$86,12) -> 46174 | AR5: =INDEX('S-Curve'!$B$7:$B$86,13) -> 46184 | AS5: =INDEX('S-Curve'!$B$7:$B$86,14) -> 46194 | AT5: =INDEX('S-Curve'!$B$7:$B$86,15) -> 46204 | AU5: =INDEX('S-Curve'!$B$7:$B$86,16) -> 46214 | AV5: =INDEX('S-Curve'!$B$7:$B$86,17) -> 46224 | AW5: =INDEX('S-Curve'!$B$7:$B$86,18) -> 46235 | AX5: =INDEX('S-Curve'!$B$7:$B$86,19) -> 46245 | AY5: =INDEX('S-Curve'!$B$7:$B$86,20) -> 46255 | AZ5: =INDEX('S-Curve'!$B$7:$B$86,21) -> 46266 | BA5: =INDEX('S-Curve'!$B$7:$B$86,22) -> 46276 | BB5: =INDEX('S-Curve'!$B$7:$B$86,23) -> 46286 | BC5: =INDEX('S-Curve'!$B$7:$B$86,24) -> 46296 | BD5: =INDEX('S-Curve'!$B$7:$B$86,25) -> 46306 | BE5: =INDEX('S-Curve'!$B$7:$B$86,26) -> 46316 | BF5: =INDEX('S-Curve'!$B$7:$B$86,27) -> 46327 | BG5: =INDEX('S-Curve'!$B$7:$B$86,28) -> 46337 | BH5: =INDEX('S-Curve'!$B$7:$B$86,29) | BI5: =INDEX('S-Curve'!$B$7:$B$86,30) | BJ5: =INDEX('S-Curve'!$B$7:$B$86,31) | BK5: =INDEX('S-Curve'!$B$7:$B$86,32) | BL5: =INDEX('S-Curve'!$B$7:$B$86,33) | BM5: =INDEX('S-Curve'!$B$7:$B$86,34) | BN5: =INDEX('S-Curve'!$B$7:$B$86,35) | BO5: =INDEX('S-Curve'!$B$7:$B$86,36) | BP5: =INDEX('S-Curve'!$B$7:$B$86,37) | BQ5: =INDEX('S-Curve'!$B$7:$B$86,38) | BR5: =INDEX('S-Curve'!$B$7:$B$86,39) | BS5: =INDEX('S-Curve'!$B$7:$B$86,40) | BT5: =INDEX('S-Curve'!$B$7:$B$86,41) | BU5: =INDEX('S-Curve'!$B$7:$B$86,42) | BV5: =INDEX('S-Curve'!$B$7:$B$86,43) | BW5: =INDEX('S-Curve'!$B$7:$B$86,44) | BX5: =INDEX('S-Curve'!$B$7:$B$86,45) | BY5: =INDEX('S-Curve'!$B$7:$B$86,46) | BZ5: =INDEX('S-Curve'!$B$7:$B$86,47) | CA5: =INDEX('S-Curve'!$B$7:$B$86,48) | CB5: =INDEX('S-Curve'!$B$7:$B$86,49) | CC5: =INDEX('S-Curve'!$B$7:$B$86,50) | CD5: =INDEX('S-Curve'!$B$7:$B$86,51) | CE5: =INDEX('S-Curve'!$B$7:$B$86,52) | CF5: =INDEX('S-Curve'!$B$7:$B$86,53) | CG5: =INDEX('S-Curve'!$B$7:$B$86,54) | CH5: =INDEX('S-Curve'!$B$7:$B$86,55) | CI5: =INDEX('S-Curve'!$B$7:$B$86,56) | CJ5: =INDEX('S-Curve'!$B$7:$B$86,57) | CK5: =INDEX('S-Curve'!$B$7:$B$86,58) | CL5: =INDEX('S-Curve'!$B$7:$B$86,59) | CM5: =INDEX('S-Curve'!$B$7:$B$86,60) | CN5: =INDEX('S-Curve'!$B$7:$B$86,61) | CO5: =INDEX('S-Curve'!$B$7:$B$86,62) | CP5: =INDEX('S-Curve'!$B$7:$B$86,63) | CQ5: =INDEX('S-Curve'!$B$7:$B$86,64) | CR5: =INDEX('S-Curve'!$B$7:$B$86,65) | CS5: =INDEX('S-Curve'!$B$7:$B$86,66) | CT5: =INDEX('S-Curve'!$B$7:$B$86,67) | CU5: =INDEX('S-Curve'!$B$7:$B$86,68) | CV5: =INDEX('S-Curve'!$B$7:$B$86,69) | CW5: =INDEX('S-Curve'!$B$7:$B$86,70) | CX5: =INDEX('S-Curve'!$B$7:$B$86,71) | CY5: =INDEX('S-Curve'!$B$7:$B$86,72) | CZ5: =INDEX('S-Curve'!$B$7:$B$86,73) | DA5: =INDEX('S-Curve'!$B$7:$B$86,74) | DB5: =INDEX('S-Curve'!$B$7:$B$86,75) | DC5: =INDEX('S-Curve'!$B$7:$B$86,76) | DD5: =INDEX('S-Curve'!$B$7:$B$86,77) | DE5: =INDEX('S-Curve'!$B$7:$B$86,78) | DF5: =INDEX('S-Curve'!$B$7:$B$86,79) | DG5: =INDEX('S-Curve'!$B$7:$B$86,80)
A6: WBS | B6: หมวดงาน Category | C6: รายการงาน Description | D6: มูลค่า BOQ BOQ Value (฿) | E6: น้ำหนักกำหนดเอง Manual Weight | F6: น้ำหนักที่ใช้ Weight Used | G6: งบประมาณ Budget (฿) | H6: เริ่ม Start | I6: เสร็จ Finish | J6: วัน Days | K6: เริ่ม Start | L6: เสร็จ Finish | M6: เริ่ม Start | N6: เสร็จ Finish | O6: % งานนี้ % Complete | P6: % แผน ณ Status (BL) | Q6: % แผนเร่งรัด ณ Status | R6: PV (฿) | S6: EV (฿) | T6: SV (฿) | U6: SPI | V6: คาดว่าเสร็จ Forecast Finish | W6: ล่าช้า (วัน) Delay vs BL | X6: สถานะ Status | Y6: หมายเหตุ / ปัญหา Remarks / Issues | Z6: RS | AA6: RF | AB6: key | AC6: LA | AD6: LAi | AF6: =INDEX('S-Curve'!$C$7:$C$86,1) -> 46073 | AG6: =INDEX('S-Curve'!$C$7:$C$86,2) -> 46081 | AH6: =INDEX('S-Curve'!$C$7:$C$86,3) -> 46091 | AI6: =INDEX('S-Curve'!$C$7:$C$86,4) -> 46101 | AJ6: =INDEX('S-Curve'!$C$7:$C$86,5) -> 46112 | AK6: =INDEX('S-Curve'!$C$7:$C$86,6) -> 46122 | AL6: =INDEX('S-Curve'!$C$7:$C$86,7) -> 46132 | AM6: =INDEX('S-Curve'!$C$7:$C$86,8) -> 46142 | AN6: =INDEX('S-Curve'!$C$7:$C$86,9) -> 46152 | AO6: =INDEX('S-Curve'!$C$7:$C$86,10) -> 46162 | AP6: =INDEX('S-Curve'!$C$7:$C$86,11) -> 46173 | AQ6: =INDEX('S-Curve'!$C$7:$C$86,12) -> 46183 | AR6: =INDEX('S-Curve'!$C$7:$C$86,13) -> 46193 | AS6: =INDEX('S-Curve'!$C$7:$C$86,14) -> 46203 | AT6: =INDEX('S-Curve'!$C$7:$C$86,15) -> 46213 | AU6: =INDEX('S-Curve'!$C$7:$C$86,16) -> 46223 | AV6: =INDEX('S-Curve'!$C$7:$C$86,17) -> 46234 | AW6: =INDEX('S-Curve'!$C$7:$C$86,18) -> 46244 | AX6: =INDEX('S-Curve'!$C$7:$C$86,19) -> 46254 | AY6: =INDEX('S-Curve'!$C$7:$C$86,20) -> 46265 | AZ6: =INDEX('S-Curve'!$C$7:$C$86,21) -> 46275 | BA6: =INDEX('S-Curve'!$C$7:$C$86,22) -> 46285 | BB6: =INDEX('S-Curve'!$C$7:$C$86,23) -> 46295 | BC6: =INDEX('S-Curve'!$C$7:$C$86,24) -> 46305 | BD6: =INDEX('S-Curve'!$C$7:$C$86,25) -> 46315 | BE6: =INDEX('S-Curve'!$C$7:$C$86,26) -> 46326 | BF6: =INDEX('S-Curve'!$C$7:$C$86,27) -> 46336 | BG6: =INDEX('S-Curve'!$C$7:$C$86,28) -> 46346 | BH6: =INDEX('S-Curve'!$C$7:$C$86,29) | BI6: =INDEX('S-Curve'!$C$7:$C$86,30) | BJ6: =INDEX('S-Curve'!$C$7:$C$86,31) | BK6: =INDEX('S-Curve'!$C$7:$C$86,32) | BL6: =INDEX('S-Curve'!$C$7:$C$86,33) | BM6: =INDEX('S-Curve'!$C$7:$C$86,34) | BN6: =INDEX('S-Curve'!$C$7:$C$86,35) | BO6: =INDEX('S-Curve'!$C$7:$C$86,36) | BP6: =INDEX('S-Curve'!$C$7:$C$86,37) | BQ6: =INDEX('S-Curve'!$C$7:$C$86,38) | BR6: =INDEX('S-Curve'!$C$7:$C$86,39) | BS6: =INDEX('S-Curve'!$C$7:$C$86,40) | BT6: =INDEX('S-Curve'!$C$7:$C$86,41) | BU6: =INDEX('S-Curve'!$C$7:$C$86,42) | BV6: =INDEX('S-Curve'!$C$7:$C$86,43) | BW6: =INDEX('S-Curve'!$C$7:$C$86,44) | BX6: =INDEX('S-Curve'!$C$7:$C$86,45) | BY6: =INDEX('S-Curve'!$C$7:$C$86,46) | BZ6: =INDEX('S-Curve'!$C$7:$C$86,47) | CA6: =INDEX('S-Curve'!$C$7:$C$86,48) | CB6: =INDEX('S-Curve'!$C$7:$C$86,49) | CC6: =INDEX('S-Curve'!$C$7:$C$86,50) | CD6: =INDEX('S-Curve'!$C$7:$C$86,51) | CE6: =INDEX('S-Curve'!$C$7:$C$86,52) | CF6: =INDEX('S-Curve'!$C$7:$C$86,53) | CG6: =INDEX('S-Curve'!$C$7:$C$86,54) | CH6: =INDEX('S-Curve'!$C$7:$C$86,55) | CI6: =INDEX('S-Curve'!$C$7:$C$86,56) | CJ6: =INDEX('S-Curve'!$C$7:$C$86,57) | CK6: =INDEX('S-Curve'!$C$7:$C$86,58) | CL6: =INDEX('S-Curve'!$C$7:$C$86,59) | CM6: =INDEX('S-Curve'!$C$7:$C$86,60) | CN6: =INDEX('S-Curve'!$C$7:$C$86,61) | CO6: =INDEX('S-Curve'!$C$7:$C$86,62) | CP6: =INDEX('S-Curve'!$C$7:$C$86,63) | CQ6: =INDEX('S-Curve'!$C$7:$C$86,64) | CR6: =INDEX('S-Curve'!$C$7:$C$86,65) | CS6: =INDEX('S-Curve'!$C$7:$C$86,66) | CT6: =INDEX('S-Curve'!$C$7:$C$86,67) | CU6: =INDEX('S-Curve'!$C$7:$C$86,68) | CV6: =INDEX('S-Curve'!$C$7:$C$86,69) | CW6: =INDEX('S-Curve'!$C$7:$C$86,70) | CX6: =INDEX('S-Curve'!$C$7:$C$86,71) | CY6: =INDEX('S-Curve'!$C$7:$C$86,72) | CZ6: =INDEX('S-Curve'!$C$7:$C$86,73) | DA6: =INDEX('S-Curve'!$C$7:$C$86,74) | DB6: =INDEX('S-Curve'!$C$7:$C$86,75) | DC6: =INDEX('S-Curve'!$C$7:$C$86,76) | DD6: =INDEX('S-Curve'!$C$7:$C$86,77) | DE6: =INDEX('S-Curve'!$C$7:$C$86,78) | DF6: =INDEX('S-Curve'!$C$7:$C$86,79) | DG6: =INDEX('S-Curve'!$C$7:$C$86,80)
A7: =IF(OR(B7="",C7=""),"",IFERROR(MATCH(B7,'ตั้งค่า Setup'!$C$26:$C$65,0)&"."&COUNTIF(B$7:B7,B7),"?")) -> 1.1 | B7: งานเตรียมการ / Preliminaries | C7: งานเตรียมการ ติดตั้งป้ายโครงการ และรื้อถอนระบบเดิม | D7: 95160 | E7: 0.0403 | F7: =IF(C7="",0,IF(E7<>"",E7,IF(SUM($D$7:$D$66)>0,N(D7)/SUM($D$7:$D$66),0))) -> 0.0403 | G7: =IF(C7="","",F7*'ตั้งค่า Setup'!$C$9) -> 487952.4 | H7: 46072 | I7: 46087 | J7: =IF(OR(H7="",I7=""),"",I7-H7+1) -> 16 | P7: =IF(OR(C7="",H7="",I7=""),"",MAX(0,MIN(1,('ตั้งค่า Setup'!$C$15-H7+1)/(I7-H7+1)))) -> 1 | Q7: =IF(OR(C7="",Z7=0),"",MAX(0,MIN(1,('ตั้งค่า Setup'!$C$15-Z7+1)/(AA7-Z7+1)))) -> 1 | R7: =IF(P7="","",G7*P7) -> 487952.4 | S7: =IF(C7="","",G7*N(O7)) -> 0 | T7: =IF(OR(R7="",S7=""),"",S7-R7) -> -487952.4 | U7: =IF(OR(R7="",S7=""),"",IF(R7=0,"",S7/R7)) -> 0 | V7: =IF(OR(C7="",Z7=0),"",IF(N7<>"",N7,IF(AND(N(O7)>0,M7<>""),M7+ROUND((MAX('ตั้งค่า Setup'!$C$15,M7)-M7+1)/O7,0)-1,MAX(AA7,'ตั้งค่า Setup'!$C$15+AA7-Z7)))) -> 46308 | W7: =IF(OR(V7="",I7=""),"",V7-I7) -> 221 | X7: =IF(OR(C7="",H7="",I7=""),"",IF(N7<>"",IF(N7<=I7,"เสร็จ / Completed","เสร็จช้า / Completed Late"),IF(AND(M7="",'ตั้งค่า Setup'!$C$15<Z7),"ยังไม่ถึงกำหนด / Not Due",IF(N(O7)>=P7,"ตามแผน / On Track",IF('ตั้งค่า Setup'!$C$15>I7,"เกินกำหนด / Overdue","ล่าช้า / Behind"))))) -> เกินกำหนด / Overdue | Z7: =IF(C7="",0,IF(K7<>"",K7,N(H7))) -> 46072 | AA7: =IF(C7="",0,IF(L7<>"",L7,N(I7))) -> 46087 | AB7: =IF(AND(C7<>"",N7="",ISNUMBER(W7)),W7+(1000-ROW())/1000000,"") -> 221.00099 | AC7: =IF(AND(C7<>"",N7="",Z7>0,Z7<='ตั้งค่า Setup'!$C$15+'ตั้งค่า Setup'!$C$20),1,0) -> 1 | AD7: =IF(AC7=1,SUM(AC$7:AC7),"") -> 1
A8: =IF(OR(B8="",C8=""),"",IFERROR(MATCH(B8,'ตั้งค่า Setup'!$C$26:$C$65,0)&"."&COUNTIF(B$7:B8,B8),"?")) -> 1.2 | B8: งานเตรียมการ / Preliminaries | C8: ก่อสร้างสำนักงานชั่วคราวและจัดเตรียมอุปกรณ์สำนักงาน | D8: 238144 | E8: 0.0195 | F8: =IF(C8="",0,IF(E8<>"",E8,IF(SUM($D$7:$D$66)>0,N(D8)/SUM($D$7:$D$66),0))) -> 0.0195 | G8: =IF(C8="","",F8*'ตั้งค่า Setup'!$C$9) -> 236106 | H8: 46083 | I8: 46127 | J8: =IF(OR(H8="",I8=""),"",I8-H8+1) -> 45 | P8: =IF(OR(C8="",H8="",I8=""),"",MAX(0,MIN(1,('ตั้งค่า Setup'!$C$15-H8+1)/(I8-H8+1)))) -> 1 | Q8: =IF(OR(C8="",Z8=0),"",MAX(0,MIN(1,('ตั้งค่า Setup'!$C$15-Z8+1)/(AA8-Z8+1)))) -> 1 | R8: =IF(P8="","",G8*P8) -> 236106 | S8: =IF(C8="","",G8*N(O8)) -> 0 | T8: =IF(OR(R8="",S8=""),"",S8-R8) -> -236106 | U8: =IF(OR(R8="",S8=""),"",IF(R8=0,"",S8/R8)) -> 0 | V8: =IF(OR(C8="",Z8=0),"",IF(N8<>"",N8,IF(AND(N(O8)>0,M8<>""),M8+ROUND((MAX('ตั้งค่า Setup'!$C$15,M8)-M8+1)/O8,0)-1,MAX(AA8,'ตั้งค่า Setup'!$C$15+AA8-Z8)))) -> 46337 | W8: =IF(OR(V8="",I8=""),"",V8-I8) -> 210 | X8: =IF(OR(C8="",H8="",I8=""),"",IF(N8<>"",IF(N8<=I8,"เสร็จ / Completed","เสร็จช้า / Completed Late"),IF(AND(M8="",'ตั้งค่า Setup'!$C$15<Z8),"ยังไม่ถึงกำหนด / Not Due",IF(N(O8)>=P8,"ตามแผน / On Track",IF('ตั้งค่า Setup'!$C$15>I8,"เกินกำหนด / Overdue","ล่าช้า / Behind"))))) -> เกินกำหนด / Overdue | Z8: =IF(C8="",0,IF(K8<>"",K8,N(H8))) -> 46083 | AA8: =IF(C8="",0,IF(L8<>"",L8,N(I8))) -> 46127 | AB8: =IF(AND(C8<>"",N8="",ISNUMBER(W8)),W8+(1000-ROW())/1000000,"") -> 210.00099 | AC8: =IF(AND(C8<>"",N8="",Z8>0,Z8<='ตั้งค่า Setup'!$C$15+'ตั้งค่า Setup'!$C$20),1,0) -> 1 | AD8: =IF(AC8=1,SUM(AC$7:AC8),"") -> 2
A9: =IF(OR(B9="",C9=""),"",IFERROR(MATCH(B9,'ตั้งค่า Setup'!$C$26:$C$65,0)&"."&COUNTIF(B$7:B9,B9),"?")) -> 1.3 | B9: งานเตรียมการ / Preliminaries | C9: งานรื้อถอนโครงสร้างเดิมและเตรียมพื้นที่ติดตั้งใหม่ | D9: 333792 | E9: 0.0213 | F9: =IF(C9="",0,IF(E9<>"",E9,IF(SUM($D$7:$D$66)>0,N(D9)/SUM($D$7:$D$66),0))) -> 0.0213 | G9: =IF(C9="","",F9*'ตั้งค่า Setup'!$C$9) -> 257900.4 | H9: 46092 | I9: 46132 | J9: =IF(OR(H9="",I9=""),"",I9-H9+1) -> 41 | P9: =IF(OR(C9="",H9="",I9=""),"",MAX(0,MIN(1,('ตั้งค่า Setup'!$C$15-H9+1)/(I9-H9+1)))) -> 1 | Q9: =IF(OR(C9="",Z9=0),"",MAX(0,MIN(1,('ตั้งค่า Setup'!$C$15-Z9+1)/(AA9-Z9+1)))) -> 1 | R9: =IF(P9="","",G9*P9) -> 257900.4 | S9: =IF(C9="","",G9*N(O9)) -> 0 | T9: =IF(OR(R9="",S9=""),"",S9-R9) -> -257900.4 | U9: =IF(OR(R9="",S9=""),"",IF(R9=0,"",S9/R9)) -> 0 | V9: =IF(OR(C9="",Z9=0),"",IF(N9<>"",N9,IF(AND(N(O9)>0,M9<>""),M9+ROUND((MAX('ตั้งค่า Setup'!$C$15,M9)-M9+1)/O9,0)-1,MAX(AA9,'ตั้งค่า Setup'!$C$15+AA9-Z9)))) -> 46333 | W9: =IF(OR(V9="",I9=""),"",V9-I9) -> 201 | X9: =IF(OR(C9="",H9="",I9=""),"",IF(N9<>"",IF(N9<=I9,"เสร็จ / Completed","เสร็จช้า / Completed Late"),IF(AND(M9="",'ตั้งค่า Setup'!$C$15<Z9),"ยังไม่ถึงกำหนด / Not Due",IF(N(O9)>=P9,"ตามแผน / On Track",IF('ตั้งค่า Setup'!$C$15>I9,"เกินกำหนด / Overdue","ล่าช้า / Behind"))))) -> เกินกำหนด / Overdue | Z9: =IF(C9="",0,IF(K9<>"",K9,N(H9))) -> 46092 | AA9: =IF(C9="",0,IF(L9<>"",L9,N(I9))) -> 46132 | AB9: =IF(AND(C9<>"",N9="",ISNUMBER(W9)),W9+(1000-ROW())/1000000,"") -> 201.00099 | AC9: =IF(AND(C9<>"",N9="",Z9>0,Z9<='ตั้งค่า Setup'!$C$15+'ตั้งค่า Setup'!$C$20),1,0) -> 1 | AD9: =IF(AC9=1,SUM(AC$7:AC9),"") -> 3
A10: =IF(OR(B10="",C10=""),"",IFERROR(MATCH(B10,'ตั้งค่า Setup'!$C$26:$C$65,0)&"."&COUNTIF(B$7:B10,B10),"?")) -> 2.1 | B10: งานโครงสร้าง / Structural Works | C10: งานฐานราก คานคอดิน พื้นชั้น 1 และเสาชั้น 1 | D10: 238144 | E10: 0.095 | F10: =IF(C10="",0,IF(E10<>"",E10,IF(SUM($D$7:$D$66)>0,N(D10)/SUM($D$7:$D$66),0))) -> 0.095 | G10: =IF(C10="","",F10*'ตั้งค่า Setup'!$C$9) -> 1150260 | H10: 46096 | I10: 46142 | J10: =IF(OR(H10="",I10=""),"",I10-H10+1) -> 47 | P10: =IF(OR(C10="",H10="",I10=""),"",MAX(0,MIN(1,('ตั้งค่า Setup'!$C$15-H10+1)/(I10-H10+1)))) -> 1 | Q10: =IF(OR(C10="",Z10=0),"",MAX(0,MIN(1,('ตั้งค่า Setup'!$C$15-Z10+1)/(AA10-Z10+1)))) -> 1 | R10: =IF(P10="","",G10*P10) -> 1150260 | S10: =IF(C10="","",G10*N(O10)) -> 0 | T10: =IF(OR(R10="",S10=""),"",S10-R10) -> -1150260 | U10: =IF(OR(R10="",S10=""),"",IF(R10=0,"",S10/R10)) -> 0 | V10: =IF(OR(C10="",Z10=0),"",IF(N10<>"",N10,IF(AND(N(O10)>0,M10<>""),M10+ROUND((MAX('ตั้งค่า Setup'!$C$15,M10)-M10+1)/O10,0)-1,MAX(AA10,'ตั้งค่า Setup'!$C$15+AA10-Z10)))) -> 46339 | W10: =IF(OR(V10="",I10=""),"",V10-I10) -> 197 | X10: =IF(OR(C10="",H10="",I10=""),"",IF(N10<>"",IF(N10<=I10,"เสร็จ / Completed","เสร็จช้า / Completed Late"),IF(AND(M10="",'ตั้งค่า Setup'!$C$15<Z10),"ยังไม่ถึงกำหนด / Not Due",IF(N(O10)>=P10,"ตามแผน / On Track",IF('ตั้งค่า Setup'!$C$15>I10,"เกินกำหนด / Overdue","ล่าช้า / Behind"))))) -> เกินกำหนด / Overdue | Z10: =IF(C10="",0,IF(K10<>"",K10,N(H10))) -> 46096 | AA10: =IF(C10="",0,IF(L10<>"",L10,N(I10))) -> 46142 | AB10: =IF(AND(C10<>"",N10="",ISNUMBER(W10)),W10+(1000-ROW())/1000000,"") -> 197.00099 | AC10: =IF(AND(C10<>"",N10="",Z10>0,Z10<='ตั้งค่า Setup'!$C$15+'ตั้งค่า Setup'!$C$20),1,0) -> 1 | AD10: =IF(AC10=1,SUM(AC$7:AC10),"") -> 4
A11: =IF(OR(B11="",C11=""),"",IFERROR(MATCH(B11,'ตั้งค่า Setup'!$C$26:$C$65,0)&"."&COUNTIF(B$7:B11,B11),"?")) -> 2.2 | B11: งานโครงสร้าง / Structural Works | C11: งานวาง SLEEVE/เดินท่อฝังในโครงสร้าง และโครงสร้างชั้น 1–2 | D11: 238144 | E11: 0.0622 | F11: =IF(C11="",0,IF(E11<>"",E11,IF(SUM($D$7:$D$66)>0,N(D11)/SUM($D$7:$D$66),0))) -> 0.0622 | G11: =IF(C11="","",F11*'ตั้งค่า Setup'!$C$9) -> 753117.6 | H11: 46127 | I11: 46157 | J11: =IF(OR(H11="",I11=""),"",I11-H11+1) -> 31 | P11: =IF(OR(C11="",H11="",I11=""),"",MAX(0,MIN(1,('ตั้งค่า Setup'!$C$15-H11+1)/(I11-H11+1)))) -> 1 | Q11: =IF(OR(C11="",Z11=0),"",MAX(0,MIN(1,('ตั้งค่า Setup'!$C$15-Z11+1)/(AA11-Z11+1)))) -> 1 | R11: =IF(P11="","",G11*P11) -> 753117.6 | S11: =IF(C11="","",G11*N(O11)) -> 0 | T11: =IF(OR(R11="",S11=""),"",S11-R11) -> -753117.6 | U11: =IF(OR(R11="",S11=""),"",IF(R11=0,"",S11/R11)) -> 0 | V11: =IF(OR(C11="",Z11=0),"",IF(N11<>"",N11,IF(AND(N(O11)>0,M11<>""),M11+ROUND((MAX('ตั้งค่า Setup'!$C$15,M11)-M11+1)/O11,0)-1,MAX(AA11,'ตั้งค่า Setup'!$C$15+AA11-Z11)))) -> 46323 | W11: =IF(OR(V11="",I11=""),"",V11-I11) -> 166 | X11: =IF(OR(C11="",H11="",I11=""),"",IF(N11<>"",IF(N11<=I11,"เสร็จ / Completed","เสร็จช้า / Completed Late"),IF(AND(M11="",'ตั้งค่า Setup'!$C$15<Z11),"ยังไม่ถึงกำหนด / Not Due",IF(N(O11)>=P11,"ตามแผน / On Track",IF('ตั้งค่า Setup'!$C$15>I11,"เกินกำหนด / Overdue","ล่าช้า / Behind"))))) -> เกินกำหนด / Overdue | Z11: =IF(C11="",0,IF(K11<>"",K11,N(H11))) -> 46127 | AA11: =IF(C11="",0,IF(L11<>"",L11,N(I11))) -> 46157 | AB11: =IF(AND(C11<>"",N11="",ISNUMBER(W11)),W11+(1000-ROW())/1000000,"") -> 166.00099 | AC11: =IF(AND(C11<>"",N11="",Z11>0,Z11<='ตั้งค่า Setup'!$C$15+'ตั้งค่า Setup'!$C$20),1,0) -> 1 | AD11: =IF(AC11=1,SUM(AC$7:AC11),"") -> 5
A12: =IF(OR(B12="",C12=""),"",IFERROR(MATCH(B12,'ตั้งค่า Setup'!$C$26:$C$65,0)&"."&COUNTIF(B$7:B12,B12),"?")) -> 2.3 | B12: งานโครงสร้าง / Structural Works | C12: งานคานและพื้นชั้น 2 พร้อมวาง SLEEVE ชั้น 2 | D12: 95160 | E12: 0.0639 | F12: =IF(C12="",0,IF(E12<>"",E12,IF(SUM($D$7:$D$66)>0,N(D12)/SUM($D$7:$D$66),0))) -> 0.0639 | G12: =IF(C12="","",F12*'ตั้งค่า Setup'!$C$9) -> 773701.2 | H12: 46153 | I12: 46178 | J12: =IF(OR(H12="",I12=""),"",I12-H12+1) -> 26 | P12: =IF(OR(C12="",H12="",I12=""),"",MAX(0,MIN(1,('ตั้งค่า Setup'!$C$15-H12+1)/(I12-H12+1)))) -> 1 | Q12: =IF(OR(C12="",Z12=0),"",MAX(0,MIN(1,('ตั้งค่า Setup'!$C$15-Z12+1)/(AA12-Z12+1)))) -> 1 | R12: =IF(P12="","",G12*P12) -> 773701.2 | S12: =IF(C12="","",G12*N(O12)) -> 0 | T12: =IF(OR(R12="",S12=""),"",S12-R12) -> -773701.2 | U12: =IF(OR(R12="",S12=""),"",IF(R12=0,"",S12/R12)) -> 0 | V12: =IF(OR(C12="",Z12=0),"",IF(N12<>"",N12,IF(AND(N(O12)>0,M12<>""),M12+ROUND((MAX('ตั้งค่า Setup'!$C$15,M12)-M12+1)/O12,0)-1,MAX(AA12,'ตั้งค่า Setup'!$C$15+AA12-Z12)))) -> 46318 | W12: =IF(OR(V12="",I12=""),"",V12-I12) -> 140 | X12: =IF(OR(C12="",H12="",I12=""),"",IF(N12<>"",IF(N12<=I12,"เสร็จ / Completed","เสร็จช้า / Completed Late"),IF(AND(M12="",'ตั้งค่า Setup'!$C$15<Z12),"ยังไม่ถึงกำหนด / Not Due",IF(N(O12)>=P12,"ตามแผน / On Track",IF('ตั้งค่า Setup'!$C$15>I12,"เกินกำหนด / Overdue","ล่าช้า / Behind"))))) -> เกินกำหนด / Overdue | Z12: =IF(C12="",0,IF(K12<>"",K12,N(H12))) -> 46153 | AA12: =IF(C12="",0,IF(L12<>"",L12,N(I12))) -> 46178 | AB12: =IF(AND(C12<>"",N12="",ISNUMBER(W12)),W12+(1000-ROW())/1000000,"") -> 140.00099 | AC12: =IF(AND(C12<>"",N12="",Z12>0,Z12<='ตั้งค่า Setup'!$C$15+'ตั้งค่า Setup'!$C$20),1,0) -> 1 | AD12: =IF(AC12=1,SUM(AC$7:AC12),"") -> 6
A13: =IF(OR(B13="",C13=""),"",IFERROR(MATCH(B13,'ตั้งค่า Setup'!$C$26:$C$65,0)&"."&COUNTIF(B$7:B13,B13),"?")) -> 2.4 | B13: งานโครงสร้าง / Structural Works | C13: งานโครงสร้างหลังคาและมุงหลังคา | D13: 285968 | E13: 0.0639 | F13: =IF(C13="",0,IF(E13<>"",E13,IF(SUM($D$7:$D$66)>0,N(D13)/SUM($D$7:$D$66),0))) -> 0.0639 | G13: =IF(C13="","",F13*'ตั้งค่า Setup'!$C$9) -> 773701.2 | H13: 46174 | I13: 46198 | J13: =IF(OR(H13="",I13=""),"",I13-H13+1) -> 25 | P13: =IF(OR(C13="",H13="",I13=""),"",MAX(0,MIN(1,('ตั้งค่า Setup'!$C$15-H13+1)/(I13-H13+1)))) -> 1 | Q13: =IF(OR(C13="",Z13=0),"",MAX(0,MIN(1,('ตั้งค่า Setup'!$C$15-Z13+1)/(AA13-Z13+1)))) -> 1 | R13: =IF(P13="","",G13*P13) -> 773701.2 | S13: =IF(C13="","",G13*N(O13)) -> 0 | T13: =IF(OR(R13="",S13=""),"",S13-R13) -> -773701.2 | U13: =IF(OR(R13="",S13=""),"",IF(R13=0,"",S13/R13)) -> 0 | V13: =IF(OR(C13="",Z13=0),"",IF(N13<>"",N13,IF(AND(N(O13)>0,M13<>""),M13+ROUND((MAX('ตั้งค่า Setup'!$C$15,M13)-M13+1)/O13,0)-1,MAX(AA13,'ตั้งค่า Setup'!$C$15+AA13-Z13)))) -> 46317 | W13: =IF(OR(V13="",I13=""),"",V13-I13) -> 119 | X13: =IF(OR(C13="",H13="",I13=""),"",IF(N13<>"",IF(N13<=I13,"เสร็จ / Completed","เสร็จช้า / Completed Late"),IF(AND(M13="",'ตั้งค่า Setup'!$C$15<Z13),"ยังไม่ถึงกำหนด / Not Due",IF(N(O13)>=P13,"ตามแผน / On Track",IF('ตั้งค่า Setup'!$C$15>I13,"เกินกำหนด / Overdue","ล่าช้า / Behind"))))) -> เกินกำหนด / Overdue | Z13: =IF(C13="",0,IF(K13<>"",K13,N(H13))) -> 46174 | AA13: =IF(C13="",0,IF(L13<>"",L13,N(I13))) -> 46198 | AB13: =IF(AND(C13<>"",N13="",ISNUMBER(W13)),W13+(1000-ROW())/1000000,"") -> 119.00099 | AC13: =IF(AND(C13<>"",N13="",Z13>0,Z13<='ตั้งค่า Setup'!$C$15+'ตั้งค่า Setup'!$C$20),1,0) -> 1 | AD13: =IF(AC13=1,SUM(AC$7:AC13),"") -> 7
A14: =IF(OR(B14="",C14=""),"",IFERROR(MATCH(B14,'ตั้งค่า Setup'!$C$26:$C$65,0)&"."&COUNTIF(B$7:B14,B14),"?")) -> 3.1 | B14: งานสถาปัตยกรรม / Architectural Works | C14: งานผนัง/โครงเคร่า ติดตั้งฉนวน PU Foam และรางน้ำ | D14: 238144 | E14: 0.0622 | F14: =IF(C14="",0,IF(E14<>"",E14,IF(SUM($D$7:$D$66)>0,N(D14)/SUM($D$7:$D$66),0))) -> 0.0622 | G14: =IF(C14="","",F14*'ตั้งค่า Setup'!$C$9) -> 753117.6 | H14: 46188 | I14: 46218 | J14: =IF(OR(H14="",I14=""),"",I14-H14+1) -> 31 | P14: =IF(OR(C14="",H14="",I14=""),"",MAX(0,MIN(1,('ตั้งค่า Setup'!$C$15-H14+1)/(I14-H14+1)))) -> 1 | Q14: =IF(OR(C14="",Z14=0),"",MAX(0,MIN(1,('ตั้งค่า Setup'!$C$15-Z14+1)/(AA14-Z14+1)))) -> 1 | R14: =IF(P14="","",G14*P14) -> 753117.6 | S14: =IF(C14="","",G14*N(O14)) -> 0 | T14: =IF(OR(R14="",S14=""),"",S14-R14) -> -753117.6 | U14: =IF(OR(R14="",S14=""),"",IF(R14=0,"",S14/R14)) -> 0 | V14: =IF(OR(C14="",Z14=0),"",IF(N14<>"",N14,IF(AND(N(O14)>0,M14<>""),M14+ROUND((MAX('ตั้งค่า Setup'!$C$15,M14)-M14+1)/O14,0)-1,MAX(AA14,'ตั้งค่า Setup'!$C$15+AA14-Z14)))) -> 46323 | W14: =IF(OR(V14="",I14=""),"",V14-I14) -> 105 | X14: =IF(OR(C14="",H14="",I14=""),"",IF(N14<>"",IF(N14<=I14,"เสร็จ / Completed","เสร็จช้า / Completed Late"),IF(AND(M14="",'ตั้งค่า Setup'!$C$15<Z14),"ยังไม่ถึงกำหนด / Not Due",IF(N(O14)>=P14,"ตามแผน / On Track",IF('ตั้งค่า Setup'!$C$15>I14,"เกินกำหนด / Overdue","ล่าช้า / Behind"))))) -> เกินกำหนด / Overdue | Z14: =IF(C14="",0,IF(K14<>"",K14,N(H14))) -> 46188 | AA14: =IF(C14="",0,IF(L14<>"",L14,N(I14))) -> 46218 | AB14: =IF(AND(C14<>"",N14="",ISNUMBER(W14)),W14+(1000-ROW())/1000000,"") -> 105.00099 | AC14: =IF(AND(C14<>"",N14="",Z14>0,Z14<='ตั้งค่า Setup'!$C$15+'ตั้งค่า Setup'!$C$20),1,0) -> 1 | AD14: =IF(AC14=1,SUM(AC$7:AC14),"") -> 8
A15: =IF(OR(B15="",C15=""),"",IFERROR(MATCH(B15,'ตั้งค่า Setup'!$C$26:$C$65,0)&"."&COUNTIF(B$7:B15,B15),"?")) -> 4.1 | B15: งานระบบ / MEP Works | C15: งานเดินท่อประปา ท่อน้ำทิ้ง และงานระบบในผนัง | D15: 190808 | E15: 0.0426 | F15: =IF(C15="",0,IF(E15<>"",E15,IF(SUM($D$7:$D$66)>0,N(D15)/SUM($D$7:$D$66),0))) -> 0.0426 | G15: =IF(C15="","",F15*'ตั้งค่า Setup'!$C$9) -> 515800.8 | H15: 46214 | I15: 46233 | J15: =IF(OR(H15="",I15=""),"",I15-H15+1) -> 20 | P15: =IF(OR(C15="",H15="",I15=""),"",MAX(0,MIN(1,('ตั้งค่า Setup'!$C$15-H15+1)/(I15-H15+1)))) -> 1 | Q15: =IF(OR(C15="",Z15=0),"",MAX(0,MIN(1,('ตั้งค่า Setup'!$C$15-Z15+1)/(AA15-Z15+1)))) -> 1 | R15: =IF(P15="","",G15*P15) -> 515800.8 | S15: =IF(C15="","",G15*N(O15)) -> 0 | T15: =IF(OR(R15="",S15=""),"",S15-R15) -> -515800.8 | U15: =IF(OR(R15="",S15=""),"",IF(R15=0,"",S15/R15)) -> 0 | V15: =IF(OR(C15="",Z15=0),"",IF(N15<>"",N15,IF(AND(N(O15)>0,M15<>""),M15+ROUND((MAX('ตั้งค่า Setup'!$C$15,M15)-M15+1)/O15,0)-1,MAX(AA15,'ตั้งค่า Setup'!$C$15+AA15-Z15)))) -> 46312 | W15: =IF(OR(V15="",I15=""),"",V15-I15) -> 79 | X15: =IF(OR(C15="",H15="",I15=""),"",IF(N15<>"",IF(N15<=I15,"เสร็จ / Completed","เสร็จช้า / Completed Late"),IF(AND(M15="",'ตั้งค่า Setup'!$C$15<Z15),"ยังไม่ถึงกำหนด / Not Due",IF(N(O15)>=P15,"ตามแผน / On Track",IF('ตั้งค่า Setup'!$C$15>I15,"เกินกำหนด / Overdue","ล่าช้า / Behind"))))) -> เกินกำหนด / Overdue | Z15: =IF(C15="",0,IF(K15<>"",K15,N(H15))) -> 46214 | AA15: =IF(C15="",0,IF(L15<>"",L15,N(I15))) -> 46233 | AB15: =IF(AND(C15<>"",N15="",ISNUMBER(W15)),W15+(1000-ROW())/1000000,"") -> 79.000985 | AC15: =IF(AND(C15<>"",N15="",Z15>0,Z15<='ตั้งค่า Setup'!$C$15+'ตั้งค่า Setup'!$C$20),1,0) -> 1 | AD15: =IF(AC15=1,SUM(AC$7:AC15),"") -> 9
A16: =IF(OR(B16="",C16=""),"",IFERROR(MATCH(B16,'ตั้งค่า Setup'!$C$26:$C$65,0)&"."&COUNTIF(B$7:B16,B16),"?")) -> 3.2 | B16: งานสถาปัตยกรรม / Architectural Works | C16: งานฉาบปูน ฝ้าเพดาน ปูพื้น และทาสีภายใน-ภายนอก | D16: 285968 | E16: 0.095 | F16: =IF(C16="",0,IF(E16<>"",E16,IF(SUM($D$7:$D$66)>0,N(D16)/SUM($D$7:$D$66),0))) -> 0.095 | G16: =IF(C16="","",F16*'ตั้งค่า Setup'!$C$9) -> 1150260 | H16: 46204 | I16: 46249 | J16: =IF(OR(H16="",I16=""),"",I16-H16+1) -> 46 | P16: =IF(OR(C16="",H16="",I16=""),"",MAX(0,MIN(1,('ตั้งค่า Setup'!$C$15-H16+1)/(I16-H16+1)))) -> 1 | Q16: =IF(OR(C16="",Z16=0),"",MAX(0,MIN(1,('ตั้งค่า Setup'!$C$15-Z16+1)/(AA16-Z16+1)))) -> 1 | R16: =IF(P16="","",G16*P16) -> 1150260 | S16: =IF(C16="","",G16*N(O16)) -> 0 | T16: =IF(OR(R16="",S16=""),"",S16-R16) -> -1150260 | U16: =IF(OR(R16="",S16=""),"",IF(R16=0,"",S16/R16)) -> 0 | V16: =IF(OR(C16="",Z16=0),"",IF(N16<>"",N16,IF(AND(N(O16)>0,M16<>""),M16+ROUND((MAX('ตั้งค่า Setup'!$C$15,M16)-M16+1)/O16,0)-1,MAX(AA16,'ตั้งค่า Setup'!$C$15+AA16-Z16)))) -> 46338 | W16: =IF(OR(V16="",I16=""),"",V16-I16) -> 89 | X16: =IF(OR(C16="",H16="",I16=""),"",IF(N16<>"",IF(N16<=I16,"เสร็จ / Completed","เสร็จช้า / Completed Late"),IF(AND(M16="",'ตั้งค่า Setup'!$C$15<Z16),"ยังไม่ถึงกำหนด / Not Due",IF(N(O16)>=P16,"ตามแผน / On Track",IF('ตั้งค่า Setup'!$C$15>I16,"เกินกำหนด / Overdue","ล่าช้า / Behind"))))) -> เกินกำหนด / Overdue | Z16: =IF(C16="",0,IF(K16<>"",K16,N(H16))) -> 46204 | AA16: =IF(C16="",0,IF(L16<>"",L16,N(I16))) -> 46249 | AB16: =IF(AND(C16<>"",N16="",ISNUMBER(W16)),W16+(1000-ROW())/1000000,"") -> 89.000984 | AC16: =IF(AND(C16<>"",N16="",Z16>0,Z16<='ตั้งค่า Setup'!$C$15+'ตั้งค่า Setup'!$C$20),1,0) -> 1 | AD16: =IF(AC16=1,SUM(AC$7:AC16),"") -> 10
