Workbook

Sheet คู่มือ Guide
B1: คู่มือการใช้งาน / User Guide — Project Control v3 (Multi Work-Package)
B3: 1. ภาพรวมไฟล์ / Workbook Overview
B4: ไฟล์นี้ออกแบบสำหรับโครงการที่มีงานหลายส่วน (เช่น อาคาร รั้ว รางระบายน้ำ ถนน-ลาน ถมดิน โรงจอดรถ) ซึ่งหลายส่วนก่อสร้างพร้อมกันได้ ใช้ WBS 3 ระดับในแผนงานชีตเดียว ทำให้ S-Curve, EVM, ค่าปรับ และรายงานคำนวณจากฐานเดียวกันทั้งสัญญา และยังดูผลแยกรายงานส่วนได้
B5: ⚠ ข้อมูลทั้งหมดในไฟล์นี้เป็นข้อมูลตัวอย่าง (EXAMPLE) เพื่อสาธิตการทำงาน – ดูวิธีล้างข้อมูลในหัวข้อ 4
B6: ชีต / Sheet | C6: ใช้ทำอะไร / Purpose | D6: ต้องกรอกอะไร / What to fill
B7: ตั้งค่า Setup | C7: ข้อมูลสัญญา วันที่ตรวจวัด อัตราค่าปรับ รายชื่องานส่วน (ระดับ 1) และหมวดงาน (ระดับ 2) | D7: ช่องสีเหลืองทั้งหมด (ครั้งแรก) + Status Date ทุกงวด
B8: Dashboard | C8: ตัวชี้วัดรวมทั้งโครงการ: เวลา ต้นทุน ขยายเวลา-ค่าปรับ พร้อมกราฟ S-Curve, EVM และกราฟแท่งรายงานส่วน | D8: ไม่ต้องกรอก
B9: สรุปงานส่วน Summary | C9: สรุปผลแยกรายงานส่วนและรายหมวดงาน พร้อม Gantt ระดับงานส่วน แสดงงานที่ทำขนานกัน | D9: ไม่ต้องกรอก
B10: รายงาน Report | C10: รายงานประจำงวด A4 พร้อมพิมพ์ มีหัวข้อความก้าวหน้ารายงานส่วน | D10: หัวข้อ 6 ปัญหาและแนวทางแก้ไข
B11: แผนงาน Schedule | C11: รายการงานทั้งหมด (สูงสุด 150 รายการ) แบบ WBS 3 ระดับ พร้อม Baseline / Revised / Actual และ Gantt | D11: ครั้งแรก: งานส่วน หมวด รายการ BOQ/น้ำหนัก วันแผน • ทุกงวด: วันจริง % จริง
B12: S-Curve | C12: ตารางรายงวดสำหรับ S-Curve และ EVM รวมทั้งโครงการ | D12: ทุกงวด: Actual % สะสม, AC ในงวด, เบิกจ่ายในงวด
B13: ขยายเวลา EOT | C13: ทะเบียนเหตุการณ์ล่าช้าและการขอขยายเวลา | D13: เมื่อมีเหตุการณ์ / ยื่นหนังสือ / ได้ผลพิจารณา
B15: 2. โครงสร้างงาน 3 ระดับ / 3-Level WBS
B16: ระดับ / Level | C16: ความหมาย / Meaning | D16: ตัวอย่าง / Example
B17: ระดับ 1 งานส่วน / Work Package | C17: แบ่งตามสิ่งก่อสร้างหรือพื้นที่ – ใช้ดูว่าแต่ละส่วนคืบหน้าเท่าไร | D17: อาคาร / รั้ว / รางระบายน้ำ / ถนน-ลาน / ถมดิน / โรงจอดรถ
B18: ระดับ 2 หมวดงาน / Discipline | C18: แบ่งตามประเภทงานหรือทีมช่าง – ใช้ดูภาระงานของแต่ละทีม | D18: งานดิน / โครงสร้าง / สถาปัตย์ / ระบบ
B19: ระดับ 3 รายการงาน / Work Item | C19: งานย่อยที่วัดผลได้จริงหน้างาน | D19: งานเสาเข็มอาคาร / งานฐานรากรั้ว
B20: รหัส WBS | C20: สร้างอัตโนมัติ: งานส่วน.หมวดงาน.ลำดับ | D20: 2.3.01 = อาคาร • งานโครงสร้าง • รายการที่ 1
B22: 3. งานที่ก่อสร้างพร้อมกัน / Parallel Work
B23: • แต่ละรายการงานมีวันเริ่ม-เสร็จของตัวเอง ใส่วันที่ซ้อนทับกันได้ตามจริง เช่น งานรางระบายน้ำ (ส.ค.–ต.ค.) ทำพร้อมงานเสาเข็มอาคาร (ก.ย.–ต.ค.) และงานฐานรากรั้ว (ก.ย.–ต.ค.)
B24: • ระบบรวมผลตามน้ำหนักงาน (มูลค่า) โดยอัตโนมัติ – งานส่วนที่มีมูลค่ามากมีผลต่อ % รวมมากกว่า
B25: • Gantt ในชีต สรุปงานส่วน แสดงช่วงเวลาของทุกงานส่วนในหน้าเดียว เห็นทันทีว่าช่วงไหนมีกี่ส่วนทำขนานกัน (ใช้วางแผนกำลังคน/เครื่องจักร)
B26: • ถ้างานหนึ่งต้องรออีกงานหนึ่งเสร็จ (เช่น ถนนต้องรอรางระบายน้ำ) ให้ตั้งวันเริ่มของงานถัดไปหลังวันเสร็จของงานก่อนหน้าเอง – ไฟล์นี้ไม่ผูกความสัมพันธ์อัตโนมัติ
B27: • ในชีตแผนงาน ใช้ปุ่มกรอง (▼) ที่หัวคอลัมน์ งานส่วน เพื่อดูหรือกรอกข้อมูลทีละงานส่วนได้
B29: 4. ตั้งค่าโครงการใหม่ / New Project Setup
B30: 1) ชีต ตั้งค่า Setup: กรอกข้อมูลสัญญา • แก้รายชื่องานส่วน (สูงสุด 10) และหมวดงาน (สูงสุด 10)
B31: 2) ชีต แผนงาน Schedule: ลบข้อมูลตัวอย่างในช่องสีเหลืองทั้งหมด แล้วกรอกรายการงาน เลือกงานส่วนและหมวดจาก Drop-down
B32: 3) น้ำหนักงาน: แนะนำให้กรอก 'มูลค่า BOQ' ทุกรายการ ระบบคำนวณน้ำหนักจากสัดส่วนมูลค่าให้ (หรือกรอก 'น้ำหนักกำหนดเอง' แทน) • รวมต้องได้ 100%
B33: 4) ชีต S-Curve: ลบค่าตัวอย่างในคอลัมน์ Actual, AC และเบิกจ่าย • ชีต ขยายเวลา EOT: ลบรายการตัวอย่าง
B35: 5. อัปเดตทุกงวด / Periodic Update
... B42: 6. วิธีวัด % ความคืบหน้าของรายการงาน / Measuring % Complete
B43: ตามปริมาณงาน | C43: งานที่นับ/วัดได้: ปริมาณที่ทำแล้ว ÷ ปริมาณทั้งหมด | D43: ตอกเสาเข็ม 45 จาก 60 ต้น = 75%
B44: แบ่งขั้นตอน | C44: งานหลายขั้นตอน: กำหนดน้ำหนักแต่ละขั้น | D44: ตั้งแบบ 20% ผูกเหล็ก 30% เทคอนกรีต 40% บ่ม 10%
B45: 0 / 50 / 100 | C45: งานสั้นหรือวัดยาก | D45: ยังไม่เริ่ม 0% • กำลังทำ 50% • เสร็จ 100%
B46: ห้ามใช้ | C46: เวลาที่ผ่านไป หรือเงินที่จ่ายไป เป็นเกณฑ์วัด % | D46: จะซ่อนความล่าช้าที่แท้จริง
B48: 7. สัญลักษณ์สี / Color Legend
B49: ช่องพื้นเหลือง ตัวน้ำเงิน | C49: ช่องให้กรอก
B50: ช่องพื้นขาว | C50: สูตร – ล็อกไว้ (ปลดล็อก: Review → Unprotect Sheet ไม่มีรหัสผ่าน)
B51: Gantt ฟ้า / ส้ม / เขียว | C51: ช่วงแผนเดิม / ช่วงทำงานจริงนอกแผน / จริงตรงกับแผน
B52: หัว Gantt สีแดง | C52: งวดที่มีวันตรวจวัด
B53: สถานะ แดง / เหลือง / เขียว | C53: ล่าช้า / เฝ้าระวัง / ตามแผนหรือเสร็จ
B55: 8. อภิธานศัพท์ตัวชี้วัด / KPI Glossary
B56: ตัวชี้วัด / KPI | C56: ความหมาย / Meaning | D56: สูตรและการแปลผล / Formula & Interpretation
B57: S-Curve | C57: กราฟความก้าวหน้าสะสมตามเวลา | D57: เส้นจริงต่ำกว่าแผน = ล่าช้า • ระยะห่างแนวนอน = ช้ากี่วัน
B58: Baseline / Revised / Forecast | C58: แผนตามสัญญา / แผนเร่งรัด / เส้นคาดการณ์ | D58: Forecast ลากจากจุดจริงล่าสุดไป 100% ณ วันคาดว่าเสร็จ (แสดงถึงสุดแกนเวลา)
B59: Data Date | C59: วันที่ของข้อมูลผลงานจริงที่ใช้คำนวณ | D59: ไม่ตรงกับ Status Date (สีแดง) = ยังไม่อัปเดต
B60: PV / EV / AC | C60: มูลค่างานตามแผน / มูลค่างานที่ทำได้ / ต้นทุนจริง | D60: PV = %แผน × BAC • EV = %จริง × BAC • AC กรอกเอง
B61: SV / CV | C61: ผลต่างด้านเวลา / ด้านต้นทุน (บาท) | D61: SV = EV − PV • CV = EV − AC • ติดลบ = ไม่ดี
B62: SPI | C62: ประสิทธิภาพด้านเวลา | D62: EV ÷ PV • ≥1.00 ตามแผน • 0.90–0.99 เฝ้าระวัง • <0.90 ล่าช้ามาก
B63: CPI | C63: ประสิทธิภาพด้านต้นทุน | D63: EV ÷ AC • <1.00 ใช้เงินเกินมูลค่างาน
B64: EAC / ETC / VAC | C64: ต้นทุนรวมคาดการณ์ / ต้นทุนที่ต้องใช้อีก / คาดว่าเกินหรือต่ำกว่างบ | D64: BAC ÷ CPI • EAC − AC • BAC − EAC
B65: TCPI | C65: ประสิทธิภาพต้นทุนที่ต้องทำให้ได้กับงานที่เหลือ | D65: (BAC − EV) ÷ (BAC − AC) • >1.10 เป็นไปได้ยาก
B66: ES / AT / SV(t) / SPI(t) | C66: Earned Schedule: วัดความล่าช้าเป็นวัน (มาตรฐานสากล แม่นกว่า SPI ช่วงท้ายโครงการ) | D66: ES = วันที่แผนเท่ากับผลงานจริง • SV(t) = ES − AT • SPI(t) = ES ÷ AT
B67: Forecast Completion | C67: คาดการณ์วันแล้วเสร็จ | D67: มี % รายรายการ = วันเสร็จคาดการณ์ช้าสุด • ไม่มี = ระยะเวลา ÷ SPI(t)
... B71: SPI รายงานส่วน | C71: ประสิทธิภาพเวลาของแต่ละงานส่วน | D71: %จริงของงานส่วน ÷ %แผนของงานส่วน – ใช้หาว่าส่วนไหนเป็นตัวถ่วง
B73: 9. ข้อจำกัด / Limitations
B74: • ความจุ: 150 รายการงาน • 10 งานส่วน • 10 หมวด • 80 งวด • 50 เหตุการณ์ขยายเวลา
B75: • ไม่วิเคราะห์ความสัมพันธ์ระหว่างงาน (Critical Path) – ถ้าต้องการ ใช้ร่วมกับ MS Project หรือ Primavera P6
B76: • S-Curve รายงานส่วนแสดงเป็นตาราง % และ Gantt (ไม่มีกราฟ S-Curve แยกรายงานส่วน เพราะต้องเก็บประวัติ % จริงแยกทุกส่วนทุกงวด)
B77: • อัตราค่าปรับในตัวอย่างเป็นค่าสมมติ ต้องแก้ให้ตรงตามสัญญา
B79: รายงานต่อคณะกรรมการตรวจรับพัสดุ (รายสัปดาห์) / Weekly Committee Report
B80: ชุดรายงานนี้มี 3 ชีต (แท็บสีม่วง): งวดงาน Installments • บันทึกสัปดาห์ Weekly Log • รายงานกรรมการ Weekly (พิมพ์ได้ในรูปแบบบันทึกข้อความ)
B81: ครั้งแรก: (1) ชีตงวดงาน – กรอกงวดงานตามสัญญา: เนื้องาน, ผลงานสะสมที่กำหนด (ถ้ามี), กำหนดเสร็จ, จำนวนเงิน • ยอดรวมต้องเท่ามูลค่าสัญญา
B82: (2) ชีตบันทึกสัปดาห์ – กรอกส่วนราชการ เลขที่หนังสือ วันลงนามสัญญา ชื่อผู้ควบคุมงาน และคณะกรรมการ
B83: ทุกสัปดาห์: (1) ชีตบันทึกสัปดาห์ – กรอกแถวของสัปดาห์นั้น: % จริงสะสม, คนงาน, เครื่องจักร, วันทำงาน, งานที่ทำ, แผนสัปดาห์หน้า, วัสดุ/การทดสอบ, ปัญหา, ความเห็น
B84: (2) ช่อง 'รายงานสัปดาห์ที่' เลือกสัปดาห์ล่าสุดที่ครบ 7 วันให้อัตโนมัติ (พิมพ์ทับได้ถ้าต้องการพิมพ์สัปดาห์ย้อนหลัง)
B85: (3) ชีตงวดงาน – อัปเดตวันที่ส่งมอบ/ตรวจรับ เมื่อมี • (4) ชีตรายงานกรรมการ – แทรกรูปถ่าย แล้วสั่งพิมพ์ (A4 แนวตั้ง 3–4 หน้า)
... B97: – สถานะแดง = เลยกำหนดหรือเหลือไม่เกิน 14 วัน • ใช้ร่วมกับแอปเช็คลิสต์วัสดุ กฟภ.: ตรวจด้วยแอป → บันทึกเลขที่เอกสารและผลตรวจ AI ลงทะเบียนนี้

Sheet ตั้งค่า Setup
B1: ตั้งค่าโครงการ / Project Setup
B2: กรอกเฉพาะช่องสีเหลือง • ข้อมูลในไฟล์นี้เป็นข้อมูลตัวอย่าง (EXAMPLE) – แทนที่ด้วยข้อมูลโครงการจริง
B3: รายการ / Item | C3: ค่า / Value | D3: หมายเหตุ / Note
B4: ชื่อโครงการ (ไทย) / Project name (TH) | C4: โครงการตัวอย่าง: ก่อสร้างอาคารพร้อมงานภายนอก | D4: ข้อมูลตัวอย่าง
B5: ชื่อโครงการ (อังกฤษ) / Project name (EN) | C5: Example: Building & External Works
B6: ผู้ว่าจ้าง / Employer
B7: ผู้รับจ้าง / Contractor
B8: เลขที่สัญญา / Contract No.
B9: มูลค่าสัญญา / Contract Value = BAC (บาท) | C9: 24200000 | D9: ตัวอย่าง = ผลรวม BOQ ในชีตแผนงาน
B10: วันเริ่มสัญญา / Commencement Date | C10: 46174
B11: ระยะเวลาสัญญา / Contract Duration (วัน/days) | C11: 300
B12: วันสิ้นสุดตามสัญญาเดิม / Original Completion | C12: =C10+C11-1 -> 46473 | D12: นับวันเริ่มเป็นวันที่ 1 (พิมพ์ทับได้ถ้าสัญญาระบุต่างไป)
B13: ขยายเวลาที่อนุมัติแล้ว / Approved EOT (วัน) | C13: =SUM('ขยายเวลา EOT'!$J$8:$J$57) -> 8 | D13: ดึงจากชีต ขยายเวลา EOT อัตโนมัติ
B14: วันสิ้นสุดหลังขยายเวลา / Revised Completion | C14: =C12+C13 -> 46481
B15: วันที่ตรวจวัดผลงาน / Status Date | C15: 46293 | D15: เปลี่ยนทุกครั้งที่อัปเดตรายงาน
B16: รอบตัดงวด S-Curve / Reporting Period | C16: ทุก 10 วัน / 10-day | D16: ทุก 10 วัน / รายสัปดาห์ / รายเดือน
B17: อัตราค่าปรับต่อวัน / LD Rate (% of contract per day) | C17: 0.001 | D17: ค่าตัวอย่าง – ใส่ตามสัญญาจริง
B18: ค่าปรับขั้นต่ำต่อวัน / Minimum LD per day (บาท) | C18: 100 | D18: ตามสัญญา (ถ้าไม่มีใส่ 0)
B19: เกณฑ์เตือนค่าปรับสะสม / LD Warning Threshold | C19: 0.1 | D19: หลายสัญญาให้สิทธิ์บอกเลิกเมื่อค่าปรับเกิน 10%
B20: ช่วงแผนงานล่วงหน้า / Look-ahead (วัน/days) | C20: 30 | D20: ใช้ในรายงานประจำงวด
B21: รายงานงวดที่ / Report No. | C21: 1
B22: ผู้จัดทำรายงาน / Prepared by
B24: งานส่วน (WBS ระดับ 1) / Work Packages | C24: ชื่อ / Name | D24: หมายเหตุ
B25: เลขลำดับ = หลักแรกของรหัส WBS • ใช้แบ่งตามสิ่งก่อสร้าง เช่น อาคาร รั้ว ถนน
B26: งานส่วนที่ 1 | C26: งานถมดินและปรับพื้นที่ / Earth Filling & Site Prep
B27: งานส่วนที่ 2 | C27: งานก่อสร้างอาคาร / Building
B28: งานส่วนที่ 3 | C28: งานรางระบายน้ำ / Drainage
B29: งานส่วนที่ 4 | C29: งานถนนและลาน / Roads & Hardscape
B30: งานส่วนที่ 5 | C30: งานรั้ว / Fence
B31: งานส่วนที่ 6 | C31: งานโรงจอดรถ / Carport
B32: งานส่วนที่ 7
B33: งานส่วนที่ 8
B34: งานส่วนที่ 9
B35: งานส่วนที่ 10
B36: งานส่วนที่ 11
B37: งานส่วนที่ 12
B38: งานส่วนที่ 13
B39: งานส่วนที่ 14
B40: งานส่วนที่ 15
B41: งานส่วนที่ 16
B42: งานส่วนที่ 17
B43: งานส่วนที่ 18
... B65: งานส่วนที่ 40
B66: หมวดงาน (WBS ระดับ 2) / Disciplines | C66: ชื่อ / Name | D66: หมายเหตุ
B67: เลขลำดับ = หลักที่สองของรหัส WBS • ใช้แบ่งตามประเภทงาน
B68: หมวดที่ 1 | C68: งานเตรียมการ / Preliminaries
B69: หมวดที่ 2 | C69: งานดิน / Earthworks
B70: หมวดที่ 3 | C70: งานโครงสร้าง / Structural
B71: หมวดที่ 4 | C71: งานสถาปัตยกรรม / Architectural
B72: หมวดที่ 5 | C72: งานระบบ / MEP
B73: หมวดที่ 6 | C73: งานภายนอกและภูมิทัศน์ / External Works
B74: หมวดที่ 7
B75: หมวดที่ 8
B76: หมวดที่ 9
B77: หมวดที่ 10
B78: หมวดที่ 11
B79: หมวดที่ 12
B80: หมวดที่ 13
B81: หมวดที่ 14
B82: หมวดที่ 15
B83: หมวดที่ 16
B84: หมวดที่ 17
B85: หมวดที่ 18
... B109: ตัวช่วยคำนวณแกนเวลา (อัตโนมัติ)
B110: วันเริ่มแกนเวลา | C110: =MIN(C10,IF(COUNT('แผนงาน Schedule'!$I$7:$I$156)>0,MIN('แผนงาน Schedule'!$I$7:$I$156),C10),IF(COUNT('แผนงาน Schedule'!$L$7:$L$156)>0,MIN('แผนงาน Schedule'!$L$7:$L$156),C10),IF(COUNT('แผนงาน Schedule'!$N$7:$N$156)>0,MIN('แผนงาน Schedule'!$N$7:$N$156),C10)) -> 46174
B111: วันสิ้นสุดแกนเวลา | C111: =MAX(C14,C15,MAX('แผนงาน Schedule'!$J$7:$J$156),MAX('แผนงาน Schedule'!$M$7:$M$156),MAX('แผนงาน Schedule'!$O$7:$O$156),MAX('แผนงาน Schedule'!$W$7:$W$156)) -> 46481

Sheet Dashboard
B1: แดชบอร์ดควบคุมโครงการ / Project Control Dashboard
B2: คำนวณอัตโนมัติทั้งหมด • All values are calculated
B3: ข้อมูลอ้างอิง / Reference | C3: ค่า / Value | D3: ความหมาย / Meaning
B4: โครงการ / Project | C4: ='ตั้งค่า Setup'!C4 -> โครงการตัวอย่าง: ก่อสร้างอาคารพร้อมงานภายนอก
B5: วันที่ตรวจวัด / Status Date | C5: ='ตั้งค่า Setup'!$C$15 -> 46293
B6: แหล่งข้อมูลผลงานจริง / Actual Data Source | C6: =IF(COUNT('แผนงาน Schedule'!$P$7:$P$156)>0,"ชีตแผนงาน (รายรายการ)","ชีต S-Curve (ค่าสะสมล่าสุด)") -> ชีตแผนงาน (รายรายการ) | D6: ถ้ากรอก % จริงรายรายการ จะใช้ข้อมูลรายรายการก่อน
B7: ข้อมูลจริง ณ วันที่ / Data Date | C7: =IF(COUNT('แผนงาน Schedule'!$P$7:$P$156)>0,'ตั้งค่า Setup'!$C$15,IFERROR(INDEX('S-Curve'!$C$7:$C$86,MATCH(9.99E+307,'S-Curve'!$F$7:$F$86)),'ตั้งค่า Setup'!$C$15)) -> 46293 | D7: ถ้าไม่ตรงวันที่ตรวจวัด (สีแดง) = ยังไม่อัปเดตผลงานจริงล่าสุด
B8: ด้านเวลา / SCHEDULE PERFORMANCE | C8: ค่า / Value | D8: ความหมาย / Meaning
B9: วันเริ่มสัญญา / Commencement | C9: ='ตั้งค่า Setup'!$C$10 -> 46174
B10: วันสิ้นสุดสัญญาเดิม / Original Completion | C10: ='ตั้งค่า Setup'!C12 -> 46473
B11: ขยายเวลาที่อนุมัติ / Approved EOT (วัน) | C11: ='ตั้งค่า Setup'!C13 -> 8 | D11: จากทะเบียนขยายเวลา
B12: วันสิ้นสุดหลังขยายเวลา / Revised Completion | C12: ='ตั้งค่า Setup'!$C$14 -> 46481
B13: วันที่ดำเนินการแล้ว / Days Elapsed | C13: ='ตั้งค่า Setup'!$C$15-'ตั้งค่า Setup'!$C$10+1 -> 120 | D13: ณ วันที่ตรวจวัด นับวันเริ่มเป็นวันที่ 1
B14: % เวลาที่ใช้ไป / Time Elapsed | C14: =IFERROR(C13/(C12-C9+1),0) -> 0.38961039 | D14: เทียบกับระยะเวลารวมหลังขยายเวลา
B15: วันคงเหลือ / Days Remaining | C15: =C12-C5 -> 188 | D15: ติดลบ = เลยกำหนดสัญญาแล้ว
B16: % แผนเดิม / Baseline Planned % | C16: =SUMPRODUCT('แผนงาน Schedule'!$G$7:$G$156,('แผนงาน Schedule'!$J$7:$J$156<=C7)+('แผนงาน Schedule'!$I$7:$I$156<=C7)*('แผนงาน Schedule'!$J$7:$J$156>C7)*(C7-'แผนงาน Schedule'!$I$7:$I$156+1)/('แผนงาน Schedule'!$J$7:$J$156-'แผนงาน Schedule'!$I$7:$I$156+1)) -> 0.25365051 | D16: ผลงานที่ควรทำได้ตามแผนสัญญา ณ Data Date
B17: % แผนเร่งรัด / Revised Planned % | C17: =IF(C63,SUMPRODUCT('แผนงาน Schedule'!$G$7:$G$156,('แผนงาน Schedule'!$AB$7:$AB$156<=C7)+('แผนงาน Schedule'!$AA$7:$AA$156<=C7)*('แผนงาน Schedule'!$AB$7:$AB$156>C7)*(C7-'แผนงาน Schedule'!$AA$7:$AA$156+1)/('แผนงาน Schedule'!$AB$7:$AB$156-'แผนงาน Schedule'!$AA$7:$AA$156+1)),C16) -> 0.25365051 | D17: ถ้ายังไม่มีแผนเร่งรัด จะเท่ากับแผนเดิม
B18: ผลต่างเทียบแผนเร่งรัด / Variance vs Revised | C18: =C19-C17 -> -0.065840597 | D18: ใช้ติดตามว่าเดินตามแผนเร่งรัดได้หรือไม่
B19: % ผลงานจริง / Actual % | C19: =IF(COUNT('แผนงาน Schedule'!$P$7:$P$156)>0,'แผนงาน Schedule'!$P$157,IFERROR(INDEX('S-Curve'!$F$7:$F$86,MATCH(9.99E+307,'S-Curve'!$F$7:$F$86)),0)) -> 0.18780992
B20: ผลต่าง / Variance (Actual − Baseline) | C20: =C19-C16 -> -0.065840597 | D20: ติดลบ = ช้ากว่าแผน
B21: ผลต่างคิดเป็นวัน / Variance in Days | C21: =C20*C69 -> -19.752179 | D21: ผลต่าง % × ระยะเวลาสัญญา (วิธีรายงานแบบไทย)
B22: SPI (ดัชนีเวลา) | C22: =IFERROR(C37/C36,0) -> 0.7404279 | D22: EV ÷ PV • ≥1 ตามแผน / 0.9–1 เฝ้าระวัง / <0.9 ล่าช้ามาก
B23: Earned Schedule – ES (วัน) | C23: =C68 -> 101.623 | D23: งานที่ทำได้จริง เท่ากับแผนของวันที่เท่าใด (นับจากวันเริ่ม)
B24: Actual Time – AT (วัน) | C24: =C7-C9+1 -> 120 | D24: เวลาที่ใช้จริงถึง Data Date
B25: SV(t) – ช้ากว่าแผนจริง (วัน) | C25: =C23-C24 -> -18.376996 | D25: ติดลบ = ช้ากว่าแผนกี่วัน
B26: SPI(t) (ดัชนีเวลาเชิงวัน) | C26: =IFERROR(C23/C24,0) -> 0.84685837 | D26: ES ÷ AT
B27: คาดการณ์วันแล้วเสร็จ / Forecast Completion | C27: =IF(C19>=1,C7,IF(COUNT('แผนงาน Schedule'!$P$7:$P$156)>0,MAX('แผนงาน Schedule'!$W$7:$W$156),IFERROR(C9+ROUND(C69/C26,0)-1,"-"))) -> 46473 | D27: มี % รายรายการ = วันเสร็จคาดการณ์ช้าสุด • ไม่มี = ระยะเวลา ÷ SPI(t)
B28: คาดว่าล่าช้ากว่าสัญญา / Forecast Delay (วัน) | C28: =IFERROR(MAX(0,C27-C12),"-") -> 0 | D28: เทียบกับวันสิ้นสุดหลังขยายเวลา
B29: อัตราผลงานจริงเฉลี่ย / Actual Rate (%/วัน) | C29: =IFERROR(C19/C24,0) -> 0.0015650826
B30: อัตราที่ต้องทำ / Required Rate (%/วัน) | C30: =IF(C19>=1,0,IF(C12-C7>0,(1-C19)/(C12-C7),"เลยกำหนดแล้ว")) -> 0.00432016 | D30: เพื่อให้เสร็จทันวันสิ้นสุดหลังขยายเวลา
B31: ต้องเร่งงาน / Acceleration Needed (เท่า) | C31: =IFERROR(C30/C29,"-") -> 2.7603399 | D31: เท่าของอัตราผลงานปัจจุบัน
B32: สถานะโครงการ / Overall Status | C32: =IF(C19>=1,"แล้วเสร็จ / Completed",IF(C22>=1,"ตามแผน / On Track",IF(C22>=0.9,"เฝ้าระวัง / At Risk","ล่าช้ามาก / Critical Delay"))) -> ล่าช้ามาก / Critical Delay
B33: จำนวนรายการที่ล่าช้า / Items Behind | C33: =COUNTIF('แผนงาน Schedule'!$Y$7:$Y$156,"*ล่าช้า*")+COUNTIF('แผนงาน Schedule'!$Y$7:$Y$156,"*เกินกำหนด*") -> 5 | D33: ดูรายงานส่วนในชีต สรุปงานส่วน
B34: ด้านต้นทุน / COST PERFORMANCE (EVM) | C34: ค่า / Value | D34: ความหมาย / Meaning
B35: BAC – งบประมาณรวม / Budget at Completion | C35: ='ตั้งค่า Setup'!$C$9 -> 24200000 | D35: มูลค่าสัญญา
B36: PV – มูลค่างานตามแผน / Planned Value | C36: =C16*C35 -> 6138342.4
B37: EV – มูลค่างานที่ทำได้จริง / Earned Value | C37: =C19*C35 -> 4545000
B38: AC – ต้นทุนจริงสะสม / Actual Cost | C38: =SUMIFS('S-Curve'!$K$7:$K$86,'S-Curve'!$C$7:$C$86,"<="&C7) -> 4634800 | D38: กรอกในชีต S-Curve • ถ้าเป็น 0 จะไม่คำนวณ CPI
B39: SV – ผลต่างด้านเวลา (บาท) | C39: =C37-C36 -> -1593342.4 | D39: EV − PV
B40: CV – ผลต่างด้านต้นทุน | C40: =IF(C38>0,C37-C38,"-") -> -89800 | D40: EV − AC • ติดลบ = ใช้เงินเกิน
B41: CPI (ดัชนีต้นทุน) | C41: =IF(C38>0,C37/C38,"-") -> 0.98062484 | D41: EV ÷ AC
B42: EAC – ประมาณการต้นทุนเมื่อแล้วเสร็จ | C42: =IF(C38>0,C35/C41,"-") -> 24678143 | D42: BAC ÷ CPI
B43: ETC – ต้นทุนที่ต้องใช้อีก | C43: =IF(C38>0,C42-C38,"-") -> 20043343 | D43: EAC − AC
B44: VAC – กำไร/ขาดทุนจากงบ | C44: =IF(C38>0,C35-C42,"-") -> -478143.01 | D44: BAC − EAC
B45: TCPI – ประสิทธิภาพที่ต้องทำให้ได้ | C45: =IF(C38>0,IFERROR((C35-C37)/(C35-C38),"-"),"-") -> 1.0045898 | D45: (BAC − EV) ÷ (BAC − AC)
B46: เงินเบิกจ่ายสะสม / Certified Payment | C46: =SUMIFS('S-Curve'!$M$7:$M$86,'S-Curve'!$C$7:$C$86,"<="&C5) -> 2820800
B47: % เบิกจ่ายต่อมูลค่าสัญญา | C47: =IFERROR(C46/C35,0) -> 0.11656198
B48: ขยายเวลาและค่าปรับ / EOT & LIQUIDATED DAMAGES | C48: ค่า / Value | D48: ความหมาย / Meaning
B49: ขอขยายเวลารวม / EOT Claimed (วัน) | C49: =SUM('ขยายเวลา EOT'!$F$8:$F$57) -> 17
B50: อนุมัติแล้ว / EOT Approved (วัน) | C50: =SUM('ขยายเวลา EOT'!$J$8:$J$57) -> 8
B51: รอพิจารณา / EOT Pending (วัน) | C51: =SUMIF('ขยายเวลา EOT'!$I$8:$I$57,"รอพิจารณา / Pending",'ขยายเวลา EOT'!$F$8:$F$57) -> 7
B52: ค่าปรับต่อวัน / LD per Day (บาท) | C52: =MAX('ตั้งค่า Setup'!C18,'ตั้งค่า Setup'!C17*C35) -> 24200 | D52: MAX(ขั้นต่ำ, อัตรา × มูลค่าสัญญา)
B53: วันที่ถูกปรับแล้ว / LD Days to Date | C53: =MAX(0,C5-C12) -> 0
B54: ค่าปรับเกิดขึ้นแล้ว / LD Incurred (บาท) | C54: =C53*C52 -> 0
B55: ค่าปรับคาดการณ์ / Forecast LD (บาท) | C55: =IFERROR(C28*C52,0) -> 0 | D55: ถ้าเสร็จตามวันคาดการณ์
B56: ค่าปรับคาดการณ์ % ของสัญญา | C56: =IFERROR(C55/C35,0) -> 0
B57: สัญญาณเตือนค่าปรับ / LD Alert | C57: =IF(C56>'ตั้งค่า Setup'!C19,"⚠ เกินเกณฑ์ "&TEXT('ตั้งค่า Setup'!C19,"0%")&" – ความเสี่ยงถูกบอกเลิกสัญญา",IF(C56>0,"⚠ มีค่าปรับคาดการณ์","✓ ไม่มีค่าปรับคาดการณ์")) -> ✓ ไม่มีค่าปรับคาดการณ์
B58: ตรวจสอบน้ำหนักงานรวม / Weight Check | C58: =IF(ABS('แผนงาน Schedule'!$G$157-1)<0.0001,"✓ ครบ 100%","⚠ น้ำหนักรวม = "&TEXT('แผนงาน Schedule'!$G$157,"0.00%")) -> ✓ ครบ 100% | D58: ต้องเท่ากับ 100%
B61: ตัวช่วยคำนวณ (อัตโนมัติ)
B62: N = จำนวนงวดที่ Baseline ≤ Actual | C62: =COUNTIF('S-Curve'!$D$7:$D$86,"<="&C19) -> 9
B63: มีแผนเร่งรัดหรือไม่ | C63: =COUNT('แผนงาน Schedule'!$L$7:$L$156)+COUNT('แผนงาน Schedule'!$M$7:$M$156)>0 -> FALSE
B64: จำนวนงวดทั้งหมด | C64: =COUNT('S-Curve'!$D$7:$D$86) -> 31
B65: วันที่ ES | C65: =IF(C62=0,'ตั้งค่า Setup'!$C$110-1+IFERROR(C19/INDEX('S-Curve'!$D$7:$D$86,1),0)*(INDEX('S-Curve'!$C$7:$C$86,1)-'ตั้งค่า Setup'!$C$110+1),IF(C62>=C64,INDEX('S-Curve'!$C$7:$C$86,C64),INDEX('S-Curve'!$C$7:$C$86,C62)+IF(INDEX('S-Curve'!$D$7:$D$86,C62+1)>INDEX('S-Curve'!$D$7:$D$86,C62),(C19-INDEX('S-Curve'!$D$7:$D$86,C62))/(INDEX('S-Curve'!$D$7:$D$86,C62+1)-INDEX('S-Curve'!$D$7:$D$86,C62))*(INDEX('S-Curve'!$C$7:$C$86,C62+1)-INDEX('S-Curve'!$C$7:$C$86,C62)),0))) -> 46274.623
B68: ES (วัน) | C68: =MAX(0,C65-C9+1) -> 101.623
B69: ระยะเวลาสัญญาเดิม (วัน) | C69: ='ตั้งค่า Setup'!$C$11 -> 300

Sheet สรุปงานส่วน Summary
A1: สรุปผลรายงานส่วนและหมวดงาน / Summary by Work Package & Discipline
A2: แสดงความคืบหน้าของแต่ละงานส่วนที่ดำเนินการขนานกัน • Gantt ด้านขวา: ฟ้า=ช่วงแผน ส้ม=ช่วงทำงานจริง เขียว=จริงตรงกับแผน
A3: ข้อมูลจริง ณ วันที่ / Data Date: | D3: =Dashboard!C7 -> 46293
A5: ความก้าวหน้ารายงานส่วน / PROGRESS BY WORK PACKAGE (WBS ระดับ 1) | U5: =INDEX('S-Curve'!$B$7:$B$86,1) -> 46174 | V5: =INDEX('S-Curve'!$B$7:$B$86,2) -> 46184 | W5: =INDEX('S-Curve'!$B$7:$B$86,3) -> 46194 | X5: =INDEX('S-Curve'!$B$7:$B$86,4) -> 46204 | Y5: =INDEX('S-Curve'!$B$7:$B$86,5) -> 46214 | Z5: =INDEX('S-Curve'!$B$7:$B$86,6) -> 46224 | AA5: =INDEX('S-Curve'!$B$7:$B$86,7) -> 46235 | AB5: =INDEX('S-Curve'!$B$7:$B$86,8) -> 46245 | AC5: =INDEX('S-Curve'!$B$7:$B$86,9) -> 46255 | AD5: =INDEX('S-Curve'!$B$7:$B$86,10) -> 46266 | AE5: =INDEX('S-Curve'!$B$7:$B$86,11) -> 46276 | AF5: =INDEX('S-Curve'!$B$7:$B$86,12) -> 46286 | AG5: =INDEX('S-Curve'!$B$7:$B$86,13) -> 46296 | AH5: =INDEX('S-Curve'!$B$7:$B$86,14) -> 46306 | AI5: =INDEX('S-Curve'!$B$7:$B$86,15) -> 46316 | AJ5: =INDEX('S-Curve'!$B$7:$B$86,16) -> 46327 | AK5: =INDEX('S-Curve'!$B$7:$B$86,17) -> 46337 | AL5: =INDEX('S-Curve'!$B$7:$B$86,18) -> 46347 | AM5: =INDEX('S-Curve'!$B$7:$B$86,19) -> 46357 | AN5: =INDEX('S-Curve'!$B$7:$B$86,20) -> 46367 | AO5: =INDEX('S-Curve'!$B$7:$B$86,21) -> 46377 | AP5: =INDEX('S-Curve'!$B$7:$B$86,22) -> 46388 | AQ5: =INDEX('S-Curve'!$B$7:$B$86,23) -> 46398 | AR5: =INDEX('S-Curve'!$B$7:$B$86,24) -> 46408 | AS5: =INDEX('S-Curve'!$B$7:$B$86,25) -> 46419 | AT5: =INDEX('S-Curve'!$B$7:$B$86,26) -> 46429 | AU5: =INDEX('S-Curve'!$B$7:$B$86,27) -> 46439 | AV5: =INDEX('S-Curve'!$B$7:$B$86,28) -> 46447 | AW5: =INDEX('S-Curve'!$B$7:$B$86,29) -> 46457 | AX5: =INDEX('S-Curve'!$B$7:$B$86,30) -> 46467 | AY5: =INDEX('S-Curve'!$B$7:$B$86,31) -> 46478 | AZ5: =INDEX('S-Curve'!$B$7:$B$86,32) | BA5: =INDEX('S-Curve'!$B$7:$B$86,33) | BB5: =INDEX('S-Curve'!$B$7:$B$86,34) | BC5: =INDEX('S-Curve'!$B$7:$B$86,35) | BD5: =INDEX('S-Curve'!$B$7:$B$86,36) | BE5: =INDEX('S-Curve'!$B$7:$B$86,37) | BF5: =INDEX('S-Curve'!$B$7:$B$86,38) | BG5: =INDEX('S-Curve'!$B$7:$B$86,39) | BH5: =INDEX('S-Curve'!$B$7:$B$86,40) | BI5: =INDEX('S-Curve'!$B$7:$B$86,41) | BJ5: =INDEX('S-Curve'!$B$7:$B$86,42) | BK5: =INDEX('S-Curve'!$B$7:$B$86,43) | BL5: =INDEX('S-Curve'!$B$7:$B$86,44) | BM5: =INDEX('S-Curve'!$B$7:$B$86,45) | BN5: =INDEX('S-Curve'!$B$7:$B$86,46) | BO5: =INDEX('S-Curve'!$B$7:$B$86,47) | BP5: =INDEX('S-Curve'!$B$7:$B$86,48) | BQ5: =INDEX('S-Curve'!$B$7:$B$86,49) | BR5: =INDEX('S-Curve'!$B$7:$B$86,50) | BS5: =INDEX('S-Curve'!$B$7:$B$86,51) | BT5: =INDEX('S-Curve'!$B$7:$B$86,52) | BU5: =INDEX('S-Curve'!$B$7:$B$86,53) | BV5: =INDEX('S-Curve'!$B$7:$B$86,54) | BW5: =INDEX('S-Curve'!$B$7:$B$86,55) | BX5: =INDEX('S-Curve'!$B$7:$B$86,56) | BY5: =INDEX('S-Curve'!$B$7:$B$86,57) | BZ5: =INDEX('S-Curve'!$B$7:$B$86,58) | CA5: =INDEX('S-Curve'!$B$7:$B$86,59) | CB5: =INDEX('S-Curve'!$B$7:$B$86,60) | CC5: =INDEX('S-Curve'!$B$7:$B$86,61) | CD5: =INDEX('S-Curve'!$B$7:$B$86,62) | CE5: =INDEX('S-Curve'!$B$7:$B$86,63) | CF5: =INDEX('S-Curve'!$B$7:$B$86,64) | CG5: =INDEX('S-Curve'!$B$7:$B$86,65) | CH5: =INDEX('S-Curve'!$B$7:$B$86,66) | CI5: =INDEX('S-Curve'!$B$7:$B$86,67) | CJ5: =INDEX('S-Curve'!$B$7:$B$86,68) | CK5: =INDEX('S-Curve'!$B$7:$B$86,69) | CL5: =INDEX('S-Curve'!$B$7:$B$86,70) | CM5: =INDEX('S-Curve'!$B$7:$B$86,71) | CN5: =INDEX('S-Curve'!$B$7:$B$86,72) | CO5: =INDEX('S-Curve'!$B$7:$B$86,73) | CP5: =INDEX('S-Curve'!$B$7:$B$86,74) | CQ5: =INDEX('S-Curve'!$B$7:$B$86,75) | CR5: =INDEX('S-Curve'!$B$7:$B$86,76) | CS5: =INDEX('S-Curve'!$B$7:$B$86,77) | CT5: =INDEX('S-Curve'!$B$7:$B$86,78) | CU5: =INDEX('S-Curve'!$B$7:$B$86,79) | CV5: =INDEX('S-Curve'!$B$7:$B$86,80)
A6: No. | B6: งานส่วน / Work Package | C6: จำนวน รายการ | D6: มูลค่า Budget (฿) | E6: น้ำหนัก Weight | F6: เริ่มแผน BL Start | G6: เสร็จแผน BL Finish | H6: เริ่มจริง Actual Start | I6: % แผน Planned | J6: % จริง Actual | K6: ผลต่าง Variance | L6: SPI | M6: คาดว่าเสร็จ Forecast | N6: ล่าช้า (วัน) Delay | O6: รายการ ล่าช้า | P6: สถานะ Status | Q6: ผลงานแผน (% โครงการ) | R6: ผลงานจริง (% โครงการ) | S6: aEnd | U6: =INDEX('S-Curve'!$C$7:$C$86,1) -> 46183 | V6: =INDEX('S-Curve'!$C$7:$C$86,2) -> 46193 | W6: =INDEX('S-Curve'!$C$7:$C$86,3) -> 46203 | X6: =INDEX('S-Curve'!$C$7:$C$86,4) -> 46213 | Y6: =INDEX('S-Curve'!$C$7:$C$86,5) -> 46223 | Z6: =INDEX('S-Curve'!$C$7:$C$86,6) -> 46234 | AA6: =INDEX('S-Curve'!$C$7:$C$86,7) -> 46244 | AB6: =INDEX('S-Curve'!$C$7:$C$86,8) -> 46254 | AC6: =INDEX('S-Curve'!$C$7:$C$86,9) -> 46265 | AD6: =INDEX('S-Curve'!$C$7:$C$86,10) -> 46275 | AE6: =INDEX('S-Curve'!$C$7:$C$86,11) -> 46285 | AF6: =INDEX('S-Curve'!$C$7:$C$86,12) -> 46295 | AG6: =INDEX('S-Curve'!$C$7:$C$86,13) -> 46305 | AH6: =INDEX('S-Curve'!$C$7:$C$86,14) -> 46315 | AI6: =INDEX('S-Curve'!$C$7:$C$86,15) -> 46326 | AJ6: =INDEX('S-Curve'!$C$7:$C$86,16) -> 46336 | AK6: =INDEX('S-Curve'!$C$7:$C$86,17) -> 46346 | AL6: =INDEX('S-Curve'!$C$7:$C$86,18) -> 46356 | AM6: =INDEX('S-Curve'!$C$7:$C$86,19) -> 46366 | AN6: =INDEX('S-Curve'!$C$7:$C$86,20) -> 46376 | AO6: =INDEX('S-Curve'!$C$7:$C$86,21) -> 46387 | AP6: =INDEX('S-Curve'!$C$7:$C$86,22) -> 46397 | AQ6: =INDEX('S-Curve'!$C$7:$C$86,23) -> 46407 | AR6: =INDEX('S-Curve'!$C$7:$C$86,24) -> 46418 | AS6: =INDEX('S-Curve'!$C$7:$C$86,25) -> 46428 | AT6: =INDEX('S-Curve'!$C$7:$C$86,26) -> 46438 | AU6: =INDEX('S-Curve'!$C$7:$C$86,27) -> 46446 | AV6: =INDEX('S-Curve'!$C$7:$C$86,28) -> 46456 | AW6: =INDEX('S-Curve'!$C$7:$C$86,29) -> 46466 | AX6: =INDEX('S-Curve'!$C$7:$C$86,30) -> 46477 | AY6: =INDEX('S-Curve'!$C$7:$C$86,31) -> 46487 | AZ6: =INDEX('S-Curve'!$C$7:$C$86,32) | BA6: =INDEX('S-Curve'!$C$7:$C$86,33) | BB6: =INDEX('S-Curve'!$C$7:$C$86,34) | BC6: =INDEX('S-Curve'!$C$7:$C$86,35) | BD6: =INDEX('S-Curve'!$C$7:$C$86,36) | BE6: =INDEX('S-Curve'!$C$7:$C$86,37) | BF6: =INDEX('S-Curve'!$C$7:$C$86,38) | BG6: =INDEX('S-Curve'!$C$7:$C$86,39) | BH6: =INDEX('S-Curve'!$C$7:$C$86,40) | BI6: =INDEX('S-Curve'!$C$7:$C$86,41) | BJ6: =INDEX('S-Curve'!$C$7:$C$86,42) | BK6: =INDEX('S-Curve'!$C$7:$C$86,43) | BL6: =INDEX('S-Curve'!$C$7:$C$86,44) | BM6: =INDEX('S-Curve'!$C$7:$C$86,45) | BN6: =INDEX('S-Curve'!$C$7:$C$86,46) | BO6: =INDEX('S-Curve'!$C$7:$C$86,47) | BP6: =INDEX('S-Curve'!$C$7:$C$86,48) | BQ6: =INDEX('S-Curve'!$C$7:$C$86,49) | BR6: =INDEX('S-Curve'!$C$7:$C$86,50) | BS6: =INDEX('S-Curve'!$C$7:$C$86,51) | BT6: =INDEX('S-Curve'!$C$7:$C$86,52) | BU6: =INDEX('S-Curve'!$C$7:$C$86,53) | BV6: =INDEX('S-Curve'!$C$7:$C$86,54) | BW6: =INDEX('S-Curve'!$C$7:$C$86,55) | BX6: =INDEX('S-Curve'!$C$7:$C$86,56) | BY6: =INDEX('S-Curve'!$C$7:$C$86,57) | BZ6: =INDEX('S-Curve'!$C$7:$C$86,58) | CA6: =INDEX('S-Curve'!$C$7:$C$86,59) | CB6: =INDEX('S-Curve'!$C$7:$C$86,60) | CC6: =INDEX('S-Curve'!$C$7:$C$86,61) | CD6: =INDEX('S-Curve'!$C$7:$C$86,62) | CE6: =INDEX('S-Curve'!$C$7:$C$86,63) | CF6: =INDEX('S-Curve'!$C$7:$C$86,64) | CG6: =INDEX('S-Curve'!$C$7:$C$86,65) | CH6: =INDEX('S-Curve'!$C$7:$C$86,66) | CI6: =INDEX('S-Curve'!$C$7:$C$86,67) | CJ6: =INDEX('S-Curve'!$C$7:$C$86,68) | CK6: =INDEX('S-Curve'!$C$7:$C$86,69) | CL6: =INDEX('S-Curve'!$C$7:$C$86,70) | CM6: =INDEX('S-Curve'!$C$7:$C$86,71) | CN6: =INDEX('S-Curve'!$C$7:$C$86,72) | CO6: =INDEX('S-Curve'!$C$7:$C$86,73) | CP6: =INDEX('S-Curve'!$C$7:$C$86,74) | CQ6: =INDEX('S-Curve'!$C$7:$C$86,75) | CR6: =INDEX('S-Curve'!$C$7:$C$86,76) | CS6: =INDEX('S-Curve'!$C$7:$C$86,77) | CT6: =INDEX('S-Curve'!$C$7:$C$86,78) | CU6: =INDEX('S-Curve'!$C$7:$C$86,79) | CV6: =INDEX('S-Curve'!$C$7:$C$86,80)
A7: =IF(B7="","",1) -> 1 | B7: =IF('ตั้งค่า Setup'!$C$26="","",'ตั้งค่า Setup'!$C$26) -> งานถมดินและปรับพื้นที่ / Earth Filling & Site Prep | C7: =IF(B7="","",COUNTIFS('แผนงาน Schedule'!$B$7:$B$156,B7,'แผนงาน Schedule'!$D$7:$D$156,"<>")) -> 3 | D7: =IF(B7="","",SUMIF('แผนงาน Schedule'!$B$7:$B$156,B7,'แผนงาน Schedule'!$H$7:$H$156)) -> 3050000 | E7: =IF(B7="","",SUMIF('แผนงาน Schedule'!$B$7:$B$156,B7,'แผนงาน Schedule'!$G$7:$G$156)) -> 0.12603306 | F7: =IF(OR(B7="",N(C7)=0),"",_xlfn.MINIFS('แผนงาน Schedule'!$I$7:$I$156,'แผนงาน Schedule'!$B$7:$B$156,B7)) -> 46174 | G7: =IF(OR(B7="",N(C7)=0),"",_xlfn.MAXIFS('แผนงาน Schedule'!$J$7:$J$156,'แผนงาน Schedule'!$B$7:$B$156,B7)) -> 46265 | H7: =IF(OR(B7="",COUNTIFS('แผนงาน Schedule'!$B$7:$B$156,B7,'แผนงาน Schedule'!$N$7:$N$156,"<>")=0),"",_xlfn.MINIFS('แผนงาน Schedule'!$N$7:$N$156,'แผนงาน Schedule'!$B$7:$B$156,B7)) -> 46176 | I7: =IF(OR(B7="",N(E7)=0),"",SUMPRODUCT(('แผนงาน Schedule'!$B$7:$B$156=B7)*'แผนงาน Schedule'!$G$7:$G$156*(('แผนงาน Schedule'!$J$7:$J$156<=Dashboard!$C$7)+('แผนงาน Schedule'!$I$7:$I$156<=Dashboard!$C$7)*('แผนงาน Schedule'!$J$7:$J$156>Dashboard!$C$7)*(Dashboard!$C$7-'แผนงาน Schedule'!$I$7:$I$156+1)/('แผนงาน Schedule'!$J$7:$J$156-'แผนงาน Schedule'!$I$7:$I$156+1)))/E7) -> 1 | J7: =IF(OR(B7="",N(E7)=0),"",SUMPRODUCT(('แผนงาน Schedule'!$B$7:$B$156=B7)*'แผนงาน Schedule'!$G$7:$G$156*'แผนงาน Schedule'!$P$7:$P$156)/E7) -> 0.98032787 | K7: =IF(I7="","",J7-I7) -> -0.019672131 | L7: =IF(OR(I7="",N(I7)=0),"",J7/I7) -> 0.98032787 | M7: =IF(OR(B7="",N(C7)=0),"",_xlfn.MAXIFS('แผนงาน Schedule'!$W$7:$W$156,'แผนงาน Schedule'!$B$7:$B$156,B7)) -> 46301 | N7: =IF(OR(M7="",G7=""),"",M7-G7) -> 36 | O7: =IF(B7="","",COUNTIFS('แผนงาน Schedule'!$B$7:$B$156,B7,'แผนงาน Schedule'!$Y$7:$Y$156,"*ล่าช้า*")+COUNTIFS('แผนงาน Schedule'!$B$7:$B$156,B7,'แผนงาน Schedule'!$Y$7:$Y$156,"*เกินกำหนด*")) -> 1 | P7: =IF(OR(B7="",N(C7)=0),"",IF(N(J7)>=1,"แล้วเสร็จ / Completed",IF(AND(N(I7)=0,N(J7)=0),"ยังไม่เริ่ม / Not Started",IF(N(J7)>=N(I7),"ตามแผน / On Track",IF(N(J7)/I7>=0.9,"เฝ้าระวัง / At Risk","ล่าช้า / Behind"))))) -> เฝ้าระวัง / At Risk | Q7: =IF(B7="","",N(I7)*N(E7)) -> 0.12603306 | R7: =IF(B7="","",N(J7)*N(E7)) -> 0.12355372 | S7: =IF(H7="","",IF(COUNTIFS('แผนงาน Schedule'!$B$7:$B$156,B7,'แผนงาน Schedule'!$D$7:$D$156,"<>",'แผนงาน Schedule'!$O$7:$O$156,"")=0,_xlfn.MAXIFS('แผนงาน Schedule'!$O$7:$O$156,'แผนงาน Schedule'!$B$7:$B$156,B7),'ตั้งค่า Setup'!$C$15)) -> 46293
A8: =IF(B8="","",2) -> 2 | B8: =IF('ตั้งค่า Setup'!$C$27="","",'ตั้งค่า Setup'!$C$27) -> งานก่อสร้างอาคาร / Building | C8: =IF(B8="","",COUNTIFS('แผนงาน Schedule'!$B$7:$B$156,B8,'แผนงาน Schedule'!$D$7:$D$156,"<>")) -> 8 | D8: =IF(B8="","",SUMIF('แผนงาน Schedule'!$B$7:$B$156,B8,'แผนงาน Schedule'!$H$7:$H$156)) -> 13200000 | E8: =IF(B8="","",SUMIF('แผนงาน Schedule'!$B$7:$B$156,B8,'แผนงาน Schedule'!$G$7:$G$156)) -> 0.54545455 | F8: =IF(OR(B8="",N(C8)=0),"",_xlfn.MINIFS('แผนงาน Schedule'!$I$7:$I$156,'แผนงาน Schedule'!$B$7:$B$156,B8)) -> 46266 | G8: =IF(OR(B8="",N(C8)=0),"",_xlfn.MAXIFS('แผนงาน Schedule'!$J$7:$J$156,'แผนงาน Schedule'!$B$7:$B$156,B8)) -> 46473 | H8: =IF(OR(B8="",COUNTIFS('แผนงาน Schedule'!$B$7:$B$156,B8,'แผนงาน Schedule'!$N$7:$N$156,"<>")=0),"",_xlfn.MINIFS('แผนงาน Schedule'!$N$7:$N$156,'แผนงาน Schedule'!$B$7:$B$156,B8)) -> 46273 | I8: =IF(OR(B8="",N(E8)=0),"",SUMPRODUCT(('แผนงาน Schedule'!$B$7:$B$156=B8)*'แผนงาน Schedule'!$G$7:$G$156*(('แผนงาน Schedule'!$J$7:$J$156<=Dashboard!$C$7)+('แผนงาน Schedule'!$I$7:$I$156<=Dashboard!$C$7)*('แผนงาน Schedule'!$J$7:$J$156>Dashboard!$C$7)*(Dashboard!$C$7-'แผนงาน Schedule'!$I$7:$I$156+1)/('แผนงาน Schedule'!$J$7:$J$156-'แผนงาน Schedule'!$I$7:$I$156+1)))/E8) -> 0.084848485 | J8: =IF(OR(B8="",N(E8)=0),"",SUMPRODUCT(('แผนงาน Schedule'!$B$7:$B$156=B8)*'แผนงาน Schedule'!$G$7:$G$156*'แผนงาน Schedule'!$P$7:$P$156)/E8) -> 0.047727273 | K8: =IF(I8="","",J8-I8) -> -0.037121212 | L8: =IF(OR(I8="",N(I8)=0),"",J8/I8) -> 0.5625 | M8: =IF(OR(B8="",N(C8)=0),"",_xlfn.MAXIFS('แผนงาน Schedule'!$W$7:$W$156,'แผนงาน Schedule'!$B$7:$B$156,B8)) -> 46473 | N8: =IF(OR(M8="",G8=""),"",M8-G8) -> 0 | O8: =IF(B8="","",COUNTIFS('แผนงาน Schedule'!$B$7:$B$156,B8,'แผนงาน Schedule'!$Y$7:$Y$156,"*ล่าช้า*")+COUNTIFS('แผนงาน Schedule'!$B$7:$B$156,B8,'แผนงาน Schedule'!$Y$7:$Y$156,"*เกินกำหนด*")) -> 1 | P8: =IF(OR(B8="",N(C8)=0),"",IF(N(J8)>=1,"แล้วเสร็จ / Completed",IF(AND(N(I8)=0,N(J8)=0),"ยังไม่เริ่ม / Not Started",IF(N(J8)>=N(I8),"ตามแผน / On Track",IF(N(J8)/I8>=0.9,"เฝ้าระวัง / At Risk","ล่าช้า / Behind"))))) -> ล่าช้า / Behind | Q8: =IF(B8="","",N(I8)*N(E8)) -> 0.046280992 | R8: =IF(B8="","",N(J8)*N(E8)) -> 0.026033058 | S8: =IF(H8="","",IF(COUNTIFS('แผนงาน Schedule'!$B$7:$B$156,B8,'แผนงาน Schedule'!$D$7:$D$156,"<>",'แผนงาน Schedule'!$O$7:$O$156,"")=0,_xlfn.MAXIFS('แผนงาน Schedule'!$O$7:$O$156,'แผนงาน Schedule'!$B$7:$B$156,B8),'ตั้งค่า Setup'!$C$15)) -> 46293
A9: =IF(B9="","",3) -> 3 | B9: =IF('ตั้งค่า Setup'!$C$28="","",'ตั้งค่า Setup'!$C$28) -> งานรางระบายน้ำ / Drainage | C9: =IF(B9="","",COUNTIFS('แผนงาน Schedule'!$B$7:$B$156,B9,'แผนงาน Schedule'!$D$7:$D$156,"<>")) -> 2 | D9: =IF(B9="","",SUMIF('แผนงาน Schedule'!$B$7:$B$156,B9,'แผนงาน Schedule'!$H$7:$H$156)) -> 1900000 | E9: =IF(B9="","",SUMIF('แผนงาน Schedule'!$B$7:$B$156,B9,'แผนงาน Schedule'!$G$7:$G$156)) -> 0.078512397 | F9: =IF(OR(B9="",N(C9)=0),"",_xlfn.MINIFS('แผนงาน Schedule'!$I$7:$I$156,'แผนงาน Schedule'!$B$7:$B$156,B9)) -> 46235 | G9: =IF(OR(B9="",N(C9)=0),"",_xlfn.MAXIFS('แผนงาน Schedule'!$J$7:$J$156,'แผนงาน Schedule'!$B$7:$B$156,B9)) -> 46326 | H9: =IF(OR(B9="",COUNTIFS('แผนงาน Schedule'!$B$7:$B$156,B9,'แผนงาน Schedule'!$N$7:$N$156,"<>")=0),"",_xlfn.MINIFS('แผนงาน Schedule'!$N$7:$N$156,'แผนงาน Schedule'!$B$7:$B$156,B9)) -> 46244 | I9: =IF(OR(B9="",N(E9)=0),"",SUMPRODUCT(('แผนงาน Schedule'!$B$7:$B$156=B9)*'แผนงาน Schedule'!$G$7:$G$156*(('แผนงาน Schedule'!$J$7:$J$156<=Dashboard!$C$7)+('แผนงาน Schedule'!$I$7:$I$156<=Dashboard!$C$7)*('แผนงาน Schedule'!$J$7:$J$156>Dashboard!$C$7)*(Dashboard!$C$7-'แผนงาน Schedule'!$I$7:$I$156+1)/('แผนงาน Schedule'!$J$7:$J$156-'แผนงาน Schedule'!$I$7:$I$156+1)))/E9) -> 0.80672994 | J9: =IF(OR(B9="",N(E9)=0),"",SUMPRODUCT(('แผนงาน Schedule'!$B$7:$B$156=B9)*'แผนงาน Schedule'!$G$7:$G$156*'แผนงาน Schedule'!$P$7:$P$156)/E9) -> 0.37631579 | K9: =IF(I9="","",J9-I9) -> -0.43041415 | L9: =IF(OR(I9="",N(I9)=0),"",J9/I9) -> 0.46647059 | M9: =IF(OR(B9="",N(C9)=0),"",_xlfn.MAXIFS('แผนงาน Schedule'!$W$7:$W$156,'แผนงาน Schedule'!$B$7:$B$156,B9)) -> 46353 | N9: =IF(OR(M9="",G9=""),"",M9-G9) -> 27 | O9: =IF(B9="","",COUNTIFS('แผนงาน Schedule'!$B$7:$B$156,B9,'แผนงาน Schedule'!$Y$7:$Y$156,"*ล่าช้า*")+COUNTIFS('แผนงาน Schedule'!$B$7:$B$156,B9,'แผนงาน Schedule'!$Y$7:$Y$156,"*เกินกำหนด*")) -> 2 | P9: =IF(OR(B9="",N(C9)=0),"",IF(N(J9)>=1,"แล้วเสร็จ / Completed",IF(AND(N(I9)=0,N(J9)=0),"ยังไม่เริ่ม / Not Started",IF(N(J9)>=N(I9),"ตามแผน / On Track",IF(N(J9)/I9>=0.9,"เฝ้าระวัง / At Risk","ล่าช้า / Behind"))))) -> ล่าช้า / Behind | Q9: =IF(B9="","",N(I9)*N(E9)) -> 0.063338301 | R9: =IF(B9="","",N(J9)*N(E9)) -> 0.029545455 | S9: =IF(H9="","",IF(COUNTIFS('แผนงาน Schedule'!$B$7:$B$156,B9,'แผนงาน Schedule'!$D$7:$D$156,"<>",'แผนงาน Schedule'!$O$7:$O$156,"")=0,_xlfn.MAXIFS('แผนงาน Schedule'!$O$7:$O$156,'แผนงาน Schedule'!$B$7:$B$156,B9),'ตั้งค่า Setup'!$C$15)) -> 46293
A10: =IF(B10="","",4) -> 4 | B10: =IF('ตั้งค่า Setup'!$C$29="","",'ตั้งค่า Setup'!$C$29) -> งานถนนและลาน / Roads & Hardscape | C10: =IF(B10="","",COUNTIFS('แผนงาน Schedule'!$B$7:$B$156,B10,'แผนงาน Schedule'!$D$7:$D$156,"<>")) -> 3 | D10: =IF(B10="","",SUMIF('แผนงาน Schedule'!$B$7:$B$156,B10,'แผนงาน Schedule'!$H$7:$H$156)) -> 3250000 | E10: =IF(B10="","",SUMIF('แผนงาน Schedule'!$B$7:$B$156,B10,'แผนงาน Schedule'!$G$7:$G$156)) -> 0.13429752 | F10: =IF(OR(B10="",N(C10)=0),"",_xlfn.MINIFS('แผนงาน Schedule'!$I$7:$I$156,'แผนงาน Schedule'!$B$7:$B$156,B10)) -> 46296 | G10: =IF(OR(B10="",N(C10)=0),"",_xlfn.MAXIFS('แผนงาน Schedule'!$J$7:$J$156,'แผนงาน Schedule'!$B$7:$B$156,B10)) -> 46418 | H10: =IF(OR(B10="",COUNTIFS('แผนงาน Schedule'!$B$7:$B$156,B10,'แผนงาน Schedule'!$N$7:$N$156,"<>")=0),"",_xlfn.MINIFS('แผนงาน Schedule'!$N$7:$N$156,'แผนงาน Schedule'!$B$7:$B$156,B10)) | I10: =IF(OR(B10="",N(E10)=0),"",SUMPRODUCT(('แผนงาน Schedule'!$B$7:$B$156=B10)*'แผนงาน Schedule'!$G$7:$G$156*(('แผนงาน Schedule'!$J$7:$J$156<=Dashboard!$C$7)+('แผนงาน Schedule'!$I$7:$I$156<=Dashboard!$C$7)*('แผนงาน Schedule'!$J$7:$J$156>Dashboard!$C$7)*(Dashboard!$C$7-'แผนงาน Schedule'!$I$7:$I$156+1)/('แผนงาน Schedule'!$J$7:$J$156-'แผนงาน Schedule'!$I$7:$I$156+1)))/E10) -> 0 | J10: =IF(OR(B10="",N(E10)=0),"",SUMPRODUCT(('แผนงาน Schedule'!$B$7:$B$156=B10)*'แผนงาน Schedule'!$G$7:$G$156*'แผนงาน Schedule'!$P$7:$P$156)/E10) -> 0 | K10: =IF(I10="","",J10-I10) -> 0 | L10: =IF(OR(I10="",N(I10)=0),"",J10/I10) | M10: =IF(OR(B10="",N(C10)=0),"",_xlfn.MAXIFS('แผนงาน Schedule'!$W$7:$W$156,'แผนงาน Schedule'!$B$7:$B$156,B10)) -> 46418 | N10: =IF(OR(M10="",G10=""),"",M10-G10) -> 0 | O10: =IF(B10="","",COUNTIFS('แผนงาน Schedule'!$B$7:$B$156,B10,'แผนงาน Schedule'!$Y$7:$Y$156,"*ล่าช้า*")+COUNTIFS('แผนงาน Schedule'!$B$7:$B$156,B10,'แผนงาน Schedule'!$Y$7:$Y$156,"*เกินกำหนด*")) -> 0 | P10: =IF(OR(B10="",N(C10)=0),"",IF(N(J10)>=1,"แล้วเสร็จ / Completed",IF(AND(N(I10)=0,N(J10)=0),"ยังไม่เริ่ม / Not Started",IF(N(J10)>=N(I10),"ตามแผน / On Track",IF(N(J10)/I10>=0.9,"เฝ้าระวัง / At Risk","ล่าช้า / Behind"))))) -> ยังไม่เริ่ม / Not Started | Q10: =IF(B10="","",N(I10)*N(E10)) -> 0 | R10: =IF(B10="","",N(J10)*N(E10)) -> 0 | S10: =IF(H10="","",IF(COUNTIFS('แผนงาน Schedule'!$B$7:$B$156,B10,'แผนงาน Schedule'!$D$7:$D$156,"<>",'แผนงาน Schedule'!$O$7:$O$156,"")=0,_xlfn.MAXIFS('แผนงาน Schedule'!$O$7:$O$156,'แผนงาน Schedule'!$B$7:$B$156,B10),'ตั้งค่า Setup'!$C$15))
A11: =IF(B11="","",5) -> 5 | B11: =IF('ตั้งค่า Setup'!$C$30="","",'ตั้งค่า Setup'!$C$30) -> งานรั้ว / Fence | C11: =IF(B11="","",COUNTIFS('แผนงาน Schedule'!$B$7:$B$156,B11,'แผนงาน Schedule'!$D$7:$D$156,"<>")) -> 2 | D11: =IF(B11="","",SUMIF('แผนงาน Schedule'!$B$7:$B$156,B11,'แผนงาน Schedule'!$H$7:$H$156)) -> 1600000 | E11: =IF(B11="","",SUMIF('แผนงาน Schedule'!$B$7:$B$156,B11,'แผนงาน Schedule'!$G$7:$G$156)) -> 0.066115702 | F11: =IF(OR(B11="",N(C11)=0),"",_xlfn.MINIFS('แผนงาน Schedule'!$I$7:$I$156,'แผนงาน Schedule'!$B$7:$B$156,B11)) -> 46266 | G11: =IF(OR(B11="",N(C11)=0),"",_xlfn.MAXIFS('แผนงาน Schedule'!$J$7:$J$156,'แผนงาน Schedule'!$B$7:$B$156,B11)) -> 46371 | H11: =IF(OR(B11="",COUNTIFS('แผนงาน Schedule'!$B$7:$B$156,B11,'แผนงาน Schedule'!$N$7:$N$156,"<>")=0),"",_xlfn.MINIFS('แผนงาน Schedule'!$N$7:$N$156,'แผนงาน Schedule'!$B$7:$B$156,B11)) -> 46277 | I11: =IF(OR(B11="",N(E11)=0),"",SUMPRODUCT(('แผนงาน Schedule'!$B$7:$B$156=B11)*'แผนงาน Schedule'!$G$7:$G$156*(('แผนงาน Schedule'!$J$7:$J$156<=Dashboard!$C$7)+('แผนงาน Schedule'!$I$7:$I$156<=Dashboard!$C$7)*('แผนงาน Schedule'!$J$7:$J$156>Dashboard!$C$7)*(Dashboard!$C$7-'แผนงาน Schedule'!$I$7:$I$156+1)/('แผนงาน Schedule'!$J$7:$J$156-'แผนงาน Schedule'!$I$7:$I$156+1)))/E11) -> 0.27222222 | J11: =IF(OR(B11="",N(E11)=0),"",SUMPRODUCT(('แผนงาน Schedule'!$B$7:$B$156=B11)*'แผนงาน Schedule'!$G$7:$G$156*'แผนงาน Schedule'!$P$7:$P$156)/E11) -> 0.13125 | K11: =IF(I11="","",J11-I11) -> -0.14097222 | L11: =IF(OR(I11="",N(I11)=0),"",J11/I11) -> 0.48214286 | M11: =IF(OR(B11="",N(C11)=0),"",_xlfn.MAXIFS('แผนงาน Schedule'!$W$7:$W$156,'แผนงาน Schedule'!$B$7:$B$156,B11)) -> 46371 | N11: =IF(OR(M11="",G11=""),"",M11-G11) -> 0 | O11: =IF(B11="","",COUNTIFS('แผนงาน Schedule'!$B$7:$B$156,B11,'แผนงาน Schedule'!$Y$7:$Y$156,"*ล่าช้า*")+COUNTIFS('แผนงาน Schedule'!$B$7:$B$156,B11,'แผนงาน Schedule'!$Y$7:$Y$156,"*เกินกำหนด*")) -> 1 | P11: =IF(OR(B11="",N(C11)=0),"",IF(N(J11)>=1,"แล้วเสร็จ / Completed",IF(AND(N(I11)=0,N(J11)=0),"ยังไม่เริ่ม / Not Started",IF(N(J11)>=N(I11),"ตามแผน / On Track",IF(N(J11)/I11>=0.9,"เฝ้าระวัง / At Risk","ล่าช้า / Behind"))))) -> ล่าช้า / Behind | Q11: =IF(B11="","",N(I11)*N(E11)) -> 0.017998163 | R11: =IF(B11="","",N(J11)*N(E11)) -> 0.008677686 | S11: =IF(H11="","",IF(COUNTIFS('แผนงาน Schedule'!$B$7:$B$156,B11,'แผนงาน Schedule'!$D$7:$D$156,"<>",'แผนงาน Schedule'!$O$7:$O$156,"")=0,_xlfn.MAXIFS('แผนงาน Schedule'!$O$7:$O$156,'แผนงาน Schedule'!$B$7:$B$156,B11),'ตั้งค่า Setup'!$C$15)) -> 46293
A12: =IF(B12="","",6) -> 6 | B12: =IF('ตั้งค่า Setup'!$C$31="","",'ตั้งค่า Setup'!$C$31) -> งานโรงจอดรถ / Carport | C12: =IF(B12="","",COUNTIFS('แผนงาน Schedule'!$B$7:$B$156,B12,'แผนงาน Schedule'!$D$7:$D$156,"<>")) -> 3 | D12: =IF(B12="","",SUMIF('แผนงาน Schedule'!$B$7:$B$156,B12,'แผนงาน Schedule'!$H$7:$H$156)) -> 1200000 | E12: =IF(B12="","",SUMIF('แผนงาน Schedule'!$B$7:$B$156,B12,'แผนงาน Schedule'!$G$7:$G$156)) -> 0.049586777 | F12: =IF(OR(B12="",N(C12)=0),"",_xlfn.MINIFS('แผนงาน Schedule'!$I$7:$I$156,'แผนงาน Schedule'!$B$7:$B$156,B12)) -> 46357 | G12: =IF(OR(B12="",N(C12)=0),"",_xlfn.MAXIFS('แผนงาน Schedule'!$J$7:$J$156,'แผนงาน Schedule'!$B$7:$B$156,B12)) -> 46456 | H12: =IF(OR(B12="",COUNTIFS('แผนงาน Schedule'!$B$7:$B$156,B12,'แผนงาน Schedule'!$N$7:$N$156,"<>")=0),"",_xlfn.MINIFS('แผนงาน Schedule'!$N$7:$N$156,'แผนงาน Schedule'!$B$7:$B$156,B12)) | I12: =IF(OR(B12="",N(E12)=0),"",SUMPRODUCT(('แผนงาน Schedule'!$B$7:$B$156=B12)*'แผนงาน Schedule'!$G$7:$G$156*(('แผนงาน Schedule'!$J$7:$J$156<=Dashboard!$C$7)+('แผนงาน Schedule'!$I$7:$I$156<=Dashboard!$C$7)*('แผนงาน Schedule'!$J$7:$J$156>Dashboard!$C$7)*(Dashboard!$C$7-'แผนงาน Schedule'!$I$7:$I$156+1)/('แผนงาน Schedule'!$J$7:$J$156-'แผนงาน Schedule'!$I$7:$I$156+1)))/E12) -> 0 | J12: =IF(OR(B12="",N(E12)=0),"",SUMPRODUCT(('แผนงาน Schedule'!$B$7:$B$156=B12)*'แผนงาน Schedule'!$G$7:$G$156*'แผนงาน Schedule'!$P$7:$P$156)/E12) -> 0 | K12: =IF(I12="","",J12-I12) -> 0 | L12: =IF(OR(I12="",N(I12)=0),"",J12/I12) | M12: =IF(OR(B12="",N(C12)=0),"",_xlfn.MAXIFS('แผนงาน Schedule'!$W$7:$W$156,'แผนงาน Schedule'!$B$7:$B$156,B12)) -> 46456 | N12: =IF(OR(M12="",G12=""),"",M12-G12) -> 0 | O12: =IF(B12="","",COUNTIFS('แผนงาน Schedule'!$B$7:$B$156,B12,'แผนงาน Schedule'!$Y$7:$Y$156,"*ล่าช้า*")+COUNTIFS('แผนงาน Schedule'!$B$7:$B$156,B12,'แผนงาน Schedule'!$Y$7:$Y$156,"*เกินกำหนด*")) -> 0 | P12: =IF(OR(B12="",N(C12)=0),"",IF(N(J12)>=1,"แล้วเสร็จ / Completed",IF(AND(N(I12)=0,N(J12)=0),"ยังไม่เริ่ม / Not Started",IF(N(J12)>=N(I12),"ตามแผน / On Track",IF(N(J12)/I12>=0.9,"เฝ้าระวัง / At Risk","ล่าช้า / Behind"))))) -> ยังไม่เริ่ม / Not Started | Q12: =IF(B12="","",N(I12)*N(E12)) -> 0 | R12: =IF(B12="","",N(J12)*N(E12)) -> 0 | S12: =IF(H12="","",IF(COUNTIFS('แผนงาน Schedule'!$B$7:$B$156,B12,'แผนงาน Schedule'!$D$7:$D$156,"<>",'แผนงาน Schedule'!$O$7:$O$156,"")=0,_xlfn.MAXIFS('แผนงาน Schedule'!$O$7:$O$156,'แผนงาน Schedule'!$B$7:$B$156,B12),'ตั้งค่า Setup'!$C$15))
A13: =IF(B13="","",7) | B13: =IF('ตั้งค่า Setup'!$C$32="","",'ตั้งค่า Setup'!$C$32) | C13: =IF(B13="","",COUNTIFS('แผนงาน Schedule'!$B$7:$B$156,B13,'แผนงาน Schedule'!$D$7:$D$156,"<>")) | D13: =IF(B13="","",SUMIF('แผนงาน Schedule'!$B$7:$B$156,B13,'แผนงาน Schedule'!$H$7:$H$156)) | E13: =IF(B13="","",SUMIF('แผนงาน Schedule'!$B$7:$B$156,B13,'แผนงาน Schedule'!$G$7:$G$156)) | F13: =IF(OR(B13="",N(C13)=0),"",_xlfn.MINIFS('แผนงาน Schedule'!$I$7:$I$156,'แผนงาน Schedule'!$B$7:$B$156,B13)) | G13: =IF(OR(B13="",N(C13)=0),"",_xlfn.MAXIFS('แผนงาน Schedule'!$J$7:$J$156,'แผนงาน Schedule'!$B$7:$B$156,B13)) | H13: =IF(OR(B13="",COUNTIFS('แผนงาน Schedule'!$B$7:$B$156,B13,'แผนงาน Schedule'!$N$7:$N$156,"<>")=0),"",_xlfn.MINIFS('แผนงาน Schedule'!$N$7:$N$156,'แผนงาน Schedule'!$B$7:$B$156,B13)) | I13: =IF(OR(B13="",N(E13)=0),"",SUMPRODUCT(('แผนงาน Schedule'!$B$7:$B$156=B13)*'แผนงาน Schedule'!$G$7:$G$156*(('แผนงาน Schedule'!$J$7:$J$156<=Dashboard!$C$7)+('แผนงาน Schedule'!$I$7:$I$156<=Dashboard!$C$7)*('แผนงาน Schedule'!$J$7:$J$156>Dashboard!$C$7)*(Dashboard!$C$7-'แผนงาน Schedule'!$I$7:$I$156+1)/('แผนงาน Schedule'!$J$7:$J$156-'แผนงาน Schedule'!$I$7:$I$156+1)))/E13) | J13: =IF(OR(B13="",N(E13)=0),"",SUMPRODUCT(('แผนงาน Schedule'!$B$7:$B$156=B13)*'แผนงาน Schedule'!$G$7:$G$156*'แผนงาน Schedule'!$P$7:$P$156)/E13) | K13: =IF(I13="","",J13-I13) | L13: =IF(OR(I13="",N(I13)=0),"",J13/I13) | M13: =IF(OR(B13="",N(C13)=0),"",_xlfn.MAXIFS('แผนงาน Schedule'!$W$7:$W$156,'แผนงาน Schedule'!$B$7:$B$156,B13)) | N13: =IF(OR(M13="",G13=""),"",M13-G13) | O13: =IF(B13="","",COUNTIFS('แผนงาน Schedule'!$B$7:$B$156,B13,'แผนงาน Schedule'!$Y$7:$Y$156,"*ล่าช้า*")+COUNTIFS('แผนงาน Schedule'!$B$7:$B$156,B13,'แผนงาน Schedule'!$Y$7:$Y$156,"*เกินกำหนด*")) | P13: =IF(OR(B13="",N(C13)=0),"",IF(N(J13)>=1,"แล้วเสร็จ / Completed",IF(AND(N(I13)=0,N(J13)=0),"ยังไม่เริ่ม / Not Started",IF(N(J13)>=N(I13),"ตามแผน / On Track",IF(N(J13)/I13>=0.9,"เฝ้าระวัง / At Risk","ล่าช้า / Behind"))))) | Q13: =IF(B13="","",N(I13)*N(E13)) | R13: =IF(B13="","",N(J13)*N(E13)) | S13: =IF(H13="","",IF(COUNTIFS('แผนงาน Schedule'!$B$7:$B$156,B13,'แผนงาน Schedule'!$D$7:$D$156,"<>",'แผนงาน Schedule'!$O$7:$O$156,"")=0,_xlfn.MAXIFS('แผนงาน Schedule'!$O$7:$O$156,'แผนงาน Schedule'!$B$7:$B$156,B13),'ตั้งค่า Setup'!$C$15))
A14: =IF(B14="","",8) | B14: =IF('ตั้งค่า Setup'!$C$33="","",'ตั้งค่า Setup'!$C$33) | C14: =IF(B14="","",COUNTIFS('แผนงาน Schedule'!$B$7:$B$156,B14,'แผนงาน Schedule'!$D$7:$D$156,"<>")) | D14: =IF(B14="","",SUMIF('แผนงาน Schedule'!$B$7:$B$156,B14,'แผนงาน Schedule'!$H$7:$H$156)) | E14: =IF(B14="","",SUMIF('แผนงาน Schedule'!$B$7:$B$156,B14,'แผนงาน Schedule'!$G$7:$G$156)) | F14: =IF(OR(B14="",N(C14)=0),"",_xlfn.MINIFS('แผนงาน Schedule'!$I$7:$I$156,'แผนงาน Schedule'!$B$7:$B$156,B14)) | G14: =IF(OR(B14="",N(C14)=0),"",_xlfn.MAXIFS('แผนงาน Schedule'!$J$7:$J$156,'แผนงาน Schedule'!$B$7:$B$156,B14)) | H14: =IF(OR(B14="",COUNTIFS('แผนงาน Schedule'!$B$7:$B$156,B14,'แผนงาน Schedule'!$N$7:$N$156,"<>")=0),"",_xlfn.MINIFS('แผนงาน Schedule'!$N$7:$N$156,'แผนงาน Schedule'!$B$7:$B$156,B14)) | I14: =IF(OR(B14="",N(E14)=0),"",SUMPRODUCT(('แผนงาน Schedule'!$B$7:$B$156=B14)*'แผนงาน Schedule'!$G$7:$G$156*(('แผนงาน Schedule'!$J$7:$J$156<=Dashboard!$C$7)+('แผนงาน Schedule'!$I$7:$I$156<=Dashboard!$C$7)*('แผนงาน Schedule'!$J$7:$J$156>Dashboard!$C$7)*(Dashboard!$C$7-'แผนงาน Schedule'!$I$7:$I$156+1)/('แผนงาน Schedule'!$J$7:$J$156-'แผนงาน Schedule'!$I$7:$I$156+1)))/E14) | J14: =IF(OR(B14="",N(E14)=0),"",SUMPRODUCT(('แผนงาน Schedule'!$B$7:$B$156=B14)*'แผนงาน Schedule'!$G$7:$G$156*'แผนงาน Schedule'!$P$7:$P$156)/E14) | K14: =IF(I14="","",J14-I14) | L14: =IF(OR(I14="",N(I14)=0),"",J14/I14) | M14: =IF(OR(B14="",N(C14)=0),"",_xlfn.MAXIFS('แผนงาน Schedule'!$W$7:$W$156,'แผนงาน Schedule'!$B$7:$B$156,B14)) | N14: =IF(OR(M14="",G14=""),"",M14-G14) | O14: =IF(B14="","",COUNTIFS('แผนงาน Schedule'!$B$7:$B$156,B14,'แผนงาน Schedule'!$Y$7:$Y$156,"*ล่าช้า*")+COUNTIFS('แผนงาน Schedule'!$B$7:$B$156,B14,'แผนงาน Schedule'!$Y$7:$Y$156,"*เกินกำหนด*")) | P14: =IF(OR(B14="",N(C14)=0),"",IF(N(J14)>=1,"แล้วเสร็จ / Completed",IF(AND(N(I14)=0,N(J14)=0),"ยังไม่เริ่ม / Not Started",IF(N(J14)>=N(I14),"ตามแผน / On Track",IF(N(J14)/I14>=0.9,"เฝ้าระวัง / At Risk","ล่าช้า / Behind"))))) | Q14: =IF(B14="","",N(I14)*N(E14)) | R14: =IF(B14="","",N(J14)*N(E14)) | S14: =IF(H14="","",IF(COUNTIFS('แผนงาน Schedule'!$B$7:$B$156,B14,'แผนงาน Schedule'!$D$7:$D$156,"<>",'แผนงาน Schedule'!$O$7:$O$156,"")=0,_xlfn.MAXIFS('แผนงาน Schedule'!$O$7:$O$156,'แผนงาน Schedule'!$B$7:$B$156,B14),'ตั้งค่า Setup'!$C$15))
A15: =IF(B15="","",9) | B15: =IF('ตั้งค่า Setup'!$C$34="","",'ตั้งค่า Setup'!$C$34) | C15: =IF(B15="","",COUNTIFS('แผนงาน Schedule'!$B$7:$B$156,B15,'แผนงาน Schedule'!$D$7:$D$156,"<>")) | D15: =IF(B15="","",SUMIF('แผนงาน Schedule'!$B$7:$B$156,B15,'แผนงาน Schedule'!$H$7:$H$156)) | E15: =IF(B15="","",SUMIF('แผนงาน Schedule'!$B$7:$B$156,B15,'แผนงาน Schedule'!$G$7:$G$156)) | F15: =IF(OR(B15="",N(C15)=0),"",_xlfn.MINIFS('แผนงาน Schedule'!$I$7:$I$156,'แผนงาน Schedule'!$B$7:$B$156,B15)) | G15: =IF(OR(B15="",N(C15)=0),"",_xlfn.MAXIFS('แผนงาน Schedule'!$J$7:$J$156,'แผนงาน Schedule'!$B$7:$B$156,B15)) | H15: =IF(OR(B15="",COUNTIFS('แผนงาน Schedule'!$B$7:$B$156,B15,'แผนงาน Schedule'!$N$7:$N$156,"<>")=0),"",_xlfn.MINIFS('แผนงาน Schedule'!$N$7:$N$156,'แผนงาน Schedule'!$B$7:$B$156,B15)) | I15: =IF(OR(B15="",N(E15)=0),"",SUMPRODUCT(('แผนงาน Schedule'!$B$7:$B$156=B15)*'แผนงาน Schedule'!$G$7:$G$156*(('แผนงาน Schedule'!$J$7:$J$156<=Dashboard!$C$7)+('แผนงาน Schedule'!$I$7:$I$156<=Dashboard!$C$7)*('แผนงาน Schedule'!$J$7:$J$156>Dashboard!$C$7)*(Dashboard!$C$7-'แผนงาน Schedule'!$I$7:$I$156+1)/('แผนงาน Schedule'!$J$7:$J$156-'แผนงาน Schedule'!$I$7:$I$156+1)))/E15) | J15: =IF(OR(B15="",N(E15)=0),"",SUMPRODUCT(('แผนงาน Schedule'!$B$7:$B$156=B15)*'แผนงาน Schedule'!$G$7:$G$156*'แผนงาน Schedule'!$P$7:$P$156)/E15) | K15: =IF(I15="","",J15-I15) | L15: =IF(OR(I15="",N(I15)=0),"",J15/I15) | M15: =IF(OR(B15="",N(C15)=0),"",_xlfn.MAXIFS('แผนงาน Schedule'!$W$7:$W$156,'แผนงาน Schedule'!$B$7:$B$156,B15)) | N15: =IF(OR(M15="",G15=""),"",M15-G15) | O15: =IF(B15="","",COUNTIFS('แผนงาน Schedule'!$B$7:$B$156,B15,'แผนงาน Schedule'!$Y$7:$Y$156,"*ล่าช้า*")+COUNTIFS('แผนงาน Schedule'!$B$7:$B$156,B15,'แผนงาน Schedule'!$Y$7:$Y$156,"*เกินกำหนด*")) | P15: =IF(OR(B15="",N(C15)=0),"",IF(N(J15)>=1,"แล้วเสร็จ / Completed",IF(AND(N(I15)=0,N(J15)=0),"ยังไม่เริ่ม / Not Started",IF(N(J15)>=N(I15),"ตามแผน / On Track",IF(N(J15)/I15>=0.9,"เฝ้าระวัง / At Risk","ล่าช้า / Behind"))))) | Q15: =IF(B15="","",N(I15)*N(E15)) | R15: =IF(B15="","",N(J15)*N(E15)) | S15: =IF(H15="","",IF(COUNTIFS('แผนงาน Schedule'!$B$7:$B$156,B15,'แผนงาน Schedule'!$D$7:$D$156,"<>",'แผนงาน Schedule'!$O$7:$O$156,"")=0,_xlfn.MAXIFS('แผนงาน Schedule'!$O$7:$O$156,'แผนงาน Schedule'!$B$7:$B$156,B15),'ตั้งค่า Setup'!$C$15))
A16: =IF(B16="","",10) | B16: =IF('ตั้งค่า Setup'!$C$35="","",'ตั้งค่า Setup'!$C$35) | C16: =IF(B16="","",COUNTIFS('แผนงาน Schedule'!$B$7:$B$156,B16,'แผนงาน Schedule'!$D$7:$D$156,"<>")) | D16: =IF(B16="","",SUMIF('แผนงาน Schedule'!$B$7:$B$156,B16,'แผนงาน Schedule'!$H$7:$H$156)) | E16: =IF(B16="","",SUMIF('แผนงาน Schedule'!$B$7:$B$156,B16,'แผนงาน Schedule'!$G$7:$G$156)) | F16: =IF(OR(B16="",N(C16)=0),"",_xlfn.MINIFS('แผนงาน Schedule'!$I$7:$I$156,'แผนงาน Schedule'!$B$7:$B$156,B16)) | G16: =IF(OR(B16="",N(C16)=0),"",_xlfn.MAXIFS('แผนงาน Schedule'!$J$7:$J$156,'แผนงาน Schedule'!$B$7:$B$156,B16)) | H16: =IF(OR(B16="",COUNTIFS('แผนงาน Schedule'!$B$7:$B$156,B16,'แผนงาน Schedule'!$N$7:$N$156,"<>")=0),"",_xlfn.MINIFS('แผนงาน Schedule'!$N$7:$N$156,'แผนงาน Schedule'!$B$7:$B$156,B16)) | I16: =IF(OR(B16="",N(E16)=0),"",SUMPRODUCT(('แผนงาน Schedule'!$B$7:$B$156=B16)*'แผนงาน Schedule'!$G$7:$G$156*(('แผนงาน Schedule'!$J$7:$J$156<=Dashboard!$C$7)+('แผนงาน Schedule'!$I$7:$I$156<=Dashboard!$C$7)*('แผนงาน Schedule'!$J$7:$J$156>Dashboard!$C$7)*(Dashboard!$C$7-'แผนงาน Schedule'!$I$7:$I$156+1)/('แผนงาน Schedule'!$J$7:$J$156-'แผนงาน Schedule'!$I$7:$I$156+1)))/E16) | J16: =IF(OR(B16="",N(E16)=0),"",SUMPRODUCT(('แผนงาน Schedule'!$B$7:$B$156=B16)*'แผนงาน Schedule'!$G$7:$G$156*'แผนงาน Schedule'!$P$7:$P$156)/E16) | K16: =IF(I16="","",J16-I16) | L16: =IF(OR(I16="",N(I16)=0),"",J16/I16) | M16: =IF(OR(B16="",N(C16)=0),"",_xlfn.MAXIFS('แผนงาน Schedule'!$W$7:$W$156,'แผนงาน Schedule'!$B$7:$B$156,B16)) | N16: =IF(OR(M16="",G16=""),"",M16-G16) | O16: =IF(B16="","",COUNTIFS('แผนงาน Schedule'!$B$7:$B$156,B16,'แผนงาน Schedule'!$Y$7:$Y$156,"*ล่าช้า*")+COUNTIFS('แผนงาน Schedule'!$B$7:$B$156,B16,'แผนงาน Schedule'!$Y$7:$Y$156,"*เกินกำหนด*")) | P16: =IF(OR(B16="",N(C16)=0),"",IF(N(J16)>=1,"แล้วเสร็จ / Completed",IF(AND(N(I16)=0,N(J16)=0),"ยังไม่เริ่ม / Not Started",IF(N(J16)>=N(I16),"ตามแผน / On Track",IF(N(J16)/I16>=0.9,"เฝ้าระวัง / At Risk","ล่าช้า / Behind"))))) | Q16: =IF(B16="","",N(I16)*N(E16)) | R16: =IF(B16="","",N(J16)*N(E16)) | S16: =IF(H16="","",IF(COUNTIFS('แผนงาน Schedule'!$B$7:$B$156,B16,'แผนงาน Schedule'!$D$7:$D$156,"<>",'แผนงาน Schedule'!$O$7:$O$156,"")=0,_xlfn.MAXIFS('แผนงาน Schedule'!$O$7:$O$156,'แผนงาน Schedule'!$B$7:$B$156,B16),'ตั้งค่า Setup'!$C$15))
A17: =IF(B17="","",11) | B17: =IF('ตั้งค่า Setup'!$C$36="","",'ตั้งค่า Setup'!$C$36) | C17: =IF(B17="","",COUNTIFS('แผนงาน Schedule'!$B$7:$B$156,B17,'แผนงาน Schedule'!$D$7:$D$156,"<>")) | D17: =IF(B17="","",SUMIF('แผนงาน Schedule'!$B$7:$B$156,B17,'แผนงาน Schedule'!$H$7:$H$156)) | E17: =IF(B17="","",SUMIF('แผนงาน Schedule'!$B$7:$B$156,B17,'แผนงาน Schedule'!$G$7:$G$156)) | F17: =IF(OR(B17="",N(C17)=0),"",_xlfn.MINIFS('แผนงาน Schedule'!$I$7:$I$156,'แผนงาน Schedule'!$B$7:$B$156,B17)) | G17: =IF(OR(B17="",N(C17)=0),"",_xlfn.MAXIFS('แผนงาน Schedule'!$J$7:$J$156,'แผนงาน Schedule'!$B$7:$B$156,B17)) | H17: =IF(OR(B17="",COUNTIFS('แผนงาน Schedule'!$B$7:$B$156,B17,'แผนงาน Schedule'!$N$7:$N$156,"<>")=0),"",_xlfn.MINIFS('แผนงาน Schedule'!$N$7:$N$156,'แผนงาน Schedule'!$B$7:$B$156,B17)) | I17: =IF(OR(B17="",N(E17)=0),"",SUMPRODUCT(('แผนงาน Schedule'!$B$7:$B$156=B17)*'แผนงาน Schedule'!$G$7:$G$156*(('แผนงาน Schedule'!$J$7:$J$156<=Dashboard!$C$7)+('แผนงาน Schedule'!$I$7:$I$156<=Dashboard!$C$7)*('แผนงาน Schedule'!$J$7:$J$156>Dashboard!$C$7)*(Dashboard!$C$7-'แผนงาน Schedule'!$I$7:$I$156+1)/('แผนงาน Schedule'!$J$7:$J$156-'แผนงาน Schedule'!$I$7:$I$156+1)))/E17) | J17: =IF(OR(B17="",N(E17)=0),"",SUMPRODUCT(('แผนงาน Schedule'!$B$7:$B$156=B17)*'แผนงาน Schedule'!$G$7:$G$156*'แผนงาน Schedule'!$P$7:$P$156)/E17) | K17: =IF(I17="","",J17-I17) | L17: =IF(OR(I17="",N(I17)=0),"",J17/I17) | M17: =IF(OR(B17="",N(C17)=0),"",_xlfn.MAXIFS('แผนงาน Schedule'!$W$7:$W$156,'แผนงาน Schedule'!$B$7:$B$156,B17)) | N17: =IF(OR(M17="",G17=""),"",M17-G17) | O17: =IF(B17="","",COUNTIFS('แผนงาน Schedule'!$B$7:$B$156,B17,'แผนงาน Schedule'!$Y$7:$Y$156,"*ล่าช้า*")+COUNTIFS('แผนงาน Schedule'!$B$7:$B$156,B17,'แผนงาน Schedule'!$Y$7:$Y$156,"*เกินกำหนด*")) | P17: =IF(OR(B17="",N(C17)=0),"",IF(N(J17)>=1,"แล้วเสร็จ / Completed",IF(AND(N(I17)=0,N(J17)=0),"ยังไม่เริ่ม / Not Started",IF(N(J17)>=N(I17),"ตามแผน / On Track",IF(N(J17)/I17>=0.9,"เฝ้าระวัง / At Risk","ล่าช้า / Behind"))))) | Q17: =IF(B17="","",N(I17)*N(E17)) | R17: =IF(B17="","",N(J17)*N(E17)) | S17: =IF(H17="","",IF(COUNTIFS('แผนงาน Schedule'!$B$7:$B$156,B17,'แผนงาน Schedule'!$D$7:$D$156,"<>",'แผนงาน Schedule'!$O$7:$O$156,"")=0,_xlfn.MAXIFS('แผนงาน Schedule'!$O$7:$O$156,'แผนงาน Schedule'!$B$7:$B$156,B17),'ตั้งค่า Setup'!$C$15))
A18: =IF(B18="","",12) | B18: =IF('ตั้งค่า Setup'!$C$37="","",'ตั้งค่า Setup'!$C$37) | C18: =IF(B18="","",COUNTIFS('แผนงาน Schedule'!$B$7:$B$156,B18,'แผนงาน Schedule'!$D$7:$D$156,"<>")) | D18: =IF(B18="","",SUMIF('แผนงาน Schedule'!$B$7:$B$156,B18,'แผนงาน Schedule'!$H$7:$H$156)) | E18: =IF(B18="","",SUMIF('แผนงาน Schedule'!$B$7:$B$156,B18,'แผนงาน Schedule'!$G$7:$G$156)) | F18: =IF(OR(B18="",N(C18)=0),"",_xlfn.MINIFS('แผนงาน Schedule'!$I$7:$I$156,'แผนงาน Schedule'!$B$7:$B$156,B18)) | G18: =IF(OR(B18="",N(C18)=0),"",_xlfn.MAXIFS('แผนงาน Schedule'!$J$7:$J$156,'แผนงาน Schedule'!$B$7:$B$156,B18)) | H18: =IF(OR(B18="",COUNTIFS('แผนงาน Schedule'!$B$7:$B$156,B18,'แผนงาน Schedule'!$N$7:$N$156,"<>")=0),"",_xlfn.MINIFS('แผนงาน Schedule'!$N$7:$N$156,'แผนงาน Schedule'!$B$7:$B$156,B18)) | I18: =IF(OR(B18="",N(E18)=0),"",SUMPRODUCT(('แผนงาน Schedule'!$B$7:$B$156=B18)*'แผนงาน Schedule'!$G$7:$G$156*(('แผนงาน Schedule'!$J$7:$J$156<=Dashboard!$C$7)+('แผนงาน Schedule'!$I$7:$I$156<=Dashboard!$C$7)*('แผนงาน Schedule'!$J$7:$J$156>Dashboard!$C$7)*(Dashboard!$C$7-'แผนงาน Schedule'!$I$7:$I$156+1)/('แผนงาน Schedule'!$J$7:$J$156-'แผนงาน Schedule'!$I$7:$I$156+1)))/E18) | J18: =IF(OR(B18="",N(E18)=0),"",SUMPRODUCT(('แผนงาน Schedule'!$B$7:$B$156=B18)*'แผนงาน Schedule'!$G$7:$G$156*'แผนงาน Schedule'!$P$7:$P$156)/E18) | K18: =IF(I18="","",J18-I18) | L18: =IF(OR(I18="",N(I18)=0),"",J18/I18) | M18: =IF(OR(B18="",N(C18)=0),"",_xlfn.MAXIFS('แผนงาน Schedule'!$W$7:$W$156,'แผนงาน Schedule'!$B$7:$B$156,B18)) | N18: =IF(OR(M18="",G18=""),"",M18-G18) | O18: =IF(B18="","",COUNTIFS('แผนงาน Schedule'!$B$7:$B$156,B18,'แผนงาน Schedule'!$Y$7:$Y$156,"*ล่าช้า*")+COUNTIFS('แผนงาน Schedule'!$B$7:$B$156,B18,'แผนงาน Schedule'!$Y$7:$Y$156,"*เกินกำหนด*")) | P18: =IF(OR(B18="",N(C18)=0),"",IF(N(J18)>=1,"แล้วเสร็จ / Completed",IF(AND(N(I18)=0,N(J18)=0),"ยังไม่เริ่ม / Not Started",IF(N(J18)>=N(I18),"ตามแผน / On Track",IF(N(J18)/I18>=0.9,"เฝ้าระวัง / At Risk","ล่าช้า / Behind"))))) | Q18: =IF(B18="","",N(I18)*N(E18)) | R18: =IF(B18="","",N(J18)*N(E18)) | S18: =IF(H18="","",IF(COUNTIFS('แผนงาน Schedule'!$B$7:$B$156,B18,'แผนงาน Schedule'!$D$7:$D$156,"<>",'แผนงาน Schedule'!$O$7:$O$156,"")=0,_xlfn.MAXIFS('แผนงาน Schedule'!$O$7:$O$156,'แผนงาน Schedule'!$B$7:$B$156,B18),'ตั้งค่า Setup'!$C$15))
A19: =IF(B19="","",13) | B19: =IF('ตั้งค่า Setup'!$C$38="","",'ตั้งค่า Setup'!$C$38) | C19: =IF(B19="","",COUNTIFS('แผนงาน Schedule'!$B$7:$B$156,B19,'แผนงาน Schedule'!$D$7:$D$156,"<>")) | D19: =IF(B19="","",SUMIF('แผนงาน Schedule'!$B$7:$B$156,B19,'แผนงาน Schedule'!$H$7:$H$156)) | E19: =IF(B19="","",SUMIF('แผนงาน Schedule'!$B$7:$B$156,B19,'แผนงาน Schedule'!$G$7:$G$156)) | F19: =IF(OR(B19="",N(C19)=0),"",_xlfn.MINIFS('แผนงาน Schedule'!$I$7:$I$156,'แผนงาน Schedule'!$B$7:$B$156,B19)) | G19: =IF(OR(B19="",N(C19)=0),"",_xlfn.MAXIFS('แผนงาน Schedule'!$J$7:$J$156,'แผนงาน Schedule'!$B$7:$B$156,B19)) | H19: =IF(OR(B19="",COUNTIFS('แผนงาน Schedule'!$B$7:$B$156,B19,'แผนงาน Schedule'!$N$7:$N$156,"<>")=0),"",_xlfn.MINIFS('แผนงาน Schedule'!$N$7:$N$156,'แผนงาน Schedule'!$B$7:$B$156,B19)) | I19: =IF(OR(B19="",N(E19)=0),"",SUMPRODUCT(('แผนงาน Schedule'!$B$7:$B$156=B19)*'แผนงาน Schedule'!$G$7:$G$156*(('แผนงาน Schedule'!$J$7:$J$156<=Dashboard!$C$7)+('แผนงาน Schedule'!$I$7:$I$156<=Dashboard!$C$7)*('แผนงาน Schedule'!$J$7:$J$156>Dashboard!$C$7)*(Dashboard!$C$7-'แผนงาน Schedule'!$I$7:$I$156+1)/('แผนงาน Schedule'!$J$7:$J$156-'แผนงาน Schedule'!$I$7:$I$156+1)))/E19) | J19: =IF(OR(B19="",N(E19)=0),"",SUMPRODUCT(('แผนงาน Schedule'!$B$7:$B$156=B19)*'แผนงาน Schedule'!$G$7:$G$156*'แผนงาน Schedule'!$P$7:$P$156)/E19) | K19: =IF(I19="","",J19-I19) | L19: =IF(OR(I19="",N(I19)=0),"",J19/I19) | M19: =IF(OR(B19="",N(C19)=0),"",_xlfn.MAXIFS('แผนงาน Schedule'!$W$7:$W$156,'แผนงาน Schedule'!$B$7:$B$156,B19)) | N19: =IF(OR(M19="",G19=""),"",M19-G19) | O19: =IF(B19="","",COUNTIFS('แผนงาน Schedule'!$B$7:$B$156,B19,'แผนงาน Schedule'!$Y$7:$Y$156,"*ล่าช้า*")+COUNTIFS('แผนงาน Schedule'!$B$7:$B$156,B19,'แผนงาน Schedule'!$Y$7:$Y$156,"*เกินกำหนด*")) | P19: =IF(OR(B19="",N(C19)=0),"",IF(N(J19)>=1,"แล้วเสร็จ / Completed",IF(AND(N(I19)=0,N(J19)=0),"ยังไม่เริ่ม / Not Started",IF(N(J19)>=N(I19),"ตามแผน / On Track",IF(N(J19)/I19>=0.9,"เฝ้าระวัง / At Risk","ล่าช้า / Behind"))))) | Q19: =IF(B19="","",N(I19)*N(E19)) | R19: =IF(B19="","",N(J19)*N(E19)) | S19: =IF(H19="","",IF(COUNTIFS('แผนงาน Schedule'!$B$7:$B$156,B19,'แผนงาน Schedule'!$D$7:$D$156,"<>",'แผนงาน Schedule'!$O$7:$O$156,"")=0,_xlfn.MAXIFS('แผนงาน Schedule'!$O$7:$O$156,'แผนงาน Schedule'!$B$7:$B$156,B19),'ตั้งค่า Setup'!$C$15))
A20: =IF(B20="","",14) | B20: =IF('ตั้งค่า Setup'!$C$39="","",'ตั้งค่า Setup'!$C$39) | C20: =IF(B20="","",COUNTIFS('แผนงาน Schedule'!$B$7:$B$156,B20,'แผนงาน Schedule'!$D$7:$D$156,"<>")) | D20: =IF(B20="","",SUMIF('แผนงาน Schedule'!$B$7:$B$156,B20,'แผนงาน Schedule'!$H$7:$H$156)) | E20: =IF(B20="","",SUMIF('แผนงาน Schedule'!$B$7:$B$156,B20,'แผนงาน Schedule'!$G$7:$G$156)) | F20: =IF(OR(B20="",N(C20)=0),"",_xlfn.MINIFS('แผนงาน Schedule'!$I$7:$I$156,'แผนงาน Schedule'!$B$7:$B$156,B20)) | G20: =IF(OR(B20="",N(C20)=0),"",_xlfn.MAXIFS('แผนงาน Schedule'!$J$7:$J$156,'แผนงาน Schedule'!$B$7:$B$156,B20)) | H20: =IF(OR(B20="",COUNTIFS('แผนงาน Schedule'!$B$7:$B$156,B20,'แผนงาน Schedule'!$N$7:$N$156,"<>")=0),"",_xlfn.MINIFS('แผนงาน Schedule'!$N$7:$N$156,'แผนงาน Schedule'!$B$7:$B$156,B20)) | I20: =IF(OR(B20="",N(E20)=0),"",SUMPRODUCT(('แผนงาน Schedule'!$B$7:$B$156=B20)*'แผนงาน Schedule'!$G$7:$G$156*(('แผนงาน Schedule'!$J$7:$J$156<=Dashboard!$C$7)+('แผนงาน Schedule'!$I$7:$I$156<=Dashboard!$C$7)*('แผนงาน Schedule'!$J$7:$J$156>Dashboard!$C$7)*(Dashboard!$C$7-'แผนงาน Schedule'!$I$7:$I$156+1)/('แผนงาน Schedule'!$J$7:$J$156-'แผนงาน Schedule'!$I$7:$I$156+1)))/E20) | J20: =IF(OR(B20="",N(E20)=0),"",SUMPRODUCT(('แผนงาน Schedule'!$B$7:$B$156=B20)*'แผนงาน Schedule'!$G$7:$G$156*'แผนงาน Schedule'!$P$7:$P$156)/E20) | K20: =IF(I20="","",J20-I20) | L20: =IF(OR(I20="",N(I20)=0),"",J20/I20) | M20: =IF(OR(B20="",N(C20)=0),"",_xlfn.MAXIFS('แผนงาน Schedule'!$W$7:$W$156,'แผนงาน Schedule'!$B$7:$B$156,B20)) | N20: =IF(OR(M20="",G20=""),"",M20-G20) | O20: =IF(B20="","",COUNTIFS('แผนงาน Schedule'!$B$7:$B$156,B20,'แผนงาน Schedule'!$Y$7:$Y$156,"*ล่าช้า*")+COUNTIFS('แผนงาน Schedule'!$B$7:$B$156,B20,'แผนงาน Schedule'!$Y$7:$Y$156,"*เกินกำหนด*")) | P20: =IF(OR(B20="",N(C20)=0),"",IF(N(J20)>=1,"แล้วเสร็จ / Completed",IF(AND(N(I20)=0,N(J20)=0),"ยังไม่เริ่ม / Not Started",IF(N(J20)>=N(I20),"ตามแผน / On Track",IF(N(J20)/I20>=0.9,"เฝ้าระวัง / At Risk","ล่าช้า / Behind"))))) | Q20: =IF(B20="","",N(I20)*N(E20)) | R20: =IF(B20="","",N(J20)*N(E20)) | S20: =IF(H20="","",IF(COUNTIFS('แผนงาน Schedule'!$B$7:$B$156,B20,'แผนงาน Schedule'!$D$7:$D$156,"<>",'แผนงาน Schedule'!$O$7:$O$156,"")=0,_xlfn.MAXIFS('แผนงาน Schedule'!$O$7:$O$156,'แผนงาน Schedule'!$B$7:$B$156,B20),'ตั้งค่า Setup'!$C$15))
A21: =IF(B21="","",15) | B21: =IF('ตั้งค่า Setup'!$C$40="","",'ตั้งค่า Setup'!$C$40) | C21: =IF(B21="","",COUNTIFS('แผนงาน Schedule'!$B$7:$B$156,B21,'แผนงาน Schedule'!$D$7:$D$156,"<>")) | D21: =IF(B21="","",SUMIF('แผนงาน Schedule'!$B$7:$B$156,B21,'แผนงาน Schedule'!$H$7:$H$156)) | E21: =IF(B21="","",SUMIF('แผนงาน Schedule'!$B$7:$B$156,B21,'แผนงาน Schedule'!$G$7:$G$156)) | F21: =IF(OR(B21="",N(C21)=0),"",_xlfn.MINIFS('แผนงาน Schedule'!$I$7:$I$156,'แผนงาน Schedule'!$B$7:$B$156,B21)) | G21: =IF(OR(B21="",N(C21)=0),"",_xlfn.MAXIFS('แผนงาน Schedule'!$J$7:$J$156,'แผนงาน Schedule'!$B$7:$B$156,B21)) | H21: =IF(OR(B21="",COUNTIFS('แผนงาน Schedule'!$B$7:$B$156,B21,'แผนงาน Schedule'!$N$7:$N$156,"<>")=0),"",_xlfn.MINIFS('แผนงาน Schedule'!$N$7:$N$156,'แผนงาน Schedule'!$B$7:$B$156,B21)) | I21: =IF(OR(B21="",N(E21)=0),"",SUMPRODUCT(('แผนงาน Schedule'!$B$7:$B$156=B21)*'แผนงาน Schedule'!$G$7:$G$156*(('แผนงาน Schedule'!$J$7:$J$156<=Dashboard!$C$7)+('แผนงาน Schedule'!$I$7:$I$156<=Dashboard!$C$7)*('แผนงาน Schedule'!$J$7:$J$156>Dashboard!$C$7)*(Dashboard!$C$7-'แผนงาน Schedule'!$I$7:$I$156+1)/('แผนงาน Schedule'!$J$7:$J$156-'แผนงาน Schedule'!$I$7:$I$156+1)))/E21) | J21: =IF(OR(B21="",N(E21)=0),"",SUMPRODUCT(('แผนงาน Schedule'!$B$7:$B$156=B21)*'แผนงาน Schedule'!$G$7:$G$156*'แผนงาน Schedule'!$P$7:$P$156)/E21) | K21: =IF(I21="","",J21-I21) | L21: =IF(OR(I21="",N(I21)=0),"",J21/I21) | M21: =IF(OR(B21="",N(C21)=0),"",_xlfn.MAXIFS('แผนงาน Schedule'!$W$7:$W$156,'แผนงาน Schedule'!$B$7:$B$156,B21)) | N21: =IF(OR(M21="",G21=""),"",M21-G21) | O21: =IF(B21="","",COUNTIFS('แผนงาน Schedule'!$B$7:$B$156,B21,'แผนงาน Schedule'!$Y$7:$Y$156,"*ล่าช้า*")+COUNTIFS('แผนงาน Schedule'!$B$7:$B$156,B21,'แผนงาน Schedule'!$Y$7:$Y$156,"*เกินกำหนด*")) | P21: =IF(OR(B21="",N(C21)=0),"",IF(N(J21)>=1,"แล้วเสร็จ / Completed",IF(AND(N(I21)=0,N(J21)=0),"ยังไม่เริ่ม / Not Started",IF(N(J21)>=N(I21),"ตามแผน / On Track",IF(N(J21)/I21>=0.9,"เฝ้าระวัง / At Risk","ล่าช้า / Behind"))))) | Q21: =IF(B21="","",N(I21)*N(E21)) | R21: =IF(B21="","",N(J21)*N(E21)) | S21: =IF(H21="","",IF(COUNTIFS('แผนงาน Schedule'!$B$7:$B$156,B21,'แผนงาน Schedule'!$D$7:$D$156,"<>",'แผนงาน Schedule'!$O$7:$O$156,"")=0,_xlfn.MAXIFS('แผนงาน Schedule'!$O$7:$O$156,'แผนงาน Schedule'!$B$7:$B$156,B21),'ตั้งค่า Setup'!$C$15))
A22: =IF(B22="","",16) | B22: =IF('ตั้งค่า Setup'!$C$41="","",'ตั้งค่า Setup'!$C$41) | C22: =IF(B22="","",COUNTIFS('แผนงาน Schedule'!$B$7:$B$156,B22,'แผนงาน Schedule'!$D$7:$D$156,"<>")) | D22: =IF(B22="","",SUMIF('แผนงาน Schedule'!$B$7:$B$156,B22,'แผนงาน Schedule'!$H$7:$H$156)) | E22: =IF(B22="","",SUMIF('แผนงาน Schedule'!$B$7:$B$156,B22,'แผนงาน Schedule'!$G$7:$G$156)) | F22: =IF(OR(B22="",N(C22)=0),"",_xlfn.MINIFS('แผนงาน Schedule'!$I$7:$I$156,'แผนงาน Schedule'!$B$7:$B$156,B22)) | G22: =IF(OR(B22="",N(C22)=0),"",_xlfn.MAXIFS('แผนงาน Schedule'!$J$7:$J$156,'แผนงาน Schedule'!$B$7:$B$156,B22)) | H22: =IF(OR(B22="",COUNTIFS('แผนงาน Schedule'!$B$7:$B$156,B22,'แผนงาน Schedule'!$N$7:$N$156,"<>")=0),"",_xlfn.MINIFS('แผนงาน Schedule'!$N$7:$N$156,'แผนงาน Schedule'!$B$7:$B$156,B22)) | I22: =IF(OR(B22="",N(E22)=0),"",SUMPRODUCT(('แผนงาน Schedule'!$B$7:$B$156=B22)*'แผนงาน Schedule'!$G$7:$G$156*(('แผนงาน Schedule'!$J$7:$J$156<=Dashboard!$C$7)+('แผนงาน Schedule'!$I$7:$I$156<=Dashboard!$C$7)*('แผนงาน Schedule'!$J$7:$J$156>Dashboard!$C$7)*(Dashboard!$C$7-'แผนงาน Schedule'!$I$7:$I$156+1)/('แผนงาน Schedule'!$J$7:$J$156-'แผนงาน Schedule'!$I$7:$I$156+1)))/E22) | J22: =IF(OR(B22="",N(E22)=0),"",SUMPRODUCT(('แผนงาน Schedule'!$B$7:$B$156=B22)*'แผนงาน Schedule'!$G$7:$G$156*'แผนงาน Schedule'!$P$7:$P$156)/E22) | K22: =IF(I22="","",J22-I22) | L22: =IF(OR(I22="",N(I22)=0),"",J22/I22) | M22: =IF(OR(B22="",N(C22)=0),"",_xlfn.MAXIFS('แผนงาน Schedule'!$W$7:$W$156,'แผนงาน Schedule'!$B$7:$B$156,B22)) | N22: =IF(OR(M22="",G22=""),"",M22-G22) | O22: =IF(B22="","",COUNTIFS('แผนงาน Schedule'!$B$7:$B$156,B22,'แผนงาน Schedule'!$Y$7:$Y$156,"*ล่าช้า*")+COUNTIFS('แผนงาน Schedule'!$B$7:$B$156,B22,'แผนงาน Schedule'!$Y$7:$Y$156,"*เกินกำหนด*")) | P22: =IF(OR(B22="",N(C22)=0),"",IF(N(J22)>=1,"แล้วเสร็จ / Completed",IF(AND(N(I22)=0,N(J22)=0),"ยังไม่เริ่ม / Not Started",IF(N(J22)>=N(I22),"ตามแผน / On Track",IF(N(J22)/I22>=0.9,"เฝ้าระวัง / At Risk","ล่าช้า / Behind"))))) | Q22: =IF(B22="","",N(I22)*N(E22)) | R22: =IF(B22="","",N(J22)*N(E22)) | S22: =IF(H22="","",IF(COUNTIFS('แผนงาน Schedule'!$B$7:$B$156,B22,'แผนงาน Schedule'!$D$7:$D$156,"<>",'แผนงาน Schedule'!$O$7:$O$156,"")=0,_xlfn.MAXIFS('แผนงาน Schedule'!$O$7:$O$156,'แผนงาน Schedule'!$B$7:$B$156,B22),'ตั้งค่า Setup'!$C$15))
A23: =IF(B23="","",17) | B23: =IF('ตั้งค่า Setup'!$C$42="","",'ตั้งค่า Setup'!$C$42) | C23: =IF(B23="","",COUNTIFS('แผนงาน Schedule'!$B$7:$B$156,B23,'แผนงาน Schedule'!$D$7:$D$156,"<>")) | D23: =IF(B23="","",SUMIF('แผนงาน Schedule'!$B$7:$B$156,B23,'แผนงาน Schedule'!$H$7:$H$156)) | E23: =IF(B23="","",SUMIF('แผนงาน Schedule'!$B$7:$B$156,B23,'แผนงาน Schedule'!$G$7:$G$156)) | F23: =IF(OR(B23="",N(C23)=0),"",_xlfn.MINIFS('แผนงาน Schedule'!$I$7:$I$156,'แผนงาน Schedule'!$B$7:$B$156,B23)) | G23: =IF(OR(B23="",N(C23)=0),"",_xlfn.MAXIFS('แผนงาน Schedule'!$J$7:$J$156,'แผนงาน Schedule'!$B$7:$B$156,B23)) | H23: =IF(OR(B23="",COUNTIFS('แผนงาน Schedule'!$B$7:$B$156,B23,'แผนงาน Schedule'!$N$7:$N$156,"<>")=0),"",_xlfn.MINIFS('แผนงาน Schedule'!$N$7:$N$156,'แผนงาน Schedule'!$B$7:$B$156,B23)) | I23: =IF(OR(B23="",N(E23)=0),"",SUMPRODUCT(('แผนงาน Schedule'!$B$7:$B$156=B23)*'แผนงาน Schedule'!$G$7:$G$156*(('แผนงาน Schedule'!$J$7:$J$156<=Dashboard!$C$7)+('แผนงาน Schedule'!$I$7:$I$156<=Dashboard!$C$7)*('แผนงาน Schedule'!$J$7:$J$156>Dashboard!$C$7)*(Dashboard!$C$7-'แผนงาน Schedule'!$I$7:$I$156+1)/('แผนงาน Schedule'!$J$7:$J$156-'แผนงาน Schedule'!$I$7:$I$156+1)))/E23) | J23: =IF(OR(B23="",N(E23)=0),"",SUMPRODUCT(('แผนงาน Schedule'!$B$7:$B$156=B23)*'แผนงาน Schedule'!$G$7:$G$156*'แผนงาน Schedule'!$P$7:$P$156)/E23) | K23: =IF(I23="","",J23-I23) | L23: =IF(OR(I23="",N(I23)=0),"",J23/I23) | M23: =IF(OR(B23="",N(C23)=0),"",_xlfn.MAXIFS('แผนงาน Schedule'!$W$7:$W$156,'แผนงาน Schedule'!$B$7:$B$156,B23)) | N23: =IF(OR(M23="",G23=""),"",M23-G23) | O23: =IF(B23="","",COUNTIFS('แผนงาน Schedule'!$B$7:$B$156,B23,'แผนงาน Schedule'!$Y$7:$Y$156,"*ล่าช้า*")+COUNTIFS('แผนงาน Schedule'!$B$7:$B$156,B23,'แผนงาน Schedule'!$Y$7:$Y$156,"*เกินกำหนด*")) | P23: =IF(OR(B23="",N(C23)=0),"",IF(N(J23)>=1,"แล้วเสร็จ / Completed",IF(AND(N(I23)=0,N(J23)=0),"ยังไม่เริ่ม / Not Started",IF(N(J23)>=N(I23),"ตามแผน / On Track",IF(N(J23)/I23>=0.9,"เฝ้าระวัง / At Risk","ล่าช้า / Behind"))))) | Q23: =IF(B23="","",N(I23)*N(E23)) | R23: =IF(B23="","",N(J23)*N(E23)) | S23: =IF(H23="","",IF(COUNTIFS('แผนงาน Schedule'!$B$7:$B$156,B23,'แผนงาน Schedule'!$D$7:$D$156,"<>",'แผนงาน Schedule'!$O$7:$O$156,"")=0,_xlfn.MAXIFS('แผนงาน Schedule'!$O$7:$O$156,'แผนงาน Schedule'!$B$7:$B$156,B23),'ตั้งค่า Setup'!$C$15))
A24: =IF(B24="","",18) | B24: =IF('ตั้งค่า Setup'!$C$43="","",'ตั้งค่า Setup'!$C$43) | C24: =IF(B24="","",COUNTIFS('แผนงาน Schedule'!$B$7:$B$156,B24,'แผนงาน Schedule'!$D$7:$D$156,"<>")) | D24: =IF(B24="","",SUMIF('แผนงาน Schedule'!$B$7:$B$156,B24,'แผนงาน Schedule'!$H$7:$H$156)) | E24: =IF(B24="","",SUMIF('แผนงาน Schedule'!$B$7:$B$156,B24,'แผนงาน Schedule'!$G$7:$G$156)) | F24: =IF(OR(B24="",N(C24)=0),"",_xlfn.MINIFS('แผนงาน Schedule'!$I$7:$I$156,'แผนงาน Schedule'!$B$7:$B$156,B24)) | G24: =IF(OR(B24="",N(C24)=0),"",_xlfn.MAXIFS('แผนงาน Schedule'!$J$7:$J$156,'แผนงาน Schedule'!$B$7:$B$156,B24)) | H24: =IF(OR(B24="",COUNTIFS('แผนงาน Schedule'!$B$7:$B$156,B24,'แผนงาน Schedule'!$N$7:$N$156,"<>")=0),"",_xlfn.MINIFS('แผนงาน Schedule'!$N$7:$N$156,'แผนงาน Schedule'!$B$7:$B$156,B24)) | I24: =IF(OR(B24="",N(E24)=0),"",SUMPRODUCT(('แผนงาน Schedule'!$B$7:$B$156=B24)*'แผนงาน Schedule'!$G$7:$G$156*(('แผนงาน Schedule'!$J$7:$J$156<=Dashboard!$C$7)+('แผนงาน Schedule'!$I$7:$I$156<=Dashboard!$C$7)*('แผนงาน Schedule'!$J$7:$J$156>Dashboard!$C$7)*(Dashboard!$C$7-'แผนงาน Schedule'!$I$7:$I$156+1)/('แผนงาน Schedule'!$J$7:$J$156-'แผนงาน Schedule'!$I$7:$I$156+1)))/E24) | J24: =IF(OR(B24="",N(E24)=0),"",SUMPRODUCT(('แผนงาน Schedule'!$B$7:$B$156=B24)*'แผนงาน Schedule'!$G$7:$G$156*'แผนงาน Schedule'!$P$7:$P$156)/E24) | K24: =IF(I24="","",J24-I24) | L24: =IF(OR(I24="",N(I24)=0),"",J24/I24) | M24: =IF(OR(B24="",N(C24)=0),"",_xlfn.MAXIFS('แผนงาน Schedule'!$W$7:$W$156,'แผนงาน Schedule'!$B$7:$B$156,B24)) | N24: =IF(OR(M24="",G24=""),"",M24-G24) | O24: =IF(B24="","",COUNTIFS('แผนงาน Schedule'!$B$7:$B$156,B24,'แผนงาน Schedule'!$Y$7:$Y$156,"*ล่าช้า*")+COUNTIFS('แผนงาน Schedule'!$B$7:$B$156,B24,'แผนงาน Schedule'!$Y$7:$Y$156,"*เกินกำหนด*")) | P24: =IF(OR(B24="",N(C24)=0),"",IF(N(J24)>=1,"แล้วเสร็จ / Completed",IF(AND(N(I24)=0,N(J24)=0),"ยังไม่เริ่ม / Not Started",IF(N(J24)>=N(I24),"ตามแผน / On Track",IF(N(J24)/I24>=0.9,"เฝ้าระวัง / At Risk","ล่าช้า / Behind"))))) | Q24: =IF(B24="","",N(I24)*N(E24)) | R24: =IF(B24="","",N(J24)*N(E24)) | S24: =IF(H24="","",IF(COUNTIFS('แผนงาน Schedule'!$B$7:$B$156,B24,'แผนงาน Schedule'!$D$7:$D$156,"<>",'แผนงาน Schedule'!$O$7:$O$156,"")=0,_xlfn.MAXIFS('แผนงาน Schedule'!$O$7:$O$156,'แผนงาน Schedule'!$B$7:$B$156,B24),'ตั้งค่า Setup'!$C$15))
A25: =IF(B25="","",19) | B25: =IF('ตั้งค่า Setup'!$C$44="","",'ตั้งค่า Setup'!$C$44) | C25: =IF(B25="","",COUNTIFS('แผนงาน Schedule'!$B$7:$B$156,B25,'แผนงาน Schedule'!$D$7:$D$156,"<>")) | D25: =IF(B25="","",SUMIF('แผนงาน Schedule'!$B$7:$B$156,B25,'แผนงาน Schedule'!$H$7:$H$156)) | E25: =IF(B25="","",SUMIF('แผนงาน Schedule'!$B$7:$B$156,B25,'แผนงาน Schedule'!$G$7:$G$156)) | F25: =IF(OR(B25="",N(C25)=0),"",_xlfn.MINIFS('แผนงาน Schedule'!$I$7:$I$156,'แผนงาน Schedule'!$B$7:$B$156,B25)) | G25: =IF(OR(B25="",N(C25)=0),"",_xlfn.MAXIFS('แผนงาน Schedule'!$J$7:$J$156,'แผนงาน Schedule'!$B$7:$B$156,B25)) | H25: =IF(OR(B25="",COUNTIFS('แผนงาน Schedule'!$B$7:$B$156,B25,'แผนงาน Schedule'!$N$7:$N$156,"<>")=0),"",_xlfn.MINIFS('แผนงาน Schedule'!$N$7:$N$156,'แผนงาน Schedule'!$B$7:$B$156,B25)) | I25: =IF(OR(B25="",N(E25)=0),"",SUMPRODUCT(('แผนงาน Schedule'!$B$7:$B$156=B25)*'แผนงาน Schedule'!$G$7:$G$156*(('แผนงาน Schedule'!$J$7:$J$156<=Dashboard!$C$7)+('แผนงาน Schedule'!$I$7:$I$156<=Dashboard!$C$7)*('แผนงาน Schedule'!$J$7:$J$156>Dashboard!$C$7)*(Dashboard!$C$7-'แผนงาน Schedule'!$I$7:$I$156+1)/('แผนงาน Schedule'!$J$7:$J$156-'แผนงาน Schedule'!$I$7:$I$156+1)))/E25) | J25: =IF(OR(B25="",N(E25)=0),"",SUMPRODUCT(('แผนงาน Schedule'!$B$7:$B$156=B25)*'แผนงาน Schedule'!$G$7:$G$156*'แผนงาน Schedule'!$P$7:$P$156)/E25) | K25: =IF(I25="","",J25-I25) | L25: =IF(OR(I25="",N(I25)=0),"",J25/I25) | M25: =IF(OR(B25="",N(C25)=0),"",_xlfn.MAXIFS('แผนงาน Schedule'!$W$7:$W$156,'แผนงาน Schedule'!$B$7:$B$156,B25)) | N25: =IF(OR(M25="",G25=""),"",M25-G25) | O25: =IF(B25="","",COUNTIFS('แผนงาน Schedule'!$B$7:$B$156,B25,'แผนงาน Schedule'!$Y$7:$Y$156,"*ล่าช้า*")+COUNTIFS('แผนงาน Schedule'!$B$7:$B$156,B25,'แผนงาน Schedule'!$Y$7:$Y$156,"*เกินกำหนด*")) | P25: =IF(OR(B25="",N(C25)=0),"",IF(N(J25)>=1,"แล้วเสร็จ / Completed",IF(AND(N(I25)=0,N(J25)=0),"ยังไม่เริ่ม / Not Started",IF(N(J25)>=N(I25),"ตามแผน / On Track",IF(N(J25)/I25>=0.9,"เฝ้าระวัง / At Risk","ล่าช้า / Behind"))))) | Q25: =IF(B25="","",N(I25)*N(E25)) | R25: =IF(B25="","",N(J25)*N(E25)) | S25: =IF(H25="","",IF(COUNTIFS('แผนงาน Schedule'!$B$7:$B$156,B25,'แผนงาน Schedule'!$D$7:$D$156,"<>",'แผนงาน Schedule'!$O$7:$O$156,"")=0,_xlfn.MAXIFS('แผนงาน Schedule'!$O$7:$O$156,'แผนงาน Schedule'!$B$7:$B$156,B25),'ตั้งค่า Setup'!$C$15))
A26: =IF(B26="","",20) | B26: =IF('ตั้งค่า Setup'!$C$45="","",'ตั้งค่า Setup'!$C$45) | C26: =IF(B26="","",COUNTIFS('แผนงาน Schedule'!$B$7:$B$156,B26,'แผนงาน Schedule'!$D$7:$D$156,"<>")) | D26: =IF(B26="","",SUMIF('แผนงาน Schedule'!$B$7:$B$156,B26,'แผนงาน Schedule'!$H$7:$H$156)) | E26: =IF(B26="","",SUMIF('แผนงาน Schedule'!$B$7:$B$156,B26,'แผนงาน Schedule'!$G$7:$G$156)) | F26: =IF(OR(B26="",N(C26)=0),"",_xlfn.MINIFS('แผนงาน Schedule'!$I$7:$I$156,'แผนงาน Schedule'!$B$7:$B$156,B26)) | G26: =IF(OR(B26="",N(C26)=0),"",_xlfn.MAXIFS('แผนงาน Schedule'!$J$7:$J$156,'แผนงาน Schedule'!$B$7:$B$156,B26)) | H26: =IF(OR(B26="",COUNTIFS('แผนงาน Schedule'!$B$7:$B$156,B26,'แผนงาน Schedule'!$N$7:$N$156,"<>")=0),"",_xlfn.MINIFS('แผนงาน Schedule'!$N$7:$N$156,'แผนงาน Schedule'!$B$7:$B$156,B26)) | I26: =IF(OR(B26="",N(E26)=0),"",SUMPRODUCT(('แผนงาน Schedule'!$B$7:$B$156=B26)*'แผนงาน Schedule'!$G$7:$G$156*(('แผนงาน Schedule'!$J$7:$J$156<=Dashboard!$C$7)+('แผนงาน Schedule'!$I$7:$I$156<=Dashboard!$C$7)*('แผนงาน Schedule'!$J$7:$J$156>Dashboard!$C$7)*(Dashboard!$C$7-'แผนงาน Schedule'!$I$7:$I$156+1)/('แผนงาน Schedule'!$J$7:$J$156-'แผนงาน Schedule'!$I$7:$I$156+1)))/E26) | J26: =IF(OR(B26="",N(E26)=0),"",SUMPRODUCT(('แผนงาน Schedule'!$B$7:$B$156=B26)*'แผนงาน Schedule'!$G$7:$G$156*'แผนงาน Schedule'!$P$7:$P$156)/E26) | K26: =IF(I26="","",J26-I26) | L26: =IF(OR(I26="",N(I26)=0),"",J26/I26) | M26: =IF(OR(B26="",N(C26)=0),"",_xlfn.MAXIFS('แผนงาน Schedule'!$W$7:$W$156,'แผนงาน Schedule'!$B$7:$B$156,B26)) | N26: =IF(OR(M26="",G26=""),"",M26-G26) | O26: =IF(B26="","",COUNTIFS('แผนงาน Schedule'!$B$7:$B$156,B26,'แผนงาน Schedule'!$Y$7:$Y$156,"*ล่าช้า*")+COUNTIFS('แผนงาน Schedule'!$B$7:$B$156,B26,'แผนงาน Schedule'!$Y$7:$Y$156,"*เกินกำหนด*")) | P26: =IF(OR(B26="",N(C26)=0),"",IF(N(J26)>=1,"แล้วเสร็จ / Completed",IF(AND(N(I26)=0,N(J26)=0),"ยังไม่เริ่ม / Not Started",IF(N(J26)>=N(I26),"ตามแผน / On Track",IF(N(J26)/I26>=0.9,"เฝ้าระวัง / At Risk","ล่าช้า / Behind"))))) | Q26: =IF(B26="","",N(I26)*N(E26)) | R26: =IF(B26="","",N(J26)*N(E26)) | S26: =IF(H26="","",IF(COUNTIFS('แผนงาน Schedule'!$B$7:$B$156,B26,'แผนงาน Schedule'!$D$7:$D$156,"<>",'แผนงาน Schedule'!$O$7:$O$156,"")=0,_xlfn.MAXIFS('แผนงาน Schedule'!$O$7:$O$156,'แผนงาน Schedule'!$B$7:$B$156,B26),'ตั้งค่า Setup'!$C$15))
A27: =IF(B27="","",21) | B27: =IF('ตั้งค่า Setup'!$C$46="","",'ตั้งค่า Setup'!$C$46) | C27: =IF(B27="","",COUNTIFS('แผนงาน Schedule'!$B$7:$B$156,B27,'แผนงาน Schedule'!$D$7:$D$156,"<>")) | D27: =IF(B27="","",SUMIF('แผนงาน Schedule'!$B$7:$B$156,B27,'แผนงาน Schedule'!$H$7:$H$156)) | E27: =IF(B27="","",SUMIF('แผนงาน Schedule'!$B$7:$B$156,B27,'แผนงาน Schedule'!$G$7:$G$156)) | F27: =IF(OR(B27="",N(C27)=0),"",_xlfn.MINIFS('แผนงาน Schedule'!$I$7:$I$156,'แผนงาน Schedule'!$B$7:$B$156,B27)) | G27: =IF(OR(B27="",N(C27)=0),"",_xlfn.MAXIFS('แผนงาน Schedule'!$J$7:$J$156,'แผนงาน Schedule'!$B$7:$B$156,B27)) | H27: =IF(OR(B27="",COUNTIFS('แผนงาน Schedule'!$B$7:$B$156,B27,'แผนงาน Schedule'!$N$7:$N$156,"<>")=0),"",_xlfn.MINIFS('แผนงาน Schedule'!$N$7:$N$156,'แผนงาน Schedule'!$B$7:$B$156,B27)) | I27: =IF(OR(B27="",N(E27)=0),"",SUMPRODUCT(('แผนงาน Schedule'!$B$7:$B$156=B27)*'แผนงาน Schedule'!$G$7:$G$156*(('แผนงาน Schedule'!$J$7:$J$156<=Dashboard!$C$7)+('แผนงาน Schedule'!$I$7:$I$156<=Dashboard!$C$7)*('แผนงาน Schedule'!$J$7:$J$156>Dashboard!$C$7)*(Dashboard!$C$7-'แผนงาน Schedule'!$I$7:$I$156+1)/('แผนงาน Schedule'!$J$7:$J$156-'แผนงาน Schedule'!$I$7:$I$156+1)))/E27) | J27: =IF(OR(B27="",N(E27)=0),"",SUMPRODUCT(('แผนงาน Schedule'!$B$7:$B$156=B27)*'แผนงาน Schedule'!$G$7:$G$156*'แผนงาน Schedule'!$P$7:$P$156)/E27) | K27: =IF(I27="","",J27-I27) | L27: =IF(OR(I27="",N(I27)=0),"",J27/I27) | M27: =IF(OR(B27="",N(C27)=0),"",_xlfn.MAXIFS('แผนงาน Schedule'!$W$7:$W$156,'แผนงาน Schedule'!$B$7:$B$156,B27)) | N27: =IF(OR(M27="",G27=""),"",M27-G27) | O27: =IF(B27="","",COUNTIFS('แผนงาน Schedule'!$B$7:$B$156,B27,'แผนงาน Schedule'!$Y$7:$Y$156,"*ล่าช้า*")+COUNTIFS('แผนงาน Schedule'!$B$7:$B$156,B27,'แผนงาน Schedule'!$Y$7:$Y$156,"*เกินกำหนด*")) | P27: =IF(OR(B27="",N(C27)=0),"",IF(N(J27)>=1,"แล้วเสร็จ / Completed",IF(AND(N(I27)=0,N(J27)=0),"ยังไม่เริ่ม / Not Started",IF(N(J27)>=N(I27),"ตามแผน / On Track",IF(N(J27)/I27>=0.9,"เฝ้าระวัง / At Risk","ล่าช้า / Behind"))))) | Q27: =IF(B27="","",N(I27)*N(E27)) | R27: =IF(B27="","",N(J27)*N(E27)) | S27: =IF(H27="","",IF(COUNTIFS('แผนงาน Schedule'!$B$7:$B$156,B27,'แผนงาน Schedule'!$D$7:$D$156,"<>",'แผนงาน Schedule'!$O$7:$O$156,"")=0,_xlfn.MAXIFS('แผนงาน Schedule'!$O$7:$O$156,'แผนงาน Schedule'!$B$7:$B$156,B27),'ตั้งค่า Setup'!$C$15))
A28: =IF(B28="","",22) | B28: =IF('ตั้งค่า Setup'!$C$47="","",'ตั้งค่า Setup'!$C$47) | C28: =IF(B28="","",COUNTIFS('แผนงาน Schedule'!$B$7:$B$156,B28,'แผนงาน Schedule'!$D$7:$D$156,"<>")) | D28: =IF(B28="","",SUMIF('แผนงาน Schedule'!$B$7:$B$156,B28,'แผนงาน Schedule'!$H$7:$H$156)) | E28: =IF(B28="","",SUMIF('แผนงาน Schedule'!$B$7:$B$156,B28,'แผนงาน Schedule'!$G$7:$G$156)) | F28: =IF(OR(B28="",N(C28)=0),"",_xlfn.MINIFS('แผนงาน Schedule'!$I$7:$I$156,'แผนงาน Schedule'!$B$7:$B$156,B28)) | G28: =IF(OR(B28="",N(C28)=0),"",_xlfn.MAXIFS('แผนงาน Schedule'!$J$7:$J$156,'แผนงาน Schedule'!$B$7:$B$156,B28)) | H28: =IF(OR(B28="",COUNTIFS('แผนงาน Schedule'!$B$7:$B$156,B28,'แผนงาน Schedule'!$N$7:$N$156,"<>")=0),"",_xlfn.MINIFS('แผนงาน Schedule'!$N$7:$N$156,'แผนงาน Schedule'!$B$7:$B$156,B28)) | I28: =IF(OR(B28="",N(E28)=0),"",SUMPRODUCT(('แผนงาน Schedule'!$B$7:$B$156=B28)*'แผนงาน Schedule'!$G$7:$G$156*(('แผนงาน Schedule'!$J$7:$J$156<=Dashboard!$C$7)+('แผนงาน Schedule'!$I$7:$I$156<=Dashboard!$C$7)*('แผนงาน Schedule'!$J$7:$J$156>Dashboard!$C$7)*(Dashboard!$C$7-'แผนงาน Schedule'!$I$7:$I$156+1)/('แผนงาน Schedule'!$J$7:$J$156-'แผนงาน Schedule'!$I$7:$I$156+1)))/E28) | J28: =IF(OR(B28="",N(E28)=0),"",SUMPRODUCT(('แผนงาน Schedule'!$B$7:$B$156=B28)*'แผนงาน Schedule'!$G$7:$G$156*'แผนงาน Schedule'!$P$7:$P$156)/E28) | K28: =IF(I28="","",J28-I28) | L28: =IF(OR(I28="",N(I28)=0),"",J28/I28) | M28: =IF(OR(B28="",N(C28)=0),"",_xlfn.MAXIFS('แผนงาน Schedule'!$W$7:$W$156,'แผนงาน Schedule'!$B$7:$B$156,B28)) | N28: =IF(OR(M28="",G28=""),"",M28-G28) | O28: =IF(B28="","",COUNTIFS('แผนงาน Schedule'!$B$7:$B$156,B28,'แผนงาน Schedule'!$Y$7:$Y$156,"*ล่าช้า*")+COUNTIFS('แผนงาน Schedule'!$B$7:$B$156,B28,'แผนงาน Schedule'!$Y$7:$Y$156,"*เกินกำหนด*")) | P28: =IF(OR(B28="",N(C28)=0),"",IF(N(J28)>=1,"แล้วเสร็จ / Completed",IF(AND(N(I28)=0,N(J28)=0),"ยังไม่เริ่ม / Not Started",IF(N(J28)>=N(I28),"ตามแผน / On Track",IF(N(J28)/I28>=0.9,"เฝ้าระวัง / At Risk","ล่าช้า / Behind"))))) | Q28: =IF(B28="","",N(I28)*N(E28)) | R28: =IF(B28="","",N(J28)*N(E28)) | S28: =IF(H28="","",IF(COUNTIFS('แผนงาน Schedule'!$B$7:$B$156,B28,'แผนงาน Schedule'!$D$7:$D$156,"<>",'แผนงาน Schedule'!$O$7:$O$156,"")=0,_xlfn.MAXIFS('แผนงาน Schedule'!$O$7:$O$156,'แผนงาน Schedule'!$B$7:$B$156,B28),'ตั้งค่า Setup'!$C$15))
A29: =IF(B29="","",23) | B29: =IF('ตั้งค่า Setup'!$C$48="","",'ตั้งค่า Setup'!$C$48) | C29: =IF(B29="","",COUNTIFS('แผนงาน Schedule'!$B$7:$B$156,B29,'แผนงาน Schedule'!$D$7:$D$156,"<>")) | D29: =IF(B29="","",SUMIF('แผนงาน Schedule'!$B$7:$B$156,B29,'แผนงาน Schedule'!$H$7:$H$156)) | E29: =IF(B29="","",SUMIF('แผนงาน Schedule'!$B$7:$B$156,B29,'แผนงาน Schedule'!$G$7:$G$156)) | F29: =IF(OR(B29="",N(C29)=0),"",_xlfn.MINIFS('แผนงาน Schedule'!$I$7:$I$156,'แผนงาน Schedule'!$B$7:$B$156,B29)) | G29: =IF(OR(B29="",N(C29)=0),"",_xlfn.MAXIFS('แผนงาน Schedule'!$J$7:$J$156,'แผนงาน Schedule'!$B$7:$B$156,B29)) | H29: =IF(OR(B29="",COUNTIFS('แผนงาน Schedule'!$B$7:$B$156,B29,'แผนงาน Schedule'!$N$7:$N$156,"<>")=0),"",_xlfn.MINIFS('แผนงาน Schedule'!$N$7:$N$156,'แผนงาน Schedule'!$B$7:$B$156,B29)) | I29: =IF(OR(B29="",N(E29)=0),"",SUMPRODUCT(('แผนงาน Schedule'!$B$7:$B$156=B29)*'แผนงาน Schedule'!$G$7:$G$156*(('แผนงาน Schedule'!$J$7:$J$156<=Dashboard!$C$7)+('แผนงาน Schedule'!$I$7:$I$156<=Dashboard!$C$7)*('แผนงาน Schedule'!$J$7:$J$156>Dashboard!$C$7)*(Dashboard!$C$7-'แผนงาน Schedule'!$I$7:$I$156+1)/('แผนงาน Schedule'!$J$7:$J$156-'แผนงาน Schedule'!$I$7:$I$156+1)))/E29) | J29: =IF(OR(B29="",N(E29)=0),"",SUMPRODUCT(('แผนงาน Schedule'!$B$7:$B$156=B29)*'แผนงาน Schedule'!$G$7:$G$156*'แผนงาน Schedule'!$P$7:$P$156)/E29) | K29: =IF(I29="","",J29-I29) | L29: =IF(OR(I29="",N(I29)=0),"",J29/I29) | M29: =IF(OR(B29="",N(C29)=0),"",_xlfn.MAXIFS('แผนงาน Schedule'!$W$7:$W$156,'แผนงาน Schedule'!$B$7:$B$156,B29)) | N29: =IF(OR(M29="",G29=""),"",M29-G29) | O29: =IF(B29="","",COUNTIFS('แผนงาน Schedule'!$B$7:$B$156,B29,'แผนงาน Schedule'!$Y$7:$Y$156,"*ล่าช้า*")+COUNTIFS('แผนงาน Schedule'!$B$7:$B$156,B29,'แผนงาน Schedule'!$Y$7:$Y$156,"*เกินกำหนด*")) | P29: =IF(OR(B29="",N(C29)=0),"",IF(N(J29)>=1,"แล้วเสร็จ / Completed",IF(AND(N(I29)=0,N(J29)=0),"ยังไม่เริ่ม / Not Started",IF(N(J29)>=N(I29),"ตามแผน / On Track",IF(N(J29)/I29>=0.9,"เฝ้าระวัง / At Risk","ล่าช้า / Behind"))))) | Q29: =IF(B29="","",N(I29)*N(E29)) | R29: =IF(B29="","",N(J29)*N(E29)) | S29: =IF(H29="","",IF(COUNTIFS('แผนงาน Schedule'!$B$7:$B$156,B29,'แผนงาน Schedule'!$D$7:$D$156,"<>",'แผนงาน Schedule'!$O$7:$O$156,"")=0,_xlfn.MAXIFS('แผนงาน Schedule'!$O$7:$O$156,'แผนงาน Schedule'!$B$7:$B$156,B29),'ตั้งค่า Setup'!$C$15))
A30: =IF(B30="","",24) | B30: =IF('ตั้งค่า Setup'!$C$49="","",'ตั้งค่า Setup'!$C$49) | C30: =IF(B30="","",COUNTIFS('แผนงาน Schedule'!$B$7:$B$156,B30,'แผนงาน Schedule'!$D$7:$D$156,"<>")) | D30: =IF(B30="","",SUMIF('แผนงาน Schedule'!$B$7:$B$156,B30,'แผนงาน Schedule'!$H$7:$H$156)) | E30: =IF(B30="","",SUMIF('แผนงาน Schedule'!$B$7:$B$156,B30,'แผนงาน Schedule'!$G$7:$G$156)) | F30: =IF(OR(B30="",N(C30)=0),"",_xlfn.MINIFS('แผนงาน Schedule'!$I$7:$I$156,'แผนงาน Schedule'!$B$7:$B$156,B30)) | G30: =IF(OR(B30="",N(C30)=0),"",_xlfn.MAXIFS('แผนงาน Schedule'!$J$7:$J$156,'แผนงาน Schedule'!$B$7:$B$156,B30)) | H30: =IF(OR(B30="",COUNTIFS('แผนงาน Schedule'!$B$7:$B$156,B30,'แผนงาน Schedule'!$N$7:$N$156,"<>")=0),"",_xlfn.MINIFS('แผนงาน Schedule'!$N$7:$N$156,'แผนงาน Schedule'!$B$7:$B$156,B30)) | I30: =IF(OR(B30="",N(E30)=0),"",SUMPRODUCT(('แผนงาน Schedule'!$B$7:$B$156=B30)*'แผนงาน Schedule'!$G$7:$G$156*(('แผนงาน Schedule'!$J$7:$J$156<=Dashboard!$C$7)+('แผนงาน Schedule'!$I$7:$I$156<=Dashboard!$C$7)*('แผนงาน Schedule'!$J$7:$J$156>Dashboard!$C$7)*(Dashboard!$C$7-'แผนงาน Schedule'!$I$7:$I$156+1)/('แผนงาน Schedule'!$J$7:$J$156-'แผนงาน Schedule'!$I$7:$I$156+1)))/E30) | J30: =IF(OR(B30="",N(E30)=0),"",SUMPRODUCT(('แผนงาน Schedule'!$B$7:$B$156=B30)*'แผนงาน Schedule'!$G$7:$G$156*'แผนงาน Schedule'!$P$7:$P$156)/E30) | K30: =IF(I30="","",J30-I30) | L30: =IF(OR(I30="",N(I30)=0),"",J30/I30) | M30: =IF(OR(B30="",N(C30)=0),"",_xlfn.MAXIFS('แผนงาน Schedule'!$W$7:$W$156,'แผนงาน Schedule'!$B$7:$B$156,B30)) | N30: =IF(OR(M30="",G30=""),"",M30-G30) | O30: =IF(B30="","",COUNTIFS('แผนงาน Schedule'!$B$7:$B$156,B30,'แผนงาน Schedule'!$Y$7:$Y$156,"*ล่าช้า*")+COUNTIFS('แผนงาน Schedule'!$B$7:$B$156,B30,'แผนงาน Schedule'!$Y$7:$Y$156,"*เกินกำหนด*")) | P30: =IF(OR(B30="",N(C30)=0),"",IF(N(J30)>=1,"แล้วเสร็จ / Completed",IF(AND(N(I30)=0,N(J30)=0),"ยังไม่เริ่ม / Not Started",IF(N(J30)>=N(I30),"ตามแผน / On Track",IF(N(J30)/I30>=0.9,"เฝ้าระวัง / At Risk","ล่าช้า / Behind"))))) | Q30: =IF(B30="","",N(I30)*N(E30)) | R30: =IF(B30="","",N(J30)*N(E30)) | S30: =IF(H30="","",IF(COUNTIFS('แผนงาน Schedule'!$B$7:$B$156,B30,'แผนงาน Schedule'!$D$7:$D$156,"<>",'แผนงาน Schedule'!$O$7:$O$156,"")=0,_xlfn.MAXIFS('แผนงาน Schedule'!$O$7:$O$156,'แผนงาน Schedule'!$B$7:$B$156,B30),'ตั้งค่า Setup'!$C$15))
A31: =IF(B31="","",25) | B31: =IF('ตั้งค่า Setup'!$C$50="","",'ตั้งค่า Setup'!$C$50) | C31: =IF(B31="","",COUNTIFS('แผนงาน Schedule'!$B$7:$B$156,B31,'แผนงาน Schedule'!$D$7:$D$156,"<>")) | D31: =IF(B31="","",SUMIF('แผนงาน Schedule'!$B$7:$B$156,B31,'แผนงาน Schedule'!$H$7:$H$156)) | E31: =IF(B31="","",SUMIF('แผนงาน Schedule'!$B$7:$B$156,B31,'แผนงาน Schedule'!$G$7:$G$156)) | F31: =IF(OR(B31="",N(C31)=0),"",_xlfn.MINIFS('แผนงาน Schedule'!$I$7:$I$156,'แผนงาน Schedule'!$B$7:$B$156,B31)) | G31: =IF(OR(B31="",N(C31)=0),"",_xlfn.MAXIFS('แผนงาน Schedule'!$J$7:$J$156,'แผนงาน Schedule'!$B$7:$B$156,B31)) | H31: =IF(OR(B31="",COUNTIFS('แผนงาน Schedule'!$B$7:$B$156,B31,'แผนงาน Schedule'!$N$7:$N$156,"<>")=0),"",_xlfn.MINIFS('แผนงาน Schedule'!$N$7:$N$156,'แผนงาน Schedule'!$B$7:$B$156,B31)) | I31: =IF(OR(B31="",N(E31)=0),"",SUMPRODUCT(('แผนงาน Schedule'!$B$7:$B$156=B31)*'แผนงาน Schedule'!$G$7:$G$156*(('แผนงาน Schedule'!$J$7:$J$156<=Dashboard!$C$7)+('แผนงาน Schedule'!$I$7:$I$156<=Dashboard!$C$7)*('แผนงาน Schedule'!$J$7:$J$156>Dashboard!$C$7)*(Dashboard!$C$7-'แผนงาน Schedule'!$I$7:$I$156+1)/('แผนงาน Schedule'!$J$7:$J$156-'แผนงาน Schedule'!$I$7:$I$156+1)))/E31) | J31: =IF(OR(B31="",N(E31)=0),"",SUMPRODUCT(('แผนงาน Schedule'!$B$7:$B$156=B31)*'แผนงาน Schedule'!$G$7:$G$156*'แผนงาน Schedule'!$P$7:$P$156)/E31) | K31: =IF(I31="","",J31-I31) | L31: =IF(OR(I31="",N(I31)=0),"",J31/I31) | M31: =IF(OR(B31="",N(C31)=0),"",_xlfn.MAXIFS('แผนงาน Schedule'!$W$7:$W$156,'แผนงาน Schedule'!$B$7:$B$156,B31)) | N31: =IF(OR(M31="",G31=""),"",M31-G31) | O31: =IF(B31="","",COUNTIFS('แผนงาน Schedule'!$B$7:$B$156,B31,'แผนงาน Schedule'!$Y$7:$Y$156,"*ล่าช้า*")+COUNTIFS('แผนงาน Schedule'!$B$7:$B$156,B31,'แผนงาน Schedule'!$Y$7:$Y$156,"*เกินกำหนด*")) | P31: =IF(OR(B31="",N(C31)=0),"",IF(N(J31)>=1,"แล้วเสร็จ / Completed",IF(AND(N(I31)=0,N(J31)=0),"ยังไม่เริ่ม / Not Started",IF(N(J31)>=N(I31),"ตามแผน / On Track",IF(N(J31)/I31>=0.9,"เฝ้าระวัง / At Risk","ล่าช้า / Behind"))))) | Q31: =IF(B31="","",N(I31)*N(E31)) | R31: =IF(B31="","",N(J31)*N(E31)) | S31: =IF(H31="","",IF(COUNTIFS('แผนงาน Schedule'!$B$7:$B$156,B31,'แผนงาน Schedule'!$D$7:$D$156,"<>",'แผนงาน Schedule'!$O$7:$O$156,"")=0,_xlfn.MAXIFS('แผนงาน Schedule'!$O$7:$O$156,'แผนงาน Schedule'!$B$7:$B$156,B31),'ตั้งค่า Setup'!$C$15))
A32: =IF(B32="","",26) | B32: =IF('ตั้งค่า Setup'!$C$51="","",'ตั้งค่า Setup'!$C$51) | C32: =IF(B32="","",COUNTIFS('แผนงาน Schedule'!$B$7:$B$156,B32,'แผนงาน Schedule'!$D$7:$D$156,"<>")) | D32: =IF(B32="","",SUMIF('แผนงาน Schedule'!$B$7:$B$156,B32,'แผนงาน Schedule'!$H$7:$H$156)) | E32: =IF(B32="","",SUMIF('แผนงาน Schedule'!$B$7:$B$156,B32,'แผนงาน Schedule'!$G$7:$G$156)) | F32: =IF(OR(B32="",N(C32)=0),"",_xlfn.MINIFS('แผนงาน Schedule'!$I$7:$I$156,'แผนงาน Schedule'!$B$7:$B$156,B32)) | G32: =IF(OR(B32="",N(C32)=0),"",_xlfn.MAXIFS('แผนงาน Schedule'!$J$7:$J$156,'แผนงาน Schedule'!$B$7:$B$156,B32)) | H32: =IF(OR(B32="",COUNTIFS('แผนงาน Schedule'!$B$7:$B$156,B32,'แผนงาน Schedule'!$N$7:$N$156,"<>")=0),"",_xlfn.MINIFS('แผนงาน Schedule'!$N$7:$N$156,'แผนงาน Schedule'!$B$7:$B$156,B32)) | I32: =IF(OR(B32="",N(E32)=0),"",SUMPRODUCT(('แผนงาน Schedule'!$B$7:$B$156=B32)*'แผนงาน Schedule'!$G$7:$G$156*(('แผนงาน Schedule'!$J$7:$J$156<=Dashboard!$C$7)+('แผนงาน Schedule'!$I$7:$I$156<=Dashboard!$C$7)*('แผนงาน Schedule'!$J$7:$J$156>Dashboard!$C$7)*(Dashboard!$C$7-'แผนงาน Schedule'!$I$7:$I$156+1)/('แผนงาน Schedule'!$J$7:$J$156-'แผนงาน Schedule'!$I$7:$I$156+1)))/E32) | J32: =IF(OR(B32="",N(E32)=0),"",SUMPRODUCT(('แผนงาน Schedule'!$B$7:$B$156=B32)*'แผนงาน Schedule'!$G$7:$G$156*'แผนงาน Schedule'!$P$7:$P$156)/E32) | K32: =IF(I32="","",J32-I32) | L32: =IF(OR(I32="",N(I32)=0),"",J32/I32) | M32: =IF(OR(B32="",N(C32)=0),"",_xlfn.MAXIFS('แผนงาน Schedule'!$W$7:$W$156,'แผนงาน Schedule'!$B$7:$B$156,B32)) | N32: =IF(OR(M32="",G32=""),"",M32-G32) | O32: =IF(B32="","",COUNTIFS('แผนงาน Schedule'!$B$7:$B$156,B32,'แผนงาน Schedule'!$Y$7:$Y$156,"*ล่าช้า*")+COUNTIFS('แผนงาน Schedule'!$B$7:$B$156,B32,'แผนงาน Schedule'!$Y$7:$Y$156,"*เกินกำหนด*")) | P32: =IF(OR(B32="",N(C32)=0),"",IF(N(J32)>=1,"แล้วเสร็จ / Completed",IF(AND(N(I32)=0,N(J32)=0),"ยังไม่เริ่ม / Not Started",IF(N(J32)>=N(I32),"ตามแผน / On Track",IF(N(J32)/I32>=0.9,"เฝ้าระวัง / At Risk","ล่าช้า / Behind"))))) | Q32: =IF(B32="","",N(I32)*N(E32)) | R32: =IF(B32="","",N(J32)*N(E32)) | S32: =IF(H32="","",IF(COUNTIFS('แผนงาน Schedule'!$B$7:$B$156,B32,'แผนงาน Schedule'!$D$7:$D$156,"<>",'แผนงาน Schedule'!$O$7:$O$156,"")=0,_xlfn.MAXIFS('แผนงาน Schedule'!$O$7:$O$156,'แผนงาน Schedule'!$B$7:$B$156,B32),'ตั้งค่า Setup'!$C$15))
A33: =IF(B33="","",27) | B33: =IF('ตั้งค่า Setup'!$C$52="","",'ตั้งค่า Setup'!$C$52) | C33: =IF(B33="","",COUNTIFS('แผนงาน Schedule'!$B$7:$B$156,B33,'แผนงาน Schedule'!$D$7:$D$156,"<>")) | D33: =IF(B33="","",SUMIF('แผนงาน Schedule'!$B$7:$B$156,B33,'แผนงาน Schedule'!$H$7:$H$156)) | E33: =IF(B33="","",SUMIF('แผนงาน Schedule'!$B$7:$B$156,B33,'แผนงาน Schedule'!$G$7:$G$156)) | F33: =IF(OR(B33="",N(C33)=0),"",_xlfn.MINIFS('แผนงาน Schedule'!$I$7:$I$156,'แผนงาน Schedule'!$B$7:$B$156,B33)) | G33: =IF(OR(B33="",N(C33)=0),"",_xlfn.MAXIFS('แผนงาน Schedule'!$J$7:$J$156,'แผนงาน Schedule'!$B$7:$B$156,B33)) | H33: =IF(OR(B33="",COUNTIFS('แผนงาน Schedule'!$B$7:$B$156,B33,'แผนงาน Schedule'!$N$7:$N$156,"<>")=0),"",_xlfn.MINIFS('แผนงาน Schedule'!$N$7:$N$156,'แผนงาน Schedule'!$B$7:$B$156,B33)) | I33: =IF(OR(B33="",N(E33)=0),"",SUMPRODUCT(('แผนงาน Schedule'!$B$7:$B$156=B33)*'แผนงาน Schedule'!$G$7:$G$156*(('แผนงาน Schedule'!$J$7:$J$156<=Dashboard!$C$7)+('แผนงาน Schedule'!$I$7:$I$156<=Dashboard!$C$7)*('แผนงาน Schedule'!$J$7:$J$156>Dashboard!$C$7)*(Dashboard!$C$7-'แผนงาน Schedule'!$I$7:$I$156+1)/('แผนงาน Schedule'!$J$7:$J$156-'แผนงาน Schedule'!$I$7:$I$156+1)))/E33) | J33: =IF(OR(B33="",N(E33)=0),"",SUMPRODUCT(('แผนงาน Schedule'!$B$7:$B$156=B33)*'แผนงาน Schedule'!$G$7:$G$156*'แผนงาน Schedule'!$P$7:$P$156)/E33) | K33: =IF(I33="","",J33-I33) | L33: =IF(OR(I33="",N(I33)=0),"",J33/I33) | M33: =IF(OR(B33="",N(C33)=0),"",_xlfn.MAXIFS('แผนงาน Schedule'!$W$7:$W$156,'แผนงาน Schedule'!$B$7:$B$156,B33)) | N33: =IF(OR(M33="",G33=""),"",M33-G33) | O33: =IF(B33="","",COUNTIFS('แผนงาน Schedule'!$B$7:$B$156,B33,'แผนงาน Schedule'!$Y$7:$Y$156,"*ล่าช้า*")+COUNTIFS('แผนงาน Schedule'!$B$7:$B$156,B33,'แผนงาน Schedule'!$Y$7:$Y$156,"*เกินกำหนด*")) | P33: =IF(OR(B33="",N(C33)=0),"",IF(N(J33)>=1,"แล้วเสร็จ / Completed",IF(AND(N(I33)=0,N(J33)=0),"ยังไม่เริ่ม / Not Started",IF(N(J33)>=N(I33),"ตามแผน / On Track",IF(N(J33)/I33>=0.9,"เฝ้าระวัง / At Risk","ล่าช้า / Behind"))))) | Q33: =IF(B33="","",N(I33)*N(E33)) | R33: =IF(B33="","",N(J33)*N(E33)) | S33: =IF(H33="","",IF(COUNTIFS('แผนงาน Schedule'!$B$7:$B$156,B33,'แผนงาน Schedule'!$D$7:$D$156,"<>",'แผนงาน Schedule'!$O$7:$O$156,"")=0,_xlfn.MAXIFS('แผนงาน Schedule'!$O$7:$O$156,'แผนงาน Schedule'!$B$7:$B$156,B33),'ตั้งค่า Setup'!$C$15))
A34: =IF(B34="","",28) | B34: =IF('ตั้งค่า Setup'!$C$53="","",'ตั้งค่า Setup'!$C$53) | C34: =IF(B34="","",COUNTIFS('แผนงาน Schedule'!$B$7:$B$156,B34,'แผนงาน Schedule'!$D$7:$D$156,"<>")) | D34: =IF(B34="","",SUMIF('แผนงาน Schedule'!$B$7:$B$156,B34,'แผนงาน Schedule'!$H$7:$H$156)) | E34: =IF(B34="","",SUMIF('แผนงาน Schedule'!$B$7:$B$156,B34,'แผนงาน Schedule'!$G$7:$G$156)) | F34: =IF(OR(B34="",N(C34)=0),"",_xlfn.MINIFS('แผนงาน Schedule'!$I$7:$I$156,'แผนงาน Schedule'!$B$7:$B$156,B34)) | G34: =IF(OR(B34="",N(C34)=0),"",_xlfn.MAXIFS('แผนงาน Schedule'!$J$7:$J$156,'แผนงาน Schedule'!$B$7:$B$156,B34)) | H34: =IF(OR(B34="",COUNTIFS('แผนงาน Schedule'!$B$7:$B$156,B34,'แผนงาน Schedule'!$N$7:$N$156,"<>")=0),"",_xlfn.MINIFS('แผนงาน Schedule'!$N$7:$N$156,'แผนงาน Schedule'!$B$7:$B$156,B34)) | I34: =IF(OR(B34="",N(E34)=0),"",SUMPRODUCT(('แผนงาน Schedule'!$B$7:$B$156=B34)*'แผนงาน Schedule'!$G$7:$G$156*(('แผนงาน Schedule'!$J$7:$J$156<=Dashboard!$C$7)+('แผนงาน Schedule'!$I$7:$I$156<=Dashboard!$C$7)*('แผนงาน Schedule'!$J$7:$J$156>Dashboard!$C$7)*(Dashboard!$C$7-'แผนงาน Schedule'!$I$7:$I$156+1)/('แผนงาน Schedule'!$J$7:$J$156-'แผนงาน Schedule'!$I$7:$I$156+1)))/E34) | J34: =IF(OR(B34="",N(E34)=0),"",SUMPRODUCT(('แผนงาน Schedule'!$B$7:$B$156=B34)*'แผนงาน Schedule'!$G$7:$G$156*'แผนงาน Schedule'!$P$7:$P$156)/E34) | K34: =IF(I34="","",J34-I34) | L34: =IF(OR(I34="",N(I34)=0),"",J34/I34) | M34: =IF(OR(B34="",N(C34)=0),"",_xlfn.MAXIFS('แผนงาน Schedule'!$W$7:$W$156,'แผนงาน Schedule'!$B$7:$B$156,B34)) | N34: =IF(OR(M34="",G34=""),"",M34-G34) | O34: =IF(B34="","",COUNTIFS('แผนงาน Schedule'!$B$7:$B$156,B34,'แผนงาน Schedule'!$Y$7:$Y$156,"*ล่าช้า*")+COUNTIFS('แผนงาน Schedule'!$B$7:$B$156,B34,'แผนงาน Schedule'!$Y$7:$Y$156,"*เกินกำหนด*")) | P34: =IF(OR(B34="",N(C34)=0),"",IF(N(J34)>=1,"แล้วเสร็จ / Completed",IF(AND(N(I34)=0,N(J34)=0),"ยังไม่เริ่ม / Not Started",IF(N(J34)>=N(I34),"ตามแผน / On Track",IF(N(J34)/I34>=0.9,"เฝ้าระวัง / At Risk","ล่าช้า / Behind"))))) | Q34: =IF(B34="","",N(I34)*N(E34)) | R34: =IF(B34="","",N(J34)*N(E34)) | S34: =IF(H34="","",IF(COUNTIFS('แผนงาน Schedule'!$B$7:$B$156,B34,'แผนงาน Schedule'!$D$7:$D$156,"<>",'แผนงาน Schedule'!$O$7:$O$156,"")=0,_xlfn.MAXIFS('แผนงาน Schedule'!$O$7:$O$156,'แผนงาน Schedule'!$B$7:$B$156,B34),'ตั้งค่า Setup'!$C$15))
A35: =IF(B35="","",29) | B35: =IF('ตั้งค่า Setup'!$C$54="","",'ตั้งค่า Setup'!$C$54) | C35: =IF(B35="","",COUNTIFS('แผนงาน Schedule'!$B$7:$B$156,B35,'แผนงาน Schedule'!$D$7:$D$156,"<>")) | D35: =IF(B35="","",SUMIF('แผนงาน Schedule'!$B$7:$B$156,B35,'แผนงาน Schedule'!$H$7:$H$156)) | E35: =IF(B35="","",SUMIF('แผนงาน Schedule'!$B$7:$B$156,B35,'แผนงาน Schedule'!$G$7:$G$156)) | F35: =IF(OR(B35="",N(C35)=0),"",_xlfn.MINIFS('แผนงาน Schedule'!$I$7:$I$156,'แผนงาน Schedule'!$B$7:$B$156,B35)) | G35: =IF(OR(B35="",N(C35)=0),"",_xlfn.MAXIFS('แผนงาน Schedule'!$J$7:$J$156,'แผนงาน Schedule'!$B$7:$B$156,B35)) | H35: =IF(OR(B35="",COUNTIFS('แผนงาน Schedule'!$B$7:$B$156,B35,'แผนงาน Schedule'!$N$7:$N$156,"<>")=0),"",_xlfn.MINIFS('แผนงาน Schedule'!$N$7:$N$156,'แผนงาน Schedule'!$B$7:$B$156,B35)) | I35: =IF(OR(B35="",N(E35)=0),"",SUMPRODUCT(('แผนงาน Schedule'!$B$7:$B$156=B35)*'แผนงาน Schedule'!$G$7:$G$156*(('แผนงาน Schedule'!$J$7:$J$156<=Dashboard!$C$7)+('แผนงาน Schedule'!$I$7:$I$156<=Dashboard!$C$7)*('แผนงาน Schedule'!$J$7:$J$156>Dashboard!$C$7)*(Dashboard!$C$7-'แผนงาน Schedule'!$I$7:$I$156+1)/('แผนงาน Schedule'!$J$7:$J$156-'แผนงาน Schedule'!$I$7:$I$156+1)))/E35) | J35: =IF(OR(B35="",N(E35)=0),"",SUMPRODUCT(('แผนงาน Schedule'!$B$7:$B$156=B35)*'แผนงาน Schedule'!$G$7:$G$156*'แผนงาน Schedule'!$P$7:$P$156)/E35) | K35: =IF(I35="","",J35-I35) | L35: =IF(OR(I35="",N(I35)=0),"",J35/I35) | M35: =IF(OR(B35="",N(C35)=0),"",_xlfn.MAXIFS('แผนงาน Schedule'!$W$7:$W$156,'แผนงาน Schedule'!$B$7:$B$156,B35)) | N35: =IF(OR(M35="",G35=""),"",M35-G35) | O35: =IF(B35="","",COUNTIFS('แผนงาน Schedule'!$B$7:$B$156,B35,'แผนงาน Schedule'!$Y$7:$Y$156,"*ล่าช้า*")+COUNTIFS('แผนงาน Schedule'!$B$7:$B$156,B35,'แผนงาน Schedule'!$Y$7:$Y$156,"*เกินกำหนด*")) | P35: =IF(OR(B35="",N(C35)=0),"",IF(N(J35)>=1,"แล้วเสร็จ / Completed",IF(AND(N(I35)=0,N(J35)=0),"ยังไม่เริ่ม / Not Started",IF(N(J35)>=N(I35),"ตามแผน / On Track",IF(N(J35)/I35>=0.9,"เฝ้าระวัง / At Risk","ล่าช้า / Behind"))))) | Q35: =IF(B35="","",N(I35)*N(E35)) | R35: =IF(B35="","",N(J35)*N(E35)) | S35: =IF(H35="","",IF(COUNTIFS('แผนงาน Schedule'!$B$7:$B$156,B35,'แผนงาน Schedule'!$D$7:$D$156,"<>",'แผนงาน Schedule'!$O$7:$O$156,"")=0,_xlfn.MAXIFS('แผนงาน Schedule'!$O$7:$O$156,'แผนงาน Schedule'!$B$7:$B$156,B35),'ตั้งค่า Setup'!$C$15))
A36: =IF(B36="","",30) | B36: =IF('ตั้งค่า Setup'!$C$55="","",'ตั้งค่า Setup'!$C$55) | C36: =IF(B36="","",COUNTIFS('แผนงาน Schedule'!$B$7:$B$156,B36,'แผนงาน Schedule'!$D$7:$D$156,"<>")) | D36: =IF(B36="","",SUMIF('แผนงาน Schedule'!$B$7:$B$156,B36,'แผนงาน Schedule'!$H$7:$H$156)) | E36: =IF(B36="","",SUMIF('แผนงาน Schedule'!$B$7:$B$156,B36,'แผนงาน Schedule'!$G$7:$G$156)) | F36: =IF(OR(B36="",N(C36)=0),"",_xlfn.MINIFS('แผนงาน Schedule'!$I$7:$I$156,'แผนงาน Schedule'!$B$7:$B$156,B36)) | G36: =IF(OR(B36="",N(C36)=0),"",_xlfn.MAXIFS('แผนงาน Schedule'!$J$7:$J$156,'แผนงาน Schedule'!$B$7:$B$156,B36)) | H36: =IF(OR(B36="",COUNTIFS('แผนงาน Schedule'!$B$7:$B$156,B36,'แผนงาน Schedule'!$N$7:$N$156,"<>")=0),"",_xlfn.MINIFS('แผนงาน Schedule'!$N$7:$N$156,'แผนงาน Schedule'!$B$7:$B$156,B36)) | I36: =IF(OR(B36="",N(E36)=0),"",SUMPRODUCT(('แผนงาน Schedule'!$B$7:$B$156=B36)*'แผนงาน Schedule'!$G$7:$G$156*(('แผนงาน Schedule'!$J$7:$J$156<=Dashboard!$C$7)+('แผนงาน Schedule'!$I$7:$I$156<=Dashboard!$C$7)*('แผนงาน Schedule'!$J$7:$J$156>Dashboard!$C$7)*(Dashboard!$C$7-'แผนงาน Schedule'!$I$7:$I$156+1)/('แผนงาน Schedule'!$J$7:$J$156-'แผนงาน Schedule'!$I$7:$I$156+1)))/E36) | J36: =IF(OR(B36="",N(E36)=0),"",SUMPRODUCT(('แผนงาน Schedule'!$B$7:$B$156=B36)*'แผนงาน Schedule'!$G$7:$G$156*'แผนงาน Schedule'!$P$7:$P$156)/E36) | K36: =IF(I36="","",J36-I36) | L36: =IF(OR(I36="",N(I36)=0),"",J36/I36) | M36: =IF(OR(B36="",N(C36)=0),"",_xlfn.MAXIFS('แผนงาน Schedule'!$W$7:$W$156,'แผนงาน Schedule'!$B$7:$B$156,B36)) | N36: =IF(OR(M36="",G36=""),"",M36-G36) | O36: =IF(B36="","",COUNTIFS('แผนงาน Schedule'!$B$7:$B$156,B36,'แผนงาน Schedule'!$Y$7:$Y$156,"*ล่าช้า*")+COUNTIFS('แผนงาน Schedule'!$B$7:$B$156,B36,'แผนงาน Schedule'!$Y$7:$Y$156,"*เกินกำหนด*")) | P36: =IF(OR(B36="",N(C36)=0),"",IF(N(J36)>=1,"แล้วเสร็จ / Completed",IF(AND(N(I36)=0,N(J36)=0),"ยังไม่เริ่ม / Not Started",IF(N(J36)>=N(I36),"ตามแผน / On Track",IF(N(J36)/I36>=0.9,"เฝ้าระวัง / At Risk","ล่าช้า / Behind"))))) | Q36: =IF(B36="","",N(I36)*N(E36)) | R36: =IF(B36="","",N(J36)*N(E36)) | S36: =IF(H36="","",IF(COUNTIFS('แผนงาน Schedule'!$B$7:$B$156,B36,'แผนงาน Schedule'!$D$7:$D$156,"<>",'แผนงาน Schedule'!$O$7:$O$156,"")=0,_xlfn.MAXIFS('แผนงาน Schedule'!$O$7:$O$156,'แผนงาน Schedule'!$B$7:$B$156,B36),'ตั้งค่า Setup'!$C$15))
A37: =IF(B37="","",31) | B37: =IF('ตั้งค่า Setup'!$C$56="","",'ตั้งค่า Setup'!$C$56) | C37: =IF(B37="","",COUNTIFS('แผนงาน Schedule'!$B$7:$B$156,B37,'แผนงาน Schedule'!$D$7:$D$156,"<>")) | D37: =IF(B37="","",SUMIF('แผนงาน Schedule'!$B$7:$B$156,B37,'แผนงาน Schedule'!$H$7:$H$156)) | E37: =IF(B37="","",SUMIF('แผนงาน Schedule'!$B$7:$B$156,B37,'แผนงาน Schedule'!$G$7:$G$156)) | F37: =IF(OR(B37="",N(C37)=0),"",_xlfn.MINIFS('แผนงาน Schedule'!$I$7:$I$156,'แผนงาน Schedule'!$B$7:$B$156,B37)) | G37: =IF(OR(B37="",N(C37)=0),"",_xlfn.MAXIFS('แผนงาน Schedule'!$J$7:$J$156,'แผนงาน Schedule'!$B$7:$B$156,B37)) | H37: =IF(OR(B37="",COUNTIFS('แผนงาน Schedule'!$B$7:$B$156,B37,'แผนงาน Schedule'!$N$7:$N$156,"<>")=0),"",_xlfn.MINIFS('แผนงาน Schedule'!$N$7:$N$156,'แผนงาน Schedule'!$B$7:$B$156,B37)) | I37: =IF(OR(B37="",N(E37)=0),"",SUMPRODUCT(('แผนงาน Schedule'!$B$7:$B$156=B37)*'แผนงาน Schedule'!$G$7:$G$156*(('แผนงาน Schedule'!$J$7:$J$156<=Dashboard!$C$7)+('แผนงาน Schedule'!$I$7:$I$156<=Dashboard!$C$7)*('แผนงาน Schedule'!$J$7:$J$156>Dashboard!$C$7)*(Dashboard!$C$7-'แผนงาน Schedule'!$I$7:$I$156+1)/('แผนงาน Schedule'!$J$7:$J$156-'แผนงาน Schedule'!$I$7:$I$156+1)))/E37) | J37: =IF(OR(B37="",N(E37)=0),"",SUMPRODUCT(('แผนงาน Schedule'!$B$7:$B$156=B37)*'แผนงาน Schedule'!$G$7:$G$156*'แผนงาน Schedule'!$P$7:$P$156)/E37) | K37: =IF(I37="","",J37-I37) | L37: =IF(OR(I37="",N(I37)=0),"",J37/I37) | M37: =IF(OR(B37="",N(C37)=0),"",_xlfn.MAXIFS('แผนงาน Schedule'!$W$7:$W$156,'แผนงาน Schedule'!$B$7:$B$156,B37)) | N37: =IF(OR(M37="",G37=""),"",M37-G37) | O37: =IF(B37="","",COUNTIFS('แผนงาน Schedule'!$B$7:$B$156,B37,'แผนงาน Schedule'!$Y$7:$Y$156,"*ล่าช้า*")+COUNTIFS('แผนงาน Schedule'!$B$7:$B$156,B37,'แผนงาน Schedule'!$Y$7:$Y$156,"*เกินกำหนด*")) | P37: =IF(OR(B37="",N(C37)=0),"",IF(N(J37)>=1,"แล้วเสร็จ / Completed",IF(AND(N(I37)=0,N(J37)=0),"ยังไม่เริ่ม / Not Started",IF(N(J37)>=N(I37),"ตามแผน / On Track",IF(N(J37)/I37>=0.9,"เฝ้าระวัง / At Risk","ล่าช้า / Behind"))))) | Q37: =IF(B37="","",N(I37)*N(E37)) | R37: =IF(B37="","",N(J37)*N(E37)) | S37: =IF(H37="","",IF(COUNTIFS('แผนงาน Schedule'!$B$7:$B$156,B37,'แผนงาน Schedule'!$D$7:$D$156,"<>",'แผนงาน Schedule'!$O$7:$O$156,"")=0,_xlfn.MAXIFS('แผนงาน Schedule'!$O$7:$O$156,'แผนงาน Schedule'!$B$7:$B$156,B37),'ตั้งค่า Setup'!$C$15))
A38: =IF(B38="","",32) | B38: =IF('ตั้งค่า Setup'!$C$57="","",'ตั้งค่า Setup'!$C$57) | C38: =IF(B38="","",COUNTIFS('แผนงาน Schedule'!$B$7:$B$156,B38,'แผนงาน Schedule'!$D$7:$D$156,"<>")) | D38: =IF(B38="","",SUMIF('แผนงาน Schedule'!$B$7:$B$156,B38,'แผนงาน Schedule'!$H$7:$H$156)) | E38: =IF(B38="","",SUMIF('แผนงาน Schedule'!$B$7:$B$156,B38,'แผนงาน Schedule'!$G$7:$G$156)) | F38: =IF(OR(B38="",N(C38)=0),"",_xlfn.MINIFS('แผนงาน Schedule'!$I$7:$I$156,'แผนงาน Schedule'!$B$7:$B$156,B38)) | G38: =IF(OR(B38="",N(C38)=0),"",_xlfn.MAXIFS('แผนงาน Schedule'!$J$7:$J$156,'แผนงาน Schedule'!$B$7:$B$156,B38)) | H38: =IF(OR(B38="",COUNTIFS('แผนงาน Schedule'!$B$7:$B$156,B38,'แผนงาน Schedule'!$N$7:$N$156,"<>")=0),"",_xlfn.MINIFS('แผนงาน Schedule'!$N$7:$N$156,'แผนงาน Schedule'!$B$7:$B$156,B38)) | I38: =IF(OR(B38="",N(E38)=0),"",SUMPRODUCT(('แผนงาน Schedule'!$B$7:$B$156=B38)*'แผนงาน Schedule'!$G$7:$G$156*(('แผนงาน Schedule'!$J$7:$J$156<=Dashboard!$C$7)+('แผนงาน Schedule'!$I$7:$I$156<=Dashboard!$C$7)*('แผนงาน Schedule'!$J$7:$J$156>Dashboard!$C$7)*(Dashboard!$C$7-'แผนงาน Schedule'!$I$7:$I$156+1)/('แผนงาน Schedule'!$J$7:$J$156-'แผนงาน Schedule'!$I$7:$I$156+1)))/E38) | J38: =IF(OR(B38="",N(E38)=0),"",SUMPRODUCT(('แผนงาน Schedule'!$B$7:$B$156=B38)*'แผนงาน Schedule'!$G$7:$G$156*'แผนงาน Schedule'!$P$7:$P$156)/E38) | K38: =IF(I38="","",J38-I38) | L38: =IF(OR(I38="",N(I38)=0),"",J38/I38) | M38: =IF(OR(B38="",N(C38)=0),"",_xlfn.MAXIFS('แผนงาน Schedule'!$W$7:$W$156,'แผนงาน Schedule'!$B$7:$B$156,B38)) | N38: =IF(OR(M38="",G38=""),"",M38-G38) | O38: =IF(B38="","",COUNTIFS('แผนงาน Schedule'!$B$7:$B$156,B38,'แผนงาน Schedule'!$Y$7:$Y$156,"*ล่าช้า*")+COUNTIFS('แผนงาน Schedule'!$B$7:$B$156,B38,'แผนงาน Schedule'!$Y$7:$Y$156,"*เกินกำหนด*")) | P38: =IF(OR(B38="",N(C38)=0),"",IF(N(J38)>=1,"แล้วเสร็จ / Completed",IF(AND(N(I38)=0,N(J38)=0),"ยังไม่เริ่ม / Not Started",IF(N(J38)>=N(I38),"ตามแผน / On Track",IF(N(J38)/I38>=0.9,"เฝ้าระวัง / At Risk","ล่าช้า / Behind"))))) | Q38: =IF(B38="","",N(I38)*N(E38)) | R38: =IF(B38="","",N(J38)*N(E38)) | S38: =IF(H38="","",IF(COUNTIFS('แผนงาน Schedule'!$B$7:$B$156,B38,'แผนงาน Schedule'!$D$7:$D$156,"<>",'แผนงาน Schedule'!$O$7:$O$156,"")=0,_xlfn.MAXIFS('แผนงาน Schedule'!$O$7:$O$156,'แผนงาน Schedule'!$B$7:$B$156,B38),'ตั้งค่า Setup'!$C$15))
A39: =IF(B39="","",33) | B39: =IF('ตั้งค่า Setup'!$C$58="","",'ตั้งค่า Setup'!$C$58) | C39: =IF(B39="","",COUNTIFS('แผนงาน Schedule'!$B$7:$B$156,B39,'แผนงาน Schedule'!$D$7:$D$156,"<>")) | D39: =IF(B39="","",SUMIF('แผนงาน Schedule'!$B$7:$B$156,B39,'แผนงาน Schedule'!$H$7:$H$156)) | E39: =IF(B39="","",SUMIF('แผนงาน Schedule'!$B$7:$B$156,B39,'แผนงาน Schedule'!$G$7:$G$156)) | F39: =IF(OR(B39="",N(C39)=0),"",_xlfn.MINIFS('แผนงาน Schedule'!$I$7:$I$156,'แผนงาน Schedule'!$B$7:$B$156,B39)) | G39: =IF(OR(B39="",N(C39)=0),"",_xlfn.MAXIFS('แผนงาน Schedule'!$J$7:$J$156,'แผนงาน Schedule'!$B$7:$B$156,B39)) | H39: =IF(OR(B39="",COUNTIFS('แผนงาน Schedule'!$B$7:$B$156,B39,'แผนงาน Schedule'!$N$7:$N$156,"<>")=0),"",_xlfn.MINIFS('แผนงาน Schedule'!$N$7:$N$156,'แผนงาน Schedule'!$B$7:$B$156,B39)) | I39: =IF(OR(B39="",N(E39)=0),"",SUMPRODUCT(('แผนงาน Schedule'!$B$7:$B$156=B39)*'แผนงาน Schedule'!$G$7:$G$156*(('แผนงาน Schedule'!$J$7:$J$156<=Dashboard!$C$7)+('แผนงาน Schedule'!$I$7:$I$156<=Dashboard!$C$7)*('แผนงาน Schedule'!$J$7:$J$156>Dashboard!$C$7)*(Dashboard!$C$7-'แผนงาน Schedule'!$I$7:$I$156+1)/('แผนงาน Schedule'!$J$7:$J$156-'แผนงาน Schedule'!$I$7:$I$156+1)))/E39) | J39: =IF(OR(B39="",N(E39)=0),"",SUMPRODUCT(('แผนงาน Schedule'!$B$7:$B$156=B39)*'แผนงาน Schedule'!$G$7:$G$156*'แผนงาน Schedule'!$P$7:$P$156)/E39) | K39: =IF(I39="","",J39-I39) | L39: =IF(OR(I39="",N(I39)=0),"",J39/I39) | M39: =IF(OR(B39="",N(C39)=0),"",_xlfn.MAXIFS('แผนงาน Schedule'!$W$7:$W$156,'แผนงาน Schedule'!$B$7:$B$156,B39)) | N39: =IF(OR(M39="",G39=""),"",M39-G39) | O39: =IF(B39="","",COUNTIFS('แผนงาน Schedule'!$B$7:$B$156,B39,'แผนงาน Schedule'!$Y$7:$Y$156,"*ล่าช้า*")+COUNTIFS('แผนงาน Schedule'!$B$7:$B$156,B39,'แผนงาน Schedule'!$Y$7:$Y$156,"*เกินกำหนด*")) | P39: =IF(OR(B39="",N(C39)=0),"",IF(N(J39)>=1,"แล้วเสร็จ / Completed",IF(AND(N(I39)=0,N(J39)=0),"ยังไม่เริ่ม / Not Started",IF(N(J39)>=N(I39),"ตามแผน / On Track",IF(N(J39)/I39>=0.9,"เฝ้าระวัง / At Risk","ล่าช้า / Behind"))))) | Q39: =IF(B39="","",N(I39)*N(E39)) | R39: =IF(B39="","",N(J39)*N(E39)) | S39: =IF(H39="","",IF(COUNTIFS('แผนงาน Schedule'!$B$7:$B$156,B39,'แผนงาน Schedule'!$D$7:$D$156,"<>",'แผนงาน Schedule'!$O$7:$O$156,"")=0,_xlfn.MAXIFS('แผนงาน Schedule'!$O$7:$O$156,'แผนงาน Schedule'!$B$7:$B$156,B39),'ตั้งค่า Setup'!$C$15))
A40: =IF(B40="","",34) | B40: =IF('ตั้งค่า Setup'!$C$59="","",'ตั้งค่า Setup'!$C$59) | C40: =IF(B40="","",COUNTIFS('แผนงาน Schedule'!$B$7:$B$156,B40,'แผนงาน Schedule'!$D$7:$D$156,"<>")) | D40: =IF(B40="","",SUMIF('แผนงาน Schedule'!$B$7:$B$156,B40,'แผนงาน Schedule'!$H$7:$H$156)) | E40: =IF(B40="","",SUMIF('แผนงาน Schedule'!$B$7:$B$156,B40,'แผนงาน Schedule'!$G$7:$G$156)) | F40: =IF(OR(B40="",N(C40)=0),"",_xlfn.MINIFS('แผนงาน Schedule'!$I$7:$I$156,'แผนงาน Schedule'!$B$7:$B$156,B40)) | G40: =IF(OR(B40="",N(C40)=0),"",_xlfn.MAXIFS('แผนงาน Schedule'!$J$7:$J$156,'แผนงาน Schedule'!$B$7:$B$156,B40)) | H40: =IF(OR(B40="",COUNTIFS('แผนงาน Schedule'!$B$7:$B$156,B40,'แผนงาน Schedule'!$N$7:$N$156,"<>")=0),"",_xlfn.MINIFS('แผนงาน Schedule'!$N$7:$N$156,'แผนงาน Schedule'!$B$7:$B$156,B40)) | I40: =IF(OR(B40="",N(E40)=0),"",SUMPRODUCT(('แผนงาน Schedule'!$B$7:$B$156=B40)*'แผนงาน Schedule'!$G$7:$G$156*(('แผนงาน Schedule'!$J$7:$J$156<=Dashboard!$C$7)+('แผนงาน Schedule'!$I$7:$I$156<=Dashboard!$C$7)*('แผนงาน Schedule'!$J$7:$J$156>Dashboard!$C$7)*(Dashboard!$C$7-'แผนงาน Schedule'!$I$7:$I$156+1)/('แผนงาน Schedule'!$J$7:$J$156-'แผนงาน Schedule'!$I$7:$I$156+1)))/E40) | J40: =IF(OR(B40="",N(E40)=0),"",SUMPRODUCT(('แผนงาน Schedule'!$B$7:$B$156=B40)*'แผนงาน Schedule'!$G$7:$G$156*'แผนงาน Schedule'!$P$7:$P$156)/E40) | K40: =IF(I40="","",J40-I40) | L40: =IF(OR(I40="",N(I40)=0),"",J40/I40) | M40: =IF(OR(B40="",N(C40)=0),"",_xlfn.MAXIFS('แผนงาน Schedule'!$W$7:$W$156,'แผนงาน Schedule'!$B$7:$B$156,B40)) | N40: =IF(OR(M40="",G40=""),"",M40-G40) | O40: =IF(B40="","",COUNTIFS('แผนงาน Schedule'!$B$7:$B$156,B40,'แผนงาน Schedule'!$Y$7:$Y$156,"*ล่าช้า*")+COUNTIFS('แผนงาน Schedule'!$B$7:$B$156,B40,'แผนงาน Schedule'!$Y$7:$Y$156,"*เกินกำหนด*")) | P40: =IF(OR(B40="",N(C40)=0),"",IF(N(J40)>=1,"แล้วเสร็จ / Completed",IF(AND(N(I40)=0,N(J40)=0),"ยังไม่เริ่ม / Not Started",IF(N(J40)>=N(I40),"ตามแผน / On Track",IF(N(J40)/I40>=0.9,"เฝ้าระวัง / At Risk","ล่าช้า / Behind"))))) | Q40: =IF(B40="","",N(I40)*N(E40)) | R40: =IF(B40="","",N(J40)*N(E40)) | S40: =IF(H40="","",IF(COUNTIFS('แผนงาน Schedule'!$B$7:$B$156,B40,'แผนงาน Schedule'!$D$7:$D$156,"<>",'แผนงาน Schedule'!$O$7:$O$156,"")=0,_xlfn.MAXIFS('แผนงาน Schedule'!$O$7:$O$156,'แผนงาน Schedule'!$B$7:$B$156,B40),'ตั้งค่า Setup'!$C$15))
A41: =IF(B41="","",35) | B41: =IF('ตั้งค่า Setup'!$C$60="","",'ตั้งค่า Setup'!$C$60) | C41: =IF(B41="","",COUNTIFS('แผนงาน Schedule'!$B$7:$B$156,B41,'แผนงาน Schedule'!$D$7:$D$156,"<>")) | D41: =IF(B41="","",SUMIF('แผนงาน Schedule'!$B$7:$B$156,B41,'แผนงาน Schedule'!$H$7:$H$156)) | E41: =IF(B41="","",SUMIF('แผนงาน Schedule'!$B$7:$B$156,B41,'แผนงาน Schedule'!$G$7:$G$156)) | F41: =IF(OR(B41="",N(C41)=0),"",_xlfn.MINIFS('แผนงาน Schedule'!$I$7:$I$156,'แผนงาน Schedule'!$B$7:$B$156,B41)) | G41: =IF(OR(B41="",N(C41)=0),"",_xlfn.MAXIFS('แผนงาน Schedule'!$J$7:$J$156,'แผนงาน Schedule'!$B$7:$B$156,B41)) | H41: =IF(OR(B41="",COUNTIFS('แผนงาน Schedule'!$B$7:$B$156,B41,'แผนงาน Schedule'!$N$7:$N$156,"<>")=0),"",_xlfn.MINIFS('แผนงาน Schedule'!$N$7:$N$156,'แผนงาน Schedule'!$B$7:$B$156,B41)) | I41: =IF(OR(B41="",N(E41)=0),"",SUMPRODUCT(('แผนงาน Schedule'!$B$7:$B$156=B41)*'แผนงาน Schedule'!$G$7:$G$156*(('แผนงาน Schedule'!$J$7:$J$156<=Dashboard!$C$7)+('แผนงาน Schedule'!$I$7:$I$156<=Dashboard!$C$7)*('แผนงาน Schedule'!$J$7:$J$156>Dashboard!$C$7)*(Dashboard!$C$7-'แผนงาน Schedule'!$I$7:$I$156+1)/('แผนงาน Schedule'!$J$7:$J$156-'แผนงาน Schedule'!$I$7:$I$156+1)))/E41) | J41: =IF(OR(B41="",N(E41)=0),"",SUMPRODUCT(('แผนงาน Schedule'!$B$7:$B$156=B41)*'แผนงาน Schedule'!$G$7:$G$156*'แผนงาน Schedule'!$P$7:$P$156)/E41) | K41: =IF(I41="","",J41-I41) | L41: =IF(OR(I41="",N(I41)=0),"",J41/I41) | M41: =IF(OR(B41="",N(C41)=0),"",_xlfn.MAXIFS('แผนงาน Schedule'!$W$7:$W$156,'แผนงาน Schedule'!$B$7:$B$156,B41)) | N41: =IF(OR(M41="",G41=""),"",M41-G41) | O41: =IF(B41="","",COUNTIFS('แผนงาน Schedule'!$B$7:$B$156,B41,'แผนงาน Schedule'!$Y$7:$Y$156,"*ล่าช้า*")+COUNTIFS('แผนงาน Schedule'!$B$7:$B$156,B41,'แผนงาน Schedule'!$Y$7:$Y$156,"*เกินกำหนด*")) | P41: =IF(OR(B41="",N(C41)=0),"",IF(N(J41)>=1,"แล้วเสร็จ / Completed",IF(AND(N(I41)=0,N(J41)=0),"ยังไม่เริ่ม / Not Started",IF(N(J41)>=N(I41),"ตามแผน / On Track",IF(N(J41)/I41>=0.9,"เฝ้าระวัง / At Risk","ล่าช้า / Behind"))))) | Q41: =IF(B41="","",N(I41)*N(E41)) | R41: =IF(B41="","",N(J41)*N(E41)) | S41: =IF(H41="","",IF(COUNTIFS('แผนงาน Schedule'!$B$7:$B$156,B41,'แผนงาน Schedule'!$D$7:$D$156,"<>",'แผนงาน Schedule'!$O$7:$O$156,"")=0,_xlfn.MAXIFS('แผนงาน Schedule'!$O$7:$O$156,'แผนงาน Schedule'!$B$7:$B$156,B41),'ตั้งค่า Setup'!$C$15))
A42: =IF(B42="","",36) | B42: =IF('ตั้งค่า Setup'!$C$61="","",'ตั้งค่า Setup'!$C$61) | C42: =IF(B42="","",COUNTIFS('แผนงาน Schedule'!$B$7:$B$156,B42,'แผนงาน Schedule'!$D$7:$D$156,"<>")) | D42: =IF(B42="","",SUMIF('แผนงาน Schedule'!$B$7:$B$156,B42,'แผนงาน Schedule'!$H$7:$H$156)) | E42: =IF(B42="","",SUMIF('แผนงาน Schedule'!$B$7:$B$156,B42,'แผนงาน Schedule'!$G$7:$G$156)) | F42: =IF(OR(B42="",N(C42)=0),"",_xlfn.MINIFS('แผนงาน Schedule'!$I$7:$I$156,'แผนงาน Schedule'!$B$7:$B$156,B42)) | G42: =IF(OR(B42="",N(C42)=0),"",_xlfn.MAXIFS('แผนงาน Schedule'!$J$7:$J$156,'แผนงาน Schedule'!$B$7:$B$156,B42)) | H42: =IF(OR(B42="",COUNTIFS('แผนงาน Schedule'!$B$7:$B$156,B42,'แผนงาน Schedule'!$N$7:$N$156,"<>")=0),"",_xlfn.MINIFS('แผนงาน Schedule'!$N$7:$N$156,'แผนงาน Schedule'!$B$7:$B$156,B42)) | I42: =IF(OR(B42="",N(E42)=0),"",SUMPRODUCT(('แผนงาน Schedule'!$B$7:$B$156=B42)*'แผนงาน Schedule'!$G$7:$G$156*(('แผนงาน Schedule'!$J$7:$J$156<=Dashboard!$C$7)+('แผนงาน Schedule'!$I$7:$I$156<=Dashboard!$C$7)*('แผนงาน Schedule'!$J$7:$J$156>Dashboard!$C$7)*(Dashboard!$C$7-'แผนงาน Schedule'!$I$7:$I$156+1)/('แผนงาน Schedule'!$J$7:$J$156-'แผนงาน Schedule'!$I$7:$I$156+1)))/E42) | J42: =IF(OR(B42="",N(E42)=0),"",SUMPRODUCT(('แผนงาน Schedule'!$B$7:$B$156=B42)*'แผนงาน Schedule'!$G$7:$G$156*'แผนงาน Schedule'!$P$7:$P$156)/E42) | K42: =IF(I42="","",J42-I42) | L42: =IF(OR(I42="",N(I42)=0),"",J42/I42) | M42: =IF(OR(B42="",N(C42)=0),"",_xlfn.MAXIFS('แผนงาน Schedule'!$W$7:$W$156,'แผนงาน Schedule'!$B$7:$B$156,B42)) | N42: =IF(OR(M42="",G42=""),"",M42-G42) | O42: =IF(B42="","",COUNTIFS('แผนงาน Schedule'!$B$7:$B$156,B42,'แผนงาน Schedule'!$Y$7:$Y$156,"*ล่าช้า*")+COUNTIFS('แผนงาน Schedule'!$B$7:$B$156,B42,'แผนงาน Schedule'!$Y$7:$Y$156,"*เกินกำหนด*")) | P42: =IF(OR(B42="",N(C42)=0),"",IF(N(J42)>=1,"แล้วเสร็จ / Completed",IF(AND(N(I42)=0,N(J42)=0),"ยังไม่เริ่ม / Not Started",IF(N(J42)>=N(I42),"ตามแผน / On Track",IF(N(J42)/I42>=0.9,"เฝ้าระวัง / At Risk","ล่าช้า / Behind"))))) | Q42: =IF(B42="","",N(I42)*N(E42)) | R42: =IF(B42="","",N(J42)*N(E42)) | S42: =IF(H42="","",IF(COUNTIFS('แผนงาน Schedule'!$B$7:$B$156,B42,'แผนงาน Schedule'!$D$7:$D$156,"<>",'แผนงาน Schedule'!$O$7:$O$156,"")=0,_xlfn.MAXIFS('แผนงาน Schedule'!$O$7:$O$156,'แผนงาน Schedule'!$B$7:$B$156,B42),'ตั้งค่า Setup'!$C$15))
A43: =IF(B43="","",37) | B43: =IF('ตั้งค่า Setup'!$C$62="","",'ตั้งค่า Setup'!$C$62) | C43: =IF(B43="","",COUNTIFS('แผนงาน Schedule'!$B$7:$B$156,B43,'แผนงาน Schedule'!$D$7:$D$156,"<>")) | D43: =IF(B43="","",SUMIF('แผนงาน Schedule'!$B$7:$B$156,B43,'แผนงาน Schedule'!$H$7:$H$156)) | E43: =IF(B43="","",SUMIF('แผนงาน Schedule'!$B$7:$B$156,B43,'แผนงาน Schedule'!$G$7:$G$156)) | F43: =IF(OR(B43="",N(C43)=0),"",_xlfn.MINIFS('แผนงาน Schedule'!$I$7:$I$156,'แผนงาน Schedule'!$B$7:$B$156,B43)) | G43: =IF(OR(B43="",N(C43)=0),"",_xlfn.MAXIFS('แผนงาน Schedule'!$J$7:$J$156,'แผนงาน Schedule'!$B$7:$B$156,B43)) | H43: =IF(OR(B43="",COUNTIFS('แผนงาน Schedule'!$B$7:$B$156,B43,'แผนงาน Schedule'!$N$7:$N$156,"<>")=0),"",_xlfn.MINIFS('แผนงาน Schedule'!$N$7:$N$156,'แผนงาน Schedule'!$B$7:$B$156,B43)) | I43: =IF(OR(B43="",N(E43)=0),"",SUMPRODUCT(('แผนงาน Schedule'!$B$7:$B$156=B43)*'แผนงาน Schedule'!$G$7:$G$156*(('แผนงาน Schedule'!$J$7:$J$156<=Dashboard!$C$7)+('แผนงาน Schedule'!$I$7:$I$156<=Dashboard!$C$7)*('แผนงาน Schedule'!$J$7:$J$156>Dashboard!$C$7)*(Dashboard!$C$7-'แผนงาน Schedule'!$I$7:$I$156+1)/('แผนงาน Schedule'!$J$7:$J$156-'แผนงาน Schedule'!$I$7:$I$156+1)))/E43) | J43: =IF(OR(B43="",N(E43)=0),"",SUMPRODUCT(('แผนงาน Schedule'!$B$7:$B$156=B43)*'แผนงาน Schedule'!$G$7:$G$156*'แผนงาน Schedule'!$P$7:$P$156)/E43) | K43: =IF(I43="","",J43-I43) | L43: =IF(OR(I43="",N(I43)=0),"",J43/I43) | M43: =IF(OR(B43="",N(C43)=0),"",_xlfn.MAXIFS('แผนงาน Schedule'!$W$7:$W$156,'แผนงาน Schedule'!$B$7:$B$156,B43)) | N43: =IF(OR(M43="",G43=""),"",M43-G43) | O43: =IF(B43="","",COUNTIFS('แผนงาน Schedule'!$B$7:$B$156,B43,'แผนงาน Schedule'!$Y$7:$Y$156,"*ล่าช้า*")+COUNTIFS('แผนงาน Schedule'!$B$7:$B$156,B43,'แผนงาน Schedule'!$Y$7:$Y$156,"*เกินกำหนด*")) | P43: =IF(OR(B43="",N(C43)=0),"",IF(N(J43)>=1,"แล้วเสร็จ / Completed",IF(AND(N(I43)=0,N(J43)=0),"ยังไม่เริ่ม / Not Started",IF(N(J43)>=N(I43),"ตามแผน / On Track",IF(N(J43)/I43>=0.9,"เฝ้าระวัง / At Risk","ล่าช้า / Behind"))))) | Q43: =IF(B43="","",N(I43)*N(E43)) | R43: =IF(B43="","",N(J43)*N(E43)) | S43: =IF(H43="","",IF(COUNTIFS('แผนงาน Schedule'!$B$7:$B$156,B43,'แผนงาน Schedule'!$D$7:$D$156,"<>",'แผนงาน Schedule'!$O$7:$O$156,"")=0,_xlfn.MAXIFS('แผนงาน Schedule'!$O$7:$O$156,'แผนงาน Schedule'!$B$7:$B$156,B43),'ตั้งค่า Setup'!$C$15))
A44: =IF(B44="","",38) | B44: =IF('ตั้งค่า Setup'!$C$63="","",'ตั้งค่า Setup'!$C$63) | C44: =IF(B44="","",COUNTIFS('แผนงาน Schedule'!$B$7:$B$156,B44,'แผนงาน Schedule'!$D$7:$D$156,"<>")) | D44: =IF(B44="","",SUMIF('แผนงาน Schedule'!$B$7:$B$156,B44,'แผนงาน Schedule'!$H$7:$H$156)) | E44: =IF(B44="","",SUMIF('แผนงาน Schedule'!$B$7:$B$156,B44,'แผนงาน Schedule'!$G$7:$G$156)) | F44: =IF(OR(B44="",N(C44)=0),"",_xlfn.MINIFS('แผนงาน Schedule'!$I$7:$I$156,'แผนงาน Schedule'!$B$7:$B$156,B44)) | G44: =IF(OR(B44="",N(C44)=0),"",_xlfn.MAXIFS('แผนงาน Schedule'!$J$7:$J$156,'แผนงาน Schedule'!$B$7:$B$156,B44)) | H44: =IF(OR(B44="",COUNTIFS('แผนงาน Schedule'!$B$7:$B$156,B44,'แผนงาน Schedule'!$N$7:$N$156,"<>")=0),"",_xlfn.MINIFS('แผนงาน Schedule'!$N$7:$N$156,'แผนงาน Schedule'!$B$7:$B$156,B44)) | I44: =IF(OR(B44="",N(E44)=0),"",SUMPRODUCT(('แผนงาน Schedule'!$B$7:$B$156=B44)*'แผนงาน Schedule'!$G$7:$G$156*(('แผนงาน Schedule'!$J$7:$J$156<=Dashboard!$C$7)+('แผนงาน Schedule'!$I$7:$I$156<=Dashboard!$C$7)*('แผนงาน Schedule'!$J$7:$J$156>Dashboard!$C$7)*(Dashboard!$C$7-'แผนงาน Schedule'!$I$7:$I$156+1)/('แผนงาน Schedule'!$J$7:$J$156-'แผนงาน Schedule'!$I$7:$I$156+1)))/E44) | J44: =IF(OR(B44="",N(E44)=0),"",SUMPRODUCT(('แผนงาน Schedule'!$B$7:$B$156=B44)*'แผนงาน Schedule'!$G$7:$G$156*'แผนงาน Schedule'!$P$7:$P$156)/E44) | K44: =IF(I44="","",J44-I44) | L44: =IF(OR(I44="",N(I44)=0),"",J44/I44) | M44: =IF(OR(B44="",N(C44)=0),"",_xlfn.MAXIFS('แผนงาน Schedule'!$W$7:$W$156,'แผนงาน Schedule'!$B$7:$B$156,B44)) | N44: =IF(OR(M44="",G44=""),"",M44-G44) | O44: =IF(B44="","",COUNTIFS('แผนงาน Schedule'!$B$7:$B$156,B44,'แผนงาน Schedule'!$Y$7:$Y$156,"*ล่าช้า*")+COUNTIFS('แผนงาน Schedule'!$B$7:$B$156,B44,'แผนงาน Schedule'!$Y$7:$Y$156,"*เกินกำหนด*")) | P44: =IF(OR(B44="",N(C44)=0),"",IF(N(J44)>=1,"แล้วเสร็จ / Completed",IF(AND(N(I44)=0,N(J44)=0),"ยังไม่เริ่ม / Not Started",IF(N(J44)>=N(I44),"ตามแผน / On Track",IF(N(J44)/I44>=0.9,"เฝ้าระวัง / At Risk","ล่าช้า / Behind"))))) | Q44: =IF(B44="","",N(I44)*N(E44)) | R44: =IF(B44="","",N(J44)*N(E44)) | S44: =IF(H44="","",IF(COUNTIFS('แผนงาน Schedule'!$B$7:$B$156,B44,'แผนงาน Schedule'!$D$7:$D$156,"<>",'แผนงาน Schedule'!$O$7:$O$156,"")=0,_xlfn.MAXIFS('แผนงาน Schedule'!$O$7:$O$156,'แผนงาน Schedule'!$B$7:$B$156,B44),'ตั้งค่า Setup'!$C$15))
A45: =IF(B45="","",39) | B45: =IF('ตั้งค่า Setup'!$C$64="","",'ตั้งค่า Setup'!$C$64) | C45: =IF(B45="","",COUNTIFS('แผนงาน Schedule'!$B$7:$B$156,B45,'แผนงาน Schedule'!$D$7:$D$156,"<>")) | D45: =IF(B45="","",SUMIF('แผนงาน Schedule'!$B$7:$B$156,B45,'แผนงาน Schedule'!$H$7:$H$156)) | E45: =IF(B45="","",SUMIF('แผนงาน Schedule'!$B$7:$B$156,B45,'แผนงาน Schedule'!$G$7:$G$156)) | F45: =IF(OR(B45="",N(C45)=0),"",_xlfn.MINIFS('แผนงาน Schedule'!$I$7:$I$156,'แผนงาน Schedule'!$B$7:$B$156,B45)) | G45: =IF(OR(B45="",N(C45)=0),"",_xlfn.MAXIFS('แผนงาน Schedule'!$J$7:$J$156,'แผนงาน Schedule'!$B$7:$B$156,B45)) | H45: =IF(OR(B45="",COUNTIFS('แผนงาน Schedule'!$B$7:$B$156,B45,'แผนงาน Schedule'!$N$7:$N$156,"<>")=0),"",_xlfn.MINIFS('แผนงาน Schedule'!$N$7:$N$156,'แผนงาน Schedule'!$B$7:$B$156,B45)) | I45: =IF(OR(B45="",N(E45)=0),"",SUMPRODUCT(('แผนงาน Schedule'!$B$7:$B$156=B45)*'แผนงาน Schedule'!$G$7:$G$156*(('แผนงาน Schedule'!$J$7:$J$156<=Dashboard!$C$7)+('แผนงาน Schedule'!$I$7:$I$156<=Dashboard!$C$7)*('แผนงาน Schedule'!$J$7:$J$156>Dashboard!$C$7)*(Dashboard!$C$7-'แผนงาน Schedule'!$I$7:$I$156+1)/('แผนงาน Schedule'!$J$7:$J$156-'แผนงาน Schedule'!$I$7:$I$156+1)))/E45) | J45: =IF(OR(B45="",N(E45)=0),"",SUMPRODUCT(('แผนงาน Schedule'!$B$7:$B$156=B45)*'แผนงาน Schedule'!$G$7:$G$156*'แผนงาน Schedule'!$P$7:$P$156)/E45) | K45: =IF(I45="","",J45-I45) | L45: =IF(OR(I45="",N(I45)=0),"",J45/I45) | M45: =IF(OR(B45="",N(C45)=0),"",_xlfn.MAXIFS('แผนงาน Schedule'!$W$7:$W$156,'แผนงาน Schedule'!$B$7:$B$156,B45)) | N45: =IF(OR(M45="",G45=""),"",M45-G45) | O45: =IF(B45="","",COUNTIFS('แผนงาน Schedule'!$B$7:$B$156,B45,'แผนงาน Schedule'!$Y$7:$Y$156,"*ล่าช้า*")+COUNTIFS('แผนงาน Schedule'!$B$7:$B$156,B45,'แผนงาน Schedule'!$Y$7:$Y$156,"*เกินกำหนด*")) | P45: =IF(OR(B45="",N(C45)=0),"",IF(N(J45)>=1,"แล้วเสร็จ / Completed",IF(AND(N(I45)=0,N(J45)=0),"ยังไม่เริ่ม / Not Started",IF(N(J45)>=N(I45),"ตามแผน / On Track",IF(N(J45)/I45>=0.9,"เฝ้าระวัง / At Risk","ล่าช้า / Behind"))))) | Q45: =IF(B45="","",N(I45)*N(E45)) | R45: =IF(B45="","",N(J45)*N(E45)) | S45: =IF(H45="","",IF(COUNTIFS('แผนงาน Schedule'!$B$7:$B$156,B45,'แผนงาน Schedule'!$D$7:$D$156,"<>",'แผนงาน Schedule'!$O$7:$O$156,"")=0,_xlfn.MAXIFS('แผนงาน Schedule'!$O$7:$O$156,'แผนงาน Schedule'!$B$7:$B$156,B45),'ตั้งค่า Setup'!$C$15))
A46: =IF(B46="","",40) | B46: =IF('ตั้งค่า Setup'!$C$65="","",'ตั้งค่า Setup'!$C$65) | C46: =IF(B46="","",COUNTIFS('แผนงาน Schedule'!$B$7:$B$156,B46,'แผนงาน Schedule'!$D$7:$D$156,"<>")) | D46: =IF(B46="","",SUMIF('แผนงาน Schedule'!$B$7:$B$156,B46,'แผนงาน Schedule'!$H$7:$H$156)) | E46: =IF(B46="","",SUMIF('แผนงาน Schedule'!$B$7:$B$156,B46,'แผนงาน Schedule'!$G$7:$G$156)) | F46: =IF(OR(B46="",N(C46)=0),"",_xlfn.MINIFS('แผนงาน Schedule'!$I$7:$I$156,'แผนงาน Schedule'!$B$7:$B$156,B46)) | G46: =IF(OR(B46="",N(C46)=0),"",_xlfn.MAXIFS('แผนงาน Schedule'!$J$7:$J$156,'แผนงาน Schedule'!$B$7:$B$156,B46)) | H46: =IF(OR(B46="",COUNTIFS('แผนงาน Schedule'!$B$7:$B$156,B46,'แผนงาน Schedule'!$N$7:$N$156,"<>")=0),"",_xlfn.MINIFS('แผนงาน Schedule'!$N$7:$N$156,'แผนงาน Schedule'!$B$7:$B$156,B46)) | I46: =IF(OR(B46="",N(E46)=0),"",SUMPRODUCT(('แผนงาน Schedule'!$B$7:$B$156=B46)*'แผนงาน Schedule'!$G$7:$G$156*(('แผนงาน Schedule'!$J$7:$J$156<=Dashboard!$C$7)+('แผนงาน Schedule'!$I$7:$I$156<=Dashboard!$C$7)*('แผนงาน Schedule'!$J$7:$J$156>Dashboard!$C$7)*(Dashboard!$C$7-'แผนงาน Schedule'!$I$7:$I$156+1)/('แผนงาน Schedule'!$J$7:$J$156-'แผนงาน Schedule'!$I$7:$I$156+1)))/E46) | J46: =IF(OR(B46="",N(E46)=0),"",SUMPRODUCT(('แผนงาน Schedule'!$B$7:$B$156=B46)*'แผนงาน Schedule'!$G$7:$G$156*'แผนงาน Schedule'!$P$7:$P$156)/E46) | K46: =IF(I46="","",J46-I46) | L46: =IF(OR(I46="",N(I46)=0),"",J46/I46) | M46: =IF(OR(B46="",N(C46)=0),"",_xlfn.MAXIFS('แผนงาน Schedule'!$W$7:$W$156,'แผนงาน Schedule'!$B$7:$B$156,B46)) | N46: =IF(OR(M46="",G46=""),"",M46-G46) | O46: =IF(B46="","",COUNTIFS('แผนงาน Schedule'!$B$7:$B$156,B46,'แผนงาน Schedule'!$Y$7:$Y$156,"*ล่าช้า*")+COUNTIFS('แผนงาน Schedule'!$B$7:$B$156,B46,'แผนงาน Schedule'!$Y$7:$Y$156,"*เกินกำหนด*")) | P46: =IF(OR(B46="",N(C46)=0),"",IF(N(J46)>=1,"แล้วเสร็จ / Completed",IF(AND(N(I46)=0,N(J46)=0),"ยังไม่เริ่ม / Not Started",IF(N(J46)>=N(I46),"ตามแผน / On Track",IF(N(J46)/I46>=0.9,"เฝ้าระวัง / At Risk","ล่าช้า / Behind"))))) | Q46: =IF(B46="","",N(I46)*N(E46)) | R46: =IF(B46="","",N(J46)*N(E46)) | S46: =IF(H46="","",IF(COUNTIFS('แผนงาน Schedule'!$B$7:$B$156,B46,'แผนงาน Schedule'!$D$7:$D$156,"<>",'แผนงาน Schedule'!$O$7:$O$156,"")=0,_xlfn.MAXIFS('แผนงาน Schedule'!$O$7:$O$156,'แผนงาน Schedule'!$B$7:$B$156,B46),'ตั้งค่า Setup'!$C$15))
B47: รวมทั้งโครงการ / PROJECT TOTAL | C47: =SUM(C7:C46) -> 21 | D47: =SUM(D7:D46) -> 24200000 | E47: =SUM(E7:E46) -> 1 | F47: =Dashboard!C9 -> 46174 | G47: =Dashboard!C10 -> 46473 | I47: =Dashboard!C16 -> 0.25365051 | J47: =Dashboard!C19 -> 0.18780992 | K47: =J47-I47 -> -0.065840597 | L47: =Dashboard!C22 -> 0.7404279 | M47: =Dashboard!C27 -> 46473 | N47: =IFERROR(M47-G47,"") -> 0 | O47: =SUM(O7:O46) -> 5 | P47: =Dashboard!C32 -> ล่าช้ามาก / Critical Delay | Q47: =SUM(Q7:Q46) -> 0.25365051 | R47: =SUM(R7:R46) -> 0.18780992
B48: หมายเหตุ: % จริงรายงานส่วนคำนวณจาก % รายรายการในชีตแผนงาน • แถวรวมใช้ค่าเดียวกับ Dashboard
A70: ความก้าวหน้ารายหมวดงาน / PROGRESS BY DISCIPLINE (WBS ระดับ 2)
A71: No. | B71: หมวดงาน / Discipline | C71: จำนวน รายการ | D71: มูลค่า Budget (฿) | E71: น้ำหนัก Weight | F71: % แผน Planned | G71: % จริง Actual | H71: ผลต่าง Variance | I71: SPI | J71: ผลงานแผน (% โครงการ) | K71: ผลงานจริง (% โครงการ)
A72: =IF(B72="","",1) -> 1 | B72: =IF('ตั้งค่า Setup'!$C$68="","",'ตั้งค่า Setup'!$C$68) -> งานเตรียมการ / Preliminaries | C72: =IF(B72="","",COUNTIFS('แผนงาน Schedule'!$C$7:$C$156,B72,'แผนงาน Schedule'!$D$7:$D$156,"<>")) -> 1 | D72: =IF(B72="","",SUMIF('แผนงาน Schedule'!$C$7:$C$156,B72,'แผนงาน Schedule'!$H$7:$H$156)) -> 350000 | E72: =IF(B72="","",SUMIF('แผนงาน Schedule'!$C$7:$C$156,B72,'แผนงาน Schedule'!$G$7:$G$156)) -> 0.01446281 | F72: =IF(OR(B72="",N(E72)=0),"",SUMPRODUCT(('แผนงาน Schedule'!$C$7:$C$156=B72)*'แผนงาน Schedule'!$G$7:$G$156*(('แผนงาน Schedule'!$J$7:$J$156<=Dashboard!$C$7)+('แผนงาน Schedule'!$I$7:$I$156<=Dashboard!$C$7)*('แผนงาน Schedule'!$J$7:$J$156>Dashboard!$C$7)*(Dashboard!$C$7-'แผนงาน Schedule'!$I$7:$I$156+1)/('แผนงาน Schedule'!$J$7:$J$156-'แผนงาน Schedule'!$I$7:$I$156+1)))/E72) -> 1 | G72: =IF(OR(B72="",N(E72)=0),"",SUMPRODUCT(('แผนงาน Schedule'!$C$7:$C$156=B72)*'แผนงาน Schedule'!$G$7:$G$156*'แผนงาน Schedule'!$P$7:$P$156)/E72) -> 1 | H72: =IF(F72="","",G72-F72) -> 0 | I72: =IF(OR(F72="",N(F72)=0),"",G72/F72) -> 1 | J72: =IF(B72="","",N(F72)*N(E72)) -> 0.01446281 | K72: =IF(B72="","",N(G72)*N(E72)) -> 0.01446281
A73: =IF(B73="","",2) -> 2 | B73: =IF('ตั้งค่า Setup'!$C$69="","",'ตั้งค่า Setup'!$C$69) -> งานดิน / Earthworks | C73: =IF(B73="","",COUNTIFS('แผนงาน Schedule'!$C$7:$C$156,B73,'แผนงาน Schedule'!$D$7:$D$156,"<>")) -> 3 | D73: =IF(B73="","",SUMIF('แผนงาน Schedule'!$C$7:$C$156,B73,'แผนงาน Schedule'!$H$7:$H$156)) -> 3600000 | E73: =IF(B73="","",SUMIF('แผนงาน Schedule'!$C$7:$C$156,B73,'แผนงาน Schedule'!$G$7:$G$156)) -> 0.14876033 | F73: =IF(OR(B73="",N(E73)=0),"",SUMPRODUCT(('แผนงาน Schedule'!$C$7:$C$156=B73)*'แผนงาน Schedule'!$G$7:$G$156*(('แผนงาน Schedule'!$J$7:$J$156<=Dashboard!$C$7)+('แผนงาน Schedule'!$I$7:$I$156<=Dashboard!$C$7)*('แผนงาน Schedule'!$J$7:$J$156>Dashboard!$C$7)*(Dashboard!$C$7-'แผนงาน Schedule'!$I$7:$I$156+1)/('แผนงาน Schedule'!$J$7:$J$156-'แผนงาน Schedule'!$I$7:$I$156+1)))/E73) -> 0.75 | G73: =IF(OR(B73="",N(E73)=0),"",SUMPRODUCT(('แผนงาน Schedule'!$C$7:$C$156=B73)*'แผนงาน Schedule'!$G$7:$G$156*'แผนงาน Schedule'!$P$7:$P$156)/E73) -> 0.73333333 | H73: =IF(F73="","",G73-F73) -> -0.016666667 | I73: =IF(OR(F73="",N(F73)=0),"",G73/F73) -> 0.97777778 | J73: =IF(B73="","",N(F73)*N(E73)) -> 0.11157025 | K73: =IF(B73="","",N(G73)*N(E73)) -> 0.10909091
A74: =IF(B74="","",3) -> 3 | B74: =IF('ตั้งค่า Setup'!$C$70="","",'ตั้งค่า Setup'!$C$70) -> งานโครงสร้าง / Structural | C74: =IF(B74="","",COUNTIFS('แผนงาน Schedule'!$C$7:$C$156,B74,'แผนงาน Schedule'!$D$7:$D$156,"<>")) -> 8 | D74: =IF(B74="","",SUMIF('แผนงาน Schedule'!$C$7:$C$156,B74,'แผนงาน Schedule'!$H$7:$H$156)) -> 11650000 | E74: =IF(B74="","",SUMIF('แผนงาน Schedule'!$C$7:$C$156,B74,'แผนงาน Schedule'!$G$7:$G$156)) -> 0.48140496 | F74: =IF(OR(B74="",N(E74)=0),"",SUMPRODUCT(('แผนงาน Schedule'!$C$7:$C$156=B74)*'แผนงาน Schedule'!$G$7:$G$156*(('แผนงาน Schedule'!$J$7:$J$156<=Dashboard!$C$7)+('แผนงาน Schedule'!$I$7:$I$156<=Dashboard!$C$7)*('แผนงาน Schedule'!$J$7:$J$156>Dashboard!$C$7)*(Dashboard!$C$7-'แผนงาน Schedule'!$I$7:$I$156+1)/('แผนงาน Schedule'!$J$7:$J$156-'แผนงาน Schedule'!$I$7:$I$156+1)))/E74) -> 0.26509377 | G74: =IF(OR(B74="",N(E74)=0),"",SUMPRODUCT(('แผนงาน Schedule'!$C$7:$C$156=B74)*'แผนงาน Schedule'!$G$7:$G$156*'แผนงาน Schedule'!$P$7:$P$156)/E74) -> 0.13347639 | H74: =IF(F74="","",G74-F74) -> -0.13161738 | I74: =IF(OR(F74="",N(F74)=0),"",G74/F74) -> 0.50350634 | J74: =IF(B74="","",N(F74)*N(E74)) -> 0.12761746 | K74: =IF(B74="","",N(G74)*N(E74)) -> 0.064256198
A75: =IF(B75="","",4) -> 4 | B75: =IF('ตั้งค่า Setup'!$C$71="","",'ตั้งค่า Setup'!$C$71) -> งานสถาปัตยกรรม / Architectural | C75: =IF(B75="","",COUNTIFS('แผนงาน Schedule'!$C$7:$C$156,B75,'แผนงาน Schedule'!$D$7:$D$156,"<>")) -> 5 | D75: =IF(B75="","",SUMIF('แผนงาน Schedule'!$C$7:$C$156,B75,'แผนงาน Schedule'!$H$7:$H$156)) -> 6350000 | E75: =IF(B75="","",SUMIF('แผนงาน Schedule'!$C$7:$C$156,B75,'แผนงาน Schedule'!$G$7:$G$156)) -> 0.26239669 | F75: =IF(OR(B75="",N(E75)=0),"",SUMPRODUCT(('แผนงาน Schedule'!$C$7:$C$156=B75)*'แผนงาน Schedule'!$G$7:$G$156*(('แผนงาน Schedule'!$J$7:$J$156<=Dashboard!$C$7)+('แผนงาน Schedule'!$I$7:$I$156<=Dashboard!$C$7)*('แผนงาน Schedule'!$J$7:$J$156>Dashboard!$C$7)*(Dashboard!$C$7-'แผนงาน Schedule'!$I$7:$I$156+1)/('แผนงาน Schedule'!$J$7:$J$156-'แผนงาน Schedule'!$I$7:$I$156+1)))/E75) -> 0 | G75: =IF(OR(B75="",N(E75)=0),"",SUMPRODUCT(('แผนงาน Schedule'!$C$7:$C$156=B75)*'แผนงาน Schedule'!$G$7:$G$156*'แผนงาน Schedule'!$P$7:$P$156)/E75) -> 0 | H75: =IF(F75="","",G75-F75) -> 0 | I75: =IF(OR(F75="",N(F75)=0),"",G75/F75) | J75: =IF(B75="","",N(F75)*N(E75)) -> 0 | K75: =IF(B75="","",N(G75)*N(E75)) -> 0
A76: =IF(B76="","",5) -> 5 | B76: =IF('ตั้งค่า Setup'!$C$72="","",'ตั้งค่า Setup'!$C$72) -> งานระบบ / MEP | C76: =IF(B76="","",COUNTIFS('แผนงาน Schedule'!$C$7:$C$156,B76,'แผนงาน Schedule'!$D$7:$D$156,"<>")) -> 3 | D76: =IF(B76="","",SUMIF('แผนงาน Schedule'!$C$7:$C$156,B76,'แผนงาน Schedule'!$H$7:$H$156)) -> 2000000 | E76: =IF(B76="","",SUMIF('แผนงาน Schedule'!$C$7:$C$156,B76,'แผนงาน Schedule'!$G$7:$G$156)) -> 0.082644628 | F76: =IF(OR(B76="",N(E76)=0),"",SUMPRODUCT(('แผนงาน Schedule'!$C$7:$C$156=B76)*'แผนงาน Schedule'!$G$7:$G$156*(('แผนงาน Schedule'!$J$7:$J$156<=Dashboard!$C$7)+('แผนงาน Schedule'!$I$7:$I$156<=Dashboard!$C$7)*('แผนงาน Schedule'!$J$7:$J$156>Dashboard!$C$7)*(Dashboard!$C$7-'แผนงาน Schedule'!$I$7:$I$156+1)/('แผนงาน Schedule'!$J$7:$J$156-'แผนงาน Schedule'!$I$7:$I$156+1)))/E76) -> 0 | G76: =IF(OR(B76="",N(E76)=0),"",SUMPRODUCT(('แผนงาน Schedule'!$C$7:$C$156=B76)*'แผนงาน Schedule'!$G$7:$G$156*'แผนงาน Schedule'!$P$7:$P$156)/E76) -> 0 | H76: =IF(F76="","",G76-F76) -> 0 | I76: =IF(OR(F76="",N(F76)=0),"",G76/F76) | J76: =IF(B76="","",N(F76)*N(E76)) -> 0 | K76: =IF(B76="","",N(G76)*N(E76)) -> 0
A77: =IF(B77="","",6) -> 6 | B77: =IF('ตั้งค่า Setup'!$C$73="","",'ตั้งค่า Setup'!$C$73) -> งานภายนอกและภูมิทัศน์ / External Works | C77: =IF(B77="","",COUNTIFS('แผนงาน Schedule'!$C$7:$C$156,B77,'แผนงาน Schedule'!$D$7:$D$156,"<>")) -> 1 | D77: =IF(B77="","",SUMIF('แผนงาน Schedule'!$C$7:$C$156,B77,'แผนงาน Schedule'!$H$7:$H$156)) -> 250000 | E77: =IF(B77="","",SUMIF('แผนงาน Schedule'!$C$7:$C$156,B77,'แผนงาน Schedule'!$G$7:$G$156)) -> 0.010330579 | F77: =IF(OR(B77="",N(E77)=0),"",SUMPRODUCT(('แผนงาน Schedule'!$C$7:$C$156=B77)*'แผนงาน Schedule'!$G$7:$G$156*(('แผนงาน Schedule'!$J$7:$J$156<=Dashboard!$C$7)+('แผนงาน Schedule'!$I$7:$I$156<=Dashboard!$C$7)*('แผนงาน Schedule'!$J$7:$J$156>Dashboard!$C$7)*(Dashboard!$C$7-'แผนงาน Schedule'!$I$7:$I$156+1)/('แผนงาน Schedule'!$J$7:$J$156-'แผนงาน Schedule'!$I$7:$I$156+1)))/E77) -> 0 | G77: =IF(OR(B77="",N(E77)=0),"",SUMPRODUCT(('แผนงาน Schedule'!$C$7:$C$156=B77)*'แผนงาน Schedule'!$G$7:$G$156*'แผนงาน Schedule'!$P$7:$P$156)/E77) -> 0 | H77: =IF(F77="","",G77-F77) -> 0 | I77: =IF(OR(F77="",N(F77)=0),"",G77/F77) | J77: =IF(B77="","",N(F77)*N(E77)) -> 0 | K77: =IF(B77="","",N(G77)*N(E77)) -> 0
A78: =IF(B78="","",7) | B78: =IF('ตั้งค่า Setup'!$C$74="","",'ตั้งค่า Setup'!$C$74) | C78: =IF(B78="","",COUNTIFS('แผนงาน Schedule'!$C$7:$C$156,B78,'แผนงาน Schedule'!$D$7:$D$156,"<>")) | D78: =IF(B78="","",SUMIF('แผนงาน Schedule'!$C$7:$C$156,B78,'แผนงาน Schedule'!$H$7:$H$156)) | E78: =IF(B78="","",SUMIF('แผนงาน Schedule'!$C$7:$C$156,B78,'แผนงาน Schedule'!$G$7:$G$156)) | F78: =IF(OR(B78="",N(E78)=0),"",SUMPRODUCT(('แผนงาน Schedule'!$C$7:$C$156=B78)*'แผนงาน Schedule'!$G$7:$G$156*(('แผนงาน Schedule'!$J$7:$J$156<=Dashboard!$C$7)+('แผนงาน Schedule'!$I$7:$I$156<=Dashboard!$C$7)*('แผนงาน Schedule'!$J$7:$J$156>Dashboard!$C$7)*(Dashboard!$C$7-'แผนงาน Schedule'!$I$7:$I$156+1)/('แผนงาน Schedule'!$J$7:$J$156-'แผนงาน Schedule'!$I$7:$I$156+1)))/E78) | G78: =IF(OR(B78="",N(E78)=0),"",SUMPRODUCT(('แผนงาน Schedule'!$C$7:$C$156=B78)*'แผนงาน Schedule'!$G$7:$G$156*'แผนงาน Schedule'!$P$7:$P$156)/E78) | H78: =IF(F78="","",G78-F78) | I78: =IF(OR(F78="",N(F78)=0),"",G78/F78) | J78: =IF(B78="","",N(F78)*N(E78)) | K78: =IF(B78="","",N(G78)*N(E78))
A79: =IF(B79="","",8) | B79: =IF('ตั้งค่า Setup'!$C$75="","",'ตั้งค่า Setup'!$C$75) | C79: =IF(B79="","",COUNTIFS('แผนงาน Schedule'!$C$7:$C$156,B79,'แผนงาน Schedule'!$D$7:$D$156,"<>")) | D79: =IF(B79="","",SUMIF('แผนงาน Schedule'!$C$7:$C$156,B79,'แผนงาน Schedule'!$H$7:$H$156)) | E79: =IF(B79="","",SUMIF('แผนงาน Schedule'!$C$7:$C$156,B79,'แผนงาน Schedule'!$G$7:$G$156)) | F79: =IF(OR(B79="",N(E79)=0),"",SUMPRODUCT(('แผนงาน Schedule'!$C$7:$C$156=B79)*'แผนงาน Schedule'!$G$7:$G$156*(('แผนงาน Schedule'!$J$7:$J$156<=Dashboard!$C$7)+('แผนงาน Schedule'!$I$7:$I$156<=Dashboard!$C$7)*('แผนงาน Schedule'!$J$7:$J$156>Dashboard!$C$7)*(Dashboard!$C$7-'แผนงาน Schedule'!$I$7:$I$156+1)/('แผนงาน Schedule'!$J$7:$J$156-'แผนงาน Schedule'!$I$7:$I$156+1)))/E79) | G79: =IF(OR(B79="",N(E79)=0),"",SUMPRODUCT(('แผนงาน Schedule'!$C$7:$C$156=B79)*'แผนงาน Schedule'!$G$7:$G$156*'แผนงาน Schedule'!$P$7:$P$156)/E79) | H79: =IF(F79="","",G79-F79) | I79: =IF(OR(F79="",N(F79)=0),"",G79/F79) | J79: =IF(B79="","",N(F79)*N(E79)) | K79: =IF(B79="","",N(G79)*N(E79))
A80: =IF(B80="","",9) | B80: =IF('ตั้งค่า Setup'!$C$76="","",'ตั้งค่า Setup'!$C$76) | C80: =IF(B80="","",COUNTIFS('แผนงาน Schedule'!$C$7:$C$156,B80,'แผนงาน Schedule'!$D$7:$D$156,"<>")) | D80: =IF(B80="","",SUMIF('แผนงาน Schedule'!$C$7:$C$156,B80,'แผนงาน Schedule'!$H$7:$H$156)) | E80: =IF(B80="","",SUMIF('แผนงาน Schedule'!$C$7:$C$156,B80,'แผนงาน Schedule'!$G$7:$G$156)) | F80: =IF(OR(B80="",N(E80)=0),"",SUMPRODUCT(('แผนงาน Schedule'!$C$7:$C$156=B80)*'แผนงาน Schedule'!$G$7:$G$156*(('แผนงาน Schedule'!$J$7:$J$156<=Dashboard!$C$7)+('แผนงาน Schedule'!$I$7:$I$156<=Dashboard!$C$7)*('แผนงาน Schedule'!$J$7:$J$156>Dashboard!$C$7)*(Dashboard!$C$7-'แผนงาน Schedule'!$I$7:$I$156+1)/('แผนงาน Schedule'!$J$7:$J$156-'แผนงาน Schedule'!$I$7:$I$156+1)))/E80) | G80: =IF(OR(B80="",N(E80)=0),"",SUMPRODUCT(('แผนงาน Schedule'!$C$7:$C$156=B80)*'แผนงาน Schedule'!$G$7:$G$156*'แผนงาน Schedule'!$P$7:$P$156)/E80) | H80: =IF(F80="","",G80-F80) | I80: =IF(OR(F80="",N(F80)=0),"",G80/F80) | J80: =IF(B80="","",N(F80)*N(E80)) | K80: =IF(B80="","",N(G80)*N(E80))
A81: =IF(B81="","",10) | B81: =IF('ตั้งค่า Setup'!$C$77="","",'ตั้งค่า Setup'!$C$77) | C81: =IF(B81="","",COUNTIFS('แผนงาน Schedule'!$C$7:$C$156,B81,'แผนงาน Schedule'!$D$7:$D$156,"<>")) | D81: =IF(B81="","",SUMIF('แผนงาน Schedule'!$C$7:$C$156,B81,'แผนงาน Schedule'!$H$7:$H$156)) | E81: =IF(B81="","",SUMIF('แผนงาน Schedule'!$C$7:$C$156,B81,'แผนงาน Schedule'!$G$7:$G$156)) | F81: =IF(OR(B81="",N(E81)=0),"",SUMPRODUCT(('แผนงาน Schedule'!$C$7:$C$156=B81)*'แผนงาน Schedule'!$G$7:$G$156*(('แผนงาน Schedule'!$J$7:$J$156<=Dashboard!$C$7)+('แผนงาน Schedule'!$I$7:$I$156<=Dashboard!$C$7)*('แผนงาน Schedule'!$J$7:$J$156>Dashboard!$C$7)*(Dashboard!$C$7-'แผนงาน Schedule'!$I$7:$I$156+1)/('แผนงาน Schedule'!$J$7:$J$156-'แผนงาน Schedule'!$I$7:$I$156+1)))/E81) | G81: =IF(OR(B81="",N(E81)=0),"",SUMPRODUCT(('แผนงาน Schedule'!$C$7:$C$156=B81)*'แผนงาน Schedule'!$G$7:$G$156*'แผนงาน Schedule'!$P$7:$P$156)/E81) | H81: =IF(F81="","",G81-F81) | I81: =IF(OR(F81="",N(F81)=0),"",G81/F81) | J81: =IF(B81="","",N(F81)*N(E81)) | K81: =IF(B81="","",N(G81)*N(E81))
A82: =IF(B82="","",11) | B82: =IF('ตั้งค่า Setup'!$C$78="","",'ตั้งค่า Setup'!$C$78) | C82: =IF(B82="","",COUNTIFS('แผนงาน Schedule'!$C$7:$C$156,B82,'แผนงาน Schedule'!$D$7:$D$156,"<>")) | D82: =IF(B82="","",SUMIF('แผนงาน Schedule'!$C$7:$C$156,B82,'แผนงาน Schedule'!$H$7:$H$156)) | E82: =IF(B82="","",SUMIF('แผนงาน Schedule'!$C$7:$C$156,B82,'แผนงาน Schedule'!$G$7:$G$156)) | F82: =IF(OR(B82="",N(E82)=0),"",SUMPRODUCT(('แผนงาน Schedule'!$C$7:$C$156=B82)*'แผนงาน Schedule'!$G$7:$G$156*(('แผนงาน Schedule'!$J$7:$J$156<=Dashboard!$C$7)+('แผนงาน Schedule'!$I$7:$I$156<=Dashboard!$C$7)*('แผนงาน Schedule'!$J$7:$J$156>Dashboard!$C$7)*(Dashboard!$C$7-'แผนงาน Schedule'!$I$7:$I$156+1)/('แผนงาน Schedule'!$J$7:$J$156-'แผนงาน Schedule'!$I$7:$I$156+1)))/E82) | G82: =IF(OR(B82="",N(E82)=0),"",SUMPRODUCT(('แผนงาน Schedule'!$C$7:$C$156=B82)*'แผนงาน Schedule'!$G$7:$G$156*'แผนงาน Schedule'!$P$7:$P$156)/E82) | H82: =IF(F82="","",G82-F82) | I82: =IF(OR(F82="",N(F82)=0),"",G82/F82) | J82: =IF(B82="","",N(F82)*N(E82)) | K82: =IF(B82="","",N(G82)*N(E82))
A83: =IF(B83="","",12) | B83: =IF('ตั้งค่า Setup'!$C$79="","",'ตั้งค่า Setup'!$C$79) | C83: =IF(B83="","",COUNTIFS('แผนงาน Schedule'!$C$7:$C$156,B83,'แผนงาน Schedule'!$D$7:$D$156,"<>")) | D83: =IF(B83="","",SUMIF('แผนงาน Schedule'!$C$7:$C$156,B83,'แผนงาน Schedule'!$H$7:$H$156)) | E83: =IF(B83="","",SUMIF('แผนงาน Schedule'!$C$7:$C$156,B83,'แผนงาน Schedule'!$G$7:$G$156)) | F83: =IF(OR(B83="",N(E83)=0),"",SUMPRODUCT(('แผนงาน Schedule'!$C$7:$C$156=B83)*'แผนงาน Schedule'!$G$7:$G$156*(('แผนงาน Schedule'!$J$7:$J$156<=Dashboard!$C$7)+('แผนงาน Schedule'!$I$7:$I$156<=Dashboard!$C$7)*('แผนงาน Schedule'!$J$7:$J$156>Dashboard!$C$7)*(Dashboard!$C$7-'แผนงาน Schedule'!$I$7:$I$156+1)/('แผนงาน Schedule'!$J$7:$J$156-'แผนงาน Schedule'!$I$7:$I$156+1)))/E83) | G83: =IF(OR(B83="",N(E83)=0),"",SUMPRODUCT(('แผนงาน Schedule'!$C$7:$C$156=B83)*'แผนงาน Schedule'!$G$7:$G$156*'แผนงาน Schedule'!$P$7:$P$156)/E83) | H83: =IF(F83="","",G83-F83) | I83: =IF(OR(F83="",N(F83)=0),"",G83/F83) | J83: =IF(B83="","",N(F83)*N(E83)) | K83: =IF(B83="","",N(G83)*N(E83))
A84: =IF(B84="","",13) | B84: =IF('ตั้งค่า Setup'!$C$80="","",'ตั้งค่า Setup'!$C$80) | C84: =IF(B84="","",COUNTIFS('แผนงาน Schedule'!$C$7:$C$156,B84,'แผนงาน Schedule'!$D$7:$D$156,"<>")) | D84: =IF(B84="","",SUMIF('แผนงาน Schedule'!$C$7:$C$156,B84,'แผนงาน Schedule'!$H$7:$H$156)) | E84: =IF(B84="","",SUMIF('แผนงาน Schedule'!$C$7:$C$156,B84,'แผนงาน Schedule'!$G$7:$G$156)) | F84: =IF(OR(B84="",N(E84)=0),"",SUMPRODUCT(('แผนงาน Schedule'!$C$7:$C$156=B84)*'แผนงาน Schedule'!$G$7:$G$156*(('แผนงาน Schedule'!$J$7:$J$156<=Dashboard!$C$7)+('แผนงาน Schedule'!$I$7:$I$156<=Dashboard!$C$7)*('แผนงาน Schedule'!$J$7:$J$156>Dashboard!$C$7)*(Dashboard!$C$7-'แผนงาน Schedule'!$I$7:$I$156+1)/('แผนงาน Schedule'!$J$7:$J$156-'แผนงาน Schedule'!$I$7:$I$156+1)))/E84) | G84: =IF(OR(B84="",N(E84)=0),"",SUMPRODUCT(('แผนงาน Schedule'!$C$7:$C$156=B84)*'แผนงาน Schedule'!$G$7:$G$156*'แผนงาน Schedule'!$P$7:$P$156)/E84) | H84: =IF(F84="","",G84-F84) | I84: =IF(OR(F84="",N(F84)=0),"",G84/F84) | J84: =IF(B84="","",N(F84)*N(E84)) | K84: =IF(B84="","",N(G84)*N(E84))
A85: =IF(B85="","",14) | B85: =IF('ตั้งค่า Setup'!$C$81="","",'ตั้งค่า Setup'!$C$81) | C85: =IF(B85="","",COUNTIFS('แผนงาน Schedule'!$C$7:$C$156,B85,'แผนงาน Schedule'!$D$7:$D$156,"<>")) | D85: =IF(B85="","",SUMIF('แผนงาน Schedule'!$C$7:$C$156,B85,'แผนงาน Schedule'!$H$7:$H$156)) | E85: =IF(B85="","",SUMIF('แผนงาน Schedule'!$C$7:$C$156,B85,'แผนงาน Schedule'!$G$7:$G$156)) | F85: =IF(OR(B85="",N(E85)=0),"",SUMPRODUCT(('แผนงาน Schedule'!$C$7:$C$156=B85)*'แผนงาน Schedule'!$G$7:$G$156*(('แผนงาน Schedule'!$J$7:$J$156<=Dashboard!$C$7)+('แผนงาน Schedule'!$I$7:$I$156<=Dashboard!$C$7)*('แผนงาน Schedule'!$J$7:$J$156>Dashboard!$C$7)*(Dashboard!$C$7-'แผนงาน Schedule'!$I$7:$I$156+1)/('แผนงาน Schedule'!$J$7:$J$156-'แผนงาน Schedule'!$I$7:$I$156+1)))/E85) | G85: =IF(OR(B85="",N(E85)=0),"",SUMPRODUCT(('แผนงาน Schedule'!$C$7:$C$156=B85)*'แผนงาน Schedule'!$G$7:$G$156*'แผนงาน Schedule'!$P$7:$P$156)/E85) | H85: =IF(F85="","",G85-F85) | I85: =IF(OR(F85="",N(F85)=0),"",G85/F85) | J85: =IF(B85="","",N(F85)*N(E85)) | K85: =IF(B85="","",N(G85)*N(E85))
A86: =IF(B86="","",15) | B86: =IF('ตั้งค่า Setup'!$C$82="","",'ตั้งค่า Setup'!$C$82) | C86: =IF(B86="","",COUNTIFS('แผนงาน Schedule'!$C$7:$C$156,B86,'แผนงาน Schedule'!$D$7:$D$156,"<>")) | D86: =IF(B86="","",SUMIF('แผนงาน Schedule'!$C$7:$C$156,B86,'แผนงาน Schedule'!$H$7:$H$156)) | E86: =IF(B86="","",SUMIF('แผนงาน Schedule'!$C$7:$C$156,B86,'แผนงาน Schedule'!$G$7:$G$156)) | F86: =IF(OR(B86="",N(E86)=0),"",SUMPRODUCT(('แผนงาน Schedule'!$C$7:$C$156=B86)*'แผนงาน Schedule'!$G$7:$G$156*(('แผนงาน Schedule'!$J$7:$J$156<=Dashboard!$C$7)+('แผนงาน Schedule'!$I$7:$I$156<=Dashboard!$C$7)*('แผนงาน Schedule'!$J$7:$J$156>Dashboard!$C$7)*(Dashboard!$C$7-'แผนงาน Schedule'!$I$7:$I$156+1)/('แผนงาน Schedule'!$J$7:$J$156-'แผนงาน Schedule'!$I$7:$I$156+1)))/E86) | G86: =IF(OR(B86="",N(E86)=0),"",SUMPRODUCT(('แผนงาน Schedule'!$C$7:$C$156=B86)*'แผนงาน Schedule'!$G$7:$G$156*'แผนงาน Schedule'!$P$7:$P$156)/E86) | H86: =IF(F86="","",G86-F86) | I86: =IF(OR(F86="",N(F86)=0),"",G86/F86) | J86: =IF(B86="","",N(F86)*N(E86)) | K86: =IF(B86="","",N(G86)*N(E86))
A87: =IF(B87="","",16) | B87: =IF('ตั้งค่า Setup'!$C$83="","",'ตั้งค่า Setup'!$C$83) | C87: =IF(B87="","",COUNTIFS('แผนงาน Schedule'!$C$7:$C$156,B87,'แผนงาน Schedule'!$D$7:$D$156,"<>")) | D87: =IF(B87="","",SUMIF('แผนงาน Schedule'!$C$7:$C$156,B87,'แผนงาน Schedule'!$H$7:$H$156)) | E87: =IF(B87="","",SUMIF('แผนงาน Schedule'!$C$7:$C$156,B87,'แผนงาน Schedule'!$G$7:$G$156)) | F87: =IF(OR(B87="",N(E87)=0),"",SUMPRODUCT(('แผนงาน Schedule'!$C$7:$C$156=B87)*'แผนงาน Schedule'!$G$7:$G$156*(('แผนงาน Schedule'!$J$7:$J$156<=Dashboard!$C$7)+('แผนงาน Schedule'!$I$7:$I$156<=Dashboard!$C$7)*('แผนงาน Schedule'!$J$7:$J$156>Dashboard!$C$7)*(Dashboard!$C$7-'แผนงาน Schedule'!$I$7:$I$156+1)/('แผนงาน Schedule'!$J$7:$J$156-'แผนงาน Schedule'!$I$7:$I$156+1)))/E87) | G87: =IF(OR(B87="",N(E87)=0),"",SUMPRODUCT(('แผนงาน Schedule'!$C$7:$C$156=B87)*'แผนงาน Schedule'!$G$7:$G$156*'แผนงาน Schedule'!$P$7:$P$156)/E87) | H87: =IF(F87="","",G87-F87) | I87: =IF(OR(F87="",N(F87)=0),"",G87/F87) | J87: =IF(B87="","",N(F87)*N(E87)) | K87: =IF(B87="","",N(G87)*N(E87))
A88: =IF(B88="","",17) | B88: =IF('ตั้งค่า Setup'!$C$84="","",'ตั้งค่า Setup'!$C$84) | C88: =IF(B88="","",COUNTIFS('แผนงาน Schedule'!$C$7:$C$156,B88,'แผนงาน Schedule'!$D$7:$D$156,"<>")) | D88: =IF(B88="","",SUMIF('แผนงาน Schedule'!$C$7:$C$156,B88,'แผนงาน Schedule'!$H$7:$H$156)) | E88: =IF(B88="","",SUMIF('แผนงาน Schedule'!$C$7:$C$156,B88,'แผนงาน Schedule'!$G$7:$G$156)) | F88: =IF(OR(B88="",N(E88)=0),"",SUMPRODUCT(('แผนงาน Schedule'!$C$7:$C$156=B88)*'แผนงาน Schedule'!$G$7:$G$156*(('แผนงาน Schedule'!$J$7:$J$156<=Dashboard!$C$7)+('แผนงาน Schedule'!$I$7:$I$156<=Dashboard!$C$7)*('แผนงาน Schedule'!$J$7:$J$156>Dashboard!$C$7)*(Dashboard!$C$7-'แผนงาน Schedule'!$I$7:$I$156+1)/('แผนงาน Schedule'!$J$7:$J$156-'แผนงาน Schedule'!$I$7:$I$156+1)))/E88) | G88: =IF(OR(B88="",N(E88)=0),"",SUMPRODUCT(('แผนงาน Schedule'!$C$7:$C$156=B88)*'แผนงาน Schedule'!$G$7:$G$156*'แผนงาน Schedule'!$P$7:$P$156)/E88) | H88: =IF(F88="","",G88-F88) | I88: =IF(OR(F88="",N(F88)=0),"",G88/F88) | J88: =IF(B88="","",N(F88)*N(E88)) | K88: =IF(B88="","",N(G88)*N(E88))
A89: =IF(B89="","",18) | B89: =IF('ตั้งค่า Setup'!$C$85="","",'ตั้งค่า Setup'!$C$85) | C89: =IF(B89="","",COUNTIFS('แผนงาน Schedule'!$C$7:$C$156,B89,'แผนงาน Schedule'!$D$7:$D$156,"<>")) | D89: =IF(B89="","",SUMIF('แผนงาน Schedule'!$C$7:$C$156,B89,'แผนงาน Schedule'!$H$7:$H$156)) | E89: =IF(B89="","",SUMIF('แผนงาน Schedule'!$C$7:$C$156,B89,'แผนงาน Schedule'!$G$7:$G$156)) | F89: =IF(OR(B89="",N(E89)=0),"",SUMPRODUCT(('แผนงาน Schedule'!$C$7:$C$156=B89)*'แผนงาน Schedule'!$G$7:$G$156*(('แผนงาน Schedule'!$J$7:$J$156<=Dashboard!$C$7)+('แผนงาน Schedule'!$I$7:$I$156<=Dashboard!$C$7)*('แผนงาน Schedule'!$J$7:$J$156>Dashboard!$C$7)*(Dashboard!$C$7-'แผนงาน Schedule'!$I$7:$I$156+1)/('แผนงาน Schedule'!$J$7:$J$156-'แผนงาน Schedule'!$I$7:$I$156+1)))/E89) | G89: =IF(OR(B89="",N(E89)=0),"",SUMPRODUCT(('แผนงาน Schedule'!$C$7:$C$156=B89)*'แผนงาน Schedule'!$G$7:$G$156*'แผนงาน Schedule'!$P$7:$P$156)/E89) | H89: =IF(F89="","",G89-F89) | I89: =IF(OR(F89="",N(F89)=0),"",G89/F89) | J89: =IF(B89="","",N(F89)*N(E89)) | K89: =IF(B89="","",N(G89)*N(E89))
A90: =IF(B90="","",19) | B90: =IF('ตั้งค่า Setup'!$C$86="","",'ตั้งค่า Setup'!$C$86) | C90: =IF(B90="","",COUNTIFS('แผนงาน Schedule'!$C$7:$C$156,B90,'แผนงาน Schedule'!$D$7:$D$156,"<>")) | D90: =IF(B90="","",SUMIF('แผนงาน Schedule'!$C$7:$C$156,B90,'แผนงาน Schedule'!$H$7:$H$156)) | E90: =IF(B90="","",SUMIF('แผนงาน Schedule'!$C$7:$C$156,B90,'แผนงาน Schedule'!$G$7:$G$156)) | F90: =IF(OR(B90="",N(E90)=0),"",SUMPRODUCT(('แผนงาน Schedule'!$C$7:$C$156=B90)*'แผนงาน Schedule'!$G$7:$G$156*(('แผนงาน Schedule'!$J$7:$J$156<=Dashboard!$C$7)+('แผนงาน Schedule'!$I$7:$I$156<=Dashboard!$C$7)*('แผนงาน Schedule'!$J$7:$J$156>Dashboard!$C$7)*(Dashboard!$C$7-'แผนงาน Schedule'!$I$7:$I$156+1)/('แผนงาน Schedule'!$J$7:$J$156-'แผนงาน Schedule'!$I$7:$I$156+1)))/E90) | G90: =IF(OR(B90="",N(E90)=0),"",SUMPRODUCT(('แผนงาน Schedule'!$C$7:$C$156=B90)*'แผนงาน Schedule'!$G$7:$G$156*'แผนงาน Schedule'!$P$7:$P$156)/E90) | H90: =IF(F90="","",G90-F90) | I90: =IF(OR(F90="",N(F90)=0),"",G90/F90) | J90: =IF(B90="","",N(F90)*N(E90)) | K90: =IF(B90="","",N(G90)*N(E90))
A91: =IF(B91="","",20) | B91: =IF('ตั้งค่า Setup'!$C$87="","",'ตั้งค่า Setup'!$C$87) | C91: =IF(B91="","",COUNTIFS('แผนงาน Schedule'!$C$7:$C$156,B91,'แผนงาน Schedule'!$D$7:$D$156,"<>")) | D91: =IF(B91="","",SUMIF('แผนงาน Schedule'!$C$7:$C$156,B91,'แผนงาน Schedule'!$H$7:$H$156)) | E91: =IF(B91="","",SUMIF('แผนงาน Schedule'!$C$7:$C$156,B91,'แผนงาน Schedule'!$G$7:$G$156)) | F91: =IF(OR(B91="",N(E91)=0),"",SUMPRODUCT(('แผนงาน Schedule'!$C$7:$C$156=B91)*'แผนงาน Schedule'!$G$7:$G$156*(('แผนงาน Schedule'!$J$7:$J$156<=Dashboard!$C$7)+('แผนงาน Schedule'!$I$7:$I$156<=Dashboard!$C$7)*('แผนงาน Schedule'!$J$7:$J$156>Dashboard!$C$7)*(Dashboard!$C$7-'แผนงาน Schedule'!$I$7:$I$156+1)/('แผนงาน Schedule'!$J$7:$J$156-'แผนงาน Schedule'!$I$7:$I$156+1)))/E91) | G91: =IF(OR(B91="",N(E91)=0),"",SUMPRODUCT(('แผนงาน Schedule'!$C$7:$C$156=B91)*'แผนงาน Schedule'!$G$7:$G$156*'แผนงาน Schedule'!$P$7:$P$156)/E91) | H91: =IF(F91="","",G91-F91) | I91: =IF(OR(F91="",N(F91)=0),"",G91/F91) | J91: =IF(B91="","",N(F91)*N(E91)) | K91: =IF(B91="","",N(G91)*N(E91))
A92: =IF(B92="","",21) | B92: =IF('ตั้งค่า Setup'!$C$88="","",'ตั้งค่า Setup'!$C$88) | C92: =IF(B92="","",COUNTIFS('แผนงาน Schedule'!$C$7:$C$156,B92,'แผนงาน Schedule'!$D$7:$D$156,"<>")) | D92: =IF(B92="","",SUMIF('แผนงาน Schedule'!$C$7:$C$156,B92,'แผนงาน Schedule'!$H$7:$H$156)) | E92: =IF(B92="","",SUMIF('แผนงาน Schedule'!$C$7:$C$156,B92,'แผนงาน Schedule'!$G$7:$G$156)) | F92: =IF(OR(B92="",N(E92)=0),"",SUMPRODUCT(('แผนงาน Schedule'!$C$7:$C$156=B92)*'แผนงาน Schedule'!$G$7:$G$156*(('แผนงาน Schedule'!$J$7:$J$156<=Dashboard!$C$7)+('แผนงาน Schedule'!$I$7:$I$156<=Dashboard!$C$7)*('แผนงาน Schedule'!$J$7:$J$156>Dashboard!$C$7)*(Dashboard!$C$7-'แผนงาน Schedule'!$I$7:$I$156+1)/('แผนงาน Schedule'!$J$7:$J$156-'แผนงาน Schedule'!$I$7:$I$156+1)))/E92) | G92: =IF(OR(B92="",N(E92)=0),"",SUMPRODUCT(('แผนงาน Schedule'!$C$7:$C$156=B92)*'แผนงาน Schedule'!$G$7:$G$156*'แผนงาน Schedule'!$P$7:$P$156)/E92) | H92: =IF(F92="","",G92-F92) | I92: =IF(OR(F92="",N(F92)=0),"",G92/F92) | J92: =IF(B92="","",N(F92)*N(E92)) | K92: =IF(B92="","",N(G92)*N(E92))
A93: =IF(B93="","",22) | B93: =IF('ตั้งค่า Setup'!$C$89="","",'ตั้งค่า Setup'!$C$89) | C93: =IF(B93="","",COUNTIFS('แผนงาน Schedule'!$C$7:$C$156,B93,'แผนงาน Schedule'!$D$7:$D$156,"<>")) | D93: =IF(B93="","",SUMIF('แผนงาน Schedule'!$C$7:$C$156,B93,'แผนงาน Schedule'!$H$7:$H$156)) | E93: =IF(B93="","",SUMIF('แผนงาน Schedule'!$C$7:$C$156,B93,'แผนงาน Schedule'!$G$7:$G$156)) | F93: =IF(OR(B93="",N(E93)=0),"",SUMPRODUCT(('แผนงาน Schedule'!$C$7:$C$156=B93)*'แผนงาน Schedule'!$G$7:$G$156*(('แผนงาน Schedule'!$J$7:$J$156<=Dashboard!$C$7)+('แผนงาน Schedule'!$I$7:$I$156<=Dashboard!$C$7)*('แผนงาน Schedule'!$J$7:$J$156>Dashboard!$C$7)*(Dashboard!$C$7-'แผนงาน Schedule'!$I$7:$I$156+1)/('แผนงาน Schedule'!$J$7:$J$156-'แผนงาน Schedule'!$I$7:$I$156+1)))/E93) | G93: =IF(OR(B93="",N(E93)=0),"",SUMPRODUCT(('แผนงาน Schedule'!$C$7:$C$156=B93)*'แผนงาน Schedule'!$G$7:$G$156*'แผนงาน Schedule'!$P$7:$P$156)/E93) | H93: =IF(F93="","",G93-F93) | I93: =IF(OR(F93="",N(F93)=0),"",G93/F93) | J93: =IF(B93="","",N(F93)*N(E93)) | K93: =IF(B93="","",N(G93)*N(E93))
A94: =IF(B94="","",23) | B94: =IF('ตั้งค่า Setup'!$C$90="","",'ตั้งค่า Setup'!$C$90) | C94: =IF(B94="","",COUNTIFS('แผนงาน Schedule'!$C$7:$C$156,B94,'แผนงาน Schedule'!$D$7:$D$156,"<>")) | D94: =IF(B94="","",SUMIF('แผนงาน Schedule'!$C$7:$C$156,B94,'แผนงาน Schedule'!$H$7:$H$156)) | E94: =IF(B94="","",SUMIF('แผนงาน Schedule'!$C$7:$C$156,B94,'แผนงาน Schedule'!$G$7:$G$156)) | F94: =IF(OR(B94="",N(E94)=0),"",SUMPRODUCT(('แผนงาน Schedule'!$C$7:$C$156=B94)*'แผนงาน Schedule'!$G$7:$G$156*(('แผนงาน Schedule'!$J$7:$J$156<=Dashboard!$C$7)+('แผนงาน Schedule'!$I$7:$I$156<=Dashboard!$C$7)*('แผนงาน Schedule'!$J$7:$J$156>Dashboard!$C$7)*(Dashboard!$C$7-'แผนงาน Schedule'!$I$7:$I$156+1)/('แผนงาน Schedule'!$J$7:$J$156-'แผนงาน Schedule'!$I$7:$I$156+1)))/E94) | G94: =IF(OR(B94="",N(E94)=0),"",SUMPRODUCT(('แผนงาน Schedule'!$C$7:$C$156=B94)*'แผนงาน Schedule'!$G$7:$G$156*'แผนงาน Schedule'!$P$7:$P$156)/E94) | H94: =IF(F94="","",G94-F94) | I94: =IF(OR(F94="",N(F94)=0),"",G94/F94) | J94: =IF(B94="","",N(F94)*N(E94)) | K94: =IF(B94="","",N(G94)*N(E94))
A95: =IF(B95="","",24) | B95: =IF('ตั้งค่า Setup'!$C$91="","",'ตั้งค่า Setup'!$C$91) | C95: =IF(B95="","",COUNTIFS('แผนงาน Schedule'!$C$7:$C$156,B95,'แผนงาน Schedule'!$D$7:$D$156,"<>")) | D95: =IF(B95="","",SUMIF('แผนงาน Schedule'!$C$7:$C$156,B95,'แผนงาน Schedule'!$H$7:$H$156)) | E95: =IF(B95="","",SUMIF('แผนงาน Schedule'!$C$7:$C$156,B95,'แผนงาน Schedule'!$G$7:$G$156)) | F95: =IF(OR(B95="",N(E95)=0),"",SUMPRODUCT(('แผนงาน Schedule'!$C$7:$C$156=B95)*'แผนงาน Schedule'!$G$7:$G$156*(('แผนงาน Schedule'!$J$7:$J$156<=Dashboard!$C$7)+('แผนงาน Schedule'!$I$7:$I$156<=Dashboard!$C$7)*('แผนงาน Schedule'!$J$7:$J$156>Dashboard!$C$7)*(Dashboard!$C$7-'แผนงาน Schedule'!$I$7:$I$156+1)/('แผนงาน Schedule'!$J$7:$J$156-'แผนงาน Schedule'!$I$7:$I$156+1)))/E95) | G95: =IF(OR(B95="",N(E95)=0),"",SUMPRODUCT(('แผนงาน Schedule'!$C$7:$C$156=B95)*'แผนงาน Schedule'!$G$7:$G$156*'แผนงาน Schedule'!$P$7:$P$156)/E95) | H95: =IF(F95="","",G95-F95) | I95: =IF(OR(F95="",N(F95)=0),"",G95/F95) | J95: =IF(B95="","",N(F95)*N(E95)) | K95: =IF(B95="","",N(G95)*N(E95))
A96: =IF(B96="","",25) | B96: =IF('ตั้งค่า Setup'!$C$92="","",'ตั้งค่า Setup'!$C$92) | C96: =IF(B96="","",COUNTIFS('แผนงาน Schedule'!$C$7:$C$156,B96,'แผนงาน Schedule'!$D$7:$D$156,"<>")) | D96: =IF(B96="","",SUMIF('แผนงาน Schedule'!$C$7:$C$156,B96,'แผนงาน Schedule'!$H$7:$H$156)) | E96: =IF(B96="","",SUMIF('แผนงาน Schedule'!$C$7:$C$156,B96,'แผนงาน Schedule'!$G$7:$G$156)) | F96: =IF(OR(B96="",N(E96)=0),"",SUMPRODUCT(('แผนงาน Schedule'!$C$7:$C$156=B96)*'แผนงาน Schedule'!$G$7:$G$156*(('แผนงาน Schedule'!$J$7:$J$156<=Dashboard!$C$7)+('แผนงาน Schedule'!$I$7:$I$156<=Dashboard!$C$7)*('แผนงาน Schedule'!$J$7:$J$156>Dashboard!$C$7)*(Dashboard!$C$7-'แผนงาน Schedule'!$I$7:$I$156+1)/('แผนงาน Schedule'!$J$7:$J$156-'แผนงาน Schedule'!$I$7:$I$156+1)))/E96) | G96: =IF(OR(B96="",N(E96)=0),"",SUMPRODUCT(('แผนงาน Schedule'!$C$7:$C$156=B96)*'แผนงาน Schedule'!$G$7:$G$156*'แผนงาน Schedule'!$P$7:$P$156)/E96) | H96: =IF(F96="","",G96-F96) | I96: =IF(OR(F96="",N(F96)=0),"",G96/F96) | J96: =IF(B96="","",N(F96)*N(E96)) | K96: =IF(B96="","",N(G96)*N(E96))
A97: =IF(B97="","",26) | B97: =IF('ตั้งค่า Setup'!$C$93="","",'ตั้งค่า Setup'!$C$93) | C97: =IF(B97="","",COUNTIFS('แผนงาน Schedule'!$C$7:$C$156,B97,'แผนงาน Schedule'!$D$7:$D$156,"<>")) | D97: =IF(B97="","",SUMIF('แผนงาน Schedule'!$C$7:$C$156,B97,'แผนงาน Schedule'!$H$7:$H$156)) | E97: =IF(B97="","",SUMIF('แผนงาน Schedule'!$C$7:$C$156,B97,'แผนงาน Schedule'!$G$7:$G$156)) | F97: =IF(OR(B97="",N(E97)=0),"",SUMPRODUCT(('แผนงาน Schedule'!$C$7:$C$156=B97)*'แผนงาน Schedule'!$G$7:$G$156*(('แผนงาน Schedule'!$J$7:$J$156<=Dashboard!$C$7)+('แผนงาน Schedule'!$I$7:$I$156<=Dashboard!$C$7)*('แผนงาน Schedule'!$J$7:$J$156>Dashboard!$C$7)*(Dashboard!$C$7-'แผนงาน Schedule'!$I$7:$I$156+1)/('แผนงาน Schedule'!$J$7:$J$156-'แผนงาน Schedule'!$I$7:$I$156+1)))/E97) | G97: =IF(OR(B97="",N(E97)=0),"",SUMPRODUCT(('แผนงาน Schedule'!$C$7:$C$156=B97)*'แผนงาน Schedule'!$G$7:$G$156*'แผนงาน Schedule'!$P$7:$P$156)/E97) | H97: =IF(F97="","",G97-F97) | I97: =IF(OR(F97="",N(F97)=0),"",G97/F97) | J97: =IF(B97="","",N(F97)*N(E97)) | K97: =IF(B97="","",N(G97)*N(E97))
A98: =IF(B98="","",27) | B98: =IF('ตั้งค่า Setup'!$C$94="","",'ตั้งค่า Setup'!$C$94) | C98: =IF(B98="","",COUNTIFS('แผนงาน Schedule'!$C$7:$C$156,B98,'แผนงาน Schedule'!$D$7:$D$156,"<>")) | D98: =IF(B98="","",SUMIF('แผนงาน Schedule'!$C$7:$C$156,B98,'แผนงาน Schedule'!$H$7:$H$156)) | E98: =IF(B98="","",SUMIF('แผนงาน Schedule'!$C$7:$C$156,B98,'แผนงาน Schedule'!$G$7:$G$156)) | F98: =IF(OR(B98="",N(E98)=0),"",SUMPRODUCT(('แผนงาน Schedule'!$C$7:$C$156=B98)*'แผนงาน Schedule'!$G$7:$G$156*(('แผนงาน Schedule'!$J$7:$J$156<=Dashboard!$C$7)+('แผนงาน Schedule'!$I$7:$I$156<=Dashboard!$C$7)*('แผนงาน Schedule'!$J$7:$J$156>Dashboard!$C$7)*(Dashboard!$C$7-'แผนงาน Schedule'!$I$7:$I$156+1)/('แผนงาน Schedule'!$J$7:$J$156-'แผนงาน Schedule'!$I$7:$I$156+1)))/E98) | G98: =IF(OR(B98="",N(E98)=0),"",SUMPRODUCT(('แผนงาน Schedule'!$C$7:$C$156=B98)*'แผนงาน Schedule'!$G$7:$G$156*'แผนงาน Schedule'!$P$7:$P$156)/E98) | H98: =IF(F98="","",G98-F98) | I98: =IF(OR(F98="",N(F98)=0),"",G98/F98) | J98: =IF(B98="","",N(F98)*N(E98)) | K98: =IF(B98="","",N(G98)*N(E98))
A99: =IF(B99="","",28) | B99: =IF('ตั้งค่า Setup'!$C$95="","",'ตั้งค่า Setup'!$C$95) | C99: =IF(B99="","",COUNTIFS('แผนงาน Schedule'!$C$7:$C$156,B99,'แผนงาน Schedule'!$D$7:$D$156,"<>")) | D99: =IF(B99="","",SUMIF('แผนงาน Schedule'!$C$7:$C$156,B99,'แผนงาน Schedule'!$H$7:$H$156)) | E99: =IF(B99="","",SUMIF('แผนงาน Schedule'!$C$7:$C$156,B99,'แผนงาน Schedule'!$G$7:$G$156)) | F99: =IF(OR(B99="",N(E99)=0),"",SUMPRODUCT(('แผนงาน Schedule'!$C$7:$C$156=B99)*'แผนงาน Schedule'!$G$7:$G$156*(('แผนงาน Schedule'!$J$7:$J$156<=Dashboard!$C$7)+('แผนงาน Schedule'!$I$7:$I$156<=Dashboard!$C$7)*('แผนงาน Schedule'!$J$7:$J$156>Dashboard!$C$7)*(Dashboard!$C$7-'แผนงาน Schedule'!$I$7:$I$156+1)/('แผนงาน Schedule'!$J$7:$J$156-'แผนงาน Schedule'!$I$7:$I$156+1)))/E99) | G99: =IF(OR(B99="",N(E99)=0),"",SUMPRODUCT(('แผนงาน Schedule'!$C$7:$C$156=B99)*'แผนงาน Schedule'!$G$7:$G$156*'แผนงาน Schedule'!$P$7:$P$156)/E99) | H99: =IF(F99="","",G99-F99) | I99: =IF(OR(F99="",N(F99)=0),"",G99/F99) | J99: =IF(B99="","",N(F99)*N(E99)) | K99: =IF(B99="","",N(G99)*N(E99))
A100: =IF(B100="","",29) | B100: =IF('ตั้งค่า Setup'!$C$96="","",'ตั้งค่า Setup'!$C$96) | C100: =IF(B100="","",COUNTIFS('แผนงาน Schedule'!$C$7:$C$156,B100,'แผนงาน Schedule'!$D$7:$D$156,"<>")) | D100: =IF(B100="","",SUMIF('แผนงาน Schedule'!$C$7:$C$156,B100,'แผนงาน Schedule'!$H$7:$H$156)) | E100: =IF(B100="","",SUMIF('แผนงาน Schedule'!$C$7:$C$156,B100,'แผนงาน Schedule'!$G$7:$G$156)) | F100: =IF(OR(B100="",N(E100)=0),"",SUMPRODUCT(('แผนงาน Schedule'!$C$7:$C$156=B100)*'แผนงาน Schedule'!$G$7:$G$156*(('แผนงาน Schedule'!$J$7:$J$156<=Dashboard!$C$7)+('แผนงาน Schedule'!$I$7:$I$156<=Dashboard!$C$7)*('แผนงาน Schedule'!$J$7:$J$156>Dashboard!$C$7)*(Dashboard!$C$7-'แผนงาน Schedule'!$I$7:$I$156+1)/('แผนงาน Schedule'!$J$7:$J$156-'แผนงาน Schedule'!$I$7:$I$156+1)))/E100) | G100: =IF(OR(B100="",N(E100)=0),"",SUMPRODUCT(('แผนงาน Schedule'!$C$7:$C$156=B100)*'แผนงาน Schedule'!$G$7:$G$156*'แผนงาน Schedule'!$P$7:$P$156)/E100) | H100: =IF(F100="","",G100-F100) | I100: =IF(OR(F100="",N(F100)=0),"",G100/F100) | J100: =IF(B100="","",N(F100)*N(E100)) | K100: =IF(B100="","",N(G100)*N(E100))
A101: =IF(B101="","",30) | B101: =IF('ตั้งค่า Setup'!$C$97="","",'ตั้งค่า Setup'!$C$97) | C101: =IF(B101="","",COUNTIFS('แผนงาน Schedule'!$C$7:$C$156,B101,'แผนงาน Schedule'!$D$7:$D$156,"<>")) | D101: =IF(B101="","",SUMIF('แผนงาน Schedule'!$C$7:$C$156,B101,'แผนงาน Schedule'!$H$7:$H$156)) | E101: =IF(B101="","",SUMIF('แผนงาน Schedule'!$C$7:$C$156,B101,'แผนงาน Schedule'!$G$7:$G$156)) | F101: =IF(OR(B101="",N(E101)=0),"",SUMPRODUCT(('แผนงาน Schedule'!$C$7:$C$156=B101)*'แผนงาน Schedule'!$G$7:$G$156*(('แผนงาน Schedule'!$J$7:$J$156<=Dashboard!$C$7)+('แผนงาน Schedule'!$I$7:$I$156<=Dashboard!$C$7)*('แผนงาน Schedule'!$J$7:$J$156>Dashboard!$C$7)*(Dashboard!$C$7-'แผนงาน Schedule'!$I$7:$I$156+1)/('แผนงาน Schedule'!$J$7:$J$156-'แผนงาน Schedule'!$I$7:$I$156+1)))/E101) | G101: =IF(OR(B101="",N(E101)=0),"",SUMPRODUCT(('แผนงาน Schedule'!$C$7:$C$156=B101)*'แผนงาน Schedule'!$G$7:$G$156*'แผนงาน Schedule'!$P$7:$P$156)/E101) | H101: =IF(F101="","",G101-F101) | I101: =IF(OR(F101="",N(F101)=0),"",G101/F101) | J101: =IF(B101="","",N(F101)*N(E101)) | K101: =IF(B101="","",N(G101)*N(E101))
A102: =IF(B102="","",31) | B102: =IF('ตั้งค่า Setup'!$C$98="","",'ตั้งค่า Setup'!$C$98) | C102: =IF(B102="","",COUNTIFS('แผนงาน Schedule'!$C$7:$C$156,B102,'แผนงาน Schedule'!$D$7:$D$156,"<>")) | D102: =IF(B102="","",SUMIF('แผนงาน Schedule'!$C$7:$C$156,B102,'แผนงาน Schedule'!$H$7:$H$156)) | E102: =IF(B102="","",SUMIF('แผนงาน Schedule'!$C$7:$C$156,B102,'แผนงาน Schedule'!$G$7:$G$156)) | F102: =IF(OR(B102="",N(E102)=0),"",SUMPRODUCT(('แผนงาน Schedule'!$C$7:$C$156=B102)*'แผนงาน Schedule'!$G$7:$G$156*(('แผนงาน Schedule'!$J$7:$J$156<=Dashboard!$C$7)+('แผนงาน Schedule'!$I$7:$I$156<=Dashboard!$C$7)*('แผนงาน Schedule'!$J$7:$J$156>Dashboard!$C$7)*(Dashboard!$C$7-'แผนงาน Schedule'!$I$7:$I$156+1)/('แผนงาน Schedule'!$J$7:$J$156-'แผนงาน Schedule'!$I$7:$I$156+1)))/E102) | G102: =IF(OR(B102="",N(E102)=0),"",SUMPRODUCT(('แผนงาน Schedule'!$C$7:$C$156=B102)*'แผนงาน Schedule'!$G$7:$G$156*'แผนงาน Schedule'!$P$7:$P$156)/E102) | H102: =IF(F102="","",G102-F102) | I102: =IF(OR(F102="",N(F102)=0),"",G102/F102) | J102: =IF(B102="","",N(F102)*N(E102)) | K102: =IF(B102="","",N(G102)*N(E102))
A103: =IF(B103="","",32) | B103: =IF('ตั้งค่า Setup'!$C$99="","",'ตั้งค่า Setup'!$C$99) | C103: =IF(B103="","",COUNTIFS('แผนงาน Schedule'!$C$7:$C$156,B103,'แผนงาน Schedule'!$D$7:$D$156,"<>")) | D103: =IF(B103="","",SUMIF('แผนงาน Schedule'!$C$7:$C$156,B103,'แผนงาน Schedule'!$H$7:$H$156)) | E103: =IF(B103="","",SUMIF('แผนงาน Schedule'!$C$7:$C$156,B103,'แผนงาน Schedule'!$G$7:$G$156)) | F103: =IF(OR(B103="",N(E103)=0),"",SUMPRODUCT(('แผนงาน Schedule'!$C$7:$C$156=B103)*'แผนงาน Schedule'!$G$7:$G$156*(('แผนงาน Schedule'!$J$7:$J$156<=Dashboard!$C$7)+('แผนงาน Schedule'!$I$7:$I$156<=Dashboard!$C$7)*('แผนงาน Schedule'!$J$7:$J$156>Dashboard!$C$7)*(Dashboard!$C$7-'แผนงาน Schedule'!$I$7:$I$156+1)/('แผนงาน Schedule'!$J$7:$J$156-'แผนงาน Schedule'!$I$7:$I$156+1)))/E103) | G103: =IF(OR(B103="",N(E103)=0),"",SUMPRODUCT(('แผนงาน Schedule'!$C$7:$C$156=B103)*'แผนงาน Schedule'!$G$7:$G$156*'แผนงาน Schedule'!$P$7:$P$156)/E103) | H103: =IF(F103="","",G103-F103) | I103: =IF(OR(F103="",N(F103)=0),"",G103/F103) | J103: =IF(B103="","",N(F103)*N(E103)) | K103: =IF(B103="","",N(G103)*N(E103))
A104: =IF(B104="","",33) | B104: =IF('ตั้งค่า Setup'!$C$100="","",'ตั้งค่า Setup'!$C$100) | C104: =IF(B104="","",COUNTIFS('แผนงาน Schedule'!$C$7:$C$156,B104,'แผนงาน Schedule'!$D$7:$D$156,"<>")) | D104: =IF(B104="","",SUMIF('แผนงาน Schedule'!$C$7:$C$156,B104,'แผนงาน Schedule'!$H$7:$H$156)) | E104: =IF(B104="","",SUMIF('แผนงาน Schedule'!$C$7:$C$156,B104,'แผนงาน Schedule'!$G$7:$G$156)) | F104: =IF(OR(B104="",N(E104)=0),"",SUMPRODUCT(('แผนงาน Schedule'!$C$7:$C$156=B104)*'แผนงาน Schedule'!$G$7:$G$156*(('แผนงาน Schedule'!$J$7:$J$156<=Dashboard!$C$7)+('แผนงาน Schedule'!$I$7:$I$156<=Dashboard!$C$7)*('แผนงาน Schedule'!$J$7:$J$156>Dashboard!$C$7)*(Dashboard!$C$7-'แผนงาน Schedule'!$I$7:$I$156+1)/('แผนงาน Schedule'!$J$7:$J$156-'แผนงาน Schedule'!$I$7:$I$156+1)))/E104) | G104: =IF(OR(B104="",N(E104)=0),"",SUMPRODUCT(('แผนงาน Schedule'!$C$7:$C$156=B104)*'แผนงาน Schedule'!$G$7:$G$156*'แผนงาน Schedule'!$P$7:$P$156)/E104) | H104: =IF(F104="","",G104-F104) | I104: =IF(OR(F104="",N(F104)=0),"",G104/F104) | J104: =IF(B104="","",N(F104)*N(E104)) | K104: =IF(B104="","",N(G104)*N(E104))
A105: =IF(B105="","",34) | B105: =IF('ตั้งค่า Setup'!$C$101="","",'ตั้งค่า Setup'!$C$101) | C105: =IF(B105="","",COUNTIFS('แผนงาน Schedule'!$C$7:$C$156,B105,'แผนงาน Schedule'!$D$7:$D$156,"<>")) | D105: =IF(B105="","",SUMIF('แผนงาน Schedule'!$C$7:$C$156,B105,'แผนงาน Schedule'!$H$7:$H$156)) | E105: =IF(B105="","",SUMIF('แผนงาน Schedule'!$C$7:$C$156,B105,'แผนงาน Schedule'!$G$7:$G$156)) | F105: =IF(OR(B105="",N(E105)=0),"",SUMPRODUCT(('แผนงาน Schedule'!$C$7:$C$156=B105)*'แผนงาน Schedule'!$G$7:$G$156*(('แผนงาน Schedule'!$J$7:$J$156<=Dashboard!$C$7)+('แผนงาน Schedule'!$I$7:$I$156<=Dashboard!$C$7)*('แผนงาน Schedule'!$J$7:$J$156>Dashboard!$C$7)*(Dashboard!$C$7-'แผนงาน Schedule'!$I$7:$I$156+1)/('แผนงาน Schedule'!$J$7:$J$156-'แผนงาน Schedule'!$I$7:$I$156+1)))/E105) | G105: =IF(OR(B105="",N(E105)=0),"",SUMPRODUCT(('แผนงาน Schedule'!$C$7:$C$156=B105)*'แผนงาน Schedule'!$G$7:$G$156*'แผนงาน Schedule'!$P$7:$P$156)/E105) | H105: =IF(F105="","",G105-F105) | I105: =IF(OR(F105="",N(F105)=0),"",G105/F105) | J105: =IF(B105="","",N(F105)*N(E105)) | K105: =IF(B105="","",N(G105)*N(E105))
A106: =IF(B106="","",35) | B106: =IF('ตั้งค่า Setup'!$C$102="","",'ตั้งค่า Setup'!$C$102) | C106: =IF(B106="","",COUNTIFS('แผนงาน Schedule'!$C$7:$C$156,B106,'แผนงาน Schedule'!$D$7:$D$156,"<>")) | D106: =IF(B106="","",SUMIF('แผนงาน Schedule'!$C$7:$C$156,B106,'แผนงาน Schedule'!$H$7:$H$156)) | E106: =IF(B106="","",SUMIF('แผนงาน Schedule'!$C$7:$C$156,B106,'แผนงาน Schedule'!$G$7:$G$156)) | F106: =IF(OR(B106="",N(E106)=0),"",SUMPRODUCT(('แผนงาน Schedule'!$C$7:$C$156=B106)*'แผนงาน Schedule'!$G$7:$G$156*(('แผนงาน Schedule'!$J$7:$J$156<=Dashboard!$C$7)+('แผนงาน Schedule'!$I$7:$I$156<=Dashboard!$C$7)*('แผนงาน Schedule'!$J$7:$J$156>Dashboard!$C$7)*(Dashboard!$C$7-'แผนงาน Schedule'!$I$7:$I$156+1)/('แผนงาน Schedule'!$J$7:$J$156-'แผนงาน Schedule'!$I$7:$I$156+1)))/E106) | G106: =IF(OR(B106="",N(E106)=0),"",SUMPRODUCT(('แผนงาน Schedule'!$C$7:$C$156=B106)*'แผนงาน Schedule'!$G$7:$G$156*'แผนงาน Schedule'!$P$7:$P$156)/E106) | H106: =IF(F106="","",G106-F106) | I106: =IF(OR(F106="",N(F106)=0),"",G106/F106) | J106: =IF(B106="","",N(F106)*N(E106)) | K106: =IF(B106="","",N(G106)*N(E106))
A107: =IF(B107="","",36) | B107: =IF('ตั้งค่า Setup'!$C$103="","",'ตั้งค่า Setup'!$C$103) | C107: =IF(B107="","",COUNTIFS('แผนงาน Schedule'!$C$7:$C$156,B107,'แผนงาน Schedule'!$D$7:$D$156,"<>")) | D107: =IF(B107="","",SUMIF('แผนงาน Schedule'!$C$7:$C$156,B107,'แผนงาน Schedule'!$H$7:$H$156)) | E107: =IF(B107="","",SUMIF('แผนงาน Schedule'!$C$7:$C$156,B107,'แผนงาน Schedule'!$G$7:$G$156)) | F107: =IF(OR(B107="",N(E107)=0),"",SUMPRODUCT(('แผนงาน Schedule'!$C$7:$C$156=B107)*'แผนงาน Schedule'!$G$7:$G$156*(('แผนงาน Schedule'!$J$7:$J$156<=Dashboard!$C$7)+('แผนงาน Schedule'!$I$7:$I$156<=Dashboard!$C$7)*('แผนงาน Schedule'!$J$7:$J$156>Dashboard!$C$7)*(Dashboard!$C$7-'แผนงาน Schedule'!$I$7:$I$156+1)/('แผนงาน Schedule'!$J$7:$J$156-'แผนงาน Schedule'!$I$7:$I$156+1)))/E107) | G107: =IF(OR(B107="",N(E107)=0),"",SUMPRODUCT(('แผนงาน Schedule'!$C$7:$C$156=B107)*'แผนงาน Schedule'!$G$7:$G$156*'แผนงาน Schedule'!$P$7:$P$156)/E107) | H107: =IF(F107="","",G107-F107) | I107: =IF(OR(F107="",N(F107)=0),"",G107/F107) | J107: =IF(B107="","",N(F107)*N(E107)) | K107: =IF(B107="","",N(G107)*N(E107))
A108: =IF(B108="","",37) | B108: =IF('ตั้งค่า Setup'!$C$104="","",'ตั้งค่า Setup'!$C$104) | C108: =IF(B108="","",COUNTIFS('แผนงาน Schedule'!$C$7:$C$156,B108,'แผนงาน Schedule'!$D$7:$D$156,"<>")) | D108: =IF(B108="","",SUMIF('แผนงาน Schedule'!$C$7:$C$156,B108,'แผนงาน Schedule'!$H$7:$H$156)) | E108: =IF(B108="","",SUMIF('แผนงาน Schedule'!$C$7:$C$156,B108,'แผนงาน Schedule'!$G$7:$G$156)) | F108: =IF(OR(B108="",N(E108)=0),"",SUMPRODUCT(('แผนงาน Schedule'!$C$7:$C$156=B108)*'แผนงาน Schedule'!$G$7:$G$156*(('แผนงาน Schedule'!$J$7:$J$156<=Dashboard!$C$7)+('แผนงาน Schedule'!$I$7:$I$156<=Dashboard!$C$7)*('แผนงาน Schedule'!$J$7:$J$156>Dashboard!$C$7)*(Dashboard!$C$7-'แผนงาน Schedule'!$I$7:$I$156+1)/('แผนงาน Schedule'!$J$7:$J$156-'แผนงาน Schedule'!$I$7:$I$156+1)))/E108) | G108: =IF(OR(B108="",N(E108)=0),"",SUMPRODUCT(('แผนงาน Schedule'!$C$7:$C$156=B108)*'แผนงาน Schedule'!$G$7:$G$156*'แผนงาน Schedule'!$P$7:$P$156)/E108) | H108: =IF(F108="","",G108-F108) | I108: =IF(OR(F108="",N(F108)=0),"",G108/F108) | J108: =IF(B108="","",N(F108)*N(E108)) | K108: =IF(B108="","",N(G108)*N(E108))
A109: =IF(B109="","",38) | B109: =IF('ตั้งค่า Setup'!$C$105="","",'ตั้งค่า Setup'!$C$105) | C109: =IF(B109="","",COUNTIFS('แผนงาน Schedule'!$C$7:$C$156,B109,'แผนงาน Schedule'!$D$7:$D$156,"<>")) | D109: =IF(B109="","",SUMIF('แผนงาน Schedule'!$C$7:$C$156,B109,'แผนงาน Schedule'!$H$7:$H$156)) | E109: =IF(B109="","",SUMIF('แผนงาน Schedule'!$C$7:$C$156,B109,'แผนงาน Schedule'!$G$7:$G$156)) | F109: =IF(OR(B109="",N(E109)=0),"",SUMPRODUCT(('แผนงาน Schedule'!$C$7:$C$156=B109)*'แผนงาน Schedule'!$G$7:$G$156*(('แผนงาน Schedule'!$J$7:$J$156<=Dashboard!$C$7)+('แผนงาน Schedule'!$I$7:$I$156<=Dashboard!$C$7)*('แผนงาน Schedule'!$J$7:$J$156>Dashboard!$C$7)*(Dashboard!$C$7-'แผนงาน Schedule'!$I$7:$I$156+1)/('แผนงาน Schedule'!$J$7:$J$156-'แผนงาน Schedule'!$I$7:$I$156+1)))/E109) | G109: =IF(OR(B109="",N(E109)=0),"",SUMPRODUCT(('แผนงาน Schedule'!$C$7:$C$156=B109)*'แผนงาน Schedule'!$G$7:$G$156*'แผนงาน Schedule'!$P$7:$P$156)/E109) | H109: =IF(F109="","",G109-F109) | I109: =IF(OR(F109="",N(F109)=0),"",G109/F109) | J109: =IF(B109="","",N(F109)*N(E109)) | K109: =IF(B109="","",N(G109)*N(E109))
A110: =IF(B110="","",39) | B110: =IF('ตั้งค่า Setup'!$C$106="","",'ตั้งค่า Setup'!$C$106) | C110: =IF(B110="","",COUNTIFS('แผนงาน Schedule'!$C$7:$C$156,B110,'แผนงาน Schedule'!$D$7:$D$156,"<>")) | D110: =IF(B110="","",SUMIF('แผนงาน Schedule'!$C$7:$C$156,B110,'แผนงาน Schedule'!$H$7:$H$156)) | E110: =IF(B110="","",SUMIF('แผนงาน Schedule'!$C$7:$C$156,B110,'แผนงาน Schedule'!$G$7:$G$156)) | F110: =IF(OR(B110="",N(E110)=0),"",SUMPRODUCT(('แผนงาน Schedule'!$C$7:$C$156=B110)*'แผนงาน Schedule'!$G$7:$G$156*(('แผนงาน Schedule'!$J$7:$J$156<=Dashboard!$C$7)+('แผนงาน Schedule'!$I$7:$I$156<=Dashboard!$C$7)*('แผนงาน Schedule'!$J$7:$J$156>Dashboard!$C$7)*(Dashboard!$C$7-'แผนงาน Schedule'!$I$7:$I$156+1)/('แผนงาน Schedule'!$J$7:$J$156-'แผนงาน Schedule'!$I$7:$I$156+1)))/E110) | G110: =IF(OR(B110="",N(E110)=0),"",SUMPRODUCT(('แผนงาน Schedule'!$C$7:$C$156=B110)*'แผนงาน Schedule'!$G$7:$G$156*'แผนงาน Schedule'!$P$7:$P$156)/E110) | H110: =IF(F110="","",G110-F110) | I110: =IF(OR(F110="",N(F110)=0),"",G110/F110) | J110: =IF(B110="","",N(F110)*N(E110)) | K110: =IF(B110="","",N(G110)*N(E110))
A111: =IF(B111="","",40) | B111: =IF('ตั้งค่า Setup'!$C$107="","",'ตั้งค่า Setup'!$C$107) | C111: =IF(B111="","",COUNTIFS('แผนงาน Schedule'!$C$7:$C$156,B111,'แผนงาน Schedule'!$D$7:$D$156,"<>")) | D111: =IF(B111="","",SUMIF('แผนงาน Schedule'!$C$7:$C$156,B111,'แผนงาน Schedule'!$H$7:$H$156)) | E111: =IF(B111="","",SUMIF('แผนงาน Schedule'!$C$7:$C$156,B111,'แผนงาน Schedule'!$G$7:$G$156)) | F111: =IF(OR(B111="",N(E111)=0),"",SUMPRODUCT(('แผนงาน Schedule'!$C$7:$C$156=B111)*'แผนงาน Schedule'!$G$7:$G$156*(('แผนงาน Schedule'!$J$7:$J$156<=Dashboard!$C$7)+('แผนงาน Schedule'!$I$7:$I$156<=Dashboard!$C$7)*('แผนงาน Schedule'!$J$7:$J$156>Dashboard!$C$7)*(Dashboard!$C$7-'แผนงาน Schedule'!$I$7:$I$156+1)/('แผนงาน Schedule'!$J$7:$J$156-'แผนงาน Schedule'!$I$7:$I$156+1)))/E111) | G111: =IF(OR(B111="",N(E111)=0),"",SUMPRODUCT(('แผนงาน Schedule'!$C$7:$C$156=B111)*'แผนงาน Schedule'!$G$7:$G$156*'แผนงาน Schedule'!$P$7:$P$156)/E111) | H111: =IF(F111="","",G111-F111) | I111: =IF(OR(F111="",N(F111)=0),"",G111/F111) | J111: =IF(B111="","",N(F111)*N(E111)) | K111: =IF(B111="","",N(G111)*N(E111))
B112: รวม / TOTAL | C112: =SUM(C72:C111) -> 21 | D112: =SUM(D72:D111) -> 24200000 | E112: =SUM(E72:E111) -> 1 | J112: =SUM(J72:J111) -> 0.25365051 | K112: =SUM(K72:K111) -> 0.18780992

Sheet รายงาน Report
B1: รายงานความก้าวหน้าโครงการ / PROJECT PROGRESS REPORT
B2: โครงการ / Project: | D2: ='ตั้งค่า Setup'!C4&IF('ตั้งค่า Setup'!C5<>""," ("&'ตั้งค่า Setup'!C5&")","") -> โครงการตัวอย่าง: ก่อสร้างอาคารพร้อมงานภายนอก (Example: Building & External Works) | G2: รายงานงวดที่ / Report No.: | I2: ='ตั้งค่า Setup'!C21 -> 1
B3: ผู้ว่าจ้าง / Employer: | D3: ='ตั้งค่า Setup'!C6&"" | G3: วันที่ตรวจวัด / Status Date: | I3: ='ตั้งค่า Setup'!$C$15 -> 46293
B4: ผู้รับจ้าง / Contractor: | D4: ='ตั้งค่า Setup'!C7&"" | G4: เลขที่สัญญา / Contract No.: | I4: ='ตั้งค่า Setup'!C8&""
B6: 1. สรุปผลการดำเนินงาน / Executive Summary
B7: ระยะเวลาที่ใช้ไป / Time Elapsed | D7: =Dashboard!C14 -> 0.38961039
B8: แผนเดิม / Baseline Planned | D8: =Dashboard!C16 -> 0.25365051
B9: แผนเร่งรัด / Revised Planned | D9: =Dashboard!C17 -> 0.25365051
B10: ผลงานจริง / Actual Progress | D10: =Dashboard!C19 -> 0.18780992
B11: ผลต่าง / Variance | D11: =Dashboard!C20 -> -0.065840597
B12: SPI | SPI(t) | D12: =TEXT(Dashboard!C22,"0.00")&" | "&TEXT(Dashboard!C26,"0.00") -> 0.74 | 0.85
B13: ช้ากว่าแผน / SV(t) (วัน) | D13: =Dashboard!C25 -> -18.376996
B14: คาดว่าแล้วเสร็จ / Forecast Completion | D14: =Dashboard!C27 -> 46473
B15: คาดว่าล่าช้า / Forecast Delay (วัน) | D15: =Dashboard!C28 -> 0
B16: ค่าปรับคาดการณ์ / Forecast LD (฿) | D16: =Dashboard!C55 -> 0
B17: CPI (ดัชนีต้นทุน) | D17: =Dashboard!C41 -> 0.98062484
B18: สถานะ / Status | D18: =Dashboard!C32 -> ล่าช้ามาก / Critical Delay
B19: ข้อมูลจริง ณ / Data Date | D19: =Dashboard!C7 -> 46293
B21: 2. ความก้าวหน้ารายงานส่วน / Progress by Work Package
B22: No. | C22: งานส่วน / Work Package | D22: น้ำหนัก Weight | E22: % แผน Planned | F22: % จริง Actual | G22: ผลต่าง Variance | H22: SPI | I22: คาดว่าเสร็จ Forecast | J22: สถานะ / Status
B23: ='สรุปงานส่วน Summary'!A7&"" -> 1 | C23: ='สรุปงานส่วน Summary'!B7&"" -> งานถมดินและปรับพื้นที่ / Earth Filling & Site Prep | D23: ='สรุปงานส่วน Summary'!E7 -> 0.12603306 | E23: ='สรุปงานส่วน Summary'!I7 -> 1 | F23: ='สรุปงานส่วน Summary'!J7 -> 0.98032787 | G23: ='สรุปงานส่วน Summary'!K7 -> -0.019672131 | H23: ='สรุปงานส่วน Summary'!L7 -> 0.98032787 | I23: ='สรุปงานส่วน Summary'!M7 -> 46301 | J23: ='สรุปงานส่วน Summary'!P7&"" -> เฝ้าระวัง / At Risk
B24: ='สรุปงานส่วน Summary'!A8&"" -> 2 | C24: ='สรุปงานส่วน Summary'!B8&"" -> งานก่อสร้างอาคาร / Building | D24: ='สรุปงานส่วน Summary'!E8 -> 0.54545455 | E24: ='สรุปงานส่วน Summary'!I8 -> 0.084848485 | F24: ='สรุปงานส่วน Summary'!J8 -> 0.047727273 | G24: ='สรุปงานส่วน Summary'!K8 -> -0.037121212 | H24: ='สรุปงานส่วน Summary'!L8 -> 0.5625 | I24: ='สรุปงานส่วน Summary'!M8 -> 46473 | J24: ='สรุปงานส่วน Summary'!P8&"" -> ล่าช้า / Behind
B25: ='สรุปงานส่วน Summary'!A9&"" -> 3 | C25: ='สรุปงานส่วน Summary'!B9&"" -> งานรางระบายน้ำ / Drainage | D25: ='สรุปงานส่วน Summary'!E9 -> 0.078512397 | E25: ='สรุปงานส่วน Summary'!I9 -> 0.80672994 | F25: ='สรุปงานส่วน Summary'!J9 -> 0.37631579 | G25: ='สรุปงานส่วน Summary'!K9 -> -0.43041415 | H25: ='สรุปงานส่วน Summary'!L9 -> 0.46647059 | I25: ='สรุปงานส่วน Summary'!M9 -> 46353 | J25: ='สรุปงานส่วน Summary'!P9&"" -> ล่าช้า / Behind
B26: ='สรุปงานส่วน Summary'!A10&"" -> 4 | C26: ='สรุปงานส่วน Summary'!B10&"" -> งานถนนและลาน / Roads & Hardscape | D26: ='สรุปงานส่วน Summary'!E10 -> 0.13429752 | E26: ='สรุปงานส่วน Summary'!I10 -> 0 | F26: ='สรุปงานส่วน Summary'!J10 -> 0 | G26: ='สรุปงานส่วน Summary'!K10 -> 0 | H26: ='สรุปงานส่วน Summary'!L10 | I26: ='สรุปงานส่วน Summary'!M10 -> 46418 | J26: ='สรุปงานส่วน Summary'!P10&"" -> ยังไม่เริ่ม / Not Started
B27: ='สรุปงานส่วน Summary'!A11&"" -> 5 | C27: ='สรุปงานส่วน Summary'!B11&"" -> งานรั้ว / Fence | D27: ='สรุปงานส่วน Summary'!E11 -> 0.066115702 | E27: ='สรุปงานส่วน Summary'!I11 -> 0.27222222 | F27: ='สรุปงานส่วน Summary'!J11 -> 0.13125 | G27: ='สรุปงานส่วน Summary'!K11 -> -0.14097222 | H27: ='สรุปงานส่วน Summary'!L11 -> 0.48214286 | I27: ='สรุปงานส่วน Summary'!M11 -> 46371 | J27: ='สรุปงานส่วน Summary'!P11&"" -> ล่าช้า / Behind
B28: ='สรุปงานส่วน Summary'!A12&"" -> 6 | C28: ='สรุปงานส่วน Summary'!B12&"" -> งานโรงจอดรถ / Carport | D28: ='สรุปงานส่วน Summary'!E12 -> 0.049586777 | E28: ='สรุปงานส่วน Summary'!I12 -> 0 | F28: ='สรุปงานส่วน Summary'!J12 -> 0 | G28: ='สรุปงานส่วน Summary'!K12 -> 0 | H28: ='สรุปงานส่วน Summary'!L12 | I28: ='สรุปงานส่วน Summary'!M12 -> 46456 | J28: ='สรุปงานส่วน Summary'!P12&"" -> ยังไม่เริ่ม / Not Started
B29: ='สรุปงานส่วน Summary'!A13&"" | C29: ='สรุปงานส่วน Summary'!B13&"" | D29: ='สรุปงานส่วน Summary'!E13 | E29: ='สรุปงานส่วน Summary'!I13 | F29: ='สรุปงานส่วน Summary'!J13 | G29: ='สรุปงานส่วน Summary'!K13 | H29: ='สรุปงานส่วน Summary'!L13 | I29: ='สรุปงานส่วน Summary'!M13 | J29: ='สรุปงานส่วน Summary'!P13&""
B30: ='สรุปงานส่วน Summary'!A14&"" | C30: ='สรุปงานส่วน Summary'!B14&"" | D30: ='สรุปงานส่วน Summary'!E14 | E30: ='สรุปงานส่วน Summary'!I14 | F30: ='สรุปงานส่วน Summary'!J14 | G30: ='สรุปงานส่วน Summary'!K14 | H30: ='สรุปงานส่วน Summary'!L14 | I30: ='สรุปงานส่วน Summary'!M14 | J30: ='สรุปงานส่วน Summary'!P14&""
B31: ='สรุปงานส่วน Summary'!A15&"" | C31: ='สรุปงานส่วน Summary'!B15&"" | D31: ='สรุปงานส่วน Summary'!E15 | E31: ='สรุปงานส่วน Summary'!I15 | F31: ='สรุปงานส่วน Summary'!J15 | G31: ='สรุปงานส่วน Summary'!K15 | H31: ='สรุปงานส่วน Summary'!L15 | I31: ='สรุปงานส่วน Summary'!M15 | J31: ='สรุปงานส่วน Summary'!P15&""
B32: ='สรุปงานส่วน Summary'!A46&"" | C32: ='สรุปงานส่วน Summary'!B46&"" | D32: ='สรุปงานส่วน Summary'!E46 | E32: ='สรุปงานส่วน Summary'!I46 | F32: ='สรุปงานส่วน Summary'!J46 | G32: ='สรุปงานส่วน Summary'!K46 | H32: ='สรุปงานส่วน Summary'!L46 | I32: ='สรุปงานส่วน Summary'!M46 | J32: ='สรุปงานส่วน Summary'!P46&""
B33: ='สรุปงานส่วน Summary'!A47&"" | C33: รวมทั้งโครงการ / PROJECT TOTAL | D33: ='สรุปงานส่วน Summary'!E47 -> 1 | E33: ='สรุปงานส่วน Summary'!I47 -> 0.25365051 | F33: ='สรุปงานส่วน Summary'!J47 -> 0.18780992 | G33: ='สรุปงานส่วน Summary'!K47 -> -0.065840597 | H33: ='สรุปงานส่วน Summary'!L47 -> 0.7404279 | I33: ='สรุปงานส่วน Summary'!M47 -> 46473 | J33: ='สรุปงานส่วน Summary'!P47&"" -> ล่าช้ามาก / Critical Delay
B34: รายละเอียดรายหมวดงานและ Gantt รายงานส่วน ดูในชีต สรุปงานส่วน Summary
B36: 3. รายการที่ล่าช้ามากที่สุด / Top 5 Delayed Items
B37: อันดับ | C37: WBS / รายการงาน | D37: เสร็จตามแผน BL Finish | E37: คาดว่าเสร็จ Forecast | F37: ล่าช้า (วัน) Delay | G37: % จริง Actual | H37: สถานะ / Status | J37: หมายเหตุ / Remarks
B38: =IF(L38="","",1) -> 1 | C38: =IF(L38="","",INDEX('แผนงาน Schedule'!$A$7:$A$156,L38)&" "&INDEX('แผนงาน Schedule'!$D$7:$D$156,L38)) -> 3.3.01 งานขุดและวางรางระบายน้ำ คสล. | D38: =IF(L38="","",INDEX('แผนงาน Schedule'!$J$7:$J$156,L38)) -> 46295 | E38: =IF(L38="","",INDEX('แผนงาน Schedule'!$W$7:$W$156,L38)) -> 46334 | F38: =IF(L38="","",INDEX('แผนงาน Schedule'!$X$7:$X$156,L38)) -> 39 | G38: =IF(L38="","",N(INDEX('แผนงาน Schedule'!$P$7:$P$156,L38))) -> 0.55 | H38: =IF(L38="","",INDEX('แผนงาน Schedule'!$Y$7:$Y$156,L38)) -> ล่าช้า / Behind | J38: =IF(L38="","",INDEX('แผนงาน Schedule'!$Z$7:$Z$156,L38)&"") | L38: =IFERROR(MATCH(LARGE('แผนงาน Schedule'!$AC$7:$AC$156,1),'แผนงาน Schedule'!$AC$7:$AC$156,0),"") -> 12
B39: =IF(L39="","",2) -> 2 | C39: =IF(L39="","",INDEX('แผนงาน Schedule'!$A$7:$A$156,L39)&" "&INDEX('แผนงาน Schedule'!$D$7:$D$156,L39)) -> 1.2.02 งานปรับระดับและทดสอบความแน่นดิน | D39: =IF(L39="","",INDEX('แผนงาน Schedule'!$J$7:$J$156,L39)) -> 46265 | E39: =IF(L39="","",INDEX('แผนงาน Schedule'!$W$7:$W$156,L39)) -> 46301 | F39: =IF(L39="","",INDEX('แผนงาน Schedule'!$X$7:$X$156,L39)) -> 36 | G39: =IF(L39="","",N(INDEX('แผนงาน Schedule'!$P$7:$P$156,L39))) -> 0.8 | H39: =IF(L39="","",INDEX('แผนงาน Schedule'!$Y$7:$Y$156,L39)) -> เกินกำหนด / Overdue | J39: =IF(L39="","",INDEX('แผนงาน Schedule'!$Z$7:$Z$156,L39)&"") -> รอผลทดสอบความแน่น 2 จุด | L39: =IFERROR(MATCH(LARGE('แผนงาน Schedule'!$AC$7:$AC$156,2),'แผนงาน Schedule'!$AC$7:$AC$156,0),"") -> 3
B40: =IF(L40="","",3) -> 3 | C40: =IF(L40="","",INDEX('แผนงาน Schedule'!$A$7:$A$156,L40)&" "&INDEX('แผนงาน Schedule'!$D$7:$D$156,L40)) -> 3.3.02 งานบ่อพักและท่อลอด | D40: =IF(L40="","",INDEX('แผนงาน Schedule'!$J$7:$J$156,L40)) -> 46326 | E40: =IF(L40="","",INDEX('แผนงาน Schedule'!$W$7:$W$156,L40)) -> 46353 | F40: =IF(L40="","",INDEX('แผนงาน Schedule'!$X$7:$X$156,L40)) -> 27 | G40: =IF(L40="","",N(INDEX('แผนงาน Schedule'!$P$7:$P$156,L40))) -> 0 | H40: =IF(L40="","",INDEX('แผนงาน Schedule'!$Y$7:$Y$156,L40)) -> ล่าช้า / Behind | J40: =IF(L40="","",INDEX('แผนงาน Schedule'!$Z$7:$Z$156,L40)&"") -> รอแบบแก้ไขจากผู้ว่าจ้าง | L40: =IFERROR(MATCH(LARGE('แผนงาน Schedule'!$AC$7:$AC$156,3),'แผนงาน Schedule'!$AC$7:$AC$156,0),"") -> 13
B41: =IF(L41="","",4) -> 4 | C41: =IF(L41="","",INDEX('แผนงาน Schedule'!$A$7:$A$156,L41)&" "&INDEX('แผนงาน Schedule'!$D$7:$D$156,L41)) -> 5.3.01 งานฐานรากและเสารั้ว | D41: =IF(L41="","",INDEX('แผนงาน Schedule'!$J$7:$J$156,L41)) -> 46310 | E41: =IF(L41="","",INDEX('แผนงาน Schedule'!$W$7:$W$156,L41)) -> 46333 | F41: =IF(L41="","",INDEX('แผนงาน Schedule'!$X$7:$X$156,L41)) -> 23 | G41: =IF(L41="","",N(INDEX('แผนงาน Schedule'!$P$7:$P$156,L41))) -> 0.3 | H41: =IF(L41="","",INDEX('แผนงาน Schedule'!$Y$7:$Y$156,L41)) -> ล่าช้า / Behind | J41: =IF(L41="","",INDEX('แผนงาน Schedule'!$Z$7:$Z$156,L41)&"") | L41: =IFERROR(MATCH(LARGE('แผนงาน Schedule'!$AC$7:$AC$156,4),'แผนงาน Schedule'!$AC$7:$AC$156,0),"") -> 17
B42: =IF(L42="","",5) -> 5 | C42: =IF(L42="","",INDEX('แผนงาน Schedule'!$A$7:$A$156,L42)&" "&INDEX('แผนงาน Schedule'!$D$7:$D$156,L42)) -> 2.3.01 งานเสาเข็มอาคาร | D42: =IF(L42="","",INDEX('แผนงาน Schedule'!$J$7:$J$156,L42)) -> 46310 | E42: =IF(L42="","",INDEX('แผนงาน Schedule'!$W$7:$W$156,L42)) -> 46332 | F42: =IF(L42="","",INDEX('แผนงาน Schedule'!$X$7:$X$156,L42)) -> 22 | G42: =IF(L42="","",N(INDEX('แผนงาน Schedule'!$P$7:$P$156,L42))) -> 0.35 | H42: =IF(L42="","",INDEX('แผนงาน Schedule'!$Y$7:$Y$156,L42)) -> ล่าช้า / Behind | J42: =IF(L42="","",INDEX('แผนงาน Schedule'!$Z$7:$Z$156,L42)&"") | L42: =IFERROR(MATCH(LARGE('แผนงาน Schedule'!$AC$7:$AC$156,5),'แผนงาน Schedule'!$AC$7:$AC$156,0),"") -> 4
B44: ="4. แผนงานล่วงหน้า "&'ตั้งค่า Setup'!$C$20&" วัน (งานค้างและงานที่ต้องเริ่ม) / "&'ตั้งค่า Setup'!$C$20&"-Day Look-ahead" -> 4. แผนงานล่วงหน้า 30 วัน (งานค้างและงานที่ต้องเริ่ม) / 30-Day Look-ahead
B45: ลำดับ | C45: WBS / รายการงาน | D45: เริ่ม (แผนใช้งาน) Start | E45: เสร็จ (แผนใช้งาน) Finish | F45: % จริง Actual | G45: คาดว่าเสร็จ Forecast | H45: สถานะ / Status | J45: หมายเหตุ / Remarks
B46: =IF(L46="","",1) -> 1 | C46: =IF(L46="","",INDEX('แผนงาน Schedule'!$A$7:$A$156,L46)&" "&INDEX('แผนงาน Schedule'!$D$7:$D$156,L46)) -> 1.2.02 งานปรับระดับและทดสอบความแน่นดิน | D46: =IF(L46="","",INDEX('แผนงาน Schedule'!$AA$7:$AA$156,L46)) -> 46244 | E46: =IF(L46="","",INDEX('แผนงาน Schedule'!$AB$7:$AB$156,L46)) -> 46265 | F46: =IF(L46="","",N(INDEX('แผนงาน Schedule'!$P$7:$P$156,L46))) -> 0.8 | G46: =IF(L46="","",INDEX('แผนงาน Schedule'!$W$7:$W$156,L46)) -> 46301 | H46: =IF(L46="","",INDEX('แผนงาน Schedule'!$Y$7:$Y$156,L46)) -> เกินกำหนด / Overdue | J46: =IF(L46="","",INDEX('แผนงาน Schedule'!$Z$7:$Z$156,L46)&"") -> รอผลทดสอบความแน่น 2 จุด | L46: =IFERROR(MATCH(1,'แผนงาน Schedule'!$AE$7:$AE$156,0),"") -> 3
B47: =IF(L47="","",2) -> 2 | C47: =IF(L47="","",INDEX('แผนงาน Schedule'!$A$7:$A$156,L47)&" "&INDEX('แผนงาน Schedule'!$D$7:$D$156,L47)) -> 2.3.01 งานเสาเข็มอาคาร | D47: =IF(L47="","",INDEX('แผนงาน Schedule'!$AA$7:$AA$156,L47)) -> 46266 | E47: =IF(L47="","",INDEX('แผนงาน Schedule'!$AB$7:$AB$156,L47)) -> 46310 | F47: =IF(L47="","",N(INDEX('แผนงาน Schedule'!$P$7:$P$156,L47))) -> 0.35 | G47: =IF(L47="","",INDEX('แผนงาน Schedule'!$W$7:$W$156,L47)) -> 46332 | H47: =IF(L47="","",INDEX('แผนงาน Schedule'!$Y$7:$Y$156,L47)) -> ล่าช้า / Behind | J47: =IF(L47="","",INDEX('แผนงาน Schedule'!$Z$7:$Z$156,L47)&"") | L47: =IFERROR(MATCH(2,'แผนงาน Schedule'!$AE$7:$AE$156,0),"") -> 4
B48: =IF(L48="","",3) -> 3 | C48: =IF(L48="","",INDEX('แผนงาน Schedule'!$A$7:$A$156,L48)&" "&INDEX('แผนงาน Schedule'!$D$7:$D$156,L48)) -> 2.3.02 งานฐานราก คานคอดิน และพื้นชั้นล่าง | D48: =IF(L48="","",INDEX('แผนงาน Schedule'!$AA$7:$AA$156,L48)) -> 46296 | E48: =IF(L48="","",INDEX('แผนงาน Schedule'!$AB$7:$AB$156,L48)) -> 46341 | F48: =IF(L48="","",N(INDEX('แผนงาน Schedule'!$P$7:$P$156,L48))) -> 0 | G48: =IF(L48="","",INDEX('แผนงาน Schedule'!$W$7:$W$156,L48)) -> 46341 | H48: =IF(L48="","",INDEX('แผนงาน Schedule'!$Y$7:$Y$156,L48)) -> ยังไม่ถึงกำหนด / Not Due | J48: =IF(L48="","",INDEX('แผนงาน Schedule'!$Z$7:$Z$156,L48)&"") | L48: =IFERROR(MATCH(3,'แผนงาน Schedule'!$AE$7:$AE$156,0),"") -> 5
B49: =IF(L49="","",4) -> 4 | C49: =IF(L49="","",INDEX('แผนงาน Schedule'!$A$7:$A$156,L49)&" "&INDEX('แผนงาน Schedule'!$D$7:$D$156,L49)) -> 3.3.01 งานขุดและวางรางระบายน้ำ คสล. | D49: =IF(L49="","",INDEX('แผนงาน Schedule'!$AA$7:$AA$156,L49)) -> 46235 | E49: =IF(L49="","",INDEX('แผนงาน Schedule'!$AB$7:$AB$156,L49)) -> 46295 | F49: =IF(L49="","",N(INDEX('แผนงาน Schedule'!$P$7:$P$156,L49))) -> 0.55 | G49: =IF(L49="","",INDEX('แผนงาน Schedule'!$W$7:$W$156,L49)) -> 46334 | H49: =IF(L49="","",INDEX('แผนงาน Schedule'!$Y$7:$Y$156,L49)) -> ล่าช้า / Behind | J49: =IF(L49="","",INDEX('แผนงาน Schedule'!$Z$7:$Z$156,L49)&"") | L49: =IFERROR(MATCH(4,'แผนงาน Schedule'!$AE$7:$AE$156,0),"") -> 12
B50: =IF(L50="","",5) -> 5 | C50: =IF(L50="","",INDEX('แผนงาน Schedule'!$A$7:$A$156,L50)&" "&INDEX('แผนงาน Schedule'!$D$7:$D$156,L50)) -> 3.3.02 งานบ่อพักและท่อลอด | D50: =IF(L50="","",INDEX('แผนงาน Schedule'!$AA$7:$AA$156,L50)) -> 46266 | E50: =IF(L50="","",INDEX('แผนงาน Schedule'!$AB$7:$AB$156,L50)) -> 46326 | F50: =IF(L50="","",N(INDEX('แผนงาน Schedule'!$P$7:$P$156,L50))) -> 0 | G50: =IF(L50="","",INDEX('แผนงาน Schedule'!$W$7:$W$156,L50)) -> 46353 | H50: =IF(L50="","",INDEX('แผนงาน Schedule'!$Y$7:$Y$156,L50)) -> ล่าช้า / Behind | J50: =IF(L50="","",INDEX('แผนงาน Schedule'!$Z$7:$Z$156,L50)&"") -> รอแบบแก้ไขจากผู้ว่าจ้าง | L50: =IFERROR(MATCH(5,'แผนงาน Schedule'!$AE$7:$AE$156,0),"") -> 13
B51: =IF(L51="","",6) -> 6 | C51: =IF(L51="","",INDEX('แผนงาน Schedule'!$A$7:$A$156,L51)&" "&INDEX('แผนงาน Schedule'!$D$7:$D$156,L51)) -> 4.2.01 งานชั้นรองพื้นทางและพื้นทาง | D51: =IF(L51="","",INDEX('แผนงาน Schedule'!$AA$7:$AA$156,L51)) -> 46296 | E51: =IF(L51="","",INDEX('แผนงาน Schedule'!$AB$7:$AB$156,L51)) -> 46341 | F51: =IF(L51="","",N(INDEX('แผนงาน Schedule'!$P$7:$P$156,L51))) -> 0 | G51: =IF(L51="","",INDEX('แผนงาน Schedule'!$W$7:$W$156,L51)) -> 46341 | H51: =IF(L51="","",INDEX('แผนงาน Schedule'!$Y$7:$Y$156,L51)) -> ยังไม่ถึงกำหนด / Not Due | J51: =IF(L51="","",INDEX('แผนงาน Schedule'!$Z$7:$Z$156,L51)&"") | L51: =IFERROR(MATCH(6,'แผนงาน Schedule'!$AE$7:$AE$156,0),"") -> 14
B52: =IF(L52="","",7) -> 7 | C52: =IF(L52="","",INDEX('แผนงาน Schedule'!$A$7:$A$156,L52)&" "&INDEX('แผนงาน Schedule'!$D$7:$D$156,L52)) -> 5.3.01 งานฐานรากและเสารั้ว | D52: =IF(L52="","",INDEX('แผนงาน Schedule'!$AA$7:$AA$156,L52)) -> 46266 | E52: =IF(L52="","",INDEX('แผนงาน Schedule'!$AB$7:$AB$156,L52)) -> 46310 | F52: =IF(L52="","",N(INDEX('แผนงาน Schedule'!$P$7:$P$156,L52))) -> 0.3 | G52: =IF(L52="","",INDEX('แผนงาน Schedule'!$W$7:$W$156,L52)) -> 46333 | H52: =IF(L52="","",INDEX('แผนงาน Schedule'!$Y$7:$Y$156,L52)) -> ล่าช้า / Behind | J52: =IF(L52="","",INDEX('แผนงาน Schedule'!$Z$7:$Z$156,L52)&"") | L52: =IFERROR(MATCH(7,'แผนงาน Schedule'!$AE$7:$AE$156,0),"") -> 17
B53: =IF(L53="","",8) -> 8 | C53: =IF(L53="","",INDEX('แผนงาน Schedule'!$A$7:$A$156,L53)&" "&INDEX('แผนงาน Schedule'!$D$7:$D$156,L53)) -> 5.4.01 งานผนังรั้ว รั้วเหล็ก และประตูรั้ว | D53: =IF(L53="","",INDEX('แผนงาน Schedule'!$AA$7:$AA$156,L53)) -> 46305 | E53: =IF(L53="","",INDEX('แผนงาน Schedule'!$AB$7:$AB$156,L53)) -> 46371 | F53: =IF(L53="","",N(INDEX('แผนงาน Schedule'!$P$7:$P$156,L53))) -> 0 | G53: =IF(L53="","",INDEX('แผนงาน Schedule'!$W$7:$W$156,L53)) -> 46371 | H53: =IF(L53="","",INDEX('แผนงาน Schedule'!$Y$7:$Y$156,L53)) -> ยังไม่ถึงกำหนด / Not Due | J53: =IF(L53="","",INDEX('แผนงาน Schedule'!$Z$7:$Z$156,L53)&"") | L53: =IFERROR(MATCH(8,'แผนงาน Schedule'!$AE$7:$AE$156,0),"") -> 18
B54: =IF(L54="","",9) | C54: =IF(L54="","",INDEX('แผนงาน Schedule'!$A$7:$A$156,L54)&" "&INDEX('แผนงาน Schedule'!$D$7:$D$156,L54)) | D54: =IF(L54="","",INDEX('แผนงาน Schedule'!$AA$7:$AA$156,L54)) | E54: =IF(L54="","",INDEX('แผนงาน Schedule'!$AB$7:$AB$156,L54)) | F54: =IF(L54="","",N(INDEX('แผนงาน Schedule'!$P$7:$P$156,L54))) | G54: =IF(L54="","",INDEX('แผนงาน Schedule'!$W$7:$W$156,L54)) | H54: =IF(L54="","",INDEX('แผนงาน Schedule'!$Y$7:$Y$156,L54)) | J54: =IF(L54="","",INDEX('แผนงาน Schedule'!$Z$7:$Z$156,L54)&"") | L54: =IFERROR(MATCH(9,'แผนงาน Schedule'!$AE$7:$AE$156,0),"")
B55: =IF(L55="","",10) | C55: =IF(L55="","",INDEX('แผนงาน Schedule'!$A$7:$A$156,L55)&" "&INDEX('แผนงาน Schedule'!$D$7:$D$156,L55)) | D55: =IF(L55="","",INDEX('แผนงาน Schedule'!$AA$7:$AA$156,L55)) | E55: =IF(L55="","",INDEX('แผนงาน Schedule'!$AB$7:$AB$156,L55)) | F55: =IF(L55="","",N(INDEX('แผนงาน Schedule'!$P$7:$P$156,L55))) | G55: =IF(L55="","",INDEX('แผนงาน Schedule'!$W$7:$W$156,L55)) | H55: =IF(L55="","",INDEX('แผนงาน Schedule'!$Y$7:$Y$156,L55)) | J55: =IF(L55="","",INDEX('แผนงาน Schedule'!$Z$7:$Z$156,L55)&"") | L55: =IFERROR(MATCH(10,'แผนงาน Schedule'!$AE$7:$AE$156,0),"")
B56: =IF(L56="","",11) | C56: =IF(L56="","",INDEX('แผนงาน Schedule'!$A$7:$A$156,L56)&" "&INDEX('แผนงาน Schedule'!$D$7:$D$156,L56)) | D56: =IF(L56="","",INDEX('แผนงาน Schedule'!$AA$7:$AA$156,L56)) | E56: =IF(L56="","",INDEX('แผนงาน Schedule'!$AB$7:$AB$156,L56)) | F56: =IF(L56="","",N(INDEX('แผนงาน Schedule'!$P$7:$P$156,L56))) | G56: =IF(L56="","",INDEX('แผนงาน Schedule'!$W$7:$W$156,L56)) | H56: =IF(L56="","",INDEX('แผนงาน Schedule'!$Y$7:$Y$156,L56)) | J56: =IF(L56="","",INDEX('แผนงาน Schedule'!$Z$7:$Z$156,L56)&"") | L56: =IFERROR(MATCH(11,'แผนงาน Schedule'!$AE$7:$AE$156,0),"")
B57: =IF(L57="","",12) | C57: =IF(L57="","",INDEX('แผนงาน Schedule'!$A$7:$A$156,L57)&" "&INDEX('แผนงาน Schedule'!$D$7:$D$156,L57)) | D57: =IF(L57="","",INDEX('แผนงาน Schedule'!$AA$7:$AA$156,L57)) | E57: =IF(L57="","",INDEX('แผนงาน Schedule'!$AB$7:$AB$156,L57)) | F57: =IF(L57="","",N(INDEX('แผนงาน Schedule'!$P$7:$P$156,L57))) | G57: =IF(L57="","",INDEX('แผนงาน Schedule'!$W$7:$W$156,L57)) | H57: =IF(L57="","",INDEX('แผนงาน Schedule'!$Y$7:$Y$156,L57)) | J57: =IF(L57="","",INDEX('แผนงาน Schedule'!$Z$7:$Z$156,L57)&"") | L57: =IFERROR(MATCH(12,'แผนงาน Schedule'!$AE$7:$AE$156,0),"")
B59: 5. การขยายเวลาและค่าปรับ / Extension of Time & Liquidated Damages
B60: ขอขยายเวลารวม / Claimed | D60: =Dashboard!C49 -> 17 | F60: อนุมัติแล้ว / Approved | I60: =Dashboard!C50 -> 8
B61: รอพิจารณา / Pending | D61: =Dashboard!C51 -> 7 | F61: วันสิ้นสุดหลังขยายเวลา / Revised Completion | I61: =Dashboard!C12 -> 46481
B62: ค่าปรับต่อวัน / LD per Day (฿) | D62: =Dashboard!C52 -> 24200 | F62: ค่าปรับเกิดขึ้นแล้ว / LD Incurred (฿) | I62: =Dashboard!C54 -> 0
B63: ค่าปรับคาดการณ์ / Forecast LD (฿) | D63: =Dashboard!C55 -> 0 | F63: สัญญาณเตือน / Alert | I63: =Dashboard!C57 -> ✓ ไม่มีค่าปรับคาดการณ์
B65: 6. ปัญหา อุปสรรค และแนวทางแก้ไข / Issues, Risks & Corrective Actions
B66: ลำดับ | C66: ปัญหา / Issue | G66: แนวทางแก้ไข / ผู้รับผิดชอบ / กำหนดเสร็จ
B67: 1
B68: 2
B69: 3
B70: 4
B71: 5
B74: ลงชื่อ .................................... | E74: ลงชื่อ .................................... | H74: ลงชื่อ ....................................
B75: (....................................) | E75: (....................................) | H75: (....................................)
B76: ผู้จัดทำ / Prepared by | E76: ผู้ตรวจสอบ / Checked by | H76: ผู้อนุมัติ / Approved by
B77: วันที่ ........../........../.......... | E77: วันที่ ........../........../.......... | H77: วันที่ ........../........../..........

Sheet งวดงาน Installments
A1: งวดงานตามสัญญา / Contract Payment Installments
A2: กรอกตามงวดงานที่ระบุในสัญญา/TOR • ระบบแสดงสถานะ ความล่าช้า และเช็คว่าผลงานถึงเกณฑ์ของงวดแล้วหรือยัง
A3: ข้อมูลในตารางเป็นตัวอย่าง – แทนที่ด้วยงวดงานตามสัญญาจริง
A6: งวดที่ No. | B6: เนื้องานที่ต้องแล้วเสร็จในงวด Scope of Installment | C6: ผลงานสะสม ที่กำหนด (%) | D6: กำหนดแล้วเสร็จ Due Date | E6: จำนวนเงิน (บาท) Amount | F6: % ของ ค่าจ้าง | G6: วันที่ส่งมอบงาน Submitted | H6: วันที่ตรวจรับ Accepted | I6: เบิกจ่ายแล้ว (บาท) | J6: ผลงานปัจจุบัน เทียบเกณฑ์ | K6: สถานะ Status | L6: ล่าช้า (วัน) | M6: หมายเหตุ Remarks
A7: 1 | B7: งานถมดินและปรับพื้นที่แล้วเสร็จทั้งหมด | C7: 0.12 | D7: 46265 | E7: 3630000 | F7: =IF(E7="","",E7/'ตั้งค่า Setup'!$C$9) -> 0.15 | I7: =IF(OR(E7="",H7=""),"",E7) | J7: =IF(OR(B7="",C7=""),"",IF(Dashboard!$C$19>=C7,"✓ ถึงเกณฑ์แล้ว","ยังขาด "&TEXT(C7-Dashboard!$C$19,"0.00%"))) -> ✓ ถึงเกณฑ์แล้ว | K7: =IF(B7="","",IF(H7<>"","ตรวจรับแล้ว",IF(G7<>"","ส่งมอบแล้ว รอตรวจรับ",IF(D7="","-",IF('ตั้งค่า Setup'!$C$15>D7,"เกินกำหนด",IF(D7-'ตั้งค่า Setup'!$C$15<=14,"ใกล้ครบกำหนด (≤14 วัน)","ยังไม่ถึงกำหนด")))))) -> เกินกำหนด | L7: =IF(OR(B7="",D7=""),"",MAX(0,IF(G7<>"",G7,IF(H7<>"",H7,'ตั้งค่า Setup'!$C$15))-D7)) -> 28
A8: 2 | B8: งานรางระบายน้ำ งานเสาเข็มอาคาร และฐานรากรั้วแล้วเสร็จ | C8: 0.3 | D8: 46326 | E8: 4840000 | F8: =IF(E8="","",E8/'ตั้งค่า Setup'!$C$9) -> 0.2 | I8: =IF(OR(E8="",H8=""),"",E8) | J8: =IF(OR(B8="",C8=""),"",IF(Dashboard!$C$19>=C8,"✓ ถึงเกณฑ์แล้ว","ยังขาด "&TEXT(C8-Dashboard!$C$19,"0.00%"))) -> ยังขาด 11.22% | K8: =IF(B8="","",IF(H8<>"","ตรวจรับแล้ว",IF(G8<>"","ส่งมอบแล้ว รอตรวจรับ",IF(D8="","-",IF('ตั้งค่า Setup'!$C$15>D8,"เกินกำหนด",IF(D8-'ตั้งค่า Setup'!$C$15<=14,"ใกล้ครบกำหนด (≤14 วัน)","ยังไม่ถึงกำหนด")))))) -> ยังไม่ถึงกำหนด | L8: =IF(OR(B8="",D8=""),"",MAX(0,IF(G8<>"",G8,IF(H8<>"",H8,'ตั้งค่า Setup'!$C$15))-D8)) -> 0
A9: 3 | B9: งานโครงสร้างอาคาร งานถนน-ลาน และงานรั้วแล้วเสร็จ | C9: 0.6 | D9: 46402 | E9: 6050000 | F9: =IF(E9="","",E9/'ตั้งค่า Setup'!$C$9) -> 0.25 | I9: =IF(OR(E9="",H9=""),"",E9) | J9: =IF(OR(B9="",C9=""),"",IF(Dashboard!$C$19>=C9,"✓ ถึงเกณฑ์แล้ว","ยังขาด "&TEXT(C9-Dashboard!$C$19,"0.00%"))) -> ยังขาด 41.22% | K9: =IF(B9="","",IF(H9<>"","ตรวจรับแล้ว",IF(G9<>"","ส่งมอบแล้ว รอตรวจรับ",IF(D9="","-",IF('ตั้งค่า Setup'!$C$15>D9,"เกินกำหนด",IF(D9-'ตั้งค่า Setup'!$C$15<=14,"ใกล้ครบกำหนด (≤14 วัน)","ยังไม่ถึงกำหนด")))))) -> ยังไม่ถึงกำหนด | L9: =IF(OR(B9="",D9=""),"",MAX(0,IF(G9<>"",G9,IF(H9<>"",H9,'ตั้งค่า Setup'!$C$15))-D9)) -> 0
A10: 4 | B10: งานสถาปัตยกรรมอาคารและงานโรงจอดรถแล้วเสร็จ | C10: 0.85 | D10: 46446 | E10: 4840000 | F10: =IF(E10="","",E10/'ตั้งค่า Setup'!$C$9) -> 0.2 | I10: =IF(OR(E10="",H10=""),"",E10) | J10: =IF(OR(B10="",C10=""),"",IF(Dashboard!$C$19>=C10,"✓ ถึงเกณฑ์แล้ว","ยังขาด "&TEXT(C10-Dashboard!$C$19,"0.00%"))) -> ยังขาด 66.22% | K10: =IF(B10="","",IF(H10<>"","ตรวจรับแล้ว",IF(G10<>"","ส่งมอบแล้ว รอตรวจรับ",IF(D10="","-",IF('ตั้งค่า Setup'!$C$15>D10,"เกินกำหนด",IF(D10-'ตั้งค่า Setup'!$C$15<=14,"ใกล้ครบกำหนด (≤14 วัน)","ยังไม่ถึงกำหนด")))))) -> ยังไม่ถึงกำหนด | L10: =IF(OR(B10="",D10=""),"",MAX(0,IF(G10<>"",G10,IF(H10<>"",H10,'ตั้งค่า Setup'!$C$15))-D10)) -> 0
A11: 5 | B11: งานทั้งหมดแล้วเสร็จ ทดสอบระบบ และส่งมอบงาน | C11: 1 | D11: 46473 | E11: 4840000 | F11: =IF(E11="","",E11/'ตั้งค่า Setup'!$C$9) -> 0.2 | I11: =IF(OR(E11="",H11=""),"",E11) | J11: =IF(OR(B11="",C11=""),"",IF(Dashboard!$C$19>=C11,"✓ ถึงเกณฑ์แล้ว","ยังขาด "&TEXT(C11-Dashboard!$C$19,"0.00%"))) -> ยังขาด 81.22% | K11: =IF(B11="","",IF(H11<>"","ตรวจรับแล้ว",IF(G11<>"","ส่งมอบแล้ว รอตรวจรับ",IF(D11="","-",IF('ตั้งค่า Setup'!$C$15>D11,"เกินกำหนด",IF(D11-'ตั้งค่า Setup'!$C$15<=14,"ใกล้ครบกำหนด (≤14 วัน)","ยังไม่ถึงกำหนด")))))) -> ยังไม่ถึงกำหนด | L11: =IF(OR(B11="",D11=""),"",MAX(0,IF(G11<>"",G11,IF(H11<>"",H11,'ตั้งค่า Setup'!$C$15))-D11)) -> 0
F12: =IF(E12="","",E12/'ตั้งค่า Setup'!$C$9) | I12: =IF(OR(E12="",H12=""),"",E12) | J12: =IF(OR(B12="",C12=""),"",IF(Dashboard!$C$19>=C12,"✓ ถึงเกณฑ์แล้ว","ยังขาด "&TEXT(C12-Dashboard!$C$19,"0.00%"))) | K12: =IF(B12="","",IF(H12<>"","ตรวจรับแล้ว",IF(G12<>"","ส่งมอบแล้ว รอตรวจรับ",IF(D12="","-",IF('ตั้งค่า Setup'!$C$15>D12,"เกินกำหนด",IF(D12-'ตั้งค่า Setup'!$C$15<=14,"ใกล้ครบกำหนด (≤14 วัน)","ยังไม่ถึงกำหนด")))))) | L12: =IF(OR(B12="",D12=""),"",MAX(0,IF(G12<>"",G12,IF(H12<>"",H12,'ตั้งค่า Setup'!$C$15))-D12))
F13: =IF(E13="","",E13/'ตั้งค่า Setup'!$C$9) | I13: =IF(OR(E13="",H13=""),"",E13) | J13: =IF(OR(B13="",C13=""),"",IF(Dashboard!$C$19>=C13,"✓ ถึงเกณฑ์แล้ว","ยังขาด "&TEXT(C13-Dashboard!$C$19,"0.00%"))) | K13: =IF(B13="","",IF(H13<>"","ตรวจรับแล้ว",IF(G13<>"","ส่งมอบแล้ว รอตรวจรับ",IF(D13="","-",IF('ตั้งค่า Setup'!$C$15>D13,"เกินกำหนด",IF(D13-'ตั้งค่า Setup'!$C$15<=14,"ใกล้ครบกำหนด (≤14 วัน)","ยังไม่ถึงกำหนด")))))) | L13: =IF(OR(B13="",D13=""),"",MAX(0,IF(G13<>"",G13,IF(H13<>"",H13,'ตั้งค่า Setup'!$C$15))-D13))
F14: =IF(E14="","",E14/'ตั้งค่า Setup'!$C$9) | I14: =IF(OR(E14="",H14=""),"",E14) | J14: =IF(OR(B14="",C14=""),"",IF(Dashboard!$C$19>=C14,"✓ ถึงเกณฑ์แล้ว","ยังขาด "&TEXT(C14-Dashboard!$C$19,"0.00%"))) | K14: =IF(B14="","",IF(H14<>"","ตรวจรับแล้ว",IF(G14<>"","ส่งมอบแล้ว รอตรวจรับ",IF(D14="","-",IF('ตั้งค่า Setup'!$C$15>D14,"เกินกำหนด",IF(D14-'ตั้งค่า Setup'!$C$15<=14,"ใกล้ครบกำหนด (≤14 วัน)","ยังไม่ถึงกำหนด")))))) | L14: =IF(OR(B14="",D14=""),"",MAX(0,IF(G14<>"",G14,IF(H14<>"",H14,'ตั้งค่า Setup'!$C$15))-D14))
F15: =IF(E15="","",E15/'ตั้งค่า Setup'!$C$9) | I15: =IF(OR(E15="",H15=""),"",E15) | J15: =IF(OR(B15="",C15=""),"",IF(Dashboard!$C$19>=C15,"✓ ถึงเกณฑ์แล้ว","ยังขาด "&TEXT(C15-Dashboard!$C$19,"0.00%"))) | K15: =IF(B15="","",IF(H15<>"","ตรวจรับแล้ว",IF(G15<>"","ส่งมอบแล้ว รอตรวจรับ",IF(D15="","-",IF('ตั้งค่า Setup'!$C$15>D15,"เกินกำหนด",IF(D15-'ตั้งค่า Setup'!$C$15<=14,"ใกล้ครบกำหนด (≤14 วัน)","ยังไม่ถึงกำหนด")))))) | L15: =IF(OR(B15="",D15=""),"",MAX(0,IF(G15<>"",G15,IF(H15<>"",H15,'ตั้งค่า Setup'!$C$15))-D15))
F16: =IF(E16="","",E16/'ตั้งค่า Setup'!$C$9) | I16: =IF(OR(E16="",H16=""),"",E16) | J16: =IF(OR(B16="",C16=""),"",IF(Dashboard!$C$19>=C16,"✓ ถึงเกณฑ์แล้ว","ยังขาด "&TEXT(C16-Dashboard!$C$19,"0.00%"))) | K16: =IF(B16="","",IF(H16<>"","ตรวจรับแล้ว",IF(G16<>"","ส่งมอบแล้ว รอตรวจรับ",IF(D16="","-",IF('ตั้งค่า Setup'!$C$15>D16,"เกินกำหนด",IF(D16-'ตั้งค่า Setup'!$C$15<=14,"ใกล้ครบกำหนด (≤14 วัน)","ยังไม่ถึงกำหนด")))))) | L16: =IF(OR(B16="",D16=""),"",MAX(0,IF(G16<>"",G16,IF(H16<>"",H16,'ตั้งค่า Setup'!$C$15))-D16))
F17: =IF(E17="","",E17/'ตั้งค่า Setup'!$C$9) | I17: =IF(OR(E17="",H17=""),"",E17) | J17: =IF(OR(B17="",C17=""),"",IF(Dashboard!$C$19>=C17,"✓ ถึงเกณฑ์แล้ว","ยังขาด "&TEXT(C17-Dashboard!$C$19,"0.00%"))) | K17: =IF(B17="","",IF(H17<>"","ตรวจรับแล้ว",IF(G17<>"","ส่งมอบแล้ว รอตรวจรับ",IF(D17="","-",IF('ตั้งค่า Setup'!$C$15>D17,"เกินกำหนด",IF(D17-'ตั้งค่า Setup'!$C$15<=14,"ใกล้ครบกำหนด (≤14 วัน)","ยังไม่ถึงกำหนด")))))) | L17: =IF(OR(B17="",D17=""),"",MAX(0,IF(G17<>"",G17,IF(H17<>"",H17,'ตั้งค่า Setup'!$C$15))-D17))
F18: =IF(E18="","",E18/'ตั้งค่า Setup'!$C$9) | I18: =IF(OR(E18="",H18=""),"",E18) | J18: =IF(OR(B18="",C18=""),"",IF(Dashboard!$C$19>=C18,"✓ ถึงเกณฑ์แล้ว","ยังขาด "&TEXT(C18-Dashboard!$C$19,"0.00%"))) | K18: =IF(B18="","",IF(H18<>"","ตรวจรับแล้ว",IF(G18<>"","ส่งมอบแล้ว รอตรวจรับ",IF(D18="","-",IF('ตั้งค่า Setup'!$C$15>D18,"เกินกำหนด",IF(D18-'ตั้งค่า Setup'!$C$15<=14,"ใกล้ครบกำหนด (≤14 วัน)","ยังไม่ถึงกำหนด")))))) | L18: =IF(OR(B18="",D18=""),"",MAX(0,IF(G18<>"",G18,IF(H18<>"",H18,'ตั้งค่า Setup'!$C$15))-D18))
F19: =IF(E19="","",E19/'ตั้งค่า Setup'!$C$9) | I19: =IF(OR(E19="",H19=""),"",E19) | J19: =IF(OR(B19="",C19=""),"",IF(Dashboard!$C$19>=C19,"✓ ถึงเกณฑ์แล้ว","ยังขาด "&TEXT(C19-Dashboard!$C$19,"0.00%"))) | K19: =IF(B19="","",IF(H19<>"","ตรวจรับแล้ว",IF(G19<>"","ส่งมอบแล้ว รอตรวจรับ",IF(D19="","-",IF('ตั้งค่า Setup'!$C$15>D19,"เกินกำหนด",IF(D19-'ตั้งค่า Setup'!$C$15<=14,"ใกล้ครบกำหนด (≤14 วัน)","ยังไม่ถึงกำหนด")))))) | L19: =IF(OR(B19="",D19=""),"",MAX(0,IF(G19<>"",G19,IF(H19<>"",H19,'ตั้งค่า Setup'!$C$15))-D19))
F20: =IF(E20="","",E20/'ตั้งค่า Setup'!$C$9) | I20: =IF(OR(E20="",H20=""),"",E20) | J20: =IF(OR(B20="",C20=""),"",IF(Dashboard!$C$19>=C20,"✓ ถึงเกณฑ์แล้ว","ยังขาด "&TEXT(C20-Dashboard!$C$19,"0.00%"))) | K20: =IF(B20="","",IF(H20<>"","ตรวจรับแล้ว",IF(G20<>"","ส่งมอบแล้ว รอตรวจรับ",IF(D20="","-",IF('ตั้งค่า Setup'!$C$15>D20,"เกินกำหนด",IF(D20-'ตั้งค่า Setup'!$C$15<=14,"ใกล้ครบกำหนด (≤14 วัน)","ยังไม่ถึงกำหนด")))))) | L20: =IF(OR(B20="",D20=""),"",MAX(0,IF(G20<>"",G20,IF(H20<>"",H20,'ตั้งค่า Setup'!$C$15))-D20))
F21: =IF(E21="","",E21/'ตั้งค่า Setup'!$C$9) | I21: =IF(OR(E21="",H21=""),"",E21) | J21: =IF(OR(B21="",C21=""),"",IF(Dashboard!$C$19>=C21,"✓ ถึงเกณฑ์แล้ว","ยังขาด "&TEXT(C21-Dashboard!$C$19,"0.00%"))) | K21: =IF(B21="","",IF(H21<>"","ตรวจรับแล้ว",IF(G21<>"","ส่งมอบแล้ว รอตรวจรับ",IF(D21="","-",IF('ตั้งค่า Setup'!$C$15>D21,"เกินกำหนด",IF(D21-'ตั้งค่า Setup'!$C$15<=14,"ใกล้ครบกำหนด (≤14 วัน)","ยังไม่ถึงกำหนด")))))) | L21: =IF(OR(B21="",D21=""),"",MAX(0,IF(G21<>"",G21,IF(H21<>"",H21,'ตั้งค่า Setup'!$C$15))-D21))
F22: =IF(E22="","",E22/'ตั้งค่า Setup'!$C$9) | I22: =IF(OR(E22="",H22=""),"",E22) | J22: =IF(OR(B22="",C22=""),"",IF(Dashboard!$C$19>=C22,"✓ ถึงเกณฑ์แล้ว","ยังขาด "&TEXT(C22-Dashboard!$C$19,"0.00%"))) | K22: =IF(B22="","",IF(H22<>"","ตรวจรับแล้ว",IF(G22<>"","ส่งมอบแล้ว รอตรวจรับ",IF(D22="","-",IF('ตั้งค่า Setup'!$C$15>D22,"เกินกำหนด",IF(D22-'ตั้งค่า Setup'!$C$15<=14,"ใกล้ครบกำหนด (≤14 วัน)","ยังไม่ถึงกำหนด")))))) | L22: =IF(OR(B22="",D22=""),"",MAX(0,IF(G22<>"",G22,IF(H22<>"",H22,'ตั้งค่า Setup'!$C$15))-D22))
F23: =IF(E23="","",E23/'ตั้งค่า Setup'!$C$9) | I23: =IF(OR(E23="",H23=""),"",E23) | J23: =IF(OR(B23="",C23=""),"",IF(Dashboard!$C$19>=C23,"✓ ถึงเกณฑ์แล้ว","ยังขาด "&TEXT(C23-Dashboard!$C$19,"0.00%"))) | K23: =IF(B23="","",IF(H23<>"","ตรวจรับแล้ว",IF(G23<>"","ส่งมอบแล้ว รอตรวจรับ",IF(D23="","-",IF('ตั้งค่า Setup'!$C$15>D23,"เกินกำหนด",IF(D23-'ตั้งค่า Setup'!$C$15<=14,"ใกล้ครบกำหนด (≤14 วัน)","ยังไม่ถึงกำหนด")))))) | L23: =IF(OR(B23="",D23=""),"",MAX(0,IF(G23<>"",G23,IF(H23<>"",H23,'ตั้งค่า Setup'!$C$15))-D23))
... F26: =IF(E26="","",E26/'ตั้งค่า Setup'!$C$9) | I26: =IF(OR(E26="",H26=""),"",E26) | J26: =IF(OR(B26="",C26=""),"",IF(Dashboard!$C$19>=C26,"✓ ถึงเกณฑ์แล้ว","ยังขาด "&TEXT(C26-Dashboard!$C$19,"0.00%"))) | K26: =IF(B26="","",IF(H26<>"","ตรวจรับแล้ว",IF(G26<>"","ส่งมอบแล้ว รอตรวจรับ",IF(D26="","-",IF('ตั้งค่า Setup'!$C$15>D26,"เกินกำหนด",IF(D26-'ตั้งค่า Setup'!$C$15<=14,"ใกล้ครบกำหนด (≤14 วัน)","ยังไม่ถึงกำหนด")))))) | L26: =IF(OR(B26="",D26=""),"",MAX(0,IF(G26<>"",G26,IF(H26<>"",H26,'ตั้งค่า Setup'!$C$15))-D26))
B27: รวม / TOTAL | E27: =SUM(E7:E26) -> 24200000 | F27: =SUM(F7:F26) -> 1 | I27: =SUM(I7:I26) -> 0 | K27: =IF(COUNT(E7:E26)=0,"",IF(ABS(E27-'ตั้งค่า Setup'!$C$9)<1,"✓ ตรงกับมูลค่าสัญญา","⚠ ต่างจากมูลค่าสัญญา "&TEXT(E27-'ตั้งค่า Setup'!$C$9,"#,##0"))) -> ✓ ตรงกับมูลค่าสัญญา

Sheet บันทึกสัปดาห์ Weekly Log
A1: บันทึกผลการปฏิบัติงานประจำสัปดาห์ / Weekly Site Log
A2: กรอกทุกสัปดาห์ 1 แถว • ข้อมูลในแถวของสัปดาห์ที่เลือกจะไปแสดงในชีต รายงานกรรมการ Weekly อัตโนมัติ
B3: ข้อมูลสำหรับหนังสือรายงาน / Memo Details | C3: ค่า / Value | D3: หมายเหตุ
B4: ส่วนราชการ / หน่วยงาน | C4: (ตัวอย่าง) กองช่าง องค์การบริหารส่วนตำบลตัวอย่าง
B5: เลขที่หนังสือ (ที่) | C5: (ตัวอย่าง) ตย 0001/2569 | D5: เช่น กท 1234/2569
B6: วันที่ลงนามสัญญา | C6: 46167 | D6: ใช้ในย่อหน้าอ้างถึงสัญญา
B7: ชื่อผู้ควบคุมงาน | C7: (ตัวอย่าง) นายช่างโยธา ผู้ควบคุมงาน | D7: ผู้ลงนามในรายงาน
B8: ตำแหน่งผู้ควบคุมงาน | C8: นายช่างโยธาชำนาญงาน
B9: ประธานกรรมการตรวจรับพัสดุ | C9: (ตัวอย่าง) ประธานกรรมการ
B10: กรรมการตรวจรับพัสดุ คนที่ 1 | C10: (ตัวอย่าง) กรรมการ 1
B11: กรรมการตรวจรับพัสดุ คนที่ 2 | C11: (ตัวอย่าง) กรรมการ 2
B12: รายงานสัปดาห์ที่ (เลือก) | C12: =MAX(1,INT(('ตั้งค่า Setup'!$C$15-'ตั้งค่า Setup'!$C$10+1)/7)) -> 17 | D12: ค่าเริ่มต้น = สัปดาห์ล่าสุดที่ครบ 7 วันแล้ว (พิมพ์ทับได้)
B13: วันที่ออกรายงาน | C13: ='ตั้งค่า Setup'!$C$15 -> 46293 | D13: ค่าเริ่มต้น = Status Date (พิมพ์ทับได้)
A15: ตารางบันทึกรายสัปดาห์ (แถวสีส้ม = สัปดาห์ที่เลือกรายงาน) • ช่วงวันที่คำนวณจากวันเริ่มสัญญา ทุก 7 วัน
A16: สัปดาห์ ที่ | B16: จาก From | C16: ถึง To | D16: % แผน สะสม | E16: % จริง สะสม (กรอก) | F16: ผลงาน สัปดาห์นี้ | G16: ผลต่าง (จริง−แผน) | H16: คนงานเฉลี่ย (คน/วัน) | I16: เครื่องจักรหลัก Machinery | J16: วันทำงาน / หยุด-ฝนตก | K16: งานที่ดำเนินการในสัปดาห์นี้ Work Done This Week | L16: แผนงานสัปดาห์หน้า Plan Next Week | M16: วัสดุเข้าหน่วยงาน / การทดสอบ Materials & Tests | N16: ปัญหา อุปสรรค Issues | O16: ความเห็นผู้ควบคุมงาน Supervisor's Opinion
A17: =IF('ตั้งค่า Setup'!$C$10+7*0>MAX('ตั้งค่า Setup'!$C$111,'ตั้งค่า Setup'!$C$15)+7,"",1) -> 1 | B17: =IF(A17="","",'ตั้งค่า Setup'!$C$10+7*0) -> 46174 | C17: =IF(A17="","",B17+6) -> 46180 | D17: =IF(A17="","",SUMPRODUCT('แผนงาน Schedule'!$G$7:$G$156,('แผนงาน Schedule'!$J$7:$J$156<=C17)+('แผนงาน Schedule'!$I$7:$I$156<=C17)*('แผนงาน Schedule'!$J$7:$J$156>C17)*(C17-'แผนงาน Schedule'!$I$7:$I$156+1)/('แผนงาน Schedule'!$J$7:$J$156-'แผนงาน Schedule'!$I$7:$I$156+1))) -> 0.0050619835 | E17: 0.0043 | F17: =IF(E17="","",E17-0) -> 0.0043 | G17: =IF(OR(E17="",D17=""),"",E17-D17) -> -0.00076198347 | H17: 21 | I17: รถแบ็คโฮ 1 คัน, รถบดสั่นสะเทือน 1 คัน | J17: 7 / 0
A18: =IF('ตั้งค่า Setup'!$C$10+7*1>MAX('ตั้งค่า Setup'!$C$111,'ตั้งค่า Setup'!$C$15)+7,"",2) -> 2 | B18: =IF(A18="","",'ตั้งค่า Setup'!$C$10+7*1) -> 46181 | C18: =IF(A18="","",B18+6) -> 46187 | D18: =IF(A18="","",SUMPRODUCT('แผนงาน Schedule'!$G$7:$G$156,('แผนงาน Schedule'!$J$7:$J$156<=C18)+('แผนงาน Schedule'!$I$7:$I$156<=C18)*('แผนงาน Schedule'!$J$7:$J$156>C18)*(C18-'แผนงาน Schedule'!$I$7:$I$156+1)/('แผนงาน Schedule'!$J$7:$J$156-'แผนงาน Schedule'!$I$7:$I$156+1))) -> 0.010123967 | E18: 0.0121 | F18: =IF(E18="","",E18-N(E17)) -> 0.0078 | G18: =IF(OR(E18="",D18=""),"",E18-D18) -> 0.0019760331 | H18: 24 | I18: รถแบ็คโฮ 1 คัน, รถบดสั่นสะเทือน 1 คัน | J18: 7 / 0
A19: =IF('ตั้งค่า Setup'!$C$10+7*2>MAX('ตั้งค่า Setup'!$C$111,'ตั้งค่า Setup'!$C$15)+7,"",3) -> 3 | B19: =IF(A19="","",'ตั้งค่า Setup'!$C$10+7*2) -> 46188 | C19: =IF(A19="","",B19+6) -> 46194 | D19: =IF(A19="","",SUMPRODUCT('แผนงาน Schedule'!$G$7:$G$156,('แผนงาน Schedule'!$J$7:$J$156<=C19)+('แผนงาน Schedule'!$I$7:$I$156<=C19)*('แผนงาน Schedule'!$J$7:$J$156>C19)*(C19-'แผนงาน Schedule'!$I$7:$I$156+1)/('แผนงาน Schedule'!$J$7:$J$156-'แผนงาน Schedule'!$I$7:$I$156+1))) -> 0.025659824 | E19: 0.0227 | F19: =IF(E19="","",E19-N(E18)) -> 0.0106 | G19: =IF(OR(E19="",D19=""),"",E19-D19) -> -0.002959824 | H19: 27 | I19: รถแบ็คโฮ 1 คัน, รถบดสั่นสะเทือน 1 คัน | J19: 7 / 0
A20: =IF('ตั้งค่า Setup'!$C$10+7*3>MAX('ตั้งค่า Setup'!$C$111,'ตั้งค่า Setup'!$C$15)+7,"",4) -> 4 | B20: =IF(A20="","",'ตั้งค่า Setup'!$C$10+7*3) -> 46195 | C20: =IF(A20="","",B20+6) -> 46201 | D20: =IF(A20="","",SUMPRODUCT('แผนงาน Schedule'!$G$7:$G$156,('แผนงาน Schedule'!$J$7:$J$156<=C20)+('แผนงาน Schedule'!$I$7:$I$156<=C20)*('แผนงาน Schedule'!$J$7:$J$156>C20)*(C20-'แผนงาน Schedule'!$I$7:$I$156+1)/('แผนงาน Schedule'!$J$7:$J$156-'แผนงาน Schedule'!$I$7:$I$156+1))) -> 0.036856838 | E20: 0.0331 | F20: =IF(E20="","",E20-N(E19)) -> 0.0104 | G20: =IF(OR(E20="",D20=""),"",E20-D20) -> -0.0037568382 | H20: 30 | I20: รถแบ็คโฮ 1 คัน, รถบดสั่นสะเทือน 1 คัน | J20: 5 / 2 (ฝนตก)
A21: =IF('ตั้งค่า Setup'!$C$10+7*4>MAX('ตั้งค่า Setup'!$C$111,'ตั้งค่า Setup'!$C$15)+7,"",5) -> 5 | B21: =IF(A21="","",'ตั้งค่า Setup'!$C$10+7*4) -> 46202 | C21: =IF(A21="","",B21+6) -> 46208 | D21: =IF(A21="","",SUMPRODUCT('แผนงาน Schedule'!$G$7:$G$156,('แผนงาน Schedule'!$J$7:$J$156<=C21)+('แผนงาน Schedule'!$I$7:$I$156<=C21)*('แผนงาน Schedule'!$J$7:$J$156>C21)*(C21-'แผนงาน Schedule'!$I$7:$I$156+1)/('แผนงาน Schedule'!$J$7:$J$156-'แผนงาน Schedule'!$I$7:$I$156+1))) -> 0.048053852 | E21: 0.0433 | F21: =IF(E21="","",E21-N(E20)) -> 0.0102 | G21: =IF(OR(E21="",D21=""),"",E21-D21) -> -0.0047538523 | H21: 18 | I21: รถแบ็คโฮ 1 คัน, รถบดสั่นสะเทือน 1 คัน | J21: 7 / 0
A22: =IF('ตั้งค่า Setup'!$C$10+7*5>MAX('ตั้งค่า Setup'!$C$111,'ตั้งค่า Setup'!$C$15)+7,"",6) -> 6 | B22: =IF(A22="","",'ตั้งค่า Setup'!$C$10+7*5) -> 46209 | C22: =IF(A22="","",B22+6) -> 46215 | D22: =IF(A22="","",SUMPRODUCT('แผนงาน Schedule'!$G$7:$G$156,('แผนงาน Schedule'!$J$7:$J$156<=C22)+('แผนงาน Schedule'!$I$7:$I$156<=C22)*('แผนงาน Schedule'!$J$7:$J$156>C22)*(C22-'แผนงาน Schedule'!$I$7:$I$156+1)/('แผนงาน Schedule'!$J$7:$J$156-'แผนงาน Schedule'!$I$7:$I$156+1))) -> 0.059250866 | E22: 0.053 | F22: =IF(E22="","",E22-N(E21)) -> 0.0097 | G22: =IF(OR(E22="",D22=""),"",E22-D22) -> -0.0062508664 | H22: 21 | I22: รถแบ็คโฮ 1 คัน, รถบดสั่นสะเทือน 1 คัน | J22: 7 / 0
A23: =IF('ตั้งค่า Setup'!$C$10+7*6>MAX('ตั้งค่า Setup'!$C$111,'ตั้งค่า Setup'!$C$15)+7,"",7) -> 7 | B23: =IF(A23="","",'ตั้งค่า Setup'!$C$10+7*6) -> 46216 | C23: =IF(A23="","",B23+6) -> 46222 | D23: =IF(A23="","",SUMPRODUCT('แผนงาน Schedule'!$G$7:$G$156,('แผนงาน Schedule'!$J$7:$J$156<=C23)+('แผนงาน Schedule'!$I$7:$I$156<=C23)*('แผนงาน Schedule'!$J$7:$J$156>C23)*(C23-'แผนงาน Schedule'!$I$7:$I$156+1)/('แผนงาน Schedule'!$J$7:$J$156-'แผนงาน Schedule'!$I$7:$I$156+1))) -> 0.070447881 | E23: 0.0621 | F23: =IF(E23="","",E23-N(E22)) -> 0.0091 | G23: =IF(OR(E23="",D23=""),"",E23-D23) -> -0.0083478806 | H23: 24 | I23: รถแบ็คโฮ 1 คัน, รถบดสั่นสะเทือน 1 คัน | J23: 7 / 0
A24: =IF('ตั้งค่า Setup'!$C$10+7*7>MAX('ตั้งค่า Setup'!$C$111,'ตั้งค่า Setup'!$C$15)+7,"",8) -> 8 | B24: =IF(A24="","",'ตั้งค่า Setup'!$C$10+7*7) -> 46223 | C24: =IF(A24="","",B24+6) -> 46229 | D24: =IF(A24="","",SUMPRODUCT('แผนงาน Schedule'!$G$7:$G$156,('แผนงาน Schedule'!$J$7:$J$156<=C24)+('แผนงาน Schedule'!$I$7:$I$156<=C24)*('แผนงาน Schedule'!$J$7:$J$156>C24)*(C24-'แผนงาน Schedule'!$I$7:$I$156+1)/('แผนงาน Schedule'!$J$7:$J$156-'แผนงาน Schedule'!$I$7:$I$156+1))) -> 0.081644895 | E24: 0.0709 | F24: =IF(E24="","",E24-N(E23)) -> 0.0088 | G24: =IF(OR(E24="",D24=""),"",E24-D24) -> -0.010744895 | H24: 27 | I24: รถแบ็คโฮ 1 คัน, รถบดสั่นสะเทือน 1 คัน | J24: 5 / 2 (ฝนตก)
